Workbook

Sheet Scores
A1: ID | B1: ELL | C1: IEP | D1: MC | E1: CRQ | F1: EIE | G1: Final | H1: 1 | I1: 2 | J1: 3 | K1: 4 | L1: 5 | M1: 6 | N1: 7 | O1: 8 | P1: 9 | Q1: 10 | R1: 11 | S1: 12 | T1: 13 | U1: 14 | V1: 15 | W1: 16 | X1: 17 | Y1: 18 | Z1: 19 | AA1: 20 | AB1: 21 | AC1: 22 | AD1: 23 | AE1: 24 | AF1: 25 | AG1: 26 | AH1: 27 | AI1: 28 | AJ1: 29 | AK1: 30 | AL1: 31 | AM1: 32 | AN1: 33 | AO1: 34a | AP1: 34b | AQ1: 35 | AR1: Q1 | AS1: Q2 | AT1: Q3 | AU1: Q4 | AV1: Q5 | AW1: Q6 | AX1: Q7 | AY1: Q8 | AZ1: Q9 | BA1: Q10 | BB1: Q11 | BC1: Q12 | BD1: Q13 | BE1: Q14 | BF1: Q15 | BG1: Q16 | BH1: Q17 | BI1: Q18 | BJ1: Q19 | BK1: Q20 | BL1: Q21 | BM1: Q22 | BN1: Q23 | BO1: Q24 | BP1: Q25 | BQ1: Q26 | BR1: Q27 | BS1: Q28
A2: 1 | B2: FALSE | C2: FALSE | D2: =SUM(Scores[[#This Row],[Q1]:[Q28]]) -> 22 | E2: =SUM(Scores[[#This Row],[29]:[34b]]) -> 0 | F2: =Scores[[#This Row],[35]] -> 0 | G2: =INDEX('Conversion Chart'!$C$3:$M$38,MATCH(SUM(Scores[[#This Row],[MC]:[CRQ]]),'Conversion Chart'!$B$3:$B$38,0),MATCH(Scores[[#This Row],[EIE]],'Conversion Chart'!$C$2:$M$2,0)) -> 57 | H2: 4 | I2: 3 | J2: 1 | K2: 3 | L2: 2 | M2: 3 | N2: 3 | O2: 4 | P2: 1 | Q2: 1 | R2: 4 | S2: 3 | T2: 1 | U2: 4 | V2: 1 | W2: 4 | X2: 2 | Y2: 3 | Z2: 2 | AA2: 1 | AB2: 2 | AC2: 1 | AD2: 3 | AE2: 2 | AF2: 4 | AG2: 3 | AH2: 1 | AI2: 1 | AR2: =IF(H2=VLOOKUP(VALUE(H$1),Questions!$A:$E,5,FALSE),1,0) -> 1 | AS2: =IF(I2=VLOOKUP(VALUE(I$1),Questions!$A:$E,5,FALSE),1,0) -> 1 | AT2: =IF(J2=VLOOKUP(VALUE(J$1),Questions!$A:$E,5,FALSE),1,0) -> 1 | AU2: =IF(K2=VLOOKUP(VALUE(K$1),Questions!$A:$E,5,FALSE),1,0) -> 0 | AV2: =IF(L2=VLOOKUP(VALUE(L$1),Questions!$A:$E,5,FALSE),1,0) -> 1 | AW2: =IF(M2=VLOOKUP(VALUE(M$1),Questions!$A:$E,5,FALSE),1,0) -> 0 | AX2: =IF(N2=VLOOKUP(VALUE(N$1),Questions!$A:$E,5,FALSE),1,0) -> 1 | AY2: =IF(O2=VLOOKUP(VALUE(O$1),Questions!$A:$E,5,FALSE),1,0) -> 0 | ... BS2: =IF(AI2=VLOOKUP(VALUE(AI$1),Questions!$A:$E,5,FALSE),1,0) -> 1
A3: 2 | B3: FALSE | C3: FALSE | D3: =SUM(Scores[[#This Row],[Q1]:[Q28]]) -> 24 | E3: =SUM(Scores[[#This Row],[29]:[34b]]) -> 0 | F3: =Scores[[#This Row],[35]] -> 0 | G3: =INDEX('Conversion Chart'!$C$3:$M$38,MATCH(SUM(Scores[[#This Row],[MC]:[CRQ]]),'Conversion Chart'!$B$3:$B$38,0),MATCH(Scores[[#This Row],[EIE]],'Conversion Chart'!$C$2:$M$2,0)) -> 61 | H3: 4 | I3: 3 | J3: 1 | K3: 2 | L3: 4 | M3: 4 | N3: 3 | O3: 4 | P3: 1 | Q3: 1 | R3: 4 | S3: 2 | T3: 1 | U3: 4 | V3: 3 | W3: 4 | X3: 2 | Y3: 3 | Z3: 2 | AA3: 3 | AB3: 2 | AC3: 3 | AD3: 3 | AE3: 4 | AF3: 4 | AG3: 3 | AH3: 1 | AI3: 1 | AR3: =IF(H3=VLOOKUP(VALUE(H$1),Questions!$A:$E,5,FALSE),1,0) -> 1 | AS3: =IF(I3=VLOOKUP(VALUE(I$1),Questions!$A:$E,5,FALSE),1,0) -> 1 | AT3: =IF(J3=VLOOKUP(VALUE(J$1),Questions!$A:$E,5,FALSE),1,0) -> 1 | AU3: =IF(K3=VLOOKUP(VALUE(K$1),Questions!$A:$E,5,FALSE),1,0) -> 1 | AV3: =IF(L3=VLOOKUP(VALUE(L$1),Questions!$A:$E,5,FALSE),1,0) -> 0 | AW3: =IF(M3=VLOOKUP(VALUE(M$1),Questions!$A:$E,5,FALSE),1,0) -> 1 | AX3: =IF(N3=VLOOKUP(VALUE(N$1),Questions!$A:$E,5,FALSE),1,0) -> 1 | AY3: =IF(O3=VLOOKUP(VALUE(O$1),Questions!$A:$E,5,FALSE),1,0) -> 0 | ... BS3: =IF(AI3=VLOOKUP(VALUE(AI$1),Questions!$A:$E,5,FALSE),1,0) -> 1
A4: 3 | B4: FALSE | C4: FALSE | D4: =SUM(Scores[[#This Row],[Q1]:[Q28]]) -> 15 | E4: =SUM(Scores[[#This Row],[29]:[34b]]) -> 0 | F4: =Scores[[#This Row],[35]] -> 0 | G4: =INDEX('Conversion Chart'!$C$3:$M$38,MATCH(SUM(Scores[[#This Row],[MC]:[CRQ]]),'Conversion Chart'!$B$3:$B$38,0),MATCH(Scores[[#This Row],[EIE]],'Conversion Chart'!$C$2:$M$2,0)) -> 42 | H4: 4 | I4: 3 | J4: 1 | K4: 2 | L4: 1 | M4: 4 | N4: 3 | O4: 3 | P4: 2 | Q4: 3 | R4: 4 | S4: 3 | T4: 2 | U4: 1 | V4: 1 | W4: 4 | X4: 2 | Y4: 3 | Z4: 2 | AA4: 1 | AB4: 2 | AC4: 4 | AD4: 3 | AE4: 4 | AF4: 4 | AG4: 2 | AH4: 3 | AI4: 1 | AR4: =IF(H4=VLOOKUP(VALUE(H$1),Questions!$A:$E,5,FALSE),1,0) -> 1 | AS4: =IF(I4=VLOOKUP(VALUE(I$1),Questions!$A:$E,5,FALSE),1,0) -> 1 | AT4: =IF(J4=VLOOKUP(VALUE(J$1),Questions!$A:$E,5,FALSE),1,0) -> 1 | AU4: =IF(K4=VLOOKUP(VALUE(K$1),Questions!$A:$E,5,FALSE),1,0) -> 1 | AV4: =IF(L4=VLOOKUP(VALUE(L$1),Questions!$A:$E,5,FALSE),1,0) -> 0 | AW4: =IF(M4=VLOOKUP(VALUE(M$1),Questions!$A:$E,5,FALSE),1,0) -> 1 | AX4: =IF(N4=VLOOKUP(VALUE(N$1),Questions!$A:$E,5,FALSE),1,0) -> 1 | AY4: =IF(O4=VLOOKUP(VALUE(O$1),Questions!$A:$E,5,FALSE),1,0) -> 0 | ... BS4: =IF(AI4=VLOOKUP(VALUE(AI$1),Questions!$A:$E,5,FALSE),1,0) -> 1
A5: 4 | B5: FALSE | C5: FALSE | D5: =SUM(Scores[[#This Row],[Q1]:[Q28]]) -> 19 | E5: =SUM(Scores[[#This Row],[29]:[34b]]) -> 0 | F5: =Scores[[#This Row],[35]] -> 0 | G5: =INDEX('Conversion Chart'!$C$3:$M$38,MATCH(SUM(Scores[[#This Row],[MC]:[CRQ]]),'Conversion Chart'!$B$3:$B$38,0),MATCH(Scores[[#This Row],[EIE]],'Conversion Chart'!$C$2:$M$2,0)) -> 51 | H5: 4 | I5: 3 | J5: 1 | K5: 4 | L5: 2 | M5: 4 | N5: 3 | O5: 4 | P5: 1 | Q5: 1 | R5: 4 | S5: 4 | T5: 1 | U5: 4 | V5: 1 | W5: 4 | X5: 2 | Y5: 2 | Z5: 1 | AA5: 3 | AB5: 2 | AC5: 3 | AD5: 3 | AE5: 4 | AF5: 4 | AG5: 2 | AH5: 1 | AI5: 1 | AR5: =IF(H5=VLOOKUP(VALUE(H$1),Questions!$A:$E,5,FALSE),1,0) -> 1 | AS5: =IF(I5=VLOOKUP(VALUE(I$1),Questions!$A:$E,5,FALSE),1,0) -> 1 | AT5: =IF(J5=VLOOKUP(VALUE(J$1),Questions!$A:$E,5,FALSE),1,0) -> 1 | AU5: =IF(K5=VLOOKUP(VALUE(K$1),Questions!$A:$E,5,FALSE),1,0) -> 0 | AV5: =IF(L5=VLOOKUP(VALUE(L$1),Questions!$A:$E,5,FALSE),1,0) -> 1 | AW5: =IF(M5=VLOOKUP(VALUE(M$1),Questions!$A:$E,5,FALSE),1,0) -> 1 | AX5: =IF(N5=VLOOKUP(VALUE(N$1),Questions!$A:$E,5,FALSE),1,0) -> 1 | AY5: =IF(O5=VLOOKUP(VALUE(O$1),Questions!$A:$E,5,FALSE),1,0) -> 0 | ... BS5: =IF(AI5=VLOOKUP(VALUE(AI$1),Questions!$A:$E,5,FALSE),1,0) -> 1
A6: 5 | B6: FALSE | C6: FALSE | D6: =SUM(Scores[[#This Row],[Q1]:[Q28]]) -> 20 | E6: =SUM(Scores[[#This Row],[29]:[34b]]) -> 0 | F6: =Scores[[#This Row],[35]] -> 0 | G6: =INDEX('Conversion Chart'!$C$3:$M$38,MATCH(SUM(Scores[[#This Row],[MC]:[CRQ]]),'Conversion Chart'!$B$3:$B$38,0),MATCH(Scores[[#This Row],[EIE]],'Conversion Chart'!$C$2:$M$2,0)) -> 53 | H6: 4 | I6: 3 | J6: 1 | K6: 2 | L6: 4 | M6: 4 | N6: 3 | O6: 4 | P6: 1 | Q6: 1 | R6: 4 | S6: 2 | T6: 1 | U6: 4 | V6: 1 | W6: 4 | X6: 2 | Y6: 2 | Z6: 1 | AA6: 3 | AB6: 2 | AC6: 3 | AD6: 3 | AE6: 4 | AF6: 4 | AG6: 2 | AH6: 1 | AI6: 1 | AR6: =IF(H6=VLOOKUP(VALUE(H$1),Questions!$A:$E,5,FALSE),1,0) -> 1 | AS6: =IF(I6=VLOOKUP(VALUE(I$1),Questions!$A:$E,5,FALSE),1,0) -> 1 | AT6: =IF(J6=VLOOKUP(VALUE(J$1),Questions!$A:$E,5,FALSE),1,0) -> 1 | AU6: =IF(K6=VLOOKUP(VALUE(K$1),Questions!$A:$E,5,FALSE),1,0) -> 1 | AV6: =IF(L6=VLOOKUP(VALUE(L$1),Questions!$A:$E,5,FALSE),1,0) -> 0 | AW6: =IF(M6=VLOOKUP(VALUE(M$1),Questions!$A:$E,5,FALSE),1,0) -> 1 | AX6: =IF(N6=VLOOKUP(VALUE(N$1),Questions!$A:$E,5,FALSE),1,0) -> 1 | AY6: =IF(O6=VLOOKUP(VALUE(O$1),Questions!$A:$E,5,FALSE),1,0) -> 0 | ... BS6: =IF(AI6=VLOOKUP(VALUE(AI$1),Questions!$A:$E,5,FALSE),1,0) -> 1
A7: 6 | B7: FALSE | C7: FALSE | D7: =SUM(Scores[[#This Row],[Q1]:[Q28]]) -> 15 | E7: =SUM(Scores[[#This Row],[29]:[34b]]) -> 0 | F7: =Scores[[#This Row],[35]] -> 0 | G7: =INDEX('Conversion Chart'!$C$3:$M$38,MATCH(SUM(Scores[[#This Row],[MC]:[CRQ]]),'Conversion Chart'!$B$3:$B$38,0),MATCH(Scores[[#This Row],[EIE]],'Conversion Chart'!$C$2:$M$2,0)) -> 42 | H7: 3 | I7: 3 | J7: 1 | K7: 2 | L7: 4 | M7: 4 | N7: 3 | O7: 2 | P7: 2 | Q7: 2 | R7: 4 | S7: 4 | T7: 1 | U7: 2 | V7: 3 | W7: 1 | X7: 3 | Y7: 3 | Z7: 1 | AA7: 1 | AB7: 2 | AC7: 1 | AD7: 3 | AE7: 2 | AF7: 4 | AI7: 1 | AR7: =IF(H7=VLOOKUP(VALUE(H$1),Questions!$A:$E,5,FALSE),1,0) -> 0 | AS7: =IF(I7=VLOOKUP(VALUE(I$1),Questions!$A:$E,5,FALSE),1,0) -> 1 | AT7: =IF(J7=VLOOKUP(VALUE(J$1),Questions!$A:$E,5,FALSE),1,0) -> 1 | AU7: =IF(K7=VLOOKUP(VALUE(K$1),Questions!$A:$E,5,FALSE),1,0) -> 1 | AV7: =IF(L7=VLOOKUP(VALUE(L$1),Questions!$A:$E,5,FALSE),1,0) -> 0 | AW7: =IF(M7=VLOOKUP(VALUE(M$1),Questions!$A:$E,5,FALSE),1,0) -> 1 | AX7: =IF(N7=VLOOKUP(VALUE(N$1),Questions!$A:$E,5,FALSE),1,0) -> 1 | AY7: =IF(O7=VLOOKUP(VALUE(O$1),Questions!$A:$E,5,FALSE),1,0) -> 0 | ... BS7: =IF(AI7=VLOOKUP(VALUE(AI$1),Questions!$A:$E,5,FALSE),1,0) -> 1
A8: 7 | B8: FALSE | C8: FALSE | D8: =SUM(Scores[[#This Row],[Q1]:[Q28]]) -> 17 | E8: =SUM(Scores[[#This Row],[29]:[34b]]) -> 0 | F8: =Scores[[#This Row],[35]] -> 0 | G8: =INDEX('Conversion Chart'!$C$3:$M$38,MATCH(SUM(Scores[[#This Row],[MC]:[CRQ]]),'Conversion Chart'!$B$3:$B$38,0),MATCH(Scores[[#This Row],[EIE]],'Conversion Chart'!$C$2:$M$2,0)) -> 47 | H8: 4 | I8: 3 | J8: 1 | K8: 2 | L8: 3 | M8: 2 | N8: 3 | O8: 1 | P8: 2 | Q8: 2 | R8: 4 | S8: 3 | T8: 2 | U8: 4 | V8: 3 | W8: 1 | X8: 2 | Y8: 2 | Z8: 2 | AA8: 3 | AB8: 2 | AC8: 1 | AD8: 2 | AE8: 4 | AF8: 4 | AG8: 2 | AH8: 1 | AI8: 1 | AR8: =IF(H8=VLOOKUP(VALUE(H$1),Questions!$A:$E,5,FALSE),1,0) -> 1 | AS8: =IF(I8=VLOOKUP(VALUE(I$1),Questions!$A:$E,5,FALSE),1,0) -> 1 | AT8: =IF(J8=VLOOKUP(VALUE(J$1),Questions!$A:$E,5,FALSE),1,0) -> 1 | AU8: =IF(K8=VLOOKUP(VALUE(K$1),Questions!$A:$E,5,FALSE),1,0) -> 1 | AV8: =IF(L8=VLOOKUP(VALUE(L$1),Questions!$A:$E,5,FALSE),1,0) -> 0 | AW8: =IF(M8=VLOOKUP(VALUE(M$1),Questions!$A:$E,5,FALSE),1,0) -> 0 | AX8: =IF(N8=VLOOKUP(VALUE(N$1),Questions!$A:$E,5,FALSE),1,0) -> 1 | AY8: =IF(O8=VLOOKUP(VALUE(O$1),Questions!$A:$E,5,FALSE),1,0) -> 1 | ... BS8: =IF(AI8=VLOOKUP(VALUE(AI$1),Questions!$A:$E,5,FALSE),1,0) -> 1
A9: 8 | B9: FALSE | C9: FALSE | D9: =SUM(Scores[[#This Row],[Q1]:[Q28]]) -> 16 | E9: =SUM(Scores[[#This Row],[29]:[34b]]) -> 0 | F9: =Scores[[#This Row],[35]] -> 0 | G9: =INDEX('Conversion Chart'!$C$3:$M$38,MATCH(SUM(Scores[[#This Row],[MC]:[CRQ]]),'Conversion Chart'!$B$3:$B$38,0),MATCH(Scores[[#This Row],[EIE]],'Conversion Chart'!$C$2:$M$2,0)) -> 45 | H9: 3 | I9: 3 | J9: 1 | K9: 2 | L9: 1 | M9: 4 | N9: 4 | O9: 1 | P9: 4 | Q9: 2 | R9: 4 | S9: 2 | T9: 1 | U9: 4 | V9: 1 | W9: 4 | X9: 2 | Y9: 2 | Z9: 1 | AA9: 4 | AB9: 4 | AC9: 2 | AD9: 3 | AE9: 4 | AF9: 4 | AG9: 3 | AH9: 1 | AI9: 1 | AR9: =IF(H9=VLOOKUP(VALUE(H$1),Questions!$A:$E,5,FALSE),1,0) -> 0 | AS9: =IF(I9=VLOOKUP(VALUE(I$1),Questions!$A:$E,5,FALSE),1,0) -> 1 | AT9: =IF(J9=VLOOKUP(VALUE(J$1),Questions!$A:$E,5,FALSE),1,0) -> 1 | AU9: =IF(K9=VLOOKUP(VALUE(K$1),Questions!$A:$E,5,FALSE),1,0) -> 1 | AV9: =IF(L9=VLOOKUP(VALUE(L$1),Questions!$A:$E,5,FALSE),1,0) -> 0 | AW9: =IF(M9=VLOOKUP(VALUE(M$1),Questions!$A:$E,5,FALSE),1,0) -> 1 | AX9: =IF(N9=VLOOKUP(VALUE(N$1),Questions!$A:$E,5,FALSE),1,0) -> 0 | AY9: =IF(O9=VLOOKUP(VALUE(O$1),Questions!$A:$E,5,FALSE),1,0) -> 1 | ... BS9: =IF(AI9=VLOOKUP(VALUE(AI$1),Questions!$A:$E,5,FALSE),1,0) -> 1
A10: 9 | B10: FALSE | C10: FALSE | D10: =SUM(Scores[[#This Row],[Q1]:[Q28]]) -> 25 | E10: =SUM(Scores[[#This Row],[29]:[34b]]) -> 0 | F10: =Scores[[#This Row],[35]] -> 0 | G10: =INDEX('Conversion Chart'!$C$3:$M$38,MATCH(SUM(Scores[[#This Row],[MC]:[CRQ]]),'Conversion Chart'!$B$3:$B$38,0),MATCH(Scores[[#This Row],[EIE]],'Conversion Chart'!$C$2:$M$2,0)) -> 63 | H10: 4 | I10: 3 | J10: 1 | K10: 2 | L10: 2 | M10: 4 | N10: 3 | O10: 1 | P10: 1 | Q10: 1 | R10: 4 | S10: 2 | T10: 1 | U10: 4 | V10: 3 | W10: 1 | X10: 2 | Y10: 3 | Z10: 4 | AA10: 3 | AB10: 2 | AC10: 1 | AD10: 3 | AE10: 2 | AF10: 4 | AG10: 2 | AH10: 1 | AI10: 1 | AR10: =IF(H10=VLOOKUP(VALUE(H$1),Questions!$A:$E,5,FALSE),1,0) -> 1 | AS10: =IF(I10=VLOOKUP(VALUE(I$1),Questions!$A:$E,5,FALSE),1,0) -> 1 | AT10: =IF(J10=VLOOKUP(VALUE(J$1),Questions!$A:$E,5,FALSE),1,0) -> 1 | AU10: =IF(K10=VLOOKUP(VALUE(K$1),Questions!$A:$E,5,FALSE),1,0) -> 1 | AV10: =IF(L10=VLOOKUP(VALUE(L$1),Questions!$A:$E,5,FALSE),1,0) -> 1 | AW10: =IF(M10=VLOOKUP(VALUE(M$1),Questions!$A:$E,5,FALSE),1,0) -> 1 | AX10: =IF(N10=VLOOKUP(VALUE(N$1),Questions!$A:$E,5,FALSE),1,0) -> 1 | AY10: =IF(O10=VLOOKUP(VALUE(O$1),Questions!$A:$E,5,FALSE),1,0) -> 1 | ... BS10: =IF(AI10=VLOOKUP(VALUE(AI$1),Questions!$A:$E,5,FALSE),1,0) -> 1
A11: 10 | B11: FALSE | C11: FALSE | D11: =SUM(Scores[[#This Row],[Q1]:[Q28]]) -> 22 | E11: =SUM(Scores[[#This Row],[29]:[34b]]) -> 0 | F11: =Scores[[#This Row],[35]] -> 0 | G11: =INDEX('Conversion Chart'!$C$3:$M$38,MATCH(SUM(Scores[[#This Row],[MC]:[CRQ]]),'Conversion Chart'!$B$3:$B$38,0),MATCH(Scores[[#This Row],[EIE]],'Conversion Chart'!$C$2:$M$2,0)) -> 57 | H11: 4 | I11: 3 | J11: 1 | K11: 2 | L11: 2 | M11: 4 | N11: 3 | O11: 1 | P11: 1 | Q11: 4 | R11: 4 | S11: 4 | T11: 1 | U11: 3 | V11: 3 | W11: 4 | X11: 2 | Y11: 3 | Z11: 3 | AA11: 3 | AB11: 2 | AC11: 3 | AD11: 3 | AE11: 2 | AF11: 4 | AG11: 1 | AH11: 1 | AI11: 1 | AR11: =IF(H11=VLOOKUP(VALUE(H$1),Questions!$A:$E,5,FALSE),1,0) -> 1 | AS11: =IF(I11=VLOOKUP(VALUE(I$1),Questions!$A:$E,5,FALSE),1,0) -> 1 | AT11: =IF(J11=VLOOKUP(VALUE(J$1),Questions!$A:$E,5,FALSE),1,0) -> 1 | AU11: =IF(K11=VLOOKUP(VALUE(K$1),Questions!$A:$E,5,FALSE),1,0) -> 1 | AV11: =IF(L11=VLOOKUP(VALUE(L$1),Questions!$A:$E,5,FALSE),1,0) -> 1 | AW11: =IF(M11=VLOOKUP(VALUE(M$1),Questions!$A:$E,5,FALSE),1,0) -> 1 | AX11: =IF(N11=VLOOKUP(VALUE(N$1),Questions!$A:$E,5,FALSE),1,0) -> 1 | AY11: =IF(O11=VLOOKUP(VALUE(O$1),Questions!$A:$E,5,FALSE),1,0) -> 1 | ... BS11: =IF(AI11=VLOOKUP(VALUE(AI$1),Questions!$A:$E,5,FALSE),1,0) -> 1
A12: 11 | B12: FALSE | C12: FALSE | D12: =SUM(Scores[[#This Row],[Q1]:[Q28]]) -> 12 | E12: =SUM(Scores[[#This Row],[29]:[34b]]) -> 0 | F12: =Scores[[#This Row],[35]] -> 0 | G12: =INDEX('Conversion Chart'!$C$3:$M$38,MATCH(SUM(Scores[[#This Row],[MC]:[CRQ]]),'Conversion Chart'!$B$3:$B$38,0),MATCH(Scores[[#This Row],[EIE]],'Conversion Chart'!$C$2:$M$2,0)) -> 35 | H12: 4 | I12: 3 | J12: 3 | K12: 2 | L12: 1 | M12: 4 | N12: 3 | O12: 4 | P12: 1 | Q12: 3 | R12: 2 | S12: 4 | T12: 4 | U12: 3 | V12: 1 | W12: 3 | X12: 3 | Y12: 2 | Z12: 2 | AA12: 3 | AB12: 2 | AC12: 1 | AD12: 3 | AE12: 3 | AF12: 2 | AG12: 4 | AH12: 1 | AI12: 3 | AR12: =IF(H12=VLOOKUP(VALUE(H$1),Questions!$A:$E,5,FALSE),1,0) -> 1 | AS12: =IF(I12=VLOOKUP(VALUE(I$1),Questions!$A:$E,5,FALSE),1,0) -> 1 | AT12: =IF(J12=VLOOKUP(VALUE(J$1),Questions!$A:$E,5,FALSE),1,0) -> 0 | AU12: =IF(K12=VLOOKUP(VALUE(K$1),Questions!$A:$E,5,FALSE),1,0) -> 1 | AV12: =IF(L12=VLOOKUP(VALUE(L$1),Questions!$A:$E,5,FALSE),1,0) -> 0 | AW12: =IF(M12=VLOOKUP(VALUE(M$1),Questions!$A:$E,5,FALSE),1,0) -> 1 | AX12: =IF(N12=VLOOKUP(VALUE(N$1),Questions!$A:$E,5,FALSE),1,0) -> 1 | AY12: =IF(O12=VLOOKUP(VALUE(O$1),Questions!$A:$E,5,FALSE),1,0) -> 0 | ... BS12: =IF(AI12=VLOOKUP(VALUE(AI$1),Questions!$A:$E,5,FALSE),1,0) -> 0
A13: 12 | B13: FALSE | C13: FALSE | D13: =SUM(Scores[[#This Row],[Q1]:[Q28]]) -> 22 | E13: =SUM(Scores[[#This Row],[29]:[34b]]) -> 0 | F13: =Scores[[#This Row],[35]] -> 0 | G13: =INDEX('Conversion Chart'!$C$3:$M$38,MATCH(SUM(Scores[[#This Row],[MC]:[CRQ]]),'Conversion Chart'!$B$3:$B$38,0),MATCH(Scores[[#This Row],[EIE]],'Conversion Chart'!$C$2:$M$2,0)) -> 57 | H13: 3 | I13: 3 | J13: 1 | K13: 2 | L13: 2 | M13: 4 | N13: 4 | O13: 1 | P13: 1 | Q13: 1 | R13: 4 | S13: 2 | T13: 1 | U13: 4 | V13: 3 | W13: 4 | X13: 2 | Y13: 3 | Z13: 1 | AA13: 1 | AB13: 4 | AC13: 1 | AD13: 3 | AE13: 2 | AF13: 4 | AG13: 3 | AH13: 1 | AI13: 4 | AR13: =IF(H13=VLOOKUP(VALUE(H$1),Questions!$A:$E,5,FALSE),1,0) -> 0 | AS13: =IF(I13=VLOOKUP(VALUE(I$1),Questions!$A:$E,5,FALSE),1,0) -> 1 | AT13: =IF(J13=VLOOKUP(VALUE(J$1),Questions!$A:$E,5,FALSE),1,0) -> 1 | AU13: =IF(K13=VLOOKUP(VALUE(K$1),Questions!$A:$E,5,FALSE),1,0) -> 1 | AV13: =IF(L13=VLOOKUP(VALUE(L$1),Questions!$A:$E,5,FALSE),1,0) -> 1 | AW13: =IF(M13=VLOOKUP(VALUE(M$1),Questions!$A:$E,5,FALSE),1,0) -> 1 | AX13: =IF(N13=VLOOKUP(VALUE(N$1),Questions!$A:$E,5,FALSE),1,0) -> 0 | AY13: =IF(O13=VLOOKUP(VALUE(O$1),Questions!$A:$E,5,FALSE),1,0) -> 1 | ... BS13: =IF(AI13=VLOOKUP(VALUE(AI$1),Questions!$A:$E,5,FALSE),1,0) -> 0
A14: 13 | B14: FALSE | C14: FALSE | D14: =SUM(Scores[[#This Row],[Q1]:[Q28]]) -> 24 | E14: =SUM(Scores[[#This Row],[29]:[34b]]) -> 0 | F14: =Scores[[#This Row],[35]] -> 0 | G14: =INDEX('Conversion Chart'!$C$3:$M$38,MATCH(SUM(Scores[[#This Row],[MC]:[CRQ]]),'Conversion Chart'!$B$3:$B$38,0),MATCH(Scores[[#This Row],[EIE]],'Conversion Chart'!$C$2:$M$2,0)) -> 61 | H14: 3 | I14: 3 | J14: 1 | K14: 2 | L14: 2 | M14: 4 | N14: 3 | O14: 4 | P14: 1 | Q14: 1 | R14: 4 | S14: 2 | T14: 1 | U14: 4 | V14: 3 | W14: 3 | X14: 2 | Y14: 3 | AA14: 3 | AB14: 2 | AC14: 1 | AD14: 3 | AE14: 2 | AF14: 4 | AG14: 3 | AH14: 1 | AI14: 1 | AR14: =IF(H14=VLOOKUP(VALUE(H$1),Questions!$A:$E,5,FALSE),1,0) -> 0 | AS14: =IF(I14=VLOOKUP(VALUE(I$1),Questions!$A:$E,5,FALSE),1,0) -> 1 | AT14: =IF(J14=VLOOKUP(VALUE(J$1),Questions!$A:$E,5,FALSE),1,0) -> 1 | AU14: =IF(K14=VLOOKUP(VALUE(K$1),Questions!$A:$E,5,FALSE),1,0) -> 1 | AV14: =IF(L14=VLOOKUP(VALUE(L$1),Questions!$A:$E,5,FALSE),1,0) -> 1 | AW14: =IF(M14=VLOOKUP(VALUE(M$1),Questions!$A:$E,5,FALSE),1,0) -> 1 | AX14: =IF(N14=VLOOKUP(VALUE(N$1),Questions!$A:$E,5,FALSE),1,0) -> 1 | AY14: =IF(O14=VLOOKUP(VALUE(O$1),Questions!$A:$E,5,FALSE),1,0) -> 0 | ... BS14: =IF(AI14=VLOOKUP(VALUE(AI$1),Questions!$A:$E,5,FALSE),1,0) -> 1
A15: 14 | B15: FALSE | C15: FALSE | D15: =SUM(Scores[[#This Row],[Q1]:[Q28]]) -> 10 | E15: =SUM(Scores[[#This Row],[29]:[34b]]) -> 0 | F15: =Scores[[#This Row],[35]] -> 0 | G15: =INDEX('Conversion Chart'!$C$3:$M$38,MATCH(SUM(Scores[[#This Row],[MC]:[CRQ]]),'Conversion Chart'!$B$3:$B$38,0),MATCH(Scores[[#This Row],[EIE]],'Conversion Chart'!$C$2:$M$2,0)) -> 30 | H15: 1 | I15: 3 | J15: 1 | K15: 2 | L15: 1 | M15: 2 | N15: 3 | O15: 3 | P15: 4 | Q15: 3 | R15: 4 | S15: 4 | T15: 4 | U15: 1 | V15: 4 | W15: 3 | X15: 1 | Y15: 2 | Z15: 4 | AA15: 1 | AB15: 2 | AC15: 4 | AD15: 3 | AE15: 4 | AF15: 4 | AG15: 1 | AH15: 1 | AI15: 1 | AR15: =IF(H15=VLOOKUP(VALUE(H$1),Questions!$A:$E,5,FALSE),1,0) -> 0 | AS15: =IF(I15=VLOOKUP(VALUE(I$1),Questions!$A:$E,5,FALSE),1,0) -> 1 | AT15: =IF(J15=VLOOKUP(VALUE(J$1),Questions!$A:$E,5,FALSE),1,0) -> 1 | AU15: =IF(K15=VLOOKUP(VALUE(K$1),Questions!$A:$E,5,FALSE),1,0) -> 1 | AV15: =IF(L15=VLOOKUP(VALUE(L$1),Questions!$A:$E,5,FALSE),1,0) -> 0 | AW15: =IF(M15=VLOOKUP(VALUE(M$1),Questions!$A:$E,5,FALSE),1,0) -> 0 | AX15: =IF(N15=VLOOKUP(VALUE(N$1),Questions!$A:$E,5,FALSE),1,0) -> 1 | AY15: =IF(O15=VLOOKUP(VALUE(O$1),Questions!$A:$E,5,FALSE),1,0) -> 0 | ... BS15: =IF(AI15=VLOOKUP(VALUE(AI$1),Questions!$A:$E,5,FALSE),1,0) -> 1
A16: 15 | B16: FALSE | C16: FALSE | D16: =SUM(Scores[[#This Row],[Q1]:[Q28]]) -> 25 | E16: =SUM(Scores[[#This Row],[29]:[34b]]) -> 0 | F16: =Scores[[#This Row],[35]] -> 0 | G16: =INDEX('Conversion Chart'!$C$3:$M$38,MATCH(SUM(Scores[[#This Row],[MC]:[CRQ]]),'Conversion Chart'!$B$3:$B$38,0),MATCH(Scores[[#This Row],[EIE]],'Conversion Chart'!$C$2:$M$2,0)) -> 63 | H16: 4 | I16: 3 | J16: 1 | K16: 2 | L16: 2 | M16: 4 | N16: 1 | O16: 4 | P16: 1 | Q16: 1 | R16: 4 | S16: 2 | T16: 1 | U16: 4 | V16: 3 | W16: 4 | X16: 2 | Y16: 3 | Z16: 1 | AA16: 3 | AB16: 2 | AC16: 1 | AD16: 3 | AE16: 2 | AF16: 4 | AG16: 3 | AH16: 1 | AI16: 1 | AR16: =IF(H16=VLOOKUP(VALUE(H$1),Questions!$A:$E,5,FALSE),1,0) -> 1 | AS16: =IF(I16=VLOOKUP(VALUE(I$1),Questions!$A:$E,5,FALSE),1,0) -> 1 | AT16: =IF(J16=VLOOKUP(VALUE(J$1),Questions!$A:$E,5,FALSE),1,0) -> 1 | AU16: =IF(K16=VLOOKUP(VALUE(K$1),Questions!$A:$E,5,FALSE),1,0) -> 1 | AV16: =IF(L16=VLOOKUP(VALUE(L$1),Questions!$A:$E,5,FALSE),1,0) -> 1 | AW16: =IF(M16=VLOOKUP(VALUE(M$1),Questions!$A:$E,5,FALSE),1,0) -> 1 | AX16: =IF(N16=VLOOKUP(VALUE(N$1),Questions!$A:$E,5,FALSE),1,0) -> 0 | AY16: =IF(O16=VLOOKUP(VALUE(O$1),Questions!$A:$E,5,FALSE),1,0) -> 0 | ... BS16: =IF(AI16=VLOOKUP(VALUE(AI$1),Questions!$A:$E,5,FALSE),1,0) -> 1
A17: 16 | B17: FALSE | C17: FALSE | D17: =SUM(Scores[[#This Row],[Q1]:[Q28]]) -> 27 | E17: =SUM(Scores[[#This Row],[29]:[34b]]) -> 0 | F17: =Scores[[#This Row],[35]] -> 0 | G17: =INDEX('Conversion Chart'!$C$3:$M$38,MATCH(SUM(Scores[[#This Row],[MC]:[CRQ]]),'Conversion Chart'!$B$3:$B$38,0),MATCH(Scores[[#This Row],[EIE]],'Conversion Chart'!$C$2:$M$2,0)) -> 66 | H17: 4 | I17: 3 | J17: 1 | K17: 2 | L17: 2 | M17: 4 | N17: 3 | O17: 4 | P17: 1 | Q17: 1 | R17: 4 | S17: 2 | T17: 1 | U17: 4 | V17: 3 | W17: 4 | X17: 2 | Y17: 3 | Z17: 2 | AA17: 3 | AB17: 2 | AC17: 1 | AD17: 3 | AE17: 2 | AF17: 4 | AG17: 3 | AH17: 1 | AI17: 1 | AR17: =IF(H17=VLOOKUP(VALUE(H$1),Questions!$A:$E,5,FALSE),1,0) -> 1 | AS17: =IF(I17=VLOOKUP(VALUE(I$1),Questions!$A:$E,5,FALSE),1,0) -> 1 | AT17: =IF(J17=VLOOKUP(VALUE(J$1),Questions!$A:$E,5,FALSE),1,0) -> 1 | AU17: =IF(K17=VLOOKUP(VALUE(K$1),Questions!$A:$E,5,FALSE),1,0) -> 1 | AV17: =IF(L17=VLOOKUP(VALUE(L$1),Questions!$A:$E,5,FALSE),1,0) -> 1 | AW17: =IF(M17=VLOOKUP(VALUE(M$1),Questions!$A:$E,5,FALSE),1,0) -> 1 | AX17: =IF(N17=VLOOKUP(VALUE(N$1),Questions!$A:$E,5,FALSE),1,0) -> 1 | AY17: =IF(O17=VLOOKUP(VALUE(O$1),Questions!$A:$E,5,FALSE),1,0) -> 0 | ... BS17: =IF(AI17=VLOOKUP(VALUE(AI$1),Questions!$A:$E,5,FALSE),1,0) -> 1
A18: 17 | B18: FALSE | C18: FALSE | D18: =SUM(Scores[[#This Row],[Q1]:[Q28]]) -> 24 | E18: =SUM(Scores[[#This Row],[29]:[34b]]) -> 0 | F18: =Scores[[#This Row],[35]] -> 0 | G18: =INDEX('Conversion Chart'!$C$3:$M$38,MATCH(SUM(Scores[[#This Row],[MC]:[CRQ]]),'Conversion Chart'!$B$3:$B$38,0),MATCH(Scores[[#This Row],[EIE]],'Conversion Chart'!$C$2:$M$2,0)) -> 61 | H18: 4 | I18: 3 | J18: 1 | K18: 2 | L18: 2 | M18: 4 | N18: 3 | O18: 1 | P18: 3 | Q18: 1 | R18: 4 | S18: 2 | T18: 1 | U18: 3 | V18: 3 | W18: 4 | X18: 2 | Y18: 3 | Z18: 2 | AA18: 3 | AB18: 2 | AC18: 1 | AD18: 2 | AE18: 2 | AF18: 4 | AG18: 3 | AH18: 1 | AI18: 4 | AR18: =IF(H18=VLOOKUP(VALUE(H$1),Questions!$A:$E,5,FALSE),1,0) -> 1 | AS18: =IF(I18=VLOOKUP(VALUE(I$1),Questions!$A:$E,5,FALSE),1,0) -> 1 | AT18: =IF(J18=VLOOKUP(VALUE(J$1),Questions!$A:$E,5,FALSE),1,0) -> 1 | AU18: =IF(K18=VLOOKUP(VALUE(K$1),Questions!$A:$E,5,FALSE),1,0) -> 1 | AV18: =IF(L18=VLOOKUP(VALUE(L$1),Questions!$A:$E,5,FALSE),1,0) -> 1 | AW18: =IF(M18=VLOOKUP(VALUE(M$1),Questions!$A:$E,5,FALSE),1,0) -> 1 | AX18: =IF(N18=VLOOKUP(VALUE(N$1),Questions!$A:$E,5,FALSE),1,0) -> 1 | AY18: =IF(O18=VLOOKUP(VALUE(O$1),Questions!$A:$E,5,FALSE),1,0) -> 1 | ... BS18: =IF(AI18=VLOOKUP(VALUE(AI$1),Questions!$A:$E,5,FALSE),1,0) -> 0
A19: 18 | B19: FALSE | C19: FALSE | D19: =SUM(Scores[[#This Row],[Q1]:[Q28]]) -> 24 | E19: =SUM(Scores[[#This Row],[29]:[34b]]) -> 0 | F19: =Scores[[#This Row],[35]] -> 0 | G19: =INDEX('Conversion Chart'!$C$3:$M$38,MATCH(SUM(Scores[[#This Row],[MC]:[CRQ]]),'Conversion Chart'!$B$3:$B$38,0),MATCH(Scores[[#This Row],[EIE]],'Conversion Chart'!$C$2:$M$2,0)) -> 61 | H19: 4 | I19: 3 | J19: 3 | K19: 2 | L19: 2 | M19: 4 | N19: 1 | O19: 4 | P19: 1 | Q19: 1 | R19: 4 | S19: 2 | T19: 1 | U19: 4 | V19: 3 | W19: 4 | X19: 2 | Y19: 3 | Z19: 1 | AA19: 3 | AB19: 2 | AC19: 1 | AD19: 3 | AE19: 2 | AF19: 4 | AG19: 3 | AH19: 1 | AI19: 1 | AR19: =IF(H19=VLOOKUP(VALUE(H$1),Questions!$A:$E,5,FALSE),1,0) -> 1 | AS19: =IF(I19=VLOOKUP(VALUE(I$1),Questions!$A:$E,5,FALSE),1,0) -> 1 | AT19: =IF(J19=VLOOKUP(VALUE(J$1),Questions!$A:$E,5,FALSE),1,0) -> 0 | AU19: =IF(K19=VLOOKUP(VALUE(K$1),Questions!$A:$E,5,FALSE),1,0) -> 1 | AV19: =IF(L19=VLOOKUP(VALUE(L$1),Questions!$A:$E,5,FALSE),1,0) -> 1 | AW19: =IF(M19=VLOOKUP(VALUE(M$1),Questions!$A:$E,5,FALSE),1,0) -> 1 | AX19: =IF(N19=VLOOKUP(VALUE(N$1),Questions!$A:$E,5,FALSE),1,0) -> 0 | AY19: =IF(O19=VLOOKUP(VALUE(O$1),Questions!$A:$E,5,FALSE),1,0) -> 0 | ... BS19: =IF(AI19=VLOOKUP(VALUE(AI$1),Questions!$A:$E,5,FALSE),1,0) -> 1
A20: 19 | B20: FALSE | C20: FALSE | D20: =SUM(Scores[[#This Row],[Q1]:[Q28]]) -> 28 | E20: =SUM(Scores[[#This Row],[29]:[34b]]) -> 0 | F20: =Scores[[#This Row],[35]] -> 0 | G20: =INDEX('Conversion Chart'!$C$3:$M$38,MATCH(SUM(Scores[[#This Row],[MC]:[CRQ]]),'Conversion Chart'!$B$3:$B$38,0),MATCH(Scores[[#This Row],[EIE]],'Conversion Chart'!$C$2:$M$2,0)) -> 68 | H20: 4 | I20: 3 | J20: 1 | K20: 2 | L20: 2 | M20: 4 | N20: 3 | O20: 1 | P20: 1 | Q20: 1 | R20: 4 | S20: 2 | T20: 1 | U20: 4 | V20: 3 | W20: 4 | X20: 2 | Y20: 3 | Z20: 2 | AA20: 3 | AB20: 2 | AC20: 1 | AD20: 3 | AE20: 2 | AF20: 4 | AG20: 3 | AH20: 1 | AI20: 1 | AR20: =IF(H20=VLOOKUP(VALUE(H$1),Questions!$A:$E,5,FALSE),1,0) -> 1 | AS20: =IF(I20=VLOOKUP(VALUE(I$1),Questions!$A:$E,5,FALSE),1,0) -> 1 | AT20: =IF(J20=VLOOKUP(VALUE(J$1),Questions!$A:$E,5,FALSE),1,0) -> 1 | AU20: =IF(K20=VLOOKUP(VALUE(K$1),Questions!$A:$E,5,FALSE),1,0) -> 1 | AV20: =IF(L20=VLOOKUP(VALUE(L$1),Questions!$A:$E,5,FALSE),1,0) -> 1 | AW20: =IF(M20=VLOOKUP(VALUE(M$1),Questions!$A:$E,5,FALSE),1,0) -> 1 | AX20: =IF(N20=VLOOKUP(VALUE(N$1),Questions!$A:$E,5,FALSE),1,0) -> 1 | AY20: =IF(O20=VLOOKUP(VALUE(O$1),Questions!$A:$E,5,FALSE),1,0) -> 1 | ... BS20: =IF(AI20=VLOOKUP(VALUE(AI$1),Questions!$A:$E,5,FALSE),1,0) -> 1
A21: 20 | B21: FALSE | C21: FALSE | D21: =SUM(Scores[[#This Row],[Q1]:[Q28]]) -> 20 | E21: =SUM(Scores[[#This Row],[29]:[34b]]) -> 0 | F21: =Scores[[#This Row],[35]] -> 0 | G21: =INDEX('Conversion Chart'!$C$3:$M$38,MATCH(SUM(Scores[[#This Row],[MC]:[CRQ]]),'Conversion Chart'!$B$3:$B$38,0),MATCH(Scores[[#This Row],[EIE]],'Conversion Chart'!$C$2:$M$2,0)) -> 53 | H21: 4 | I21: 3 | J21: 1 | K21: 2 | L21: 1 | M21: 4 | N21: 3 | O21: 1 | P21: 1 | Q21: 4 | R21: 1 | S21: 2 | T21: 1 | U21: 2 | V21: 3 | W21: 4 | X21: 2 | Y21: 2 | Z21: 4 | AA21: 3 | AB21: 4 | AC21: 1 | AD21: 2 | AE21: 2 | AF21: 4 | AG21: 3 | AH21: 1 | AI21: 1 | AR21: =IF(H21=VLOOKUP(VALUE(H$1),Questions!$A:$E,5,FALSE),1,0) -> 1 | AS21: =IF(I21=VLOOKUP(VALUE(I$1),Questions!$A:$E,5,FALSE),1,0) -> 1 | AT21: =IF(J21=VLOOKUP(VALUE(J$1),Questions!$A:$E,5,FALSE),1,0) -> 1 | AU21: =IF(K21=VLOOKUP(VALUE(K$1),Questions!$A:$E,5,FALSE),1,0) -> 1 | AV21: =IF(L21=VLOOKUP(VALUE(L$1),Questions!$A:$E,5,FALSE),1,0) -> 0 | AW21: =IF(M21=VLOOKUP(VALUE(M$1),Questions!$A:$E,5,FALSE),1,0) -> 1 | AX21: =IF(N21=VLOOKUP(VALUE(N$1),Questions!$A:$E,5,FALSE),1,0) -> 1 | AY21: =IF(O21=VLOOKUP(VALUE(O$1),Questions!$A:$E,5,FALSE),1,0) -> 1 | ... BS21: =IF(AI21=VLOOKUP(VALUE(AI$1),Questions!$A:$E,5,FALSE),1,0) -> 1
A22: 21 | B22: FALSE | C22: FALSE | D22: =SUM(Scores[[#This Row],[Q1]:[Q28]]) -> 16 | E22: =SUM(Scores[[#This Row],[29]:[34b]]) -> 0 | F22: =Scores[[#This Row],[35]] -> 0 | G22: =INDEX('Conversion Chart'!$C$3:$M$38,MATCH(SUM(Scores[[#This Row],[MC]:[CRQ]]),'Conversion Chart'!$B$3:$B$38,0),MATCH(Scores[[#This Row],[EIE]],'Conversion Chart'!$C$2:$M$2,0)) -> 45 | H22: 4 | I22: 3 | J22: 1 | K22: 2 | L22: 3 | M22: 4 | N22: 3 | O22: 1 | P22: 3 | Q22: 1 | R22: 4 | S22: 3 | T22: 1 | U22: 3 | V22: 3 | W22: 4 | X22: 3 | Y22: 3 | Z22: 4 | AA22: 2 | AB22: 2 | AC22: 3 | AD22: 4 | AE22: 2 | AF22: 1 | AG22: 3 | AH22: 3 | AI22: 2 | AR22: =IF(H22=VLOOKUP(VALUE(H$1),Questions!$A:$E,5,FALSE),1,0) -> 1 | AS22: =IF(I22=VLOOKUP(VALUE(I$1),Questions!$A:$E,5,FALSE),1,0) -> 1 | AT22: =IF(J22=VLOOKUP(VALUE(J$1),Questions!$A:$E,5,FALSE),1,0) -> 1 | AU22: =IF(K22=VLOOKUP(VALUE(K$1),Questions!$A:$E,5,FALSE),1,0) -> 1 | AV22: =IF(L22=VLOOKUP(VALUE(L$1),Questions!$A:$E,5,FALSE),1,0) -> 0 | AW22: =IF(M22=VLOOKUP(VALUE(M$1),Questions!$A:$E,5,FALSE),1,0) -> 1 | AX22: =IF(N22=VLOOKUP(VALUE(N$1),Questions!$A:$E,5,FALSE),1,0) -> 1 | AY22: =IF(O22=VLOOKUP(VALUE(O$1),Questions!$A:$E,5,FALSE),1,0) -> 1 | ... BS22: =IF(AI22=VLOOKUP(VALUE(AI$1),Questions!$A:$E,5,FALSE),1,0) -> 0
A23: 22 | B23: FALSE | C23: FALSE | D23: =SUM(Scores[[#This Row],[Q1]:[Q28]]) -> 19 | E23: =SUM(Scores[[#This Row],[29]:[34b]]) -> 0 | F23: =Scores[[#This Row],[35]] -> 0 | G23: =INDEX('Conversion Chart'!$C$3:$M$38,MATCH(SUM(Scores[[#This Row],[MC]:[CRQ]]),'Conversion Chart'!$B$3:$B$38,0),MATCH(Scores[[#This Row],[EIE]],'Conversion Chart'!$C$2:$M$2,0)) -> 51 | H23: 4 | I23: 3 | J23: 1 | K23: 2 | L23: 2 | M23: 4 | N23: 3 | O23: 3 | P23: 1 | Q23: 1 | R23: 4 | S23: 2 | T23: 4 | U23: 2 | V23: 3 | W23: 4 | X23: 2 | Y23: 2 | Z23: 1 | AA23: 2 | AB23: 2 | AC23: 3 | AD23: 3 | AE23: 4 | AF23: 4 | AG23: 2 | AH23: 1 | AI23: 1 | AR23: =IF(H23=VLOOKUP(VALUE(H$1),Questions!$A:$E,5,FALSE),1,0) -> 1 | AS23: =IF(I23=VLOOKUP(VALUE(I$1),Questions!$A:$E,5,FALSE),1,0) -> 1 | AT23: =IF(J23=VLOOKUP(VALUE(J$1),Questions!$A:$E,5,FALSE),1,0) -> 1 | AU23: =IF(K23=VLOOKUP(VALUE(K$1),Questions!$A:$E,5,FALSE),1,0) -> 1 | AV23: =IF(L23=VLOOKUP(VALUE(L$1),Questions!$A:$E,5,FALSE),1,0) -> 1 | AW23: =IF(M23=VLOOKUP(VALUE(M$1),Questions!$A:$E,5,FALSE),1,0) -> 1 | AX23: =IF(N23=VLOOKUP(VALUE(N$1),Questions!$A:$E,5,FALSE),1,0) -> 1 | AY23: =IF(O23=VLOOKUP(VALUE(O$1),Questions!$A:$E,5,FALSE),1,0) -> 0 | ... BS23: =IF(AI23=VLOOKUP(VALUE(AI$1),Questions!$A:$E,5,FALSE),1,0) -> 1
A24: 23 | B24: FALSE | C24: FALSE | D24: =SUM(Scores[[#This Row],[Q1]:[Q28]]) -> 15 | E24: =SUM(Scores[[#This Row],[29]:[34b]]) -> 0 | F24: =Scores[[#This Row],[35]] -> 0 | G24: =INDEX('Conversion Chart'!$C$3:$M$38,MATCH(SUM(Scores[[#This Row],[MC]:[CRQ]]),'Conversion Chart'!$B$3:$B$38,0),MATCH(Scores[[#This Row],[EIE]],'Conversion Chart'!$C$2:$M$2,0)) -> 42 | H24: 3 | I24: 3 | J24: 1 | K24: 3 | L24: 2 | M24: 4 | N24: 1 | O24: 1 | P24: 1 | Q24: 1 | R24: 4 | S24: 4 | T24: 2 | U24: 1 | V24: 4 | W24: 1 | X24: 2 | Y24: 1 | Z24: 1 | AA24: 3 | AB24: 4 | AC24: 1 | AD24: 4 | AE24: 2 | AF24: 4 | AG24: 1 | AH24: 1 | AI24: 1 | AR24: =IF(H24=VLOOKUP(VALUE(H$1),Questions!$A:$E,5,FALSE),1,0) -> 0 | AS24: =IF(I24=VLOOKUP(VALUE(I$1),Questions!$A:$E,5,FALSE),1,0) -> 1 | AT24: =IF(J24=VLOOKUP(VALUE(J$1),Questions!$A:$E,5,FALSE),1,0) -> 1 | AU24: =IF(K24=VLOOKUP(VALUE(K$1),Questions!$A:$E,5,FALSE),1,0) -> 0 | AV24: =IF(L24=VLOOKUP(VALUE(L$1),Questions!$A:$E,5,FALSE),1,0) -> 1 | AW24: =IF(M24=VLOOKUP(VALUE(M$1),Questions!$A:$E,5,FALSE),1,0) -> 1 | AX24: =IF(N24=VLOOKUP(VALUE(N$1),Questions!$A:$E,5,FALSE),1,0) -> 0 | AY24: =IF(O24=VLOOKUP(VALUE(O$1),Questions!$A:$E,5,FALSE),1,0) -> 1 | ... BS24: =IF(AI24=VLOOKUP(VALUE(AI$1),Questions!$A:$E,5,FALSE),1,0) -> 1
A25: 24 | B25: FALSE | C25: FALSE | D25: =SUM(Scores[[#This Row],[Q1]:[Q28]]) -> 0 | E25: =SUM(Scores[[#This Row],[29]:[34b]]) -> 0 | F25: =Scores[[#This Row],[35]] -> 0 | G25: =INDEX('Conversion Chart'!$C$3:$M$38,MATCH(SUM(Scores[[#This Row],[MC]:[CRQ]]),'Conversion Chart'!$B$3:$B$38,0),MATCH(Scores[[#This Row],[EIE]],'Conversion Chart'!$C$2:$M$2,0)) -> 0 | AR25: =IF(H25=VLOOKUP(VALUE(H$1),Questions!$A:$E,5,FALSE),1,0) -> 0 | AS25: =IF(I25=VLOOKUP(VALUE(I$1),Questions!$A:$E,5,FALSE),1,0) -> 0 | AT25: =IF(J25=VLOOKUP(VALUE(J$1),Questions!$A:$E,5,FALSE),1,0) -> 0 | AU25: =IF(K25=VLOOKUP(VALUE(K$1),Questions!$A:$E,5,FALSE),1,0) -> 0 | AV25: =IF(L25=VLOOKUP(VALUE(L$1),Questions!$A:$E,5,FALSE),1,0) -> 0 | AW25: =IF(M25=VLOOKUP(VALUE(M$1),Questions!$A:$E,5,FALSE),1,0) -> 0 | AX25: =IF(N25=VLOOKUP(VALUE(N$1),Questions!$A:$E,5,FALSE),1,0) -> 0 | AY25: =IF(O25=VLOOKUP(VALUE(O$1),Questions!$A:$E,5,FALSE),1,0) -> 0 | ... BS25: =IF(AI25=VLOOKUP(VALUE(AI$1),Questions!$A:$E,5,FALSE),1,0) -> 0
A26: 25 | B26: FALSE | C26: FALSE | D26: =SUM(Scores[[#This Row],[Q1]:[Q28]]) -> 17 | E26: =SUM(Scores[[#This Row],[29]:[34b]]) -> 0 | F26: =Scores[[#This Row],[35]] -> 0 | G26: =INDEX('Conversion Chart'!$C$3:$M$38,MATCH(SUM(Scores[[#This Row],[MC]:[CRQ]]),'Conversion Chart'!$B$3:$B$38,0),MATCH(Scores[[#This Row],[EIE]],'Conversion Chart'!$C$2:$M$2,0)) -> 47 | H26: 4 | I26: 3 | J26: 1 | K26: 2 | L26: 3 | M26: 2 | N26: 2 | O26: 1 | P26: 2 | Q26: 1 | R26: 4 | S26: 2 | T26: 1 | U26: 4 | V26: 3 | W26: 1 | X26: 2 | Y26: 2 | Z26: 4 | AA26: 3 | AB26: 2 | AC26: 1 | AD26: 2 | AE26: 2 | AF26: 1 | AG26: 3 | AH26: 4 | AI26: 4 | AR26: =IF(H26=VLOOKUP(VALUE(H$1),Questions!$A:$E,5,FALSE),1,0) -> 1 | AS26: =IF(I26=VLOOKUP(VALUE(I$1),Questions!$A:$E,5,FALSE),1,0) -> 1 | AT26: =IF(J26=VLOOKUP(VALUE(J$1),Questions!$A:$E,5,FALSE),1,0) -> 1 | AU26: =IF(K26=VLOOKUP(VALUE(K$1),Questions!$A:$E,5,FALSE),1,0) -> 1 | AV26: =IF(L26=VLOOKUP(VALUE(L$1),Questions!$A:$E,5,FALSE),1,0) -> 0 | AW26: =IF(M26=VLOOKUP(VALUE(M$1),Questions!$A:$E,5,FALSE),1,0) -> 0 | AX26: =IF(N26=VLOOKUP(VALUE(N$1),Questions!$A:$E,5,FALSE),1,0) -> 0 | AY26: =IF(O26=VLOOKUP(VALUE(O$1),Questions!$A:$E,5,FALSE),1,0) -> 1 | ... BS26: =IF(AI26=VLOOKUP(VALUE(AI$1),Questions!$A:$E,5,FALSE),1,0) -> 0
A27: 26 | B27: FALSE | C27: FALSE | D27: =SUM(Scores[[#This Row],[Q1]:[Q28]]) -> 12 | E27: =SUM(Scores[[#This Row],[29]:[34b]]) -> 0 | F27: =Scores[[#This Row],[35]] -> 0 | G27: =INDEX('Conversion Chart'!$C$3:$M$38,MATCH(SUM(Scores[[#This Row],[MC]:[CRQ]]),'Conversion Chart'!$B$3:$B$38,0),MATCH(Scores[[#This Row],[EIE]],'Conversion Chart'!$C$2:$M$2,0)) -> 35 | H27: 1 | I27: 3 | J27: 1 | K27: 2 | L27: 1 | M27: 4 | N27: 2 | O27: 3 | P27: 4 | Q27: 1 | R27: 4 | S27: 4 | T27: 1 | U27: 2 | V27: 1 | W27: 1 | X27: 2 | Y27: 2 | Z27: 2 | AA27: 3 | AB27: 1 | AC27: 3 | AD27: 2 | AE27: 2 | AF27: 1 | AG27: 4 | AH27: 1 | AI27: 4 | AR27: =IF(H27=VLOOKUP(VALUE(H$1),Questions!$A:$E,5,FALSE),1,0) -> 0 | AS27: =IF(I27=VLOOKUP(VALUE(I$1),Questions!$A:$E,5,FALSE),1,0) -> 1 | AT27: =IF(J27=VLOOKUP(VALUE(J$1),Questions!$A:$E,5,FALSE),1,0) -> 1 | AU27: =IF(K27=VLOOKUP(VALUE(K$1),Questions!$A:$E,5,FALSE),1,0) -> 1 | AV27: =IF(L27=VLOOKUP(VALUE(L$1),Questions!$A:$E,5,FALSE),1,0) -> 0 | AW27: =IF(M27=VLOOKUP(VALUE(M$1),Questions!$A:$E,5,FALSE),1,0) -> 1 | AX27: =IF(N27=VLOOKUP(VALUE(N$1),Questions!$A:$E,5,FALSE),1,0) -> 0 | AY27: =IF(O27=VLOOKUP(VALUE(O$1),Questions!$A:$E,5,FALSE),1,0) -> 0 | ... BS27: =IF(AI27=VLOOKUP(VALUE(AI$1),Questions!$A:$E,5,FALSE),1,0) -> 0
A28: 27 | B28: FALSE | C28: FALSE | D28: =SUM(Scores[[#This Row],[Q1]:[Q28]]) -> 24 | E28: =SUM(Scores[[#This Row],[29]:[34b]]) -> 0 | F28: =Scores[[#This Row],[35]] -> 0 | G28: =INDEX('Conversion Chart'!$C$3:$M$38,MATCH(SUM(Scores[[#This Row],[MC]:[CRQ]]),'Conversion Chart'!$B$3:$B$38,0),MATCH(Scores[[#This Row],[EIE]],'Conversion Chart'!$C$2:$M$2,0)) -> 61 | H28: 4 | I28: 3 | J28: 1 | K28: 2 | L28: 2 | M28: 4 | N28: 3 | O28: 4 | P28: 1 | Q28: 1 | R28: 4 | S28: 3 | T28: 1 | U28: 4 | V28: 3 | W28: 4 | X28: 2 | Y28: 3 | Z28: 2 | AA28: 2 | AB28: 3 | AC28: 1 | AD28: 3 | AE28: 2 | AF28: 4 | AG28: 3 | AH28: 1 | AI28: 1 | AR28: =IF(H28=VLOOKUP(VALUE(H$1),Questions!$A:$E,5,FALSE),1,0) -> 1 | AS28: =IF(I28=VLOOKUP(VALUE(I$1),Questions!$A:$E,5,FALSE),1,0) -> 1 | AT28: =IF(J28=VLOOKUP(VALUE(J$1),Questions!$A:$E,5,FALSE),1,0) -> 1 | AU28: =IF(K28=VLOOKUP(VALUE(K$1),Questions!$A:$E,5,FALSE),1,0) -> 1 | AV28: =IF(L28=VLOOKUP(VALUE(L$1),Questions!$A:$E,5,FALSE),1,0) -> 1 | AW28: =IF(M28=VLOOKUP(VALUE(M$1),Questions!$A:$E,5,FALSE),1,0) -> 1 | AX28: =IF(N28=VLOOKUP(VALUE(N$1),Questions!$A:$E,5,FALSE),1,0) -> 1 | AY28: =IF(O28=VLOOKUP(VALUE(O$1),Questions!$A:$E,5,FALSE),1,0) -> 0 | ... BS28: =IF(AI28=VLOOKUP(VALUE(AI$1),Questions!$A:$E,5,FALSE),1,0) -> 1
A29: 28 | B29: FALSE | C29: FALSE | D29: =SUM(Scores[[#This Row],[Q1]:[Q28]]) -> 12 | E29: =SUM(Scores[[#This Row],[29]:[34b]]) -> 0 | F29: =Scores[[#This Row],[35]] -> 0 | G29: =INDEX('Conversion Chart'!$C$3:$M$38,MATCH(SUM(Scores[[#This Row],[MC]:[CRQ]]),'Conversion Chart'!$B$3:$B$38,0),MATCH(Scores[[#This Row],[EIE]],'Conversion Chart'!$C$2:$M$2,0)) -> 35 | H29: 4 | I29: 3 | J29: 1 | K29: 4 | L29: 1 | M29: 4 | N29: 1 | O29: 3 | P29: 2 | Q29: 1 | R29: 4 | S29: 4 | T29: 1 | U29: 3 | V29: 1 | W29: 2 | X29: 3 | Y29: 1 | Z29: 1 | AA29: 3 | AB29: 4 | AC29: 4 | AD29: 3 | AE29: 2 | AF29: 4 | AG29: 3 | AH29: 4 | AI29: 3 | AR29: =IF(H29=VLOOKUP(VALUE(H$1),Questions!$A:$E,5,FALSE),1,0) -> 1 | AS29: =IF(I29=VLOOKUP(VALUE(I$1),Questions!$A:$E,5,FALSE),1,0) -> 1 | AT29: =IF(J29=VLOOKUP(VALUE(J$1),Questions!$A:$E,5,FALSE),1,0) -> 1 | AU29: =IF(K29=VLOOKUP(VALUE(K$1),Questions!$A:$E,5,FALSE),1,0) -> 0 | AV29: =IF(L29=VLOOKUP(VALUE(L$1),Questions!$A:$E,5,FALSE),1,0) -> 0 | AW29: =IF(M29=VLOOKUP(VALUE(M$1),Questions!$A:$E,5,FALSE),1,0) -> 1 | AX29: =IF(N29=VLOOKUP(VALUE(N$1),Questions!$A:$E,5,FALSE),1,0) -> 0 | AY29: =IF(O29=VLOOKUP(VALUE(O$1),Questions!$A:$E,5,FALSE),1,0) -> 0 | ... BS29: =IF(AI29=VLOOKUP(VALUE(AI$1),Questions!$A:$E,5,FALSE),1,0) -> 0
A30: 29 | B30: FALSE | C30: FALSE | D30: =SUM(Scores[[#This Row],[Q1]:[Q28]]) -> 21 | E30: =SUM(Scores[[#This Row],[29]:[34b]]) -> 0 | F30: =Scores[[#This Row],[35]] -> 0 | G30: =INDEX('Conversion Chart'!$C$3:$M$38,MATCH(SUM(Scores[[#This Row],[MC]:[CRQ]]),'Conversion Chart'!$B$3:$B$38,0),MATCH(Scores[[#This Row],[EIE]],'Conversion Chart'!$C$2:$M$2,0)) -> 55 | H30: 4 | I30: 3 | J30: 1 | K30: 2 | L30: 1 | M30: 4 | N30: 3 | O30: 3 | P30: 1 | Q30: 4 | R30: 4 | S30: 4 | T30: 3 | U30: 4 | V30: 3 | W30: 4 | X30: 2 | Y30: 3 | Z30: 4 | AA30: 3 | AB30: 2 | AC30: 1 | AD30: 3 | AE30: 4 | AF30: 4 | AG30: 3 | AH30: 1 | AI30: 1 | AR30: =IF(H30=VLOOKUP(VALUE(H$1),Questions!$A:$E,5,FALSE),1,0) -> 1 | AS30: =IF(I30=VLOOKUP(VALUE(I$1),Questions!$A:$E,5,FALSE),1,0) -> 1 | AT30: =IF(J30=VLOOKUP(VALUE(J$1),Questions!$A:$E,5,FALSE),1,0) -> 1 | AU30: =IF(K30=VLOOKUP(VALUE(K$1),Questions!$A:$E,5,FALSE),1,0) -> 1 | AV30: =IF(L30=VLOOKUP(VALUE(L$1),Questions!$A:$E,5,FALSE),1,0) -> 0 | AW30: =IF(M30=VLOOKUP(VALUE(M$1),Questions!$A:$E,5,FALSE),1,0) -> 1 | AX30: =IF(N30=VLOOKUP(VALUE(N$1),Questions!$A:$E,5,FALSE),1,0) -> 1 | AY30: =IF(O30=VLOOKUP(VALUE(O$1),Questions!$A:$E,5,FALSE),1,0) -> 0 | ... BS30: =IF(AI30=VLOOKUP(VALUE(AI$1),Questions!$A:$E,5,FALSE),1,0) -> 1
A31: 30 | B31: FALSE | C31: FALSE | D31: =SUM(Scores[[#This Row],[Q1]:[Q28]]) -> 23 | E31: =SUM(Scores[[#This Row],[29]:[34b]]) -> 0 | F31: =Scores[[#This Row],[35]] -> 0 | G31: =INDEX('Conversion Chart'!$C$3:$M$38,MATCH(SUM(Scores[[#This Row],[MC]:[CRQ]]),'Conversion Chart'!$B$3:$B$38,0),MATCH(Scores[[#This Row],[EIE]],'Conversion Chart'!$C$2:$M$2,0)) -> 59 | H31: 4 | I31: 3 | J31: 1 | K31: 2 | L31: 2 | M31: 4 | N31: 3 | O31: 1 | P31: 1 | Q31: 1 | R31: 4 | S31: 2 | T31: 1 | U31: 4 | V31: 1 | W31: 1 | X31: 1 | Y31: 3 | Z31: 4 | AA31: 3 | AB31: 2 | AC31: 1 | AD31: 3 | AE31: 2 | AF31: 4 | AG31: 3 | AH31: 4 | AI31: 1 | AR31: =IF(H31=VLOOKUP(VALUE(H$1),Questions!$A:$E,5,FALSE),1,0) -> 1 | AS31: =IF(I31=VLOOKUP(VALUE(I$1),Questions!$A:$E,5,FALSE),1,0) -> 1 | AT31: =IF(J31=VLOOKUP(VALUE(J$1),Questions!$A:$E,5,FALSE),1,0) -> 1 | AU31: =IF(K31=VLOOKUP(VALUE(K$1),Questions!$A:$E,5,FALSE),1,0) -> 1 | AV31: =IF(L31=VLOOKUP(VALUE(L$1),Questions!$A:$E,5,FALSE),1,0) -> 1 | AW31: =IF(M31=VLOOKUP(VALUE(M$1),Questions!$A:$E,5,FALSE),1,0) -> 1 | AX31: =IF(N31=VLOOKUP(VALUE(N$1),Questions!$A:$E,5,FALSE),1,0) -> 1 | AY31: =IF(O31=VLOOKUP(VALUE(O$1),Questions!$A:$E,5,FALSE),1,0) -> 1 | ... BS31: =IF(AI31=VLOOKUP(VALUE(AI$1),Questions!$A:$E,5,FALSE),1,0) -> 1
A32: 31 | B32: FALSE | C32: FALSE | D32: =SUM(Scores[[#This Row],[Q1]:[Q28]]) -> 27 | E32: =SUM(Scores[[#This Row],[29]:[34b]]) -> 0 | F32: =Scores[[#This Row],[35]] -> 0 | G32: =INDEX('Conversion Chart'!$C$3:$M$38,MATCH(SUM(Scores[[#This Row],[MC]:[CRQ]]),'Conversion Chart'!$B$3:$B$38,0),MATCH(Scores[[#This Row],[EIE]],'Conversion Chart'!$C$2:$M$2,0)) -> 66 | H32: 4 | I32: 3 | J32: 1 | K32: 2 | L32: 2 | M32: 4 | N32: 3 | O32: 3 | P32: 1 | Q32: 1 | R32: 4 | S32: 2 | T32: 1 | U32: 4 | V32: 3 | W32: 4 | X32: 2 | Y32: 3 | Z32: 2 | AA32: 3 | AB32: 2 | AC32: 1 | AD32: 3 | AE32: 2 | AF32: 4 | AG32: 3 | AH32: 1 | AI32: 1 | AR32: =IF(H32=VLOOKUP(VALUE(H$1),Questions!$A:$E,5,FALSE),1,0) -> 1 | AS32: =IF(I32=VLOOKUP(VALUE(I$1),Questions!$A:$E,5,FALSE),1,0) -> 1 | AT32: =IF(J32=VLOOKUP(VALUE(J$1),Questions!$A:$E,5,FALSE),1,0) -> 1 | AU32: =IF(K32=VLOOKUP(VALUE(K$1),Questions!$A:$E,5,FALSE),1,0) -> 1 | AV32: =IF(L32=VLOOKUP(VALUE(L$1),Questions!$A:$E,5,FALSE),1,0) -> 1 | AW32: =IF(M32=VLOOKUP(VALUE(M$1),Questions!$A:$E,5,FALSE),1,0) -> 1 | AX32: =IF(N32=VLOOKUP(VALUE(N$1),Questions!$A:$E,5,FALSE),1,0) -> 1 | AY32: =IF(O32=VLOOKUP(VALUE(O$1),Questions!$A:$E,5,FALSE),1,0) -> 0 | ... BS32: =IF(AI32=VLOOKUP(VALUE(AI$1),Questions!$A:$E,5,FALSE),1,0) -> 1
A33: 32 | B33: FALSE | C33: FALSE | D33: =SUM(Scores[[#This Row],[Q1]:[Q28]]) -> 21 | E33: =SUM(Scores[[#This Row],[29]:[34b]]) -> 0 | F33: =Scores[[#This Row],[35]] -> 0 | G33: =INDEX('Conversion Chart'!$C$3:$M$38,MATCH(SUM(Scores[[#This Row],[MC]:[CRQ]]),'Conversion Chart'!$B$3:$B$38,0),MATCH(Scores[[#This Row],[EIE]],'Conversion Chart'!$C$2:$M$2,0)) -> 55 | H33: 4 | I33: 3 | J33: 1 | K33: 2 | L33: 2 | M33: 4 | N33: 3 | O33: 2 | P33: 1 | Q33: 3 | R33: 1 | S33: 4 | T33: 1 | U33: 4 | V33: 1 | W33: 3 | X33: 1 | Y33: 3 | Z33: 2 | AA33: 3 | AB33: 2 | AC33: 1 | AD33: 3 | AE33: 2 | AF33: 4 | AG33: 3 | AH33: 1 | AI33: 1 | AR33: =IF(H33=VLOOKUP(VALUE(H$1),Questions!$A:$E,5,FALSE),1,0) -> 1 | AS33: =IF(I33=VLOOKUP(VALUE(I$1),Questions!$A:$E,5,FALSE),1,0) -> 1 | AT33: =IF(J33=VLOOKUP(VALUE(J$1),Questions!$A:$E,5,FALSE),1,0) -> 1 | AU33: =IF(K33=VLOOKUP(VALUE(K$1),Questions!$A:$E,5,FALSE),1,0) -> 1 | AV33: =IF(L33=VLOOKUP(VALUE(L$1),Questions!$A:$E,5,FALSE),1,0) -> 1 | AW33: =IF(M33=VLOOKUP(VALUE(M$1),Questions!$A:$E,5,FALSE),1,0) -> 1 | AX33: =IF(N33=VLOOKUP(VALUE(N$1),Questions!$A:$E,5,FALSE),1,0) -> 1 | AY33: =IF(O33=VLOOKUP(VALUE(O$1),Questions!$A:$E,5,FALSE),1,0) -> 0 | ... BS33: =IF(AI33=VLOOKUP(VALUE(AI$1),Questions!$A:$E,5,FALSE),1,0) -> 1
A34: 33 | B34: FALSE | C34: FALSE | D34: =SUM(Scores[[#This Row],[Q1]:[Q28]]) -> 16 | E34: =SUM(Scores[[#This Row],[29]:[34b]]) -> 0 | F34: =Scores[[#This Row],[35]] -> 0 | G34: =INDEX('Conversion Chart'!$C$3:$M$38,MATCH(SUM(Scores[[#This Row],[MC]:[CRQ]]),'Conversion Chart'!$B$3:$B$38,0),MATCH(Scores[[#This Row],[EIE]],'Conversion Chart'!$C$2:$M$2,0)) -> 45 | H34: 4 | I34: 1 | J34: 1 | K34: 2 | L34: 1 | M34: 2 | N34: 3 | O34: 4 | P34: 1 | Q34: 1 | R34: 3 | S34: 4 | T34: 4 | U34: 3 | V34: 1 | W34: 4 | X34: 2 | Y34: 1 | Z34: 2 | AA34: 4 | AB34: 2 | AC34: 1 | AD34: 3 | AE34: 2 | AF34: 4 | AG34: 3 | AH34: 4 | AI34: 1 | AR34: =IF(H34=VLOOKUP(VALUE(H$1),Questions!$A:$E,5,FALSE),1,0) -> 1 | AS34: =IF(I34=VLOOKUP(VALUE(I$1),Questions!$A:$E,5,FALSE),1,0) -> 0 | AT34: =IF(J34=VLOOKUP(VALUE(J$1),Questions!$A:$E,5,FALSE),1,0) -> 1 | AU34: =IF(K34=VLOOKUP(VALUE(K$1),Questions!$A:$E,5,FALSE),1,0) -> 1 | AV34: =IF(L34=VLOOKUP(VALUE(L$1),Questions!$A:$E,5,FALSE),1,0) -> 0 | AW34: =IF(M34=VLOOKUP(VALUE(M$1),Questions!$A:$E,5,FALSE),1,0) -> 0 | AX34: =IF(N34=VLOOKUP(VALUE(N$1),Questions!$A:$E,5,FALSE),1,0) -> 1 | AY34: =IF(O34=VLOOKUP(VALUE(O$1),Questions!$A:$E,5,FALSE),1,0) -> 0 | ... BS34: =IF(AI34=VLOOKUP(VALUE(AI$1),Questions!$A:$E,5,FALSE),1,0) -> 1
A35: 34 | B35: FALSE | C35: FALSE | D35: =SUM(Scores[[#This Row],[Q1]:[Q28]]) -> 26 | E35: =SUM(Scores[[#This Row],[29]:[34b]]) -> 0 | F35: =Scores[[#This Row],[35]] -> 0 | G35: =INDEX('Conversion Chart'!$C$3:$M$38,MATCH(SUM(Scores[[#This Row],[MC]:[CRQ]]),'Conversion Chart'!$B$3:$B$38,0),MATCH(Scores[[#This Row],[EIE]],'Conversion Chart'!$C$2:$M$2,0)) -> 64 | H35: 4 | I35: 3 | J35: 1 | K35: 2 | L35: 2 | M35: 4 | N35: 3 | O35: 3 | P35: 1 | Q35: 1 | R35: 4 | S35: 2 | T35: 1 | U35: 4 | V35: 3 | W35: 4 | X35: 2 | Y35: 3 | Z35: 2 | AA35: 4 | AB35: 2 | AC35: 1 | AD35: 3 | AE35: 2 | AF35: 4 | AG35: 3 | AH35: 1 | AI35: 1 | AR35: =IF(H35=VLOOKUP(VALUE(H$1),Questions!$A:$E,5,FALSE),1,0) -> 1 | AS35: =IF(I35=VLOOKUP(VALUE(I$1),Questions!$A:$E,5,FALSE),1,0) -> 1 | AT35: =IF(J35=VLOOKUP(VALUE(J$1),Questions!$A:$E,5,FALSE),1,0) -> 1 | AU35: =IF(K35=VLOOKUP(VALUE(K$1),Questions!$A:$E,5,FALSE),1,0) -> 1 | AV35: =IF(L35=VLOOKUP(VALUE(L$1),Questions!$A:$E,5,FALSE),1,0) -> 1 | AW35: =IF(M35=VLOOKUP(VALUE(M$1),Questions!$A:$E,5,FALSE),1,0) -> 1 | AX35: =IF(N35=VLOOKUP(VALUE(N$1),Questions!$A:$E,5,FALSE),1,0) -> 1 | AY35: =IF(O35=VLOOKUP(VALUE(O$1),Questions!$A:$E,5,FALSE),1,0) -> 0 | ... BS35: =IF(AI35=VLOOKUP(VALUE(AI$1),Questions!$A:$E,5,FALSE),1,0) -> 1
A36: 35 | B36: FALSE | C36: FALSE | D36: =SUM(Scores[[#This Row],[Q1]:[Q28]]) -> 20 | E36: =SUM(Scores[[#This Row],[29]:[34b]]) -> 0 | F36: =Scores[[#This Row],[35]] -> 0 | G36: =INDEX('Conversion Chart'!$C$3:$M$38,MATCH(SUM(Scores[[#This Row],[MC]:[CRQ]]),'Conversion Chart'!$B$3:$B$38,0),MATCH(Scores[[#This Row],[EIE]],'Conversion Chart'!$C$2:$M$2,0)) -> 53 | H36: 4 | I36: 3 | J36: 1 | K36: 3 | L36: 4 | M36: 4 | N36: 3 | O36: 1 | P36: 4 | Q36: 1 | R36: 4 | S36: 3 | T36: 1 | U36: 4 | V36: 3 | W36: 1 | X36: 2 | Y36: 1 | Z36: 2 | AA36: 1 | AB36: 2 | AC36: 1 | AD36: 3 | AE36: 4 | AF36: 4 | AG36: 3 | AH36: 1 | AI36: 1 | AR36: =IF(H36=VLOOKUP(VALUE(H$1),Questions!$A:$E,5,FALSE),1,0) -> 1 | AS36: =IF(I36=VLOOKUP(VALUE(I$1),Questions!$A:$E,5,FALSE),1,0) -> 1 | AT36: =IF(J36=VLOOKUP(VALUE(J$1),Questions!$A:$E,5,FALSE),1,0) -> 1 | AU36: =IF(K36=VLOOKUP(VALUE(K$1),Questions!$A:$E,5,FALSE),1,0) -> 0 | AV36: =IF(L36=VLOOKUP(VALUE(L$1),Questions!$A:$E,5,FALSE),1,0) -> 0 | AW36: =IF(M36=VLOOKUP(VALUE(M$1),Questions!$A:$E,5,FALSE),1,0) -> 1 | AX36: =IF(N36=VLOOKUP(VALUE(N$1),Questions!$A:$E,5,FALSE),1,0) -> 1 | AY36: =IF(O36=VLOOKUP(VALUE(O$1),Questions!$A:$E,5,FALSE),1,0) -> 1 | ... BS36: =IF(AI36=VLOOKUP(VALUE(AI$1),Questions!$A:$E,5,FALSE),1,0) -> 1
A37: 36 | B37: FALSE | C37: FALSE | D37: =SUM(Scores[[#This Row],[Q1]:[Q28]]) -> 20 | E37: =SUM(Scores[[#This Row],[29]:[34b]]) -> 0 | F37: =Scores[[#This Row],[35]] -> 0 | G37: =INDEX('Conversion Chart'!$C$3:$M$38,MATCH(SUM(Scores[[#This Row],[MC]:[CRQ]]),'Conversion Chart'!$B$3:$B$38,0),MATCH(Scores[[#This Row],[EIE]],'Conversion Chart'!$C$2:$M$2,0)) -> 53 | H37: 4 | I37: 3 | J37: 1 | K37: 3 | L37: 2 | M37: 3 | N37: 1 | O37: 4 | P37: 1 | Q37: 1 | R37: 4 | S37: 3 | T37: 1 | U37: 4 | V37: 1 | W37: 4 | X37: 1 | Y37: 3 | Z37: 2 | AA37: 1 | AB37: 2 | AC37: 1 | AD37: 3 | AE37: 2 | AF37: 4 | AG37: 3 | AH37: 1 | AI37: 1 | AR37: =IF(H37=VLOOKUP(VALUE(H$1),Questions!$A:$E,5,FALSE),1,0) -> 1 | AS37: =IF(I37=VLOOKUP(VALUE(I$1),Questions!$A:$E,5,FALSE),1,0) -> 1 | AT37: =IF(J37=VLOOKUP(VALUE(J$1),Questions!$A:$E,5,FALSE),1,0) -> 1 | AU37: =IF(K37=VLOOKUP(VALUE(K$1),Questions!$A:$E,5,FALSE),1,0) -> 0 | AV37: =IF(L37=VLOOKUP(VALUE(L$1),Questions!$A:$E,5,FALSE),1,0) -> 1 | AW37: =IF(M37=VLOOKUP(VALUE(M$1),Questions!$A:$E,5,FALSE),1,0) -> 0 | AX37: =IF(N37=VLOOKUP(VALUE(N$1),Questions!$A:$E,5,FALSE),1,0) -> 0 | AY37: =IF(O37=VLOOKUP(VALUE(O$1),Questions!$A:$E,5,FALSE),1,0) -> 0 | ... BS37: =IF(AI37=VLOOKUP(VALUE(AI$1),Questions!$A:$E,5,FALSE),1,0) -> 1
... A43: 42 | B43: FALSE | C43: FALSE | D43: =SUM(Scores[[#This Row],[Q1]:[Q28]]) -> 23 | E43: =SUM(Scores[[#This Row],[29]:[34b]]) -> 0 | F43: =Scores[[#This Row],[35]] -> 0 | G43: =INDEX('Conversion Chart'!$C$3:$M$38,MATCH(SUM(Scores[[#This Row],[MC]:[CRQ]]),'Conversion Chart'!$B$3:$B$38,0),MATCH(Scores[[#This Row],[EIE]],'Conversion Chart'!$C$2:$M$2,0)) -> 59 | H43: 4 | I43: 3 | J43: 1 | K43: 3 | L43: 2 | M43: 4 | N43: 3 | O43: 1 | P43: 2 | Q43: 1 | R43: 4 | S43: 4 | T43: 1 | U43: 4 | V43: 4 | W43: 4 | X43: 2 | Y43: 3 | Z43: 4 | AA43: 3 | AB43: 2 | AC43: 1 | AD43: 3 | AE43: 2 | AF43: 4 | AG43: 3 | AH43: 1 | AI43: 1 | AR43: =IF(H43=VLOOKUP(VALUE(H$1),Questions!$A:$E,5,FALSE),1,0) -> 1 | AS43: =IF(I43=VLOOKUP(VALUE(I$1),Questions!$A:$E,5,FALSE),1,0) -> 1 | AT43: =IF(J43=VLOOKUP(VALUE(J$1),Questions!$A:$E,5,FALSE),1,0) -> 1 | AU43: =IF(K43=VLOOKUP(VALUE(K$1),Questions!$A:$E,5,FALSE),1,0) -> 0 | AV43: =IF(L43=VLOOKUP(VALUE(L$1),Questions!$A:$E,5,FALSE),1,0) -> 1 | AW43: =IF(M43=VLOOKUP(VALUE(M$1),Questions!$A:$E,5,FALSE),1,0) -> 1 | AX43: =IF(N43=VLOOKUP(VALUE(N$1),Questions!$A:$E,5,FALSE),1,0) -> 1 | AY43: =IF(O43=VLOOKUP(VALUE(O$1),Questions!$A:$E,5,FALSE),1,0) -> 1 | ... BS43: =IF(AI43=VLOOKUP(VALUE(AI$1),Questions!$A:$E,5,FALSE),1,0) -> 1
A44: 43 | B44: FALSE | C44: FALSE | D44: =SUM(Scores[[#This Row],[Q1]:[Q28]]) -> 0 | E44: =SUM(Scores[[#This Row],[29]:[34b]]) -> 0 | F44: =Scores[[#This Row],[35]] -> 0 | G44: =INDEX('Conversion Chart'!$C$3:$M$38,MATCH(SUM(Scores[[#This Row],[MC]:[CRQ]]),'Conversion Chart'!$B$3:$B$38,0),MATCH(Scores[[#This Row],[EIE]],'Conversion Chart'!$C$2:$M$2,0)) -> 0 | AR44: =IF(H44=VLOOKUP(VALUE(H$1),Questions!$A:$E,5,FALSE),1,0) -> 0 | AS44: =IF(I44=VLOOKUP(VALUE(I$1),Questions!$A:$E,5,FALSE),1,0) -> 0 | AT44: =IF(J44=VLOOKUP(VALUE(J$1),Questions!$A:$E,5,FALSE),1,0) -> 0 | AU44: =IF(K44=VLOOKUP(VALUE(K$1),Questions!$A:$E,5,FALSE),1,0) -> 0 | AV44: =IF(L44=VLOOKUP(VALUE(L$1),Questions!$A:$E,5,FALSE),1,0) -> 0 | AW44: =IF(M44=VLOOKUP(VALUE(M$1),Questions!$A:$E,5,FALSE),1,0) -> 0 | AX44: =IF(N44=VLOOKUP(VALUE(N$1),Questions!$A:$E,5,FALSE),1,0) -> 0 | AY44: =IF(O44=VLOOKUP(VALUE(O$1),Questions!$A:$E,5,FALSE),1,0) -> 0 | ... BS44: =IF(AI44=VLOOKUP(VALUE(AI$1),Questions!$A:$E,5,FALSE),1,0) -> 0
A45: 44 | B45: FALSE | C45: FALSE | D45: =SUM(Scores[[#This Row],[Q1]:[Q28]]) -> 22 | E45: =SUM(Scores[[#This Row],[29]:[34b]]) -> 0 | F45: =Scores[[#This Row],[35]] -> 0 | G45: =INDEX('Conversion Chart'!$C$3:$M$38,MATCH(SUM(Scores[[#This Row],[MC]:[CRQ]]),'Conversion Chart'!$B$3:$B$38,0),MATCH(Scores[[#This Row],[EIE]],'Conversion Chart'!$C$2:$M$2,0)) -> 57 | H45: 4 | I45: 3 | J45: 1 | K45: 2 | L45: 2 | M45: 4 | N45: 3 | O45: 4 | P45: 1 | Q45: 1 | R45: 4 | S45: 3 | T45: 1 | U45: 2 | V45: 1 | W45: 3 | X45: 2 | Y45: 2 | Z45: 2 | AA45: 3 | AB45: 2 | AC45: 1 | AD45: 3 | AE45: 2 | AF45: 4 | AG45: 3 | AH45: 1 | AI45: 1 | AR45: =IF(H45=VLOOKUP(VALUE(H$1),Questions!$A:$E,5,FALSE),1,0) -> 1 | AS45: =IF(I45=VLOOKUP(VALUE(I$1),Questions!$A:$E,5,FALSE),1,0) -> 1 | AT45: =IF(J45=VLOOKUP(VALUE(J$1),Questions!$A:$E,5,FALSE),1,0) -> 1 | AU45: =IF(K45=VLOOKUP(VALUE(K$1),Questions!$A:$E,5,FALSE),1,0) -> 1 | AV45: =IF(L45=VLOOKUP(VALUE(L$1),Questions!$A:$E,5,FALSE),1,0) -> 1 | AW45: =IF(M45=VLOOKUP(VALUE(M$1),Questions!$A:$E,5,FALSE),1,0) -> 1 | AX45: =IF(N45=VLOOKUP(VALUE(N$1),Questions!$A:$E,5,FALSE),1,0) -> 1 | AY45: =IF(O45=VLOOKUP(VALUE(O$1),Questions!$A:$E,5,FALSE),1,0) -> 0 | ... BS45: =IF(AI45=VLOOKUP(VALUE(AI$1),Questions!$A:$E,5,FALSE),1,0) -> 1
A46: 45 | B46: FALSE | C46: FALSE | D46: =SUM(Scores[[#This Row],[Q1]:[Q28]]) -> 13 | E46: =SUM(Scores[[#This Row],[29]:[34b]]) -> 0 | F46: =Scores[[#This Row],[35]] -> 0 | G46: =INDEX('Conversion Chart'!$C$3:$M$38,MATCH(SUM(Scores[[#This Row],[MC]:[CRQ]]),'Conversion Chart'!$B$3:$B$38,0),MATCH(Scores[[#This Row],[EIE]],'Conversion Chart'!$C$2:$M$2,0)) -> 38 | H46: 4 | I46: 3 | J46: 1 | K46: 2 | L46: 4 | M46: 4 | N46: 2 | O46: 3 | P46: 3 | Q46: 4 | R46: 1 | S46: 2 | T46: 3 | U46: 1 | V46: 1 | W46: 4 | X46: 2 | Y46: 3 | Z46: 1 | AA46: 4 | AB46: 2 | AC46: 4 | AD46: 3 | AE46: 1 | AF46: 2 | AG46: 3 | AH46: 4 | AI46: 1 | AR46: =IF(H46=VLOOKUP(VALUE(H$1),Questions!$A:$E,5,FALSE),1,0) -> 1 | AS46: =IF(I46=VLOOKUP(VALUE(I$1),Questions!$A:$E,5,FALSE),1,0) -> 1 | AT46: =IF(J46=VLOOKUP(VALUE(J$1),Questions!$A:$E,5,FALSE),1,0) -> 1 | AU46: =IF(K46=VLOOKUP(VALUE(K$1),Questions!$A:$E,5,FALSE),1,0) -> 1 | AV46: =IF(L46=VLOOKUP(VALUE(L$1),Questions!$A:$E,5,FALSE),1,0) -> 0 | AW46: =IF(M46=VLOOKUP(VALUE(M$1),Questions!$A:$E,5,FALSE),1,0) -> 1 | AX46: =IF(N46=VLOOKUP(VALUE(N$1),Questions!$A:$E,5,FALSE),1,0) -> 0 | AY46: =IF(O46=VLOOKUP(VALUE(O$1),Questions!$A:$E,5,FALSE),1,0) -> 0 | ... BS46: =IF(AI46=VLOOKUP(VALUE(AI$1),Questions!$A:$E,5,FALSE),1,0) -> 1
A47: 46 | B47: FALSE | C47: FALSE | D47: =SUM(Scores[[#This Row],[Q1]:[Q28]]) -> 26 | E47: =SUM(Scores[[#This Row],[29]:[34b]]) -> 0 | F47: =Scores[[#This Row],[35]] -> 0 | G47: =INDEX('Conversion Chart'!$C$3:$M$38,MATCH(SUM(Scores[[#This Row],[MC]:[CRQ]]),'Conversion Chart'!$B$3:$B$38,0),MATCH(Scores[[#This Row],[EIE]],'Conversion Chart'!$C$2:$M$2,0)) -> 64 | H47: 4 | I47: 3 | J47: 1 | K47: 2 | L47: 2 | M47: 4 | N47: 3 | O47: 4 | P47: 1 | Q47: 1 | R47: 4 | S47: 2 | T47: 1 | U47: 4 | V47: 3 | W47: 4 | X47: 2 | Y47: 3 | Z47: 2 | AA47: 3 | AB47: 3 | AC47: 1 | AD47: 3 | AE47: 2 | AF47: 4 | AG47: 3 | AH47: 1 | AI47: 1 | AR47: =IF(H47=VLOOKUP(VALUE(H$1),Questions!$A:$E,5,FALSE),1,0) -> 1 | AS47: =IF(I47=VLOOKUP(VALUE(I$1),Questions!$A:$E,5,FALSE),1,0) -> 1 | AT47: =IF(J47=VLOOKUP(VALUE(J$1),Questions!$A:$E,5,FALSE),1,0) -> 1 | AU47: =IF(K47=VLOOKUP(VALUE(K$1),Questions!$A:$E,5,FALSE),1,0) -> 1 | AV47: =IF(L47=VLOOKUP(VALUE(L$1),Questions!$A:$E,5,FALSE),1,0) -> 1 | AW47: =IF(M47=VLOOKUP(VALUE(M$1),Questions!$A:$E,5,FALSE),1,0) -> 1 | AX47: =IF(N47=VLOOKUP(VALUE(N$1),Questions!$A:$E,5,FALSE),1,0) -> 1 | AY47: =IF(O47=VLOOKUP(VALUE(O$1),Questions!$A:$E,5,FALSE),1,0) -> 0 | ... BS47: =IF(AI47=VLOOKUP(VALUE(AI$1),Questions!$A:$E,5,FALSE),1,0) -> 1
A48: 47 | B48: FALSE | C48: FALSE | D48: =SUM(Scores[[#This Row],[Q1]:[Q28]]) -> 28 | E48: =SUM(Scores[[#This Row],[29]:[34b]]) -> 0 | F48: =Scores[[#This Row],[35]] -> 0 | G48: =INDEX('Conversion Chart'!$C$3:$M$38,MATCH(SUM(Scores[[#This Row],[MC]:[CRQ]]),'Conversion Chart'!$B$3:$B$38,0),MATCH(Scores[[#This Row],[EIE]],'Conversion Chart'!$C$2:$M$2,0)) -> 68 | H48: 4 | I48: 3 | J48: 1 | K48: 2 | L48: 2 | M48: 4 | N48: 3 | O48: 1 | P48: 1 | Q48: 1 | R48: 4 | S48: 2 | T48: 1 | U48: 4 | V48: 3 | W48: 4 | X48: 2 | Y48: 3 | Z48: 2 | AA48: 3 | AB48: 2 | AC48: 1 | AD48: 3 | AE48: 2 | AF48: 4 | AG48: 3 | AH48: 1 | AI48: 1 | AR48: =IF(H48=VLOOKUP(VALUE(H$1),Questions!$A:$E,5,FALSE),1,0) -> 1 | AS48: =IF(I48=VLOOKUP(VALUE(I$1),Questions!$A:$E,5,FALSE),1,0) -> 1 | AT48: =IF(J48=VLOOKUP(VALUE(J$1),Questions!$A:$E,5,FALSE),1,0) -> 1 | AU48: =IF(K48=VLOOKUP(VALUE(K$1),Questions!$A:$E,5,FALSE),1,0) -> 1 | AV48: =IF(L48=VLOOKUP(VALUE(L$1),Questions!$A:$E,5,FALSE),1,0) -> 1 | AW48: =IF(M48=VLOOKUP(VALUE(M$1),Questions!$A:$E,5,FALSE),1,0) -> 1 | AX48: =IF(N48=VLOOKUP(VALUE(N$1),Questions!$A:$E,5,FALSE),1,0) -> 1 | AY48: =IF(O48=VLOOKUP(VALUE(O$1),Questions!$A:$E,5,FALSE),1,0) -> 1 | ... BS48: =IF(AI48=VLOOKUP(VALUE(AI$1),Questions!$A:$E,5,FALSE),1,0) -> 1
A49: 48 | B49: FALSE | C49: FALSE | D49: =SUM(Scores[[#This Row],[Q1]:[Q28]]) -> 21 | E49: =SUM(Scores[[#This Row],[29]:[34b]]) -> 0 | F49: =Scores[[#This Row],[35]] -> 0 | G49: =INDEX('Conversion Chart'!$C$3:$M$38,MATCH(SUM(Scores[[#This Row],[MC]:[CRQ]]),'Conversion Chart'!$B$3:$B$38,0),MATCH(Scores[[#This Row],[EIE]],'Conversion Chart'!$C$2:$M$2,0)) -> 55 | H49: 3 | I49: 3 | J49: 1 | K49: 2 | L49: 2 | M49: 4 | N49: 4 | O49: 4 | P49: 1 | Q49: 3 | R49: 4 | S49: 2 | T49: 1 | U49: 2 | V49: 3 | W49: 4 | X49: 2 | Y49: 3 | Z49: 4 | AA49: 3 | AB49: 2 | AC49: 1 | AD49: 3 | AE49: 2 | AF49: 4 | AG49: 3 | AH49: 1 | AI49: 4 | AR49: =IF(H49=VLOOKUP(VALUE(H$1),Questions!$A:$E,5,FALSE),1,0) -> 0 | AS49: =IF(I49=VLOOKUP(VALUE(I$1),Questions!$A:$E,5,FALSE),1,0) -> 1 | AT49: =IF(J49=VLOOKUP(VALUE(J$1),Questions!$A:$E,5,FALSE),1,0) -> 1 | AU49: =IF(K49=VLOOKUP(VALUE(K$1),Questions!$A:$E,5,FALSE),1,0) -> 1 | AV49: =IF(L49=VLOOKUP(VALUE(L$1),Questions!$A:$E,5,FALSE),1,0) -> 1 | AW49: =IF(M49=VLOOKUP(VALUE(M$1),Questions!$A:$E,5,FALSE),1,0) -> 1 | AX49: =IF(N49=VLOOKUP(VALUE(N$1),Questions!$A:$E,5,FALSE),1,0) -> 0 | AY49: =IF(O49=VLOOKUP(VALUE(O$1),Questions!$A:$E,5,FALSE),1,0) -> 0 | ... BS49: =IF(AI49=VLOOKUP(VALUE(AI$1),Questions!$A:$E,5,FALSE),1,0) -> 0
A50: 49 | B50: FALSE | C50: FALSE | D50: =SUM(Scores[[#This Row],[Q1]:[Q28]]) -> 22 | E50: =SUM(Scores[[#This Row],[29]:[34b]]) -> 0 | F50: =Scores[[#This Row],[35]] -> 0 | G50: =INDEX('Conversion Chart'!$C$3:$M$38,MATCH(SUM(Scores[[#This Row],[MC]:[CRQ]]),'Conversion Chart'!$B$3:$B$38,0),MATCH(Scores[[#This Row],[EIE]],'Conversion Chart'!$C$2:$M$2,0)) -> 57 | H50: 4 | I50: 3 | J50: 1 | K50: 2 | L50: 2 | M50: 4 | N50: 3 | O50: 1 | P50: 2 | Q50: 1 | R50: 4 | S50: 4 | T50: 1 | U50: 4 | V50: 1 | W50: 1 | X50: 2 | Y50: 3 | Z50: 1 | AA50: 3 | AB50: 2 | AC50: 1 | AD50: 3 | AE50: 4 | AF50: 4 | AG50: 3 | AH50: 1 | AI50: 1 | AR50: =IF(H50=VLOOKUP(VALUE(H$1),Questions!$A:$E,5,FALSE),1,0) -> 1 | AS50: =IF(I50=VLOOKUP(VALUE(I$1),Questions!$A:$E,5,FALSE),1,0) -> 1 | AT50: =IF(J50=VLOOKUP(VALUE(J$1),Questions!$A:$E,5,FALSE),1,0) -> 1 | AU50: =IF(K50=VLOOKUP(VALUE(K$1),Questions!$A:$E,5,FALSE),1,0) -> 1 | AV50: =IF(L50=VLOOKUP(VALUE(L$1),Questions!$A:$E,5,FALSE),1,0) -> 1 | AW50: =IF(M50=VLOOKUP(VALUE(M$1),Questions!$A:$E,5,FALSE),1,0) -> 1 | AX50: =IF(N50=VLOOKUP(VALUE(N$1),Questions!$A:$E,5,FALSE),1,0) -> 1 | AY50: =IF(O50=VLOOKUP(VALUE(O$1),Questions!$A:$E,5,FALSE),1,0) -> 1 | ... BS50: =IF(AI50=VLOOKUP(VALUE(AI$1),Questions!$A:$E,5,FALSE),1,0) -> 1
A51: 50 | B51: FALSE | C51: FALSE | D51: =SUM(Scores[[#This Row],[Q1]:[Q28]]) -> 20 | E51: =SUM(Scores[[#This Row],[29]:[34b]]) -> 0 | F51: =Scores[[#This Row],[35]] -> 0 | G51: =INDEX('Conversion Chart'!$C$3:$M$38,MATCH(SUM(Scores[[#This Row],[MC]:[CRQ]]),'Conversion Chart'!$B$3:$B$38,0),MATCH(Scores[[#This Row],[EIE]],'Conversion Chart'!$C$2:$M$2,0)) -> 53 | H51: 4 | I51: 3 | J51: 1 | K51: 2 | L51: 1 | M51: 2 | N51: 3 | O51: 1 | P51: 1 | Q51: 1 | R51: 4 | S51: 4 | T51: 4 | U51: 4 | V51: 3 | W51: 4 | X51: 3 | Y51: 2 | Z51: 2 | AA51: 3 | AB51: 2 | AC51: 2 | AD51: 3 | AE51: 3 | AF51: 4 | AG51: 3 | AH51: 1 | AI51: 1 | AR51: =IF(H51=VLOOKUP(VALUE(H$1),Questions!$A:$E,5,FALSE),1,0) -> 1 | AS51: =IF(I51=VLOOKUP(VALUE(I$1),Questions!$A:$E,5,FALSE),1,0) -> 1 | AT51: =IF(J51=VLOOKUP(VALUE(J$1),Questions!$A:$E,5,FALSE),1,0) -> 1 | AU51: =IF(K51=VLOOKUP(VALUE(K$1),Questions!$A:$E,5,FALSE),1,0) -> 1 | AV51: =IF(L51=VLOOKUP(VALUE(L$1),Questions!$A:$E,5,FALSE),1,0) -> 0 | AW51: =IF(M51=VLOOKUP(VALUE(M$1),Questions!$A:$E,5,FALSE),1,0) -> 0 | AX51: =IF(N51=VLOOKUP(VALUE(N$1),Questions!$A:$E,5,FALSE),1,0) -> 1 | AY51: =IF(O51=VLOOKUP(VALUE(O$1),Questions!$A:$E,5,FALSE),1,0) -> 1 | ... BS51: =IF(AI51=VLOOKUP(VALUE(AI$1),Questions!$A:$E,5,FALSE),1,0) -> 1
A52: 51 | B52: FALSE | C52: FALSE | D52: =SUM(Scores[[#This Row],[Q1]:[Q28]]) -> 22 | E52: =SUM(Scores[[#This Row],[29]:[34b]]) -> 0 | F52: =Scores[[#This Row],[35]] -> 0 | G52: =INDEX('Conversion Chart'!$C$3:$M$38,MATCH(SUM(Scores[[#This Row],[MC]:[CRQ]]),'Conversion Chart'!$B$3:$B$38,0),MATCH(Scores[[#This Row],[EIE]],'Conversion Chart'!$C$2:$M$2,0)) -> 57 | H52: 4 | I52: 3 | J52: 1 | K52: 2 | L52: 2 | M52: 4 | N52: 3 | O52: 1 | P52: 1 | Q52: 1 | R52: 4 | S52: 4 | T52: 4 | U52: 4 | V52: 1 | W52: 4 | X52: 2 | Y52: 2 | Z52: 2 | AA52: 3 | AB52: 2 | AC52: 1 | AD52: 1 | AE52: 4 | AF52: 4 | AG52: 3 | AH52: 1 | AI52: 1 | AR52: =IF(H52=VLOOKUP(VALUE(H$1),Questions!$A:$E,5,FALSE),1,0) -> 1 | AS52: =IF(I52=VLOOKUP(VALUE(I$1),Questions!$A:$E,5,FALSE),1,0) -> 1 | AT52: =IF(J52=VLOOKUP(VALUE(J$1),Questions!$A:$E,5,FALSE),1,0) -> 1 | AU52: =IF(K52=VLOOKUP(VALUE(K$1),Questions!$A:$E,5,FALSE),1,0) -> 1 | AV52: =IF(L52=VLOOKUP(VALUE(L$1),Questions!$A:$E,5,FALSE),1,0) -> 1 | AW52: =IF(M52=VLOOKUP(VALUE(M$1),Questions!$A:$E,5,FALSE),1,0) -> 1 | AX52: =IF(N52=VLOOKUP(VALUE(N$1),Questions!$A:$E,5,FALSE),1,0) -> 1 | AY52: =IF(O52=VLOOKUP(VALUE(O$1),Questions!$A:$E,5,FALSE),1,0) -> 1 | ... BS52: =IF(AI52=VLOOKUP(VALUE(AI$1),Questions!$A:$E,5,FALSE),1,0) -> 1
A53: 52 | B53: FALSE | C53: FALSE | D53: =SUM(Scores[[#This Row],[Q1]:[Q28]]) -> 27 | E53: =SUM(Scores[[#This Row],[29]:[34b]]) -> 0 | F53: =Scores[[#This Row],[35]] -> 0 | G53: =INDEX('Conversion Chart'!$C$3:$M$38,MATCH(SUM(Scores[[#This Row],[MC]:[CRQ]]),'Conversion Chart'!$B$3:$B$38,0),MATCH(Scores[[#This Row],[EIE]],'Conversion Chart'!$C$2:$M$2,0)) -> 66 | H53: 4 | I53: 3 | J53: 1 | K53: 2 | L53: 2 | M53: 4 | N53: 3 | O53: 1 | P53: 1 | Q53: 1 | R53: 4 | S53: 2 | T53: 1 | U53: 4 | V53: 3 | W53: 4 | X53: 2 | Y53: 3 | Z53: 2 | AA53: 3 | AB53: 2 | AC53: 1 | AD53: 3 | AE53: 2 | AF53: 4 | AG53: 2 | AH53: 1 | AI53: 1 | AR53: =IF(H53=VLOOKUP(VALUE(H$1),Questions!$A:$E,5,FALSE),1,0) -> 1 | AS53: =IF(I53=VLOOKUP(VALUE(I$1),Questions!$A:$E,5,FALSE),1,0) -> 1 | AT53: =IF(J53=VLOOKUP(VALUE(J$1),Questions!$A:$E,5,FALSE),1,0) -> 1 | AU53: =IF(K53=VLOOKUP(VALUE(K$1),Questions!$A:$E,5,FALSE),1,0) -> 1 | AV53: =IF(L53=VLOOKUP(VALUE(L$1),Questions!$A:$E,5,FALSE),1,0) -> 1 | AW53: =IF(M53=VLOOKUP(VALUE(M$1),Questions!$A:$E,5,FALSE),1,0) -> 1 | AX53: =IF(N53=VLOOKUP(VALUE(N$1),Questions!$A:$E,5,FALSE),1,0) -> 1 | AY53: =IF(O53=VLOOKUP(VALUE(O$1),Questions!$A:$E,5,FALSE),1,0) -> 1 | ... BS53: =IF(AI53=VLOOKUP(VALUE(AI$1),Questions!$A:$E,5,FALSE),1,0) -> 1
A54: 53 | B54: FALSE | C54: FALSE | D54: =SUM(Scores[[#This Row],[Q1]:[Q28]]) -> 14 | E54: =SUM(Scores[[#This Row],[29]:[34b]]) -> 0 | F54: =Scores[[#This Row],[35]] -> 0 | G54: =INDEX('Conversion Chart'!$C$3:$M$38,MATCH(SUM(Scores[[#This Row],[MC]:[CRQ]]),'Conversion Chart'!$B$3:$B$38,0),MATCH(Scores[[#This Row],[EIE]],'Conversion Chart'!$C$2:$M$2,0)) -> 40 | H54: 4 | I54: 3 | J54: 1 | K54: 2 | L54: 3 | M54: 2 | N54: 3 | O54: 3 | P54: 1 | Q54: 1 | R54: 3 | S54: 4 | T54: 4 | U54: 3 | V54: 3 | W54: 1 | X54: 2 | Y54: 2 | Z54: 1 | AA54: 4 | AB54: 2 | AC54: 4 | AD54: 1 | AE54: 4 | AF54: 4 | AG54: 3 | AH54: 1 | AI54: 1 | AR54: =IF(H54=VLOOKUP(VALUE(H$1),Questions!$A:$E,5,FALSE),1,0) -> 1 | AS54: =IF(I54=VLOOKUP(VALUE(I$1),Questions!$A:$E,5,FALSE),1,0) -> 1 | AT54: =IF(J54=VLOOKUP(VALUE(J$1),Questions!$A:$E,5,FALSE),1,0) -> 1 | AU54: =IF(K54=VLOOKUP(VALUE(K$1),Questions!$A:$E,5,FALSE),1,0) -> 1 | AV54: =IF(L54=VLOOKUP(VALUE(L$1),Questions!$A:$E,5,FALSE),1,0) -> 0 | AW54: =IF(M54=VLOOKUP(VALUE(M$1),Questions!$A:$E,5,FALSE),1,0) -> 0 | AX54: =IF(N54=VLOOKUP(VALUE(N$1),Questions!$A:$E,5,FALSE),1,0) -> 1 | AY54: =IF(O54=VLOOKUP(VALUE(O$1),Questions!$A:$E,5,FALSE),1,0) -> 0 | ... BS54: =IF(AI54=VLOOKUP(VALUE(AI$1),Questions!$A:$E,5,FALSE),1,0) -> 1
A55: 54 | B55: FALSE | C55: FALSE | D55: =SUM(Scores[[#This Row],[Q1]:[Q28]]) -> 19 | E55: =SUM(Scores[[#This Row],[29]:[34b]]) -> 0 | F55: =Scores[[#This Row],[35]] -> 0 | G55: =INDEX('Conversion Chart'!$C$3:$M$38,MATCH(SUM(Scores[[#This Row],[MC]:[CRQ]]),'Conversion Chart'!$B$3:$B$38,0),MATCH(Scores[[#This Row],[EIE]],'Conversion Chart'!$C$2:$M$2,0)) -> 51 | H55: 4 | I55: 3 | J55: 1 | K55: 3 | L55: 1 | M55: 4 | N55: 3 | O55: 3 | P55: 1 | Q55: 4 | R55: 4 | S55: 2 | T55: 1 | U55: 4 | V55: 3 | W55: 1 | X55: 4 | Y55: 2 | Z55: 4 | AA55: 1 | AB55: 2 | AC55: 1 | AD55: 3 | AE55: 2 | AF55: 4 | AG55: 3 | AH55: 1 | AI55: 1 | AR55: =IF(H55=VLOOKUP(VALUE(H$1),Questions!$A:$E,5,FALSE),1,0) -> 1 | AS55: =IF(I55=VLOOKUP(VALUE(I$1),Questions!$A:$E,5,FALSE),1,0) -> 1 | AT55: =IF(J55=VLOOKUP(VALUE(J$1),Questions!$A:$E,5,FALSE),1,0) -> 1 | AU55: =IF(K55=VLOOKUP(VALUE(K$1),Questions!$A:$E,5,FALSE),1,0) -> 0 | AV55: =IF(L55=VLOOKUP(VALUE(L$1),Questions!$A:$E,5,FALSE),1,0) -> 0 | AW55: =IF(M55=VLOOKUP(VALUE(M$1),Questions!$A:$E,5,FALSE),1,0) -> 1 | AX55: =IF(N55=VLOOKUP(VALUE(N$1),Questions!$A:$E,5,FALSE),1,0) -> 1 | AY55: =IF(O55=VLOOKUP(VALUE(O$1),Questions!$A:$E,5,FALSE),1,0) -> 0 | ... BS55: =IF(AI55=VLOOKUP(VALUE(AI$1),Questions!$A:$E,5,FALSE),1,0) -> 1
A56: 55 | B56: FALSE | C56: FALSE | D56: =SUM(Scores[[#This Row],[Q1]:[Q28]]) -> 20 | E56: =SUM(Scores[[#This Row],[29]:[34b]]) -> 0 | F56: =Scores[[#This Row],[35]] -> 0 | G56: =INDEX('Conversion Chart'!$C$3:$M$38,MATCH(SUM(Scores[[#This Row],[MC]:[CRQ]]),'Conversion Chart'!$B$3:$B$38,0),MATCH(Scores[[#This Row],[EIE]],'Conversion Chart'!$C$2:$M$2,0)) -> 53 | H56: 4 | I56: 3 | J56: 1 | K56: 2 | L56: 2 | M56: 4 | N56: 3 | O56: 3 | P56: 1 | Q56: 1 | R56: 4 | S56: 2 | T56: 3 | U56: 4 | V56: 4 | W56: 1 | X56: 2 | Y56: 3 | Z56: 2 | AA56: 3 | AB56: 3 | AC56: 2 | AD56: 3 | AE56: 4 | AF56: 4 | AG56: 2 | AH56: 1 | AI56: 1 | AR56: =IF(H56=VLOOKUP(VALUE(H$1),Questions!$A:$E,5,FALSE),1,0) -> 1 | AS56: =IF(I56=VLOOKUP(VALUE(I$1),Questions!$A:$E,5,FALSE),1,0) -> 1 | AT56: =IF(J56=VLOOKUP(VALUE(J$1),Questions!$A:$E,5,FALSE),1,0) -> 1 | AU56: =IF(K56=VLOOKUP(VALUE(K$1),Questions!$A:$E,5,FALSE),1,0) -> 1 | AV56: =IF(L56=VLOOKUP(VALUE(L$1),Questions!$A:$E,5,FALSE),1,0) -> 1 | AW56: =IF(M56=VLOOKUP(VALUE(M$1),Questions!$A:$E,5,FALSE),1,0) -> 1 | AX56: =IF(N56=VLOOKUP(VALUE(N$1),Questions!$A:$E,5,FALSE),1,0) -> 1 | AY56: =IF(O56=VLOOKUP(VALUE(O$1),Questions!$A:$E,5,FALSE),1,0) -> 0 | ... BS56: =IF(AI56=VLOOKUP(VALUE(AI$1),Questions!$A:$E,5,FALSE),1,0) -> 1
... A69: 68 | B69: FALSE | C69: FALSE | D69: =SUM(Scores[[#This Row],[Q1]:[Q28]]) -> 23 | E69: =SUM(Scores[[#This Row],[29]:[34b]]) -> 0 | F69: =Scores[[#This Row],[35]] -> 0 | G69: =INDEX('Conversion Chart'!$C$3:$M$38,MATCH(SUM(Scores[[#This Row],[MC]:[CRQ]]),'Conversion Chart'!$B$3:$B$38,0),MATCH(Scores[[#This Row],[EIE]],'Conversion Chart'!$C$2:$M$2,0)) -> 59 | H69: 4 | I69: 3 | J69: 1 | K69: 2 | L69: 2 | M69: 4 | N69: 3 | O69: 1 | P69: 1 | Q69: 2 | R69: 4 | S69: 2 | T69: 1 | U69: 2 | V69: 3 | W69: 4 | X69: 2 | Y69: 1 | Z69: 1 | AA69: 1 | AB69: 2 | AC69: 1 | AD69: 3 | AE69: 2 | AF69: 4 | AG69: 3 | AH69: 1 | AI69: 1 | AR69: =IF(H69=VLOOKUP(VALUE(H$1),Questions!$A:$E,5,FALSE),1,0) -> 1 | AS69: =IF(I69=VLOOKUP(VALUE(I$1),Questions!$A:$E,5,FALSE),1,0) -> 1 | AT69: =IF(J69=VLOOKUP(VALUE(J$1),Questions!$A:$E,5,FALSE),1,0) -> 1 | AU69: =IF(K69=VLOOKUP(VALUE(K$1),Questions!$A:$E,5,FALSE),1,0) -> 1 | AV69: =IF(L69=VLOOKUP(VALUE(L$1),Questions!$A:$E,5,FALSE),1,0) -> 1 | AW69: =IF(M69=VLOOKUP(VALUE(M$1),Questions!$A:$E,5,FALSE),1,0) -> 1 | AX69: =IF(N69=VLOOKUP(VALUE(N$1),Questions!$A:$E,5,FALSE),1,0) -> 1 | AY69: =IF(O69=VLOOKUP(VALUE(O$1),Questions!$A:$E,5,FALSE),1,0) -> 1 | ... BS69: =IF(AI69=VLOOKUP(VALUE(AI$1),Questions!$A:$E,5,FALSE),1,0) -> 1
A70: 69 | B70: FALSE | C70: FALSE | D70: =SUM(Scores[[#This Row],[Q1]:[Q28]]) -> 0 | E70: =SUM(Scores[[#This Row],[29]:[34b]]) -> 0 | F70: =Scores[[#This Row],[35]] -> 0 | G70: =INDEX('Conversion Chart'!$C$3:$M$38,MATCH(SUM(Scores[[#This Row],[MC]:[CRQ]]),'Conversion Chart'!$B$3:$B$38,0),MATCH(Scores[[#This Row],[EIE]],'Conversion Chart'!$C$2:$M$2,0)) -> 0 | AR70: =IF(H70=VLOOKUP(VALUE(H$1),Questions!$A:$E,5,FALSE),1,0) -> 0 | AS70: =IF(I70=VLOOKUP(VALUE(I$1),Questions!$A:$E,5,FALSE),1,0) -> 0 | AT70: =IF(J70=VLOOKUP(VALUE(J$1),Questions!$A:$E,5,FALSE),1,0) -> 0 | AU70: =IF(K70=VLOOKUP(VALUE(K$1),Questions!$A:$E,5,FALSE),1,0) -> 0 | AV70: =IF(L70=VLOOKUP(VALUE(L$1),Questions!$A:$E,5,FALSE),1,0) -> 0 | AW70: =IF(M70=VLOOKUP(VALUE(M$1),Questions!$A:$E,5,FALSE),1,0) -> 0 | AX70: =IF(N70=VLOOKUP(VALUE(N$1),Questions!$A:$E,5,FALSE),1,0) -> 0 | AY70: =IF(O70=VLOOKUP(VALUE(O$1),Questions!$A:$E,5,FALSE),1,0) -> 0 | ... BS70: =IF(AI70=VLOOKUP(VALUE(AI$1),Questions!$A:$E,5,FALSE),1,0) -> 0
A71: 70 | B71: FALSE | C71: FALSE | D71: =SUM(Scores[[#This Row],[Q1]:[Q28]]) -> 20 | E71: =SUM(Scores[[#This Row],[29]:[34b]]) -> 0 | F71: =Scores[[#This Row],[35]] -> 0 | G71: =INDEX('Conversion Chart'!$C$3:$M$38,MATCH(SUM(Scores[[#This Row],[MC]:[CRQ]]),'Conversion Chart'!$B$3:$B$38,0),MATCH(Scores[[#This Row],[EIE]],'Conversion Chart'!$C$2:$M$2,0)) -> 53 | H71: 4 | I71: 3 | J71: 1 | K71: 2 | L71: 2 | M71: 4 | N71: 4 | O71: 1 | P71: 1 | Q71: 1 | R71: 4 | S71: 2 | T71: 1 | U71: 2 | V71: 1 | W71: 4 | X71: 2 | Y71: 3 | Z71: 3 | AA71: 4 | AB71: 4 | AC71: 2 | AD71: 3 | AE71: 2 | AF71: 4 | AG71: 3 | AH71: 2 | AI71: 1 | AR71: =IF(H71=VLOOKUP(VALUE(H$1),Questions!$A:$E,5,FALSE),1,0) -> 1 | AS71: =IF(I71=VLOOKUP(VALUE(I$1),Questions!$A:$E,5,FALSE),1,0) -> 1 | AT71: =IF(J71=VLOOKUP(VALUE(J$1),Questions!$A:$E,5,FALSE),1,0) -> 1 | AU71: =IF(K71=VLOOKUP(VALUE(K$1),Questions!$A:$E,5,FALSE),1,0) -> 1 | AV71: =IF(L71=VLOOKUP(VALUE(L$1),Questions!$A:$E,5,FALSE),1,0) -> 1 | AW71: =IF(M71=VLOOKUP(VALUE(M$1),Questions!$A:$E,5,FALSE),1,0) -> 1 | AX71: =IF(N71=VLOOKUP(VALUE(N$1),Questions!$A:$E,5,FALSE),1,0) -> 0 | AY71: =IF(O71=VLOOKUP(VALUE(O$1),Questions!$A:$E,5,FALSE),1,0) -> 1 | ... BS71: =IF(AI71=VLOOKUP(VALUE(AI$1),Questions!$A:$E,5,FALSE),1,0) -> 1
A72: 71 | B72: FALSE | C72: FALSE | D72: =SUM(Scores[[#This Row],[Q1]:[Q28]]) -> 26 | E72: =SUM(Scores[[#This Row],[29]:[34b]]) -> 0 | F72: =Scores[[#This Row],[35]] -> 0 | G72: =INDEX('Conversion Chart'!$C$3:$M$38,MATCH(SUM(Scores[[#This Row],[MC]:[CRQ]]),'Conversion Chart'!$B$3:$B$38,0),MATCH(Scores[[#This Row],[EIE]],'Conversion Chart'!$C$2:$M$2,0)) -> 64 | H72: 4 | I72: 3 | J72: 1 | K72: 2 | L72: 2 | M72: 4 | N72: 3 | O72: 1 | P72: 1 | Q72: 1 | R72: 4 | S72: 2 | T72: 1 | U72: 4 | V72: 3 | W72: 4 | X72: 2 | Y72: 3 | Z72: 1 | AA72: 1 | AB72: 2 | AC72: 1 | AD72: 3 | AE72: 2 | AF72: 4 | AG72: 3 | AH72: 1 | AI72: 1 | AR72: =IF(H72=VLOOKUP(VALUE(H$1),Questions!$A:$E,5,FALSE),1,0) -> 1 | AS72: =IF(I72=VLOOKUP(VALUE(I$1),Questions!$A:$E,5,FALSE),1,0) -> 1 | AT72: =IF(J72=VLOOKUP(VALUE(J$1),Questions!$A:$E,5,FALSE),1,0) -> 1 | AU72: =IF(K72=VLOOKUP(VALUE(K$1),Questions!$A:$E,5,FALSE),1,0) -> 1 | AV72: =IF(L72=VLOOKUP(VALUE(L$1),Questions!$A:$E,5,FALSE),1,0) -> 1 | AW72: =IF(M72=VLOOKUP(VALUE(M$1),Questions!$A:$E,5,FALSE),1,0) -> 1 | AX72: =IF(N72=VLOOKUP(VALUE(N$1),Questions!$A:$E,5,FALSE),1,0) -> 1 | AY72: =IF(O72=VLOOKUP(VALUE(O$1),Questions!$A:$E,5,FALSE),1,0) -> 1 | ... BS72: =IF(AI72=VLOOKUP(VALUE(AI$1),Questions!$A:$E,5,FALSE),1,0) -> 1
A73: 72 | B73: FALSE | C73: FALSE | D73: =SUM(Scores[[#This Row],[Q1]:[Q28]]) -> 24 | E73: =SUM(Scores[[#This Row],[29]:[34b]]) -> 0 | F73: =Scores[[#This Row],[35]] -> 0 | G73: =INDEX('Conversion Chart'!$C$3:$M$38,MATCH(SUM(Scores[[#This Row],[MC]:[CRQ]]),'Conversion Chart'!$B$3:$B$38,0),MATCH(Scores[[#This Row],[EIE]],'Conversion Chart'!$C$2:$M$2,0)) -> 61 | H73: 4 | I73: 3 | J73: 1 | K73: 1 | L73: 2 | M73: 4 | N73: 3 | O73: 1 | P73: 1 | Q73: 3 | R73: 4 | S73: 2 | T73: 1 | U73: 4 | V73: 3 | W73: 4 | X73: 2 | Y73: 3 | Z73: 2 | AA73: 3 | AB73: 2 | AC73: 1 | AD73: 3 | AE73: 4 | AF73: 4 | AG73: 4 | AH73: 1 | AI73: 1 | AR73: =IF(H73=VLOOKUP(VALUE(H$1),Questions!$A:$E,5,FALSE),1,0) -> 1 | AS73: =IF(I73=VLOOKUP(VALUE(I$1),Questions!$A:$E,5,FALSE),1,0) -> 1 | AT73: =IF(J73=VLOOKUP(VALUE(J$1),Questions!$A:$E,5,FALSE),1,0) -> 1 | AU73: =IF(K73=VLOOKUP(VALUE(K$1),Questions!$A:$E,5,FALSE),1,0) -> 0 | AV73: =IF(L73=VLOOKUP(VALUE(L$1),Questions!$A:$E,5,FALSE),1,0) -> 1 | AW73: =IF(M73=VLOOKUP(VALUE(M$1),Questions!$A:$E,5,FALSE),1,0) -> 1 | AX73: =IF(N73=VLOOKUP(VALUE(N$1),Questions!$A:$E,5,FALSE),1,0) -> 1 | AY73: =IF(O73=VLOOKUP(VALUE(O$1),Questions!$A:$E,5,FALSE),1,0) -> 1 | ... BS73: =IF(AI73=VLOOKUP(VALUE(AI$1),Questions!$A:$E,5,FALSE),1,0) -> 1
A74: 73 | B74: FALSE | C74: TRUE | D74: =SUM(Scores[[#This Row],[Q1]:[Q28]]) -> 23 | E74: =SUM(Scores[[#This Row],[29]:[34b]]) -> 0 | F74: =Scores[[#This Row],[35]] -> 0 | G74: =INDEX('Conversion Chart'!$C$3:$M$38,MATCH(SUM(Scores[[#This Row],[MC]:[CRQ]]),'Conversion Chart'!$B$3:$B$38,0),MATCH(Scores[[#This Row],[EIE]],'Conversion Chart'!$C$2:$M$2,0)) -> 59 | H74: 4 | I74: 3 | J74: 1 | K74: 2 | L74: 2 | M74: 4 | N74: 3 | O74: 4 | P74: 2 | Q74: 2 | R74: 4 | S74: 2 | T74: 1 | U74: 4 | V74: 1 | W74: 4 | X74: 2 | Y74: 3 | Z74: 2 | AA74: 3 | AB74: 2 | AC74: 1 | AD74: 3 | AE74: 2 | AF74: 4 | AG74: 2 | AH74: 1 | AI74: 1 | AR74: =IF(H74=VLOOKUP(VALUE(H$1),Questions!$A:$E,5,FALSE),1,0) -> 1 | AS74: =IF(I74=VLOOKUP(VALUE(I$1),Questions!$A:$E,5,FALSE),1,0) -> 1 | AT74: =IF(J74=VLOOKUP(VALUE(J$1),Questions!$A:$E,5,FALSE),1,0) -> 1 | AU74: =IF(K74=VLOOKUP(VALUE(K$1),Questions!$A:$E,5,FALSE),1,0) -> 1 | AV74: =IF(L74=VLOOKUP(VALUE(L$1),Questions!$A:$E,5,FALSE),1,0) -> 1 | AW74: =IF(M74=VLOOKUP(VALUE(M$1),Questions!$A:$E,5,FALSE),1,0) -> 1 | AX74: =IF(N74=VLOOKUP(VALUE(N$1),Questions!$A:$E,5,FALSE),1,0) -> 1 | AY74: =IF(O74=VLOOKUP(VALUE(O$1),Questions!$A:$E,5,FALSE),1,0) -> 0 | ... BS74: =IF(AI74=VLOOKUP(VALUE(AI$1),Questions!$A:$E,5,FALSE),1,0) -> 1
A75: 74 | B75: FALSE | C75: FALSE | D75: =SUM(Scores[[#This Row],[Q1]:[Q28]]) -> 18 | E75: =SUM(Scores[[#This Row],[29]:[34b]]) -> 0 | F75: =Scores[[#This Row],[35]] -> 0 | G75: =INDEX('Conversion Chart'!$C$3:$M$38,MATCH(SUM(Scores[[#This Row],[MC]:[CRQ]]),'Conversion Chart'!$B$3:$B$38,0),MATCH(Scores[[#This Row],[EIE]],'Conversion Chart'!$C$2:$M$2,0)) -> 49 | H75: 4 | I75: 3 | J75: 1 | K75: 4 | L75: 2 | M75: 4 | N75: 3 | O75: 4 | P75: 3 | Q75: 1 | R75: 4 | S75: 3 | T75: 2 | U75: 4 | V75: 2 | W75: 4 | X75: 2 | Y75: 1 | Z75: 4 | AA75: 3 | AB75: 4 | AC75: 2 | AD75: 3 | AE75: 2 | AF75: 4 | AG75: 3 | AH75: 1 | AI75: 1 | AR75: =IF(H75=VLOOKUP(VALUE(H$1),Questions!$A:$E,5,FALSE),1,0) -> 1 | AS75: =IF(I75=VLOOKUP(VALUE(I$1),Questions!$A:$E,5,FALSE),1,0) -> 1 | AT75: =IF(J75=VLOOKUP(VALUE(J$1),Questions!$A:$E,5,FALSE),1,0) -> 1 | AU75: =IF(K75=VLOOKUP(VALUE(K$1),Questions!$A:$E,5,FALSE),1,0) -> 0 | AV75: =IF(L75=VLOOKUP(VALUE(L$1),Questions!$A:$E,5,FALSE),1,0) -> 1 | AW75: =IF(M75=VLOOKUP(VALUE(M$1),Questions!$A:$E,5,FALSE),1,0) -> 1 | AX75: =IF(N75=VLOOKUP(VALUE(N$1),Questions!$A:$E,5,FALSE),1,0) -> 1 | AY75: =IF(O75=VLOOKUP(VALUE(O$1),Questions!$A:$E,5,FALSE),1,0) -> 0 | ... BS75: =IF(AI75=VLOOKUP(VALUE(AI$1),Questions!$A:$E,5,FALSE),1,0) -> 1
A76: 75 | B76: FALSE | C76: FALSE | D76: =SUM(Scores[[#This Row],[Q1]:[Q28]]) -> 17 | E76: =SUM(Scores[[#This Row],[29]:[34b]]) -> 0 | F76: =Scores[[#This Row],[35]] -> 0 | G76: =INDEX('Conversion Chart'!$C$3:$M$38,MATCH(SUM(Scores[[#This Row],[MC]:[CRQ]]),'Conversion Chart'!$B$3:$B$38,0),MATCH(Scores[[#This Row],[EIE]],'Conversion Chart'!$C$2:$M$2,0)) -> 47 | H76: 4 | I76: 3 | J76: 1 | K76: 4 | L76: 2 | M76: 4 | N76: 3 | O76: 4 | P76: 1 | Q76: 1 | R76: 4 | S76: 4 | T76: 2 | U76: 4 | V76: 2 | W76: 1 | X76: 2 | Y76: 1 | Z76: 4 | AA76: 3 | AB76: 4 | AC76: 2 | AD76: 3 | AE76: 4 | AF76: 4 | AG76: 3 | AH76: 1 | AI76: 1 | AR76: =IF(H76=VLOOKUP(VALUE(H$1),Questions!$A:$E,5,FALSE),1,0) -> 1 | AS76: =IF(I76=VLOOKUP(VALUE(I$1),Questions!$A:$E,5,FALSE),1,0) -> 1 | AT76: =IF(J76=VLOOKUP(VALUE(J$1),Questions!$A:$E,5,FALSE),1,0) -> 1 | AU76: =IF(K76=VLOOKUP(VALUE(K$1),Questions!$A:$E,5,FALSE),1,0) -> 0 | AV76: =IF(L76=VLOOKUP(VALUE(L$1),Questions!$A:$E,5,FALSE),1,0) -> 1 | AW76: =IF(M76=VLOOKUP(VALUE(M$1),Questions!$A:$E,5,FALSE),1,0) -> 1 | AX76: =IF(N76=VLOOKUP(VALUE(N$1),Questions!$A:$E,5,FALSE),1,0) -> 1 | AY76: =IF(O76=VLOOKUP(VALUE(O$1),Questions!$A:$E,5,FALSE),1,0) -> 0 | ... BS76: =IF(AI76=VLOOKUP(VALUE(AI$1),Questions!$A:$E,5,FALSE),1,0) -> 1
A77: 76 | B77: FALSE | C77: FALSE | D77: =SUM(Scores[[#This Row],[Q1]:[Q28]]) -> 18 | E77: =SUM(Scores[[#This Row],[29]:[34b]]) -> 0 | F77: =Scores[[#This Row],[35]] -> 0 | G77: =INDEX('Conversion Chart'!$C$3:$M$38,MATCH(SUM(Scores[[#This Row],[MC]:[CRQ]]),'Conversion Chart'!$B$3:$B$38,0),MATCH(Scores[[#This Row],[EIE]],'Conversion Chart'!$C$2:$M$2,0)) -> 49 | H77: 4 | I77: 3 | J77: 1 | K77: 2 | L77: 3 | M77: 2 | N77: 3 | O77: 1 | P77: 1 | Q77: 3 | R77: 4 | S77: 4 | T77: 1 | U77: 2 | V77: 1 | W77: 4 | X77: 1 | Y77: 3 | Z77: 2 | AA77: 1 | AB77: 2 | AC77: 4 | AD77: 3 | AE77: 2 | AF77: 1 | AG77: 3 | AH77: 1 | AI77: 1 | AR77: =IF(H77=VLOOKUP(VALUE(H$1),Questions!$A:$E,5,FALSE),1,0) -> 1 | AS77: =IF(I77=VLOOKUP(VALUE(I$1),Questions!$A:$E,5,FALSE),1,0) -> 1 | AT77: =IF(J77=VLOOKUP(VALUE(J$1),Questions!$A:$E,5,FALSE),1,0) -> 1 | AU77: =IF(K77=VLOOKUP(VALUE(K$1),Questions!$A:$E,5,FALSE),1,0) -> 1 | AV77: =IF(L77=VLOOKUP(VALUE(L$1),Questions!$A:$E,5,FALSE),1,0) -> 0 | AW77: =IF(M77=VLOOKUP(VALUE(M$1),Questions!$A:$E,5,FALSE),1,0) -> 0 | AX77: =IF(N77=VLOOKUP(VALUE(N$1),Questions!$A:$E,5,FALSE),1,0) -> 1 | AY77: =IF(O77=VLOOKUP(VALUE(O$1),Questions!$A:$E,5,FALSE),1,0) -> 1 | ... BS77: =IF(AI77=VLOOKUP(VALUE(AI$1),Questions!$A:$E,5,FALSE),1,0) -> 1
A78: 77 | B78: FALSE | C78: FALSE | D78: =SUM(Scores[[#This Row],[Q1]:[Q28]]) -> 17 | E78: =SUM(Scores[[#This Row],[29]:[34b]]) -> 0 | F78: =Scores[[#This Row],[35]] -> 0 | G78: =INDEX('Conversion Chart'!$C$3:$M$38,MATCH(SUM(Scores[[#This Row],[MC]:[CRQ]]),'Conversion Chart'!$B$3:$B$38,0),MATCH(Scores[[#This Row],[EIE]],'Conversion Chart'!$C$2:$M$2,0)) -> 47 | H78: 4 | I78: 3 | J78: 1 | K78: 2 | L78: 4 | M78: 4 | N78: 2 | O78: 1 | P78: 1 | Q78: 2 | R78: 4 | S78: 4 | T78: 4 | U78: 3 | V78: 1 | W78: 2 | X78: 2 | Y78: 1 | Z78: 2 | AA78: 3 | AB78: 4 | AC78: 1 | AD78: 3 | AE78: 4 | AF78: 4 | AG78: 3 | AH78: 1 | AI78: 1 | AR78: =IF(H78=VLOOKUP(VALUE(H$1),Questions!$A:$E,5,FALSE),1,0) -> 1 | AS78: =IF(I78=VLOOKUP(VALUE(I$1),Questions!$A:$E,5,FALSE),1,0) -> 1 | AT78: =IF(J78=VLOOKUP(VALUE(J$1),Questions!$A:$E,5,FALSE),1,0) -> 1 | AU78: =IF(K78=VLOOKUP(VALUE(K$1),Questions!$A:$E,5,FALSE),1,0) -> 1 | AV78: =IF(L78=VLOOKUP(VALUE(L$1),Questions!$A:$E,5,FALSE),1,0) -> 0 | AW78: =IF(M78=VLOOKUP(VALUE(M$1),Questions!$A:$E,5,FALSE),1,0) -> 1 | AX78: =IF(N78=VLOOKUP(VALUE(N$1),Questions!$A:$E,5,FALSE),1,0) -> 0 | AY78: =IF(O78=VLOOKUP(VALUE(O$1),Questions!$A:$E,5,FALSE),1,0) -> 1 | ... BS78: =IF(AI78=VLOOKUP(VALUE(AI$1),Questions!$A:$E,5,FALSE),1,0) -> 1
A79: 78 | B79: FALSE | C79: TRUE | D79: =SUM(Scores[[#This Row],[Q1]:[Q28]]) -> 17 | E79: =SUM(Scores[[#This Row],[29]:[34b]]) -> 0 | F79: =Scores[[#This Row],[35]] -> 0 | G79: =INDEX('Conversion Chart'!$C$3:$M$38,MATCH(SUM(Scores[[#This Row],[MC]:[CRQ]]),'Conversion Chart'!$B$3:$B$38,0),MATCH(Scores[[#This Row],[EIE]],'Conversion Chart'!$C$2:$M$2,0)) -> 47 | H79: 4 | I79: 3 | J79: 1 | K79: 2 | L79: 4 | M79: 4 | N79: 3 | O79: 3 | P79: 2 | Q79: 2 | R79: 4 | S79: 4 | T79: 1 | U79: 2 | V79: 3 | W79: 3 | X79: 1 | Y79: 3 | Z79: 2 | AA79: 1 | AB79: 4 | AC79: 1 | AD79: 3 | AE79: 4 | AF79: 4 | AG79: 3 | AH79: 1 | AI79: 1 | AR79: =IF(H79=VLOOKUP(VALUE(H$1),Questions!$A:$E,5,FALSE),1,0) -> 1 | AS79: =IF(I79=VLOOKUP(VALUE(I$1),Questions!$A:$E,5,FALSE),1,0) -> 1 | AT79: =IF(J79=VLOOKUP(VALUE(J$1),Questions!$A:$E,5,FALSE),1,0) -> 1 | AU79: =IF(K79=VLOOKUP(VALUE(K$1),Questions!$A:$E,5,FALSE),1,0) -> 1 | AV79: =IF(L79=VLOOKUP(VALUE(L$1),Questions!$A:$E,5,FALSE),1,0) -> 0 | AW79: =IF(M79=VLOOKUP(VALUE(M$1),Questions!$A:$E,5,FALSE),1,0) -> 1 | AX79: =IF(N79=VLOOKUP(VALUE(N$1),Questions!$A:$E,5,FALSE),1,0) -> 1 | AY79: =IF(O79=VLOOKUP(VALUE(O$1),Questions!$A:$E,5,FALSE),1,0) -> 0 | ... BS79: =IF(AI79=VLOOKUP(VALUE(AI$1),Questions!$A:$E,5,FALSE),1,0) -> 1
A80: 79 | B80: FALSE | C80: FALSE | D80: =SUM(Scores[[#This Row],[Q1]:[Q28]]) -> 22 | E80: =SUM(Scores[[#This Row],[29]:[34b]]) -> 0 | F80: =Scores[[#This Row],[35]] -> 0 | G80: =INDEX('Conversion Chart'!$C$3:$M$38,MATCH(SUM(Scores[[#This Row],[MC]:[CRQ]]),'Conversion Chart'!$B$3:$B$38,0),MATCH(Scores[[#This Row],[EIE]],'Conversion Chart'!$C$2:$M$2,0)) -> 57 | H80: 4 | I80: 3 | J80: 1 | K80: 2 | L80: 1 | M80: 4 | N80: 3 | O80: 1 | P80: 1 | Q80: 1 | R80: 4 | S80: 2 | T80: 1 | U80: 4 | V80: 3 | W80: 4 | X80: 2 | Y80: 4 | Z80: 1 | AA80: 3 | AB80: 2 | AC80: 3 | AD80: 3 | AE80: 2 | AF80: 4 | AG80: 1 | AH80: 4 | AI80: 1 | AR80: =IF(H80=VLOOKUP(VALUE(H$1),Questions!$A:$E,5,FALSE),1,0) -> 1 | AS80: =IF(I80=VLOOKUP(VALUE(I$1),Questions!$A:$E,5,FALSE),1,0) -> 1 | AT80: =IF(J80=VLOOKUP(VALUE(J$1),Questions!$A:$E,5,FALSE),1,0) -> 1 | AU80: =IF(K80=VLOOKUP(VALUE(K$1),Questions!$A:$E,5,FALSE),1,0) -> 1 | AV80: =IF(L80=VLOOKUP(VALUE(L$1),Questions!$A:$E,5,FALSE),1,0) -> 0 | AW80: =IF(M80=VLOOKUP(VALUE(M$1),Questions!$A:$E,5,FALSE),1,0) -> 1 | AX80: =IF(N80=VLOOKUP(VALUE(N$1),Questions!$A:$E,5,FALSE),1,0) -> 1 | AY80: =IF(O80=VLOOKUP(VALUE(O$1),Questions!$A:$E,5,FALSE),1,0) -> 1 | ... BS80: =IF(AI80=VLOOKUP(VALUE(AI$1),Questions!$A:$E,5,FALSE),1,0) -> 1
A81: 80 | B81: FALSE | C81: FALSE | D81: =SUM(Scores[[#This Row],[Q1]:[Q28]]) -> 22 | E81: =SUM(Scores[[#This Row],[29]:[34b]]) -> 0 | F81: =Scores[[#This Row],[35]] -> 0 | G81: =INDEX('Conversion Chart'!$C$3:$M$38,MATCH(SUM(Scores[[#This Row],[MC]:[CRQ]]),'Conversion Chart'!$B$3:$B$38,0),MATCH(Scores[[#This Row],[EIE]],'Conversion Chart'!$C$2:$M$2,0)) -> 57 | H81: 3 | I81: 3 | J81: 1 | K81: 2 | L81: 2 | M81: 4 | N81: 3 | O81: 1 | P81: 1 | Q81: 1 | R81: 4 | S81: 2 | T81: 1 | U81: 4 | V81: 3 | W81: 4 | X81: 2 | Y81: 3 | Z81: 4 | AA81: 4 | AB81: 4 | AC81: 2 | AD81: 3 | AE81: 2 | AF81: 4 | AG81: 3 | AH81: 1 | AI81: 4 | AR81: =IF(H81=VLOOKUP(VALUE(H$1),Questions!$A:$E,5,FALSE),1,0) -> 0 | AS81: =IF(I81=VLOOKUP(VALUE(I$1),Questions!$A:$E,5,FALSE),1,0) -> 1 | AT81: =IF(J81=VLOOKUP(VALUE(J$1),Questions!$A:$E,5,FALSE),1,0) -> 1 | AU81: =IF(K81=VLOOKUP(VALUE(K$1),Questions!$A:$E,5,FALSE),1,0) -> 1 | AV81: =IF(L81=VLOOKUP(VALUE(L$1),Questions!$A:$E,5,FALSE),1,0) -> 1 | AW81: =IF(M81=VLOOKUP(VALUE(M$1),Questions!$A:$E,5,FALSE),1,0) -> 1 | AX81: =IF(N81=VLOOKUP(VALUE(N$1),Questions!$A:$E,5,FALSE),1,0) -> 1 | AY81: =IF(O81=VLOOKUP(VALUE(O$1),Questions!$A:$E,5,FALSE),1,0) -> 1 | ... BS81: =IF(AI81=VLOOKUP(VALUE(AI$1),Questions!$A:$E,5,FALSE),1,0) -> 0
A82: 81 | B82: FALSE | C82: FALSE | D82: =SUM(Scores[[#This Row],[Q1]:[Q28]]) -> 26 | E82: =SUM(Scores[[#This Row],[29]:[34b]]) -> 0 | F82: =Scores[[#This Row],[35]] -> 0 | G82: =INDEX('Conversion Chart'!$C$3:$M$38,MATCH(SUM(Scores[[#This Row],[MC]:[CRQ]]),'Conversion Chart'!$B$3:$B$38,0),MATCH(Scores[[#This Row],[EIE]],'Conversion Chart'!$C$2:$M$2,0)) -> 64 | H82: 4 | I82: 3 | J82: 1 | K82: 2 | L82: 2 | M82: 4 | N82: 3 | O82: 4 | P82: 1 | Q82: 1 | R82: 4 | S82: 2 | T82: 1 | U82: 4 | V82: 3 | W82: 4 | X82: 2 | Y82: 3 | Z82: 2 | AA82: 3 | AB82: 2 | AC82: 1 | AD82: 3 | AE82: 2 | AF82: 4 | AG82: 3 | AH82: 4 | AI82: 1 | AR82: =IF(H82=VLOOKUP(VALUE(H$1),Questions!$A:$E,5,FALSE),1,0) -> 1 | AS82: =IF(I82=VLOOKUP(VALUE(I$1),Questions!$A:$E,5,FALSE),1,0) -> 1 | AT82: =IF(J82=VLOOKUP(VALUE(J$1),Questions!$A:$E,5,FALSE),1,0) -> 1 | AU82: =IF(K82=VLOOKUP(VALUE(K$1),Questions!$A:$E,5,FALSE),1,0) -> 1 | AV82: =IF(L82=VLOOKUP(VALUE(L$1),Questions!$A:$E,5,FALSE),1,0) -> 1 | AW82: =IF(M82=VLOOKUP(VALUE(M$1),Questions!$A:$E,5,FALSE),1,0) -> 1 | AX82: =IF(N82=VLOOKUP(VALUE(N$1),Questions!$A:$E,5,FALSE),1,0) -> 1 | AY82: =IF(O82=VLOOKUP(VALUE(O$1),Questions!$A:$E,5,FALSE),1,0) -> 0 | ... BS82: =IF(AI82=VLOOKUP(VALUE(AI$1),Questions!$A:$E,5,FALSE),1,0) -> 1
... A97: 96 | B97: FALSE | C97: TRUE | D97: =SUM(Scores[[#This Row],[Q1]:[Q28]]) -> 27 | E97: =SUM(Scores[[#This Row],[29]:[34b]]) -> 0 | F97: =Scores[[#This Row],[35]] -> 0 | G97: =INDEX('Conversion Chart'!$C$3:$M$38,MATCH(SUM(Scores[[#This Row],[MC]:[CRQ]]),'Conversion Chart'!$B$3:$B$38,0),MATCH(Scores[[#This Row],[EIE]],'Conversion Chart'!$C$2:$M$2,0)) -> 66 | H97: 4 | I97: 3 | J97: 1 | K97: 2 | L97: 2 | M97: 4 | N97: 3 | O97: 1 | P97: 1 | Q97: 1 | R97: 4 | S97: 2 | T97: 1 | U97: 1 | V97: 3 | W97: 4 | X97: 2 | Y97: 3 | Z97: 2 | AA97: 3 | AB97: 2 | AC97: 1 | AD97: 3 | AE97: 2 | AF97: 4 | AG97: 3 | AH97: 1 | AI97: 1 | AR97: =IF(H97=VLOOKUP(VALUE(H$1),Questions!$A:$E,5,FALSE),1,0) -> 1 | AS97: =IF(I97=VLOOKUP(VALUE(I$1),Questions!$A:$E,5,FALSE),1,0) -> 1 | AT97: =IF(J97=VLOOKUP(VALUE(J$1),Questions!$A:$E,5,FALSE),1,0) -> 1 | AU97: =IF(K97=VLOOKUP(VALUE(K$1),Questions!$A:$E,5,FALSE),1,0) -> 1 | AV97: =IF(L97=VLOOKUP(VALUE(L$1),Questions!$A:$E,5,FALSE),1,0) -> 1 | AW97: =IF(M97=VLOOKUP(VALUE(M$1),Questions!$A:$E,5,FALSE),1,0) -> 1 | AX97: =IF(N97=VLOOKUP(VALUE(N$1),Questions!$A:$E,5,FALSE),1,0) -> 1 | AY97: =IF(O97=VLOOKUP(VALUE(O$1),Questions!$A:$E,5,FALSE),1,0) -> 1 | ... BS97: =IF(AI97=VLOOKUP(VALUE(AI$1),Questions!$A:$E,5,FALSE),1,0) -> 1
A98: 97 | B98: FALSE | C98: FALSE | D98: =SUM(Scores[[#This Row],[Q1]:[Q28]]) -> 5 | E98: =SUM(Scores[[#This Row],[29]:[34b]]) -> 0 | F98: =Scores[[#This Row],[35]] -> 0 | G98: =INDEX('Conversion Chart'!$C$3:$M$38,MATCH(SUM(Scores[[#This Row],[MC]:[CRQ]]),'Conversion Chart'!$B$3:$B$38,0),MATCH(Scores[[#This Row],[EIE]],'Conversion Chart'!$C$2:$M$2,0)) -> 16 | H98: 4 | I98: 2 | J98: 3 | L98: 3 | N98: 3 | O98: 4 | P98: 4 | Q98: 1 | R98: 1 | S98: 4 | T98: 2 | U98: 4 | V98: 1 | W98: 3 | X98: 3 | Y98: 1 | Z98: 2 | AA98: 4 | AB98: 3 | AC98: 2 | AD98: 4 | AE98: 4 | AF98: 1 | AG98: 4 | AH98: 3 | AI98: 2 | AR98: =IF(H98=VLOOKUP(VALUE(H$1),Questions!$A:$E,5,FALSE),1,0) -> 1 | AS98: =IF(I98=VLOOKUP(VALUE(I$1),Questions!$A:$E,5,FALSE),1,0) -> 0 | AT98: =IF(J98=VLOOKUP(VALUE(J$1),Questions!$A:$E,5,FALSE),1,0) -> 0 | AU98: =IF(K98=VLOOKUP(VALUE(K$1),Questions!$A:$E,5,FALSE),1,0) -> 0 | AV98: =IF(L98=VLOOKUP(VALUE(L$1),Questions!$A:$E,5,FALSE),1,0) -> 0 | AW98: =IF(M98=VLOOKUP(VALUE(M$1),Questions!$A:$E,5,FALSE),1,0) -> 0 | AX98: =IF(N98=VLOOKUP(VALUE(N$1),Questions!$A:$E,5,FALSE),1,0) -> 1 | AY98: =IF(O98=VLOOKUP(VALUE(O$1),Questions!$A:$E,5,FALSE),1,0) -> 0 | ... BS98: =IF(AI98=VLOOKUP(VALUE(AI$1),Questions!$A:$E,5,FALSE),1,0) -> 0
A99: 98 | B99: FALSE | C99: FALSE | D99: =SUM(Scores[[#This Row],[Q1]:[Q28]]) -> 19 | E99: =SUM(Scores[[#This Row],[29]:[34b]]) -> 0 | F99: =Scores[[#This Row],[35]] -> 0 | G99: =INDEX('Conversion Chart'!$C$3:$M$38,MATCH(SUM(Scores[[#This Row],[MC]:[CRQ]]),'Conversion Chart'!$B$3:$B$38,0),MATCH(Scores[[#This Row],[EIE]],'Conversion Chart'!$C$2:$M$2,0)) -> 51 | H99: 1 | I99: 3 | J99: 1 | K99: 4 | L99: 2 | M99: 4 | N99: 3 | O99: 3 | P99: 1 | Q99: 3 | R99: 4 | S99: 4 | T99: 1 | U99: 4 | V99: 3 | W99: 4 | X99: 1 | Y99: 1 | Z99: 2 | AA99: 3 | AB99: 2 | AC99: 1 | AD99: 3 | AE99: 2 | AF99: 4 | AG99: 3 | AH99: 2 | AI99: 3 | AR99: =IF(H99=VLOOKUP(VALUE(H$1),Questions!$A:$E,5,FALSE),1,0) -> 0 | AS99: =IF(I99=VLOOKUP(VALUE(I$1),Questions!$A:$E,5,FALSE),1,0) -> 1 | AT99: =IF(J99=VLOOKUP(VALUE(J$1),Questions!$A:$E,5,FALSE),1,0) -> 1 | AU99: =IF(K99=VLOOKUP(VALUE(K$1),Questions!$A:$E,5,FALSE),1,0) -> 0 | AV99: =IF(L99=VLOOKUP(VALUE(L$1),Questions!$A:$E,5,FALSE),1,0) -> 1 | AW99: =IF(M99=VLOOKUP(VALUE(M$1),Questions!$A:$E,5,FALSE),1,0) -> 1 | AX99: =IF(N99=VLOOKUP(VALUE(N$1),Questions!$A:$E,5,FALSE),1,0) -> 1 | AY99: =IF(O99=VLOOKUP(VALUE(O$1),Questions!$A:$E,5,FALSE),1,0) -> 0 | ... BS99: =IF(AI99=VLOOKUP(VALUE(AI$1),Questions!$A:$E,5,FALSE),1,0) -> 0
A100: 99 | B100: FALSE | C100: FALSE | D100: =SUM(Scores[[#This Row],[Q1]:[Q28]]) -> 0 | E100: =SUM(Scores[[#This Row],[29]:[34b]]) -> 0 | F100: =Scores[[#This Row],[35]] -> 0 | G100: =INDEX('Conversion Chart'!$C$3:$M$38,MATCH(SUM(Scores[[#This Row],[MC]:[CRQ]]),'Conversion Chart'!$B$3:$B$38,0),MATCH(Scores[[#This Row],[EIE]],'Conversion Chart'!$C$2:$M$2,0)) -> 0 | AR100: =IF(H100=VLOOKUP(VALUE(H$1),Questions!$A:$E,5,FALSE),1,0) -> 0 | AS100: =IF(I100=VLOOKUP(VALUE(I$1),Questions!$A:$E,5,FALSE),1,0) -> 0 | AT100: =IF(J100=VLOOKUP(VALUE(J$1),Questions!$A:$E,5,FALSE),1,0) -> 0 | AU100: =IF(K100=VLOOKUP(VALUE(K$1),Questions!$A:$E,5,FALSE),1,0) -> 0 | AV100: =IF(L100=VLOOKUP(VALUE(L$1),Questions!$A:$E,5,FALSE),1,0) -> 0 | AW100: =IF(M100=VLOOKUP(VALUE(M$1),Questions!$A:$E,5,FALSE),1,0) -> 0 | AX100: =IF(N100=VLOOKUP(VALUE(N$1),Questions!$A:$E,5,FALSE),1,0) -> 0 | AY100: =IF(O100=VLOOKUP(VALUE(O$1),Questions!$A:$E,5,FALSE),1,0) -> 0 | ... BS100: =IF(AI100=VLOOKUP(VALUE(AI$1),Questions!$A:$E,5,FALSE),1,0) -> 0
A101: 100 | B101: FALSE | C101: FALSE | D101: =SUM(Scores[[#This Row],[Q1]:[Q28]]) -> 27 | E101: =SUM(Scores[[#This Row],[29]:[34b]]) -> 0 | F101: =Scores[[#This Row],[35]] -> 0 | G101: =INDEX('Conversion Chart'!$C$3:$M$38,MATCH(SUM(Scores[[#This Row],[MC]:[CRQ]]),'Conversion Chart'!$B$3:$B$38,0),MATCH(Scores[[#This Row],[EIE]],'Conversion Chart'!$C$2:$M$2,0)) -> 66 | H101: 4 | I101: 3 | J101: 1 | K101: 2 | L101: 2 | M101: 4 | N101: 3 | O101: 1 | P101: 1 | Q101: 1 | R101: 4 | S101: 2 | T101: 1 | U101: 4 | V101: 3 | W101: 4 | X101: 2 | Y101: 1 | Z101: 2 | AA101: 3 | AB101: 2 | AC101: 1 | AD101: 3 | AE101: 2 | AF101: 4 | AG101: 3 | AH101: 1 | AI101: 1 | AR101: =IF(H101=VLOOKUP(VALUE(H$1),Questions!$A:$E,5,FALSE),1,0) -> 1 | AS101: =IF(I101=VLOOKUP(VALUE(I$1),Questions!$A:$E,5,FALSE),1,0) -> 1 | AT101: =IF(J101=VLOOKUP(VALUE(J$1),Questions!$A:$E,5,FALSE),1,0) -> 1 | AU101: =IF(K101=VLOOKUP(VALUE(K$1),Questions!$A:$E,5,FALSE),1,0) -> 1 | AV101: =IF(L101=VLOOKUP(VALUE(L$1),Questions!$A:$E,5,FALSE),1,0) -> 1 | AW101: =IF(M101=VLOOKUP(VALUE(M$1),Questions!$A:$E,5,FALSE),1,0) -> 1 | AX101: =IF(N101=VLOOKUP(VALUE(N$1),Questions!$A:$E,5,FALSE),1,0) -> 1 | AY101: =IF(O101=VLOOKUP(VALUE(O$1),Questions!$A:$E,5,FALSE),1,0) -> 1 | ... BS101: =IF(AI101=VLOOKUP(VALUE(AI$1),Questions!$A:$E,5,FALSE),1,0) -> 1
A102: 101 | B102: FALSE | C102: FALSE | D102: =SUM(Scores[[#This Row],[Q1]:[Q28]]) -> 23 | E102: =SUM(Scores[[#This Row],[29]:[34b]]) -> 0 | F102: =Scores[[#This Row],[35]] -> 0 | G102: =INDEX('Conversion Chart'!$C$3:$M$38,MATCH(SUM(Scores[[#This Row],[MC]:[CRQ]]),'Conversion Chart'!$B$3:$B$38,0),MATCH(Scores[[#This Row],[EIE]],'Conversion Chart'!$C$2:$M$2,0)) -> 59 | H102: 4 | I102: 3 | J102: 1 | K102: 2 | L102: 2 | M102: 4 | N102: 3 | O102: 2 | P102: 1 | Q102: 2 | R102: 4 | S102: 2 | T102: 1 | U102: 4 | V102: 3 | W102: 2 | X102: 2 | Y102: 1 | Z102: 2 | AA102: 3 | AB102: 2 | AC102: 1 | AD102: 3 | AE102: 4 | AF102: 4 | AG102: 3 | AH102: 1 | AI102: 1 | AR102: =IF(H102=VLOOKUP(VALUE(H$1),Questions!$A:$E,5,FALSE),1,0) -> 1 | AS102: =IF(I102=VLOOKUP(VALUE(I$1),Questions!$A:$E,5,FALSE),1,0) -> 1 | AT102: =IF(J102=VLOOKUP(VALUE(J$1),Questions!$A:$E,5,FALSE),1,0) -> 1 | AU102: =IF(K102=VLOOKUP(VALUE(K$1),Questions!$A:$E,5,FALSE),1,0) -> 1 | AV102: =IF(L102=VLOOKUP(VALUE(L$1),Questions!$A:$E,5,FALSE),1,0) -> 1 | AW102: =IF(M102=VLOOKUP(VALUE(M$1),Questions!$A:$E,5,FALSE),1,0) -> 1 | AX102: =IF(N102=VLOOKUP(VALUE(N$1),Questions!$A:$E,5,FALSE),1,0) -> 1 | AY102: =IF(O102=VLOOKUP(VALUE(O$1),Questions!$A:$E,5,FALSE),1,0) -> 0 | ... BS102: =IF(AI102=VLOOKUP(VALUE(AI$1),Questions!$A:$E,5,FALSE),1,0) -> 1
A103: 102 | B103: FALSE | C103: FALSE | D103: =SUM(Scores[[#This Row],[Q1]:[Q28]]) -> 15 | E103: =SUM(Scores[[#This Row],[29]:[34b]]) -> 0 | F103: =Scores[[#This Row],[35]] -> 0 | G103: =INDEX('Conversion Chart'!$C$3:$M$38,MATCH(SUM(Scores[[#This Row],[MC]:[CRQ]]),'Conversion Chart'!$B$3:$B$38,0),MATCH(Scores[[#This Row],[EIE]],'Conversion Chart'!$C$2:$M$2,0)) -> 42 | H103: 1 | I103: 3 | J103: 1 | K103: 1 | L103: 2 | M103: 3 | N103: 3 | O103: 4 | P103: 1 | Q103: 1 | R103: 4 | S103: 2 | T103: 4 | U103: 2 | V103: 3 | W103: 4 | X103: 3 | Y103: 4 | Z103: 3 | AA103: 1 | AB103: 2 | AC103: 3 | AD103: 3 | AE103: 2 | AF103: 4 | AG103: 3 | AH103: 2 | AI103: 4 | AR103: =IF(H103=VLOOKUP(VALUE(H$1),Questions!$A:$E,5,FALSE),1,0) -> 0 | AS103: =IF(I103=VLOOKUP(VALUE(I$1),Questions!$A:$E,5,FALSE),1,0) -> 1 | AT103: =IF(J103=VLOOKUP(VALUE(J$1),Questions!$A:$E,5,FALSE),1,0) -> 1 | AU103: =IF(K103=VLOOKUP(VALUE(K$1),Questions!$A:$E,5,FALSE),1,0) -> 0 | AV103: =IF(L103=VLOOKUP(VALUE(L$1),Questions!$A:$E,5,FALSE),1,0) -> 1 | AW103: =IF(M103=VLOOKUP(VALUE(M$1),Questions!$A:$E,5,FALSE),1,0) -> 0 | AX103: =IF(N103=VLOOKUP(VALUE(N$1),Questions!$A:$E,5,FALSE),1,0) -> 1 | AY103: =IF(O103=VLOOKUP(VALUE(O$1),Questions!$A:$E,5,FALSE),1,0) -> 0 | ... BS103: =IF(AI103=VLOOKUP(VALUE(AI$1),Questions!$A:$E,5,FALSE),1,0) -> 0
A104: 103 | B104: FALSE | C104: FALSE | D104: =SUM(Scores[[#This Row],[Q1]:[Q28]]) -> 22 | E104: =SUM(Scores[[#This Row],[29]:[34b]]) -> 0 | F104: =Scores[[#This Row],[35]] -> 0 | G104: =INDEX('Conversion Chart'!$C$3:$M$38,MATCH(SUM(Scores[[#This Row],[MC]:[CRQ]]),'Conversion Chart'!$B$3:$B$38,0),MATCH(Scores[[#This Row],[EIE]],'Conversion Chart'!$C$2:$M$2,0)) -> 57 | H104: 4 | I104: 1 | J104: 1 | K104: 2 | L104: 1 | M104: 4 | N104: 3 | O104: 1 | P104: 1 | Q104: 1 | R104: 1 | S104: 2 | T104: 2 | U104: 4 | V104: 3 | W104: 4 | X104: 2 | Y104: 3 | Z104: 1 | AA104: 3 | AB104: 2 | AC104: 1 | AD104: 3 | AE104: 2 | AF104: 4 | AG104: 2 | AH104: 1 | AI104: 1 | AR104: =IF(H104=VLOOKUP(VALUE(H$1),Questions!$A:$E,5,FALSE),1,0) -> 1 | AS104: =IF(I104=VLOOKUP(VALUE(I$1),Questions!$A:$E,5,FALSE),1,0) -> 0 | AT104: =IF(J104=VLOOKUP(VALUE(J$1),Questions!$A:$E,5,FALSE),1,0) -> 1 | AU104: =IF(K104=VLOOKUP(VALUE(K$1),Questions!$A:$E,5,FALSE),1,0) -> 1 | AV104: =IF(L104=VLOOKUP(VALUE(L$1),Questions!$A:$E,5,FALSE),1,0) -> 0 | AW104: =IF(M104=VLOOKUP(VALUE(M$1),Questions!$A:$E,5,FALSE),1,0) -> 1 | AX104: =IF(N104=VLOOKUP(VALUE(N$1),Questions!$A:$E,5,FALSE),1,0) -> 1 | AY104: =IF(O104=VLOOKUP(VALUE(O$1),Questions!$A:$E,5,FALSE),1,0) -> 1 | ... BS104: =IF(AI104=VLOOKUP(VALUE(AI$1),Questions!$A:$E,5,FALSE),1,0) -> 1
A105: 104 | B105: FALSE | C105: TRUE | D105: =SUM(Scores[[#This Row],[Q1]:[Q28]]) -> 10 | E105: =SUM(Scores[[#This Row],[29]:[34b]]) -> 0 | F105: =Scores[[#This Row],[35]] -> 0 | G105: =INDEX('Conversion Chart'!$C$3:$M$38,MATCH(SUM(Scores[[#This Row],[MC]:[CRQ]]),'Conversion Chart'!$B$3:$B$38,0),MATCH(Scores[[#This Row],[EIE]],'Conversion Chart'!$C$2:$M$2,0)) -> 30 | H105: 4 | I105: 2 | J105: 4 | K105: 4 | L105: 3 | M105: 2 | N105: 3 | O105: 3 | P105: 2 | Q105: 1 | R105: 4 | S105: 4 | T105: 1 | U105: 4 | V105: 4 | W105: 3 | X105: 3 | Y105: 3 | Z105: 2 | AA105: 3 | AB105: 3 | AC105: 1 | AD105: 4 | AE105: 1 | AF105: 3 | AG105: 2 | AH105: 4 | AI105: 4 | AR105: =IF(H105=VLOOKUP(VALUE(H$1),Questions!$A:$E,5,FALSE),1,0) -> 1 | AS105: =IF(I105=VLOOKUP(VALUE(I$1),Questions!$A:$E,5,FALSE),1,0) -> 0 | AT105: =IF(J105=VLOOKUP(VALUE(J$1),Questions!$A:$E,5,FALSE),1,0) -> 0 | AU105: =IF(K105=VLOOKUP(VALUE(K$1),Questions!$A:$E,5,FALSE),1,0) -> 0 | AV105: =IF(L105=VLOOKUP(VALUE(L$1),Questions!$A:$E,5,FALSE),1,0) -> 0 | AW105: =IF(M105=VLOOKUP(VALUE(M$1),Questions!$A:$E,5,FALSE),1,0) -> 0 | AX105: =IF(N105=VLOOKUP(VALUE(N$1),Questions!$A:$E,5,FALSE),1,0) -> 1 | AY105: =IF(O105=VLOOKUP(VALUE(O$1),Questions!$A:$E,5,FALSE),1,0) -> 0 | ... BS105: =IF(AI105=VLOOKUP(VALUE(AI$1),Questions!$A:$E,5,FALSE),1,0) -> 0
A106: 105 | B106: FALSE | C106: FALSE | D106: =SUM(Scores[[#This Row],[Q1]:[Q28]]) -> 14 | E106: =SUM(Scores[[#This Row],[29]:[34b]]) -> 0 | F106: =Scores[[#This Row],[35]] -> 0 | G106: =INDEX('Conversion Chart'!$C$3:$M$38,MATCH(SUM(Scores[[#This Row],[MC]:[CRQ]]),'Conversion Chart'!$B$3:$B$38,0),MATCH(Scores[[#This Row],[EIE]],'Conversion Chart'!$C$2:$M$2,0)) -> 40 | H106: 4 | I106: 3 | J106: 1 | K106: 2 | L106: 2 | M106: 4 | N106: 3 | O106: 4 | P106: 1 | Q106: 1 | R106: 1 | S106: 3 | T106: 4 | U106: 2 | V106: 1 | W106: 1 | X106: 2 | Y106: 3 | Z106: 1 | AA106: 2 | AB106: 2 | AC106: 4 | AD106: 3 | AE106: 3 | AF106: 4 | AG106: 1 | AH106: 2 | AI106: 3 | AR106: =IF(H106=VLOOKUP(VALUE(H$1),Questions!$A:$E,5,FALSE),1,0) -> 1 | AS106: =IF(I106=VLOOKUP(VALUE(I$1),Questions!$A:$E,5,FALSE),1,0) -> 1 | AT106: =IF(J106=VLOOKUP(VALUE(J$1),Questions!$A:$E,5,FALSE),1,0) -> 1 | AU106: =IF(K106=VLOOKUP(VALUE(K$1),Questions!$A:$E,5,FALSE),1,0) -> 1 | AV106: =IF(L106=VLOOKUP(VALUE(L$1),Questions!$A:$E,5,FALSE),1,0) -> 1 | AW106: =IF(M106=VLOOKUP(VALUE(M$1),Questions!$A:$E,5,FALSE),1,0) -> 1 | AX106: =IF(N106=VLOOKUP(VALUE(N$1),Questions!$A:$E,5,FALSE),1,0) -> 1 | AY106: =IF(O106=VLOOKUP(VALUE(O$1),Questions!$A:$E,5,FALSE),1,0) -> 0 | ... BS106: =IF(AI106=VLOOKUP(VALUE(AI$1),Questions!$A:$E,5,FALSE),1,0) -> 0
A107: 106 | B107: TRUE | C107: TRUE | D107: =SUM(Scores[[#This Row],[Q1]:[Q28]]) -> 23 | E107: =SUM(Scores[[#This Row],[29]:[34b]]) -> 0 | F107: =Scores[[#This Row],[35]] -> 0 | G107: =INDEX('Conversion Chart'!$C$3:$M$38,MATCH(SUM(Scores[[#This Row],[MC]:[CRQ]]),'Conversion Chart'!$B$3:$B$38,0),MATCH(Scores[[#This Row],[EIE]],'Conversion Chart'!$C$2:$M$2,0)) -> 59 | H107: 4 | I107: 3 | J107: 1 | K107: 2 | L107: 2 | M107: 4 | N107: 3 | O107: 1 | P107: 1 | Q107: 1 | R107: 4 | S107: 2 | T107: 1 | U107: 4 | V107: 1 | W107: 4 | X107: 1 | Y107: 3 | Z107: 1 | AA107: 1 | AB107: 2 | AC107: 1 | AD107: 3 | AE107: 2 | AF107: 4 | AG107: 2 | AH107: 1 | AI107: 1 | AR107: =IF(H107=VLOOKUP(VALUE(H$1),Questions!$A:$E,5,FALSE),1,0) -> 1 | AS107: =IF(I107=VLOOKUP(VALUE(I$1),Questions!$A:$E,5,FALSE),1,0) -> 1 | AT107: =IF(J107=VLOOKUP(VALUE(J$1),Questions!$A:$E,5,FALSE),1,0) -> 1 | AU107: =IF(K107=VLOOKUP(VALUE(K$1),Questions!$A:$E,5,FALSE),1,0) -> 1 | AV107: =IF(L107=VLOOKUP(VALUE(L$1),Questions!$A:$E,5,FALSE),1,0) -> 1 | AW107: =IF(M107=VLOOKUP(VALUE(M$1),Questions!$A:$E,5,FALSE),1,0) -> 1 | AX107: =IF(N107=VLOOKUP(VALUE(N$1),Questions!$A:$E,5,FALSE),1,0) -> 1 | AY107: =IF(O107=VLOOKUP(VALUE(O$1),Questions!$A:$E,5,FALSE),1,0) -> 1 | ... BS107: =IF(AI107=VLOOKUP(VALUE(AI$1),Questions!$A:$E,5,FALSE),1,0) -> 1
A108: 107 | B108: FALSE | C108: FALSE | D108: =SUM(Scores[[#This Row],[Q1]:[Q28]]) -> 8 | E108: =SUM(Scores[[#This Row],[29]:[34b]]) -> 0 | F108: =Scores[[#This Row],[35]] -> 0 | G108: =INDEX('Conversion Chart'!$C$3:$M$38,MATCH(SUM(Scores[[#This Row],[MC]:[CRQ]]),'Conversion Chart'!$B$3:$B$38,0),MATCH(Scores[[#This Row],[EIE]],'Conversion Chart'!$C$2:$M$2,0)) -> 25 | H108: 2 | I108: 3 | J108: 2 | K108: 1 | L108: 3 | M108: 2 | N108: 4 | O108: 3 | P108: 1 | Q108: 4 | R108: 3 | S108: 2 | T108: 3 | U108: 4 | V108: 1 | W108: 2 | X108: 2 | Y108: 3 | Z108: 2 | AA108: 4 | AB108: 3 | AC108: 2 | AD108: 1 | AE108: 2 | AF108: 3 | AG108: 1 | AH108: 4 | AI108: 3 | AR108: =IF(H108=VLOOKUP(VALUE(H$1),Questions!$A:$E,5,FALSE),1,0) -> 0 | AS108: =IF(I108=VLOOKUP(VALUE(I$1),Questions!$A:$E,5,FALSE),1,0) -> 1 | AT108: =IF(J108=VLOOKUP(VALUE(J$1),Questions!$A:$E,5,FALSE),1,0) -> 0 | AU108: =IF(K108=VLOOKUP(VALUE(K$1),Questions!$A:$E,5,FALSE),1,0) -> 0 | AV108: =IF(L108=VLOOKUP(VALUE(L$1),Questions!$A:$E,5,FALSE),1,0) -> 0 | AW108: =IF(M108=VLOOKUP(VALUE(M$1),Questions!$A:$E,5,FALSE),1,0) -> 0 | AX108: =IF(N108=VLOOKUP(VALUE(N$1),Questions!$A:$E,5,FALSE),1,0) -> 0 | AY108: =IF(O108=VLOOKUP(VALUE(O$1),Questions!$A:$E,5,FALSE),1,0) -> 0 | ... BS108: =IF(AI108=VLOOKUP(VALUE(AI$1),Questions!$A:$E,5,FALSE),1,0) -> 0
A109: 108 | B109: TRUE | C109: FALSE | D109: =SUM(Scores[[#This Row],[Q1]:[Q28]]) -> 22 | E109: =SUM(Scores[[#This Row],[29]:[34b]]) -> 0 | F109: =Scores[[#This Row],[35]] -> 0 | G109: =INDEX('Conversion Chart'!$C$3:$M$38,MATCH(SUM(Scores[[#This Row],[MC]:[CRQ]]),'Conversion Chart'!$B$3:$B$38,0),MATCH(Scores[[#This Row],[EIE]],'Conversion Chart'!$C$2:$M$2,0)) -> 57 | H109: 4 | I109: 3 | J109: 1 | K109: 2 | L109: 2 | M109: 4 | N109: 3 | O109: 4 | P109: 1 | Q109: 1 | R109: 4 | S109: 3 | T109: 1 | U109: 4 | V109: 3 | W109: 4 | X109: 3 | Y109: 2 | Z109: 2 | AA109: 2 | AB109: 3 | AC109: 1 | AD109: 3 | AE109: 2 | AF109: 4 | AG109: 3 | AH109: 1 | AI109: 1 | AR109: =IF(H109=VLOOKUP(VALUE(H$1),Questions!$A:$E,5,FALSE),1,0) -> 1 | AS109: =IF(I109=VLOOKUP(VALUE(I$1),Questions!$A:$E,5,FALSE),1,0) -> 1 | AT109: =IF(J109=VLOOKUP(VALUE(J$1),Questions!$A:$E,5,FALSE),1,0) -> 1 | AU109: =IF(K109=VLOOKUP(VALUE(K$1),Questions!$A:$E,5,FALSE),1,0) -> 1 | AV109: =IF(L109=VLOOKUP(VALUE(L$1),Questions!$A:$E,5,FALSE),1,0) -> 1 | AW109: =IF(M109=VLOOKUP(VALUE(M$1),Questions!$A:$E,5,FALSE),1,0) -> 1 | AX109: =IF(N109=VLOOKUP(VALUE(N$1),Questions!$A:$E,5,FALSE),1,0) -> 1 | AY109: =IF(O109=VLOOKUP(VALUE(O$1),Questions!$A:$E,5,FALSE),1,0) -> 0 | ... BS109: =IF(AI109=VLOOKUP(VALUE(AI$1),Questions!$A:$E,5,FALSE),1,0) -> 1
A110: 109 | B110: FALSE | C110: FALSE | D110: =SUM(Scores[[#This Row],[Q1]:[Q28]]) -> 15 | E110: =SUM(Scores[[#This Row],[29]:[34b]]) -> 0 | F110: =Scores[[#This Row],[35]] -> 0 | G110: =INDEX('Conversion Chart'!$C$3:$M$38,MATCH(SUM(Scores[[#This Row],[MC]:[CRQ]]),'Conversion Chart'!$B$3:$B$38,0),MATCH(Scores[[#This Row],[EIE]],'Conversion Chart'!$C$2:$M$2,0)) -> 42 | H110: 1 | I110: 2 | J110: 1 | K110: 3 | L110: 2 | M110: 2 | N110: 3 | O110: 4 | P110: 4 | Q110: 2 | R110: 4 | S110: 4 | T110: 1 | U110: 3 | V110: 3 | W110: 4 | X110: 2 | Y110: 3 | Z110: 2 | AA110: 4 | AB110: 2 | AC110: 1 | AD110: 2 | AE110: 3 | AF110: 4 | AG110: 3 | AH110: 2 | AI110: 1 | AR110: =IF(H110=VLOOKUP(VALUE(H$1),Questions!$A:$E,5,FALSE),1,0) -> 0 | AS110: =IF(I110=VLOOKUP(VALUE(I$1),Questions!$A:$E,5,FALSE),1,0) -> 0 | AT110: =IF(J110=VLOOKUP(VALUE(J$1),Questions!$A:$E,5,FALSE),1,0) -> 1 | AU110: =IF(K110=VLOOKUP(VALUE(K$1),Questions!$A:$E,5,FALSE),1,0) -> 0 | AV110: =IF(L110=VLOOKUP(VALUE(L$1),Questions!$A:$E,5,FALSE),1,0) -> 1 | AW110: =IF(M110=VLOOKUP(VALUE(M$1),Questions!$A:$E,5,FALSE),1,0) -> 0 | AX110: =IF(N110=VLOOKUP(VALUE(N$1),Questions!$A:$E,5,FALSE),1,0) -> 1 | AY110: =IF(O110=VLOOKUP(VALUE(O$1),Questions!$A:$E,5,FALSE),1,0) -> 0 | ... BS110: =IF(AI110=VLOOKUP(VALUE(AI$1),Questions!$A:$E,5,FALSE),1,0) -> 1
A111: 110 | B111: FALSE | C111: FALSE | D111: =SUM(Scores[[#This Row],[Q1]:[Q28]]) -> 26 | E111: =SUM(Scores[[#This Row],[29]:[34b]]) -> 0 | F111: =Scores[[#This Row],[35]] -> 0 | G111: =INDEX('Conversion Chart'!$C$3:$M$38,MATCH(SUM(Scores[[#This Row],[MC]:[CRQ]]),'Conversion Chart'!$B$3:$B$38,0),MATCH(Scores[[#This Row],[EIE]],'Conversion Chart'!$C$2:$M$2,0)) -> 64 | H111: 4 | I111: 3 | J111: 1 | K111: 2 | L111: 2 | M111: 4 | N111: 3 | O111: 1 | P111: 1 | Q111: 1 | R111: 4 | S111: 2 | T111: 1 | U111: 4 | V111: 3 | W111: 4 | X111: 2 | Y111: 3 | Z111: 4 | AA111: 2 | AB111: 2 | AC111: 1 | AD111: 3 | AE111: 2 | AF111: 4 | AG111: 3 | AH111: 1 | AI111: 1 | AR111: =IF(H111=VLOOKUP(VALUE(H$1),Questions!$A:$E,5,FALSE),1,0) -> 1 | AS111: =IF(I111=VLOOKUP(VALUE(I$1),Questions!$A:$E,5,FALSE),1,0) -> 1 | AT111: =IF(J111=VLOOKUP(VALUE(J$1),Questions!$A:$E,5,FALSE),1,0) -> 1 | AU111: =IF(K111=VLOOKUP(VALUE(K$1),Questions!$A:$E,5,FALSE),1,0) -> 1 | AV111: =IF(L111=VLOOKUP(VALUE(L$1),Questions!$A:$E,5,FALSE),1,0) -> 1 | AW111: =IF(M111=VLOOKUP(VALUE(M$1),Questions!$A:$E,5,FALSE),1,0) -> 1 | AX111: =IF(N111=VLOOKUP(VALUE(N$1),Questions!$A:$E,5,FALSE),1,0) -> 1 | AY111: =IF(O111=VLOOKUP(VALUE(O$1),Questions!$A:$E,5,FALSE),1,0) -> 1 | ... BS111: =IF(AI111=VLOOKUP(VALUE(AI$1),Questions!$A:$E,5,FALSE),1,0) -> 1
A112: 111 | B112: FALSE | C112: TRUE | D112: =SUM(Scores[[#This Row],[Q1]:[Q28]]) -> 13 | E112: =SUM(Scores[[#This Row],[29]:[34b]]) -> 0 | F112: =Scores[[#This Row],[35]] -> 0 | G112: =INDEX('Conversion Chart'!$C$3:$M$38,MATCH(SUM(Scores[[#This Row],[MC]:[CRQ]]),'Conversion Chart'!$B$3:$B$38,0),MATCH(Scores[[#This Row],[EIE]],'Conversion Chart'!$C$2:$M$2,0)) -> 38 | H112: 4 | I112: 3 | J112: 1 | K112: 2 | L112: 4 | M112: 3 | N112: 2 | O112: 1 | P112: 1 | Q112: 4 | R112: 3 | S112: 1 | T112: 1 | U112: 1 | V112: 3 | W112: 4 | X112: 4 | Y112: 3 | Z112: 1 | AA112: 1 | AB112: 3 | AC112: 2 | AD112: 4 | AE112: 4 | AF112: 4 | AG112: 2 | AH112: 1 | AI112: 1 | AR112: =IF(H112=VLOOKUP(VALUE(H$1),Questions!$A:$E,5,FALSE),1,0) -> 1 | AS112: =IF(I112=VLOOKUP(VALUE(I$1),Questions!$A:$E,5,FALSE),1,0) -> 1 | AT112: =IF(J112=VLOOKUP(VALUE(J$1),Questions!$A:$E,5,FALSE),1,0) -> 1 | AU112: =IF(K112=VLOOKUP(VALUE(K$1),Questions!$A:$E,5,FALSE),1,0) -> 1 | AV112: =IF(L112=VLOOKUP(VALUE(L$1),Questions!$A:$E,5,FALSE),1,0) -> 0 | AW112: =IF(M112=VLOOKUP(VALUE(M$1),Questions!$A:$E,5,FALSE),1,0) -> 0 | AX112: =IF(N112=VLOOKUP(VALUE(N$1),Questions!$A:$E,5,FALSE),1,0) -> 0 | AY112: =IF(O112=VLOOKUP(VALUE(O$1),Questions!$A:$E,5,FALSE),1,0) -> 1 | ... BS112: =IF(AI112=VLOOKUP(VALUE(AI$1),Questions!$A:$E,5,FALSE),1,0) -> 1
... A114: 113 | B114: FALSE | C114: FALSE | D114: =SUM(Scores[[#This Row],[Q1]:[Q28]]) -> 26 | E114: =SUM(Scores[[#This Row],[29]:[34b]]) -> 0 | F114: =Scores[[#This Row],[35]] -> 0 | G114: =INDEX('Conversion Chart'!$C$3:$M$38,MATCH(SUM(Scores[[#This Row],[MC]:[CRQ]]),'Conversion Chart'!$B$3:$B$38,0),MATCH(Scores[[#This Row],[EIE]],'Conversion Chart'!$C$2:$M$2,0)) -> 64 | H114: 4 | I114: 3 | J114: 4 | K114: 2 | L114: 2 | M114: 4 | N114: 3 | O114: 1 | P114: 1 | Q114: 1 | R114: 4 | S114: 2 | T114: 1 | U114: 4 | V114: 3 | W114: 4 | X114: 2 | Y114: 3 | Z114: 2 | AA114: 3 | AB114: 2 | AC114: 1 | AD114: 3 | AE114: 2 | AF114: 4 | AG114: 3 | AH114: 4 | AI114: 1 | AR114: =IF(H114=VLOOKUP(VALUE(H$1),Questions!$A:$E,5,FALSE),1,0) -> 1 | AS114: =IF(I114=VLOOKUP(VALUE(I$1),Questions!$A:$E,5,FALSE),1,0) -> 1 | AT114: =IF(J114=VLOOKUP(VALUE(J$1),Questions!$A:$E,5,FALSE),1,0) -> 0 | AU114: =IF(K114=VLOOKUP(VALUE(K$1),Questions!$A:$E,5,FALSE),1,0) -> 1 | AV114: =IF(L114=VLOOKUP(VALUE(L$1),Questions!$A:$E,5,FALSE),1,0) -> 1 | AW114: =IF(M114=VLOOKUP(VALUE(M$1),Questions!$A:$E,5,FALSE),1,0) -> 1 | AX114: =IF(N114=VLOOKUP(VALUE(N$1),Questions!$A:$E,5,FALSE),1,0) -> 1 | AY114: =IF(O114=VLOOKUP(VALUE(O$1),Questions!$A:$E,5,FALSE),1,0) -> 1 | ... BS114: =IF(AI114=VLOOKUP(VALUE(AI$1),Questions!$A:$E,5,FALSE),1,0) -> 1
A115: 114 | B115: FALSE | C115: FALSE | D115: =SUM(Scores[[#This Row],[Q1]:[Q28]]) -> 13 | E115: =SUM(Scores[[#This Row],[29]:[34b]]) -> 0 | F115: =Scores[[#This Row],[35]] -> 0 | G115: =INDEX('Conversion Chart'!$C$3:$M$38,MATCH(SUM(Scores[[#This Row],[MC]:[CRQ]]),'Conversion Chart'!$B$3:$B$38,0),MATCH(Scores[[#This Row],[EIE]],'Conversion Chart'!$C$2:$M$2,0)) -> 38 | H115: 4 | I115: 3 | J115: 2 | K115: 2 | L115: 2 | M115: 1 | N115: 2 | O115: 1 | P115: 1 | Q115: 2 | R115: 4 | S115: 4 | T115: 4 | U115: 2 | V115: 1 | W115: 1 | X115: 2 | Y115: 1 | Z115: 2 | AA115: 3 | AB115: 2 | AC115: 3 | AD115: 1 | AE115: 2 | AF115: 4 | AG115: 1 | AR115: =IF(H115=VLOOKUP(VALUE(H$1),Questions!$A:$E,5,FALSE),1,0) -> 1 | AS115: =IF(I115=VLOOKUP(VALUE(I$1),Questions!$A:$E,5,FALSE),1,0) -> 1 | AT115: =IF(J115=VLOOKUP(VALUE(J$1),Questions!$A:$E,5,FALSE),1,0) -> 0 | AU115: =IF(K115=VLOOKUP(VALUE(K$1),Questions!$A:$E,5,FALSE),1,0) -> 1 | AV115: =IF(L115=VLOOKUP(VALUE(L$1),Questions!$A:$E,5,FALSE),1,0) -> 1 | AW115: =IF(M115=VLOOKUP(VALUE(M$1),Questions!$A:$E,5,FALSE),1,0) -> 0 | AX115: =IF(N115=VLOOKUP(VALUE(N$1),Questions!$A:$E,5,FALSE),1,0) -> 0 | AY115: =IF(O115=VLOOKUP(VALUE(O$1),Questions!$A:$E,5,FALSE),1,0) -> 1 | ... BS115: =IF(AI115=VLOOKUP(VALUE(AI$1),Questions!$A:$E,5,FALSE),1,0) -> 0
A116: 115 | B116: FALSE | C116: TRUE | D116: =SUM(Scores[[#This Row],[Q1]:[Q28]]) -> 17 | E116: =SUM(Scores[[#This Row],[29]:[34b]]) -> 0 | F116: =Scores[[#This Row],[35]] -> 0 | G116: =INDEX('Conversion Chart'!$C$3:$M$38,MATCH(SUM(Scores[[#This Row],[MC]:[CRQ]]),'Conversion Chart'!$B$3:$B$38,0),MATCH(Scores[[#This Row],[EIE]],'Conversion Chart'!$C$2:$M$2,0)) -> 47 | H116: 4 | I116: 3 | J116: 3 | K116: 3 | L116: 1 | M116: 4 | N116: 3 | O116: 4 | P116: 1 | Q116: 1 | R116: 4 | S116: 3 | T116: 3 | U116: 4 | V116: 1 | W116: 3 | X116: 2 | Y116: 1 | Z116: 1 | AA116: 3 | AB116: 2 | AC116: 1 | AD116: 3 | AE116: 4 | AF116: 4 | AG116: 3 | AH116: 1 | AI116: 1 | AR116: =IF(H116=VLOOKUP(VALUE(H$1),Questions!$A:$E,5,FALSE),1,0) -> 1 | AS116: =IF(I116=VLOOKUP(VALUE(I$1),Questions!$A:$E,5,FALSE),1,0) -> 1 | AT116: =IF(J116=VLOOKUP(VALUE(J$1),Questions!$A:$E,5,FALSE),1,0) -> 0 | AU116: =IF(K116=VLOOKUP(VALUE(K$1),Questions!$A:$E,5,FALSE),1,0) -> 0 | AV116: =IF(L116=VLOOKUP(VALUE(L$1),Questions!$A:$E,5,FALSE),1,0) -> 0 | AW116: =IF(M116=VLOOKUP(VALUE(M$1),Questions!$A:$E,5,FALSE),1,0) -> 1 | AX116: =IF(N116=VLOOKUP(VALUE(N$1),Questions!$A:$E,5,FALSE),1,0) -> 1 | AY116: =IF(O116=VLOOKUP(VALUE(O$1),Questions!$A:$E,5,FALSE),1,0) -> 0 | ... BS116: =IF(AI116=VLOOKUP(VALUE(AI$1),Questions!$A:$E,5,FALSE),1,0) -> 1
A117: 116 | B117: FALSE | C117: FALSE | D117: =SUM(Scores[[#This Row],[Q1]:[Q28]]) -> 0 | E117: =SUM(Scores[[#This Row],[29]:[34b]]) -> 0 | F117: =Scores[[#This Row],[35]] -> 0 | G117: =INDEX('Conversion Chart'!$C$3:$M$38,MATCH(SUM(Scores[[#This Row],[MC]:[CRQ]]),'Conversion Chart'!$B$3:$B$38,0),MATCH(Scores[[#This Row],[EIE]],'Conversion Chart'!$C$2:$M$2,0)) -> 0 | AR117: =IF(H117=VLOOKUP(VALUE(H$1),Questions!$A:$E,5,FALSE),1,0) -> 0 | AS117: =IF(I117=VLOOKUP(VALUE(I$1),Questions!$A:$E,5,FALSE),1,0) -> 0 | AT117: =IF(J117=VLOOKUP(VALUE(J$1),Questions!$A:$E,5,FALSE),1,0) -> 0 | AU117: =IF(K117=VLOOKUP(VALUE(K$1),Questions!$A:$E,5,FALSE),1,0) -> 0 | AV117: =IF(L117=VLOOKUP(VALUE(L$1),Questions!$A:$E,5,FALSE),1,0) -> 0 | AW117: =IF(M117=VLOOKUP(VALUE(M$1),Questions!$A:$E,5,FALSE),1,0) -> 0 | AX117: =IF(N117=VLOOKUP(VALUE(N$1),Questions!$A:$E,5,FALSE),1,0) -> 0 | AY117: =IF(O117=VLOOKUP(VALUE(O$1),Questions!$A:$E,5,FALSE),1,0) -> 0 | ... BS117: =IF(AI117=VLOOKUP(VALUE(AI$1),Questions!$A:$E,5,FALSE),1,0) -> 0
A118: 117 | B118: FALSE | C118: FALSE | D118: =SUM(Scores[[#This Row],[Q1]:[Q28]]) -> 24 | E118: =SUM(Scores[[#This Row],[29]:[34b]]) -> 0 | F118: =Scores[[#This Row],[35]] -> 0 | G118: =INDEX('Conversion Chart'!$C$3:$M$38,MATCH(SUM(Scores[[#This Row],[MC]:[CRQ]]),'Conversion Chart'!$B$3:$B$38,0),MATCH(Scores[[#This Row],[EIE]],'Conversion Chart'!$C$2:$M$2,0)) -> 61 | H118: 1 | I118: 3 | J118: 1 | K118: 2 | L118: 1 | M118: 4 | N118: 3 | O118: 4 | P118: 1 | Q118: 1 | R118: 4 | S118: 2 | T118: 1 | U118: 4 | V118: 4 | W118: 4 | X118: 2 | Y118: 3 | Z118: 2 | AA118: 3 | AB118: 2 | AC118: 1 | AD118: 3 | AE118: 2 | AF118: 4 | AG118: 3 | AH118: 1 | AI118: 1 | AR118: =IF(H118=VLOOKUP(VALUE(H$1),Questions!$A:$E,5,FALSE),1,0) -> 0 | AS118: =IF(I118=VLOOKUP(VALUE(I$1),Questions!$A:$E,5,FALSE),1,0) -> 1 | AT118: =IF(J118=VLOOKUP(VALUE(J$1),Questions!$A:$E,5,FALSE),1,0) -> 1 | AU118: =IF(K118=VLOOKUP(VALUE(K$1),Questions!$A:$E,5,FALSE),1,0) -> 1 | AV118: =IF(L118=VLOOKUP(VALUE(L$1),Questions!$A:$E,5,FALSE),1,0) -> 0 | AW118: =IF(M118=VLOOKUP(VALUE(M$1),Questions!$A:$E,5,FALSE),1,0) -> 1 | AX118: =IF(N118=VLOOKUP(VALUE(N$1),Questions!$A:$E,5,FALSE),1,0) -> 1 | AY118: =IF(O118=VLOOKUP(VALUE(O$1),Questions!$A:$E,5,FALSE),1,0) -> 0 | ... BS118: =IF(AI118=VLOOKUP(VALUE(AI$1),Questions!$A:$E,5,FALSE),1,0) -> 1
A119: 118 | B119: FALSE | C119: FALSE | D119: =SUM(Scores[[#This Row],[Q1]:[Q28]]) -> 10 | E119: =SUM(Scores[[#This Row],[29]:[34b]]) -> 0 | F119: =Scores[[#This Row],[35]] -> 0 | G119: =INDEX('Conversion Chart'!$C$3:$M$38,MATCH(SUM(Scores[[#This Row],[MC]:[CRQ]]),'Conversion Chart'!$B$3:$B$38,0),MATCH(Scores[[#This Row],[EIE]],'Conversion Chart'!$C$2:$M$2,0)) -> 30 | H119: 4 | I119: 1 | J119: 1 | K119: 4 | L119: 3 | M119: 3 | N119: 3 | P119: 4 | Q119: 1 | R119: 1 | S119: 4 | T119: 4 | U119: 4 | V119: 1 | W119: 4 | X119: 3 | Y119: 2 | Z119: 2 | AA119: 1 | AB119: 3 | AC119: 4 | AD119: 1 | AE119: 2 | AF119: 2 | AG119: 3 | AH119: 4 | AI119: 1 | AR119: =IF(H119=VLOOKUP(VALUE(H$1),Questions!$A:$E,5,FALSE),1,0) -> 1 | AS119: =IF(I119=VLOOKUP(VALUE(I$1),Questions!$A:$E,5,FALSE),1,0) -> 0 | AT119: =IF(J119=VLOOKUP(VALUE(J$1),Questions!$A:$E,5,FALSE),1,0) -> 1 | AU119: =IF(K119=VLOOKUP(VALUE(K$1),Questions!$A:$E,5,FALSE),1,0) -> 0 | AV119: =IF(L119=VLOOKUP(VALUE(L$1),Questions!$A:$E,5,FALSE),1,0) -> 0 | AW119: =IF(M119=VLOOKUP(VALUE(M$1),Questions!$A:$E,5,FALSE),1,0) -> 0 | AX119: =IF(N119=VLOOKUP(VALUE(N$1),Questions!$A:$E,5,FALSE),1,0) -> 1 | AY119: =IF(O119=VLOOKUP(VALUE(O$1),Questions!$A:$E,5,FALSE),1,0) -> 0 | ... BS119: =IF(AI119=VLOOKUP(VALUE(AI$1),Questions!$A:$E,5,FALSE),1,0) -> 1
A120: 119 | B120: FALSE | C120: FALSE | D120: =SUM(Scores[[#This Row],[Q1]:[Q28]]) -> 27 | E120: =SUM(Scores[[#This Row],[29]:[34b]]) -> 0 | F120: =Scores[[#This Row],[35]] -> 0 | G120: =INDEX('Conversion Chart'!$C$3:$M$38,MATCH(SUM(Scores[[#This Row],[MC]:[CRQ]]),'Conversion Chart'!$B$3:$B$38,0),MATCH(Scores[[#This Row],[EIE]],'Conversion Chart'!$C$2:$M$2,0)) -> 66 | H120: 4 | I120: 3 | J120: 1 | K120: 2 | L120: 2 | M120: 4 | N120: 3 | O120: 1 | P120: 1 | Q120: 1 | R120: 4 | S120: 2 | T120: 1 | U120: 4 | V120: 3 | W120: 4 | X120: 2 | Y120: 3 | Z120: 3 | AA120: 3 | AB120: 2 | AC120: 1 | AD120: 3 | AE120: 2 | AF120: 4 | AG120: 3 | AH120: 1 | AI120: 1 | AR120: =IF(H120=VLOOKUP(VALUE(H$1),Questions!$A:$E,5,FALSE),1,0) -> 1 | AS120: =IF(I120=VLOOKUP(VALUE(I$1),Questions!$A:$E,5,FALSE),1,0) -> 1 | AT120: =IF(J120=VLOOKUP(VALUE(J$1),Questions!$A:$E,5,FALSE),1,0) -> 1 | AU120: =IF(K120=VLOOKUP(VALUE(K$1),Questions!$A:$E,5,FALSE),1,0) -> 1 | AV120: =IF(L120=VLOOKUP(VALUE(L$1),Questions!$A:$E,5,FALSE),1,0) -> 1 | AW120: =IF(M120=VLOOKUP(VALUE(M$1),Questions!$A:$E,5,FALSE),1,0) -> 1 | AX120: =IF(N120=VLOOKUP(VALUE(N$1),Questions!$A:$E,5,FALSE),1,0) -> 1 | AY120: =IF(O120=VLOOKUP(VALUE(O$1),Questions!$A:$E,5,FALSE),1,0) -> 1 | ... BS120: =IF(AI120=VLOOKUP(VALUE(AI$1),Questions!$A:$E,5,FALSE),1,0) -> 1
A121: 120 | B121: FALSE | C121: TRUE | D121: =SUM(Scores[[#This Row],[Q1]:[Q28]]) -> 8 | E121: =SUM(Scores[[#This Row],[29]:[34b]]) -> 0 | F121: =Scores[[#This Row],[35]] -> 0 | G121: =INDEX('Conversion Chart'!$C$3:$M$38,MATCH(SUM(Scores[[#This Row],[MC]:[CRQ]]),'Conversion Chart'!$B$3:$B$38,0),MATCH(Scores[[#This Row],[EIE]],'Conversion Chart'!$C$2:$M$2,0)) -> 25 | H121: 1 | I121: 2 | J121: 2 | K121: 1 | L121: 1 | M121: 2 | N121: 1 | O121: 4 | P121: 2 | Q121: 2 | R121: 4 | S121: 2 | T121: 1 | U121: 4 | V121: 3 | W121: 4 | X121: 1 | Y121: 1 | Z121: 2 | AA121: 4 | AB121: 4 | AC121: 3 | AD121: 2 | AE121: 1 | AF121: 4 | AG121: 2 | AH121: 4 | AI121: 3 | AR121: =IF(H121=VLOOKUP(VALUE(H$1),Questions!$A:$E,5,FALSE),1,0) -> 0 | AS121: =IF(I121=VLOOKUP(VALUE(I$1),Questions!$A:$E,5,FALSE),1,0) -> 0 | AT121: =IF(J121=VLOOKUP(VALUE(J$1),Questions!$A:$E,5,FALSE),1,0) -> 0 | AU121: =IF(K121=VLOOKUP(VALUE(K$1),Questions!$A:$E,5,FALSE),1,0) -> 0 | AV121: =IF(L121=VLOOKUP(VALUE(L$1),Questions!$A:$E,5,FALSE),1,0) -> 0 | AW121: =IF(M121=VLOOKUP(VALUE(M$1),Questions!$A:$E,5,FALSE),1,0) -> 0 | AX121: =IF(N121=VLOOKUP(VALUE(N$1),Questions!$A:$E,5,FALSE),1,0) -> 0 | AY121: =IF(O121=VLOOKUP(VALUE(O$1),Questions!$A:$E,5,FALSE),1,0) -> 0 | ... BS121: =IF(AI121=VLOOKUP(VALUE(AI$1),Questions!$A:$E,5,FALSE),1,0) -> 0
A122: 121 | B122: FALSE | C122: TRUE | D122: =SUM(Scores[[#This Row],[Q1]:[Q28]]) -> 24 | E122: =SUM(Scores[[#This Row],[29]:[34b]]) -> 0 | F122: =Scores[[#This Row],[35]] -> 0 | G122: =INDEX('Conversion Chart'!$C$3:$M$38,MATCH(SUM(Scores[[#This Row],[MC]:[CRQ]]),'Conversion Chart'!$B$3:$B$38,0),MATCH(Scores[[#This Row],[EIE]],'Conversion Chart'!$C$2:$M$2,0)) -> 61 | H122: 4 | I122: 3 | J122: 1 | K122: 2 | L122: 2 | M122: 4 | N122: 3 | O122: 4 | P122: 1 | Q122: 1 | R122: 4 | S122: 3 | T122: 1 | U122: 4 | V122: 3 | W122: 4 | X122: 2 | Y122: 3 | Z122: 2 | AA122: 2 | AB122: 3 | AC122: 1 | AD122: 3 | AE122: 2 | AF122: 4 | AG122: 3 | AH122: 1 | AI122: 1 | AR122: =IF(H122=VLOOKUP(VALUE(H$1),Questions!$A:$E,5,FALSE),1,0) -> 1 | AS122: =IF(I122=VLOOKUP(VALUE(I$1),Questions!$A:$E,5,FALSE),1,0) -> 1 | AT122: =IF(J122=VLOOKUP(VALUE(J$1),Questions!$A:$E,5,FALSE),1,0) -> 1 | AU122: =IF(K122=VLOOKUP(VALUE(K$1),Questions!$A:$E,5,FALSE),1,0) -> 1 | AV122: =IF(L122=VLOOKUP(VALUE(L$1),Questions!$A:$E,5,FALSE),1,0) -> 1 | AW122: =IF(M122=VLOOKUP(VALUE(M$1),Questions!$A:$E,5,FALSE),1,0) -> 1 | AX122: =IF(N122=VLOOKUP(VALUE(N$1),Questions!$A:$E,5,FALSE),1,0) -> 1 | AY122: =IF(O122=VLOOKUP(VALUE(O$1),Questions!$A:$E,5,FALSE),1,0) -> 0 | ... BS122: =IF(AI122=VLOOKUP(VALUE(AI$1),Questions!$A:$E,5,FALSE),1,0) -> 1
A123: 122 | B123: FALSE | C123: FALSE | D123: =SUM(Scores[[#This Row],[Q1]:[Q28]]) -> 17 | E123: =SUM(Scores[[#This Row],[29]:[34b]]) -> 0 | F123: =Scores[[#This Row],[35]] -> 0 | G123: =INDEX('Conversion Chart'!$C$3:$M$38,MATCH(SUM(Scores[[#This Row],[MC]:[CRQ]]),'Conversion Chart'!$B$3:$B$38,0),MATCH(Scores[[#This Row],[EIE]],'Conversion Chart'!$C$2:$M$2,0)) -> 47 | H123: 4 | I123: 3 | J123: 1 | K123: 2 | L123: 3 | M123: 2 | N123: 4 | O123: 3 | P123: 1 | Q123: 1 | R123: 4 | S123: 2 | T123: 1 | U123: 2 | V123: 1 | W123: 3 | X123: 1 | Y123: 1 | Z123: 2 | AA123: 3 | AB123: 2 | AC123: 1 | AD123: 3 | AE123: 3 | AF123: 1 | AG123: 3 | AH123: 1 | AI123: 1 | AR123: =IF(H123=VLOOKUP(VALUE(H$1),Questions!$A:$E,5,FALSE),1,0) -> 1 | AS123: =IF(I123=VLOOKUP(VALUE(I$1),Questions!$A:$E,5,FALSE),1,0) -> 1 | AT123: =IF(J123=VLOOKUP(VALUE(J$1),Questions!$A:$E,5,FALSE),1,0) -> 1 | AU123: =IF(K123=VLOOKUP(VALUE(K$1),Questions!$A:$E,5,FALSE),1,0) -> 1 | AV123: =IF(L123=VLOOKUP(VALUE(L$1),Questions!$A:$E,5,FALSE),1,0) -> 0 | AW123: =IF(M123=VLOOKUP(VALUE(M$1),Questions!$A:$E,5,FALSE),1,0) -> 0 | AX123: =IF(N123=VLOOKUP(VALUE(N$1),Questions!$A:$E,5,FALSE),1,0) -> 0 | AY123: =IF(O123=VLOOKUP(VALUE(O$1),Questions!$A:$E,5,FALSE),1,0) -> 0 | ... BS123: =IF(AI123=VLOOKUP(VALUE(AI$1),Questions!$A:$E,5,FALSE),1,0) -> 1
A124: 123 | B124: FALSE | C124: TRUE | D124: =SUM(Scores[[#This Row],[Q1]:[Q28]]) -> 13 | E124: =SUM(Scores[[#This Row],[29]:[34b]]) -> 0 | F124: =Scores[[#This Row],[35]] -> 0 | G124: =INDEX('Conversion Chart'!$C$3:$M$38,MATCH(SUM(Scores[[#This Row],[MC]:[CRQ]]),'Conversion Chart'!$B$3:$B$38,0),MATCH(Scores[[#This Row],[EIE]],'Conversion Chart'!$C$2:$M$2,0)) -> 38 | H124: 4 | I124: 3 | J124: 1 | K124: 1 | L124: 3 | M124: 2 | N124: 3 | O124: 3 | P124: 1 | Q124: 3 | R124: 4 | S124: 4 | T124: 3 | U124: 4 | V124: 3 | W124: 3 | X124: 2 | Y124: 2 | Z124: 2 | AA124: 4 | AB124: 4 | AC124: 1 | AD124: 4 | AE124: 2 | AF124: 4 | AG124: 2 | AH124: 4 | AI124: 2 | AR124: =IF(H124=VLOOKUP(VALUE(H$1),Questions!$A:$E,5,FALSE),1,0) -> 1 | AS124: =IF(I124=VLOOKUP(VALUE(I$1),Questions!$A:$E,5,FALSE),1,0) -> 1 | AT124: =IF(J124=VLOOKUP(VALUE(J$1),Questions!$A:$E,5,FALSE),1,0) -> 1 | AU124: =IF(K124=VLOOKUP(VALUE(K$1),Questions!$A:$E,5,FALSE),1,0) -> 0 | AV124: =IF(L124=VLOOKUP(VALUE(L$1),Questions!$A:$E,5,FALSE),1,0) -> 0 | AW124: =IF(M124=VLOOKUP(VALUE(M$1),Questions!$A:$E,5,FALSE),1,0) -> 0 | AX124: =IF(N124=VLOOKUP(VALUE(N$1),Questions!$A:$E,5,FALSE),1,0) -> 1 | AY124: =IF(O124=VLOOKUP(VALUE(O$1),Questions!$A:$E,5,FALSE),1,0) -> 0 | ... BS124: =IF(AI124=VLOOKUP(VALUE(AI$1),Questions!$A:$E,5,FALSE),1,0) -> 0
A125: 124 | B125: FALSE | C125: FALSE | D125: =SUM(Scores[[#This Row],[Q1]:[Q28]]) -> 7 | E125: =SUM(Scores[[#This Row],[29]:[34b]]) -> 0 | F125: =Scores[[#This Row],[35]] -> 0 | G125: =INDEX('Conversion Chart'!$C$3:$M$38,MATCH(SUM(Scores[[#This Row],[MC]:[CRQ]]),'Conversion Chart'!$B$3:$B$38,0),MATCH(Scores[[#This Row],[EIE]],'Conversion Chart'!$C$2:$M$2,0)) -> 22 | H125: 2 | I125: 1 | J125: 2 | K125: 1 | L125: 2 | M125: 4 | N125: 1 | O125: 2 | P125: 4 | Q125: 4 | R125: 3 | S125: 3 | T125: 3 | U125: 4 | V125: 1 | W125: 1 | X125: 3 | Y125: 3 | Z125: 2 | AA125: 4 | AB125: 1 | AC125: 3 | AD125: 3 | AE125: 2 | AF125: 3 | AG125: 4 | AH125: 4 | AI125: 2 | AR125: =IF(H125=VLOOKUP(VALUE(H$1),Questions!$A:$E,5,FALSE),1,0) -> 0 | AS125: =IF(I125=VLOOKUP(VALUE(I$1),Questions!$A:$E,5,FALSE),1,0) -> 0 | AT125: =IF(J125=VLOOKUP(VALUE(J$1),Questions!$A:$E,5,FALSE),1,0) -> 0 | AU125: =IF(K125=VLOOKUP(VALUE(K$1),Questions!$A:$E,5,FALSE),1,0) -> 0 | AV125: =IF(L125=VLOOKUP(VALUE(L$1),Questions!$A:$E,5,FALSE),1,0) -> 1 | AW125: =IF(M125=VLOOKUP(VALUE(M$1),Questions!$A:$E,5,FALSE),1,0) -> 1 | AX125: =IF(N125=VLOOKUP(VALUE(N$1),Questions!$A:$E,5,FALSE),1,0) -> 0 | AY125: =IF(O125=VLOOKUP(VALUE(O$1),Questions!$A:$E,5,FALSE),1,0) -> 0 | ... BS125: =IF(AI125=VLOOKUP(VALUE(AI$1),Questions!$A:$E,5,FALSE),1,0) -> 0
A126: 125 | B126: FALSE | C126: FALSE | D126: =SUM(Scores[[#This Row],[Q1]:[Q28]]) -> 22 | E126: =SUM(Scores[[#This Row],[29]:[34b]]) -> 0 | F126: =Scores[[#This Row],[35]] -> 0 | G126: =INDEX('Conversion Chart'!$C$3:$M$38,MATCH(SUM(Scores[[#This Row],[MC]:[CRQ]]),'Conversion Chart'!$B$3:$B$38,0),MATCH(Scores[[#This Row],[EIE]],'Conversion Chart'!$C$2:$M$2,0)) -> 57 | H126: 4 | I126: 3 | J126: 1 | K126: 2 | L126: 2 | M126: 4 | N126: 3 | O126: 1 | P126: 1 | Q126: 1 | R126: 4 | S126: 2 | T126: 1 | U126: 4 | V126: 3 | W126: 2 | X126: 2 | Y126: 3 | Z126: 1 | AA126: 3 | AB126: 2 | AC126: 1 | AD126: 4 | AE126: 2 | AF126: 3 | AG126: 2 | AH126: 1 | AI126: 4 | AR126: =IF(H126=VLOOKUP(VALUE(H$1),Questions!$A:$E,5,FALSE),1,0) -> 1 | AS126: =IF(I126=VLOOKUP(VALUE(I$1),Questions!$A:$E,5,FALSE),1,0) -> 1 | AT126: =IF(J126=VLOOKUP(VALUE(J$1),Questions!$A:$E,5,FALSE),1,0) -> 1 | AU126: =IF(K126=VLOOKUP(VALUE(K$1),Questions!$A:$E,5,FALSE),1,0) -> 1 | AV126: =IF(L126=VLOOKUP(VALUE(L$1),Questions!$A:$E,5,FALSE),1,0) -> 1 | AW126: =IF(M126=VLOOKUP(VALUE(M$1),Questions!$A:$E,5,FALSE),1,0) -> 1 | AX126: =IF(N126=VLOOKUP(VALUE(N$1),Questions!$A:$E,5,FALSE),1,0) -> 1 | AY126: =IF(O126=VLOOKUP(VALUE(O$1),Questions!$A:$E,5,FALSE),1,0) -> 1 | ... BS126: =IF(AI126=VLOOKUP(VALUE(AI$1),Questions!$A:$E,5,FALSE),1,0) -> 0
A127: 126 | B127: FALSE | C127: TRUE | D127: =SUM(Scores[[#This Row],[Q1]:[Q28]]) -> 22 | E127: =SUM(Scores[[#This Row],[29]:[34b]]) -> 0 | F127: =Scores[[#This Row],[35]] -> 0 | G127: =INDEX('Conversion Chart'!$C$3:$M$38,MATCH(SUM(Scores[[#This Row],[MC]:[CRQ]]),'Conversion Chart'!$B$3:$B$38,0),MATCH(Scores[[#This Row],[EIE]],'Conversion Chart'!$C$2:$M$2,0)) -> 57 | H127: 4 | I127: 3 | J127: 1 | K127: 2 | L127: 2 | M127: 4 | N127: 3 | O127: 1 | P127: 1 | Q127: 4 | R127: 4 | S127: 4 | T127: 1 | U127: 4 | V127: 3 | W127: 1 | X127: 2 | Y127: 3 | Z127: 2 | AA127: 1 | AB127: 2 | AC127: 1 | AD127: 1 | AE127: 2 | AF127: 4 | AG127: 3 | AH127: 4 | AI127: 1 | AR127: =IF(H127=VLOOKUP(VALUE(H$1),Questions!$A:$E,5,FALSE),1,0) -> 1 | AS127: =IF(I127=VLOOKUP(VALUE(I$1),Questions!$A:$E,5,FALSE),1,0) -> 1 | AT127: =IF(J127=VLOOKUP(VALUE(J$1),Questions!$A:$E,5,FALSE),1,0) -> 1 | AU127: =IF(K127=VLOOKUP(VALUE(K$1),Questions!$A:$E,5,FALSE),1,0) -> 1 | AV127: =IF(L127=VLOOKUP(VALUE(L$1),Questions!$A:$E,5,FALSE),1,0) -> 1 | AW127: =IF(M127=VLOOKUP(VALUE(M$1),Questions!$A:$E,5,FALSE),1,0) -> 1 | AX127: =IF(N127=VLOOKUP(VALUE(N$1),Questions!$A:$E,5,FALSE),1,0) -> 1 | AY127: =IF(O127=VLOOKUP(VALUE(O$1),Questions!$A:$E,5,FALSE),1,0) -> 1 | ... BS127: =IF(AI127=VLOOKUP(VALUE(AI$1),Questions!$A:$E,5,FALSE),1,0) -> 1
A128: 127 | B128: FALSE | C128: TRUE | D128: =SUM(Scores[[#This Row],[Q1]:[Q28]]) -> 22 | E128: =SUM(Scores[[#This Row],[29]:[34b]]) -> 0 | F128: =Scores[[#This Row],[35]] -> 0 | G128: =INDEX('Conversion Chart'!$C$3:$M$38,MATCH(SUM(Scores[[#This Row],[MC]:[CRQ]]),'Conversion Chart'!$B$3:$B$38,0),MATCH(Scores[[#This Row],[EIE]],'Conversion Chart'!$C$2:$M$2,0)) -> 57 | H128: 4 | I128: 3 | J128: 1 | K128: 2 | L128: 2 | M128: 4 | N128: 3 | O128: 4 | P128: 1 | Q128: 1 | R128: 4 | S128: 3 | T128: 1 | U128: 4 | V128: 3 | W128: 4 | X128: 3 | Y128: 2 | Z128: 2 | AA128: 2 | AB128: 3 | AC128: 1 | AD128: 3 | AE128: 2 | AF128: 4 | AG128: 3 | AH128: 1 | AI128: 1 | AR128: =IF(H128=VLOOKUP(VALUE(H$1),Questions!$A:$E,5,FALSE),1,0) -> 1 | AS128: =IF(I128=VLOOKUP(VALUE(I$1),Questions!$A:$E,5,FALSE),1,0) -> 1 | AT128: =IF(J128=VLOOKUP(VALUE(J$1),Questions!$A:$E,5,FALSE),1,0) -> 1 | AU128: =IF(K128=VLOOKUP(VALUE(K$1),Questions!$A:$E,5,FALSE),1,0) -> 1 | AV128: =IF(L128=VLOOKUP(VALUE(L$1),Questions!$A:$E,5,FALSE),1,0) -> 1 | AW128: =IF(M128=VLOOKUP(VALUE(M$1),Questions!$A:$E,5,FALSE),1,0) -> 1 | AX128: =IF(N128=VLOOKUP(VALUE(N$1),Questions!$A:$E,5,FALSE),1,0) -> 1 | AY128: =IF(O128=VLOOKUP(VALUE(O$1),Questions!$A:$E,5,FALSE),1,0) -> 0 | ... BS128: =IF(AI128=VLOOKUP(VALUE(AI$1),Questions!$A:$E,5,FALSE),1,0) -> 1
A129: 128 | B129: FALSE | C129: FALSE | D129: =SUM(Scores[[#This Row],[Q1]:[Q28]]) -> 6 | E129: =SUM(Scores[[#This Row],[29]:[34b]]) -> 0 | F129: =Scores[[#This Row],[35]] -> 0 | G129: =INDEX('Conversion Chart'!$C$3:$M$38,MATCH(SUM(Scores[[#This Row],[MC]:[CRQ]]),'Conversion Chart'!$B$3:$B$38,0),MATCH(Scores[[#This Row],[EIE]],'Conversion Chart'!$C$2:$M$2,0)) -> 19 | H129: 3 | I129: 2 | J129: 1 | K129: 4 | L129: 4 | M129: 3 | N129: 3 | O129: 1 | P129: 3 | Q129: 4 | R129: 1 | S129: 3 | T129: 2 | U129: 1 | V129: 4 | W129: 1 | X129: 4 | Y129: 3 | Z129: 4 | AA129: 2 | AB129: 1 | AC129: 4 | AD129: 3 | AE129: 2 | AF129: 1 | AG129: 2 | AH129: 2 | AI129: 3 | AR129: =IF(H129=VLOOKUP(VALUE(H$1),Questions!$A:$E,5,FALSE),1,0) -> 0 | AS129: =IF(I129=VLOOKUP(VALUE(I$1),Questions!$A:$E,5,FALSE),1,0) -> 0 | AT129: =IF(J129=VLOOKUP(VALUE(J$1),Questions!$A:$E,5,FALSE),1,0) -> 1 | AU129: =IF(K129=VLOOKUP(VALUE(K$1),Questions!$A:$E,5,FALSE),1,0) -> 0 | AV129: =IF(L129=VLOOKUP(VALUE(L$1),Questions!$A:$E,5,FALSE),1,0) -> 0 | AW129: =IF(M129=VLOOKUP(VALUE(M$1),Questions!$A:$E,5,FALSE),1,0) -> 0 | AX129: =IF(N129=VLOOKUP(VALUE(N$1),Questions!$A:$E,5,FALSE),1,0) -> 1 | AY129: =IF(O129=VLOOKUP(VALUE(O$1),Questions!$A:$E,5,FALSE),1,0) -> 1 | ... BS129: =IF(AI129=VLOOKUP(VALUE(AI$1),Questions!$A:$E,5,FALSE),1,0) -> 0
A130: 129 | B130: FALSE | C130: TRUE | D130: =SUM(Scores[[#This Row],[Q1]:[Q28]]) -> 17 | E130: =SUM(Scores[[#This Row],[29]:[34b]]) -> 0 | F130: =Scores[[#This Row],[35]] -> 0 | G130: =INDEX('Conversion Chart'!$C$3:$M$38,MATCH(SUM(Scores[[#This Row],[MC]:[CRQ]]),'Conversion Chart'!$B$3:$B$38,0),MATCH(Scores[[#This Row],[EIE]],'Conversion Chart'!$C$2:$M$2,0)) -> 47 | H130: 4 | I130: 3 | J130: 1 | K130: 3 | L130: 1 | M130: 2 | N130: 3 | O130: 3 | P130: 1 | Q130: 3 | R130: 4 | S130: 2 | T130: 1 | U130: 4 | V130: 1 | W130: 1 | X130: 2 | Y130: 4 | Z130: 1 | AA130: 3 | AB130: 2 | AC130: 2 | AD130: 2 | AE130: 2 | AF130: 4 | AG130: 3 | AH130: 1 | AI130: 1 | AR130: =IF(H130=VLOOKUP(VALUE(H$1),Questions!$A:$E,5,FALSE),1,0) -> 1 | AS130: =IF(I130=VLOOKUP(VALUE(I$1),Questions!$A:$E,5,FALSE),1,0) -> 1 | AT130: =IF(J130=VLOOKUP(VALUE(J$1),Questions!$A:$E,5,FALSE),1,0) -> 1 | AU130: =IF(K130=VLOOKUP(VALUE(K$1),Questions!$A:$E,5,FALSE),1,0) -> 0 | AV130: =IF(L130=VLOOKUP(VALUE(L$1),Questions!$A:$E,5,FALSE),1,0) -> 0 | AW130: =IF(M130=VLOOKUP(VALUE(M$1),Questions!$A:$E,5,FALSE),1,0) -> 0 | AX130: =IF(N130=VLOOKUP(VALUE(N$1),Questions!$A:$E,5,FALSE),1,0) -> 1 | AY130: =IF(O130=VLOOKUP(VALUE(O$1),Questions!$A:$E,5,FALSE),1,0) -> 0 | ... BS130: =IF(AI130=VLOOKUP(VALUE(AI$1),Questions!$A:$E,5,FALSE),1,0) -> 1
A131: 130 | B131: FALSE | C131: TRUE | D131: =SUM(Scores[[#This Row],[Q1]:[Q28]]) -> 7 | E131: =SUM(Scores[[#This Row],[29]:[34b]]) -> 0 | F131: =Scores[[#This Row],[35]] -> 0 | G131: =INDEX('Conversion Chart'!$C$3:$M$38,MATCH(SUM(Scores[[#This Row],[MC]:[CRQ]]),'Conversion Chart'!$B$3:$B$38,0),MATCH(Scores[[#This Row],[EIE]],'Conversion Chart'!$C$2:$M$2,0)) -> 22 | H131: 4 | I131: 4 | J131: 1 | K131: 2 | L131: 3 | M131: 3 | N131: 3 | O131: 4 | P131: 4 | Q131: 3 | R131: 3 | S131: 1 | T131: 1 | U131: 2 | V131: 2 | W131: 4 | X131: 3 | Y131: 1 | Z131: 2 | AA131: 4 | AB131: 3 | AC131: 3 | AD131: 2 | AE131: 4 | AF131: 1 | AG131: 1 | AH131: 2 | AI131: 4 | AR131: =IF(H131=VLOOKUP(VALUE(H$1),Questions!$A:$E,5,FALSE),1,0) -> 1 | AS131: =IF(I131=VLOOKUP(VALUE(I$1),Questions!$A:$E,5,FALSE),1,0) -> 0 | AT131: =IF(J131=VLOOKUP(VALUE(J$1),Questions!$A:$E,5,FALSE),1,0) -> 1 | AU131: =IF(K131=VLOOKUP(VALUE(K$1),Questions!$A:$E,5,FALSE),1,0) -> 1 | AV131: =IF(L131=VLOOKUP(VALUE(L$1),Questions!$A:$E,5,FALSE),1,0) -> 0 | AW131: =IF(M131=VLOOKUP(VALUE(M$1),Questions!$A:$E,5,FALSE),1,0) -> 0 | AX131: =IF(N131=VLOOKUP(VALUE(N$1),Questions!$A:$E,5,FALSE),1,0) -> 1 | AY131: =IF(O131=VLOOKUP(VALUE(O$1),Questions!$A:$E,5,FALSE),1,0) -> 0 | ... BS131: =IF(AI131=VLOOKUP(VALUE(AI$1),Questions!$A:$E,5,FALSE),1,0) -> 0
A132: 131 | B132: FALSE | C132: FALSE | D132: =SUM(Scores[[#This Row],[Q1]:[Q28]]) -> 0 | E132: =SUM(Scores[[#This Row],[29]:[34b]]) -> 0 | F132: =Scores[[#This Row],[35]] -> 0 | G132: =INDEX('Conversion Chart'!$C$3:$M$38,MATCH(SUM(Scores[[#This Row],[MC]:[CRQ]]),'Conversion Chart'!$B$3:$B$38,0),MATCH(Scores[[#This Row],[EIE]],'Conversion Chart'!$C$2:$M$2,0)) -> 0 | AR132: =IF(H132=VLOOKUP(VALUE(H$1),Questions!$A:$E,5,FALSE),1,0) -> 0 | AS132: =IF(I132=VLOOKUP(VALUE(I$1),Questions!$A:$E,5,FALSE),1,0) -> 0 | AT132: =IF(J132=VLOOKUP(VALUE(J$1),Questions!$A:$E,5,FALSE),1,0) -> 0 | AU132: =IF(K132=VLOOKUP(VALUE(K$1),Questions!$A:$E,5,FALSE),1,0) -> 0 | AV132: =IF(L132=VLOOKUP(VALUE(L$1),Questions!$A:$E,5,FALSE),1,0) -> 0 | AW132: =IF(M132=VLOOKUP(VALUE(M$1),Questions!$A:$E,5,FALSE),1,0) -> 0 | AX132: =IF(N132=VLOOKUP(VALUE(N$1),Questions!$A:$E,5,FALSE),1,0) -> 0 | AY132: =IF(O132=VLOOKUP(VALUE(O$1),Questions!$A:$E,5,FALSE),1,0) -> 0 | ... BS132: =IF(AI132=VLOOKUP(VALUE(AI$1),Questions!$A:$E,5,FALSE),1,0) -> 0
...

Sheet Questions
A1: # | B1: Part | C1: Stimulus | D1: Question | E1: Answer | F1: Option_1 | G1: Option_2 | H1: Option_3 | I1: Option_4 | J1: Stimulus_type | K1: Source_type | L1: Task_model | M1: Skill_standard | N1: Need_OI? | O1: Content_standard | P1: Content_specification | Q1: Pct_correct | R1: Pt_biserial
A2: 1 | B2: Part I | C2: Passage on the Kingdom of Benin | D2: Which claim about Benin is best supported by this passage? | E2: 4 | F2: Its artisans produced goods for domestic use only | G2: It was fighting a war with Portugal | H2: Its wealth came from plantation agriculture | I2: It was engaged in vast trade networks | J2: Text-based | K2: Secondary | L2: 4. Claim Validity (Without Outside Information) | M2: A.5: Inferences & Conclusions | N2: No | O2: 10.01b.3 | P2: =IFERROR(VLOOKUP(Questions[[#This Row],[Content_standard]],Content[#All],2),"") -> Comparing Empire's Geography & Power | Q2: =AVERAGE(INDEX(Scores[#Data],0,MATCH("Q"&$A2,Scores[#Headers],0))) -> 0.79259259 | R2: =IFERROR(CORREL(INDEX(Scores[#Data],0,MATCH("Q"&$A2,Scores[#Headers],0)),Scores[MC]),"") -> 0.48014997
A3: 2 | B3: Part I | C3: Passage on Mughal religious intolerance | D3: Which claim is best supported by this passage? | E3: 3 | F3: The threat of the British unified Hindus and Muslims in the 1700s | G3: The military campaigns of Aurangzeb led to prosperity for Muslims in India | H3: Aurangzeb's rule was characterized by intolerance and oppression of Hindus | I3: The end of the Mughal Dynasty was marked by advances in learning and scholarship | J3: Text-based | K3: Secondary | L3: 4. Claim Validity (Without Outside Information) | M3: A.5: Inferences & Conclusions | N3: No | O3: 10.01a.1 | P3: =IFERROR(VLOOKUP(Questions[[#This Row],[Content_standard]],Content[#All],2),"") -> Mughal & Ottoman (c. 1750) | Q3: =AVERAGE(INDEX(Scores[#Data],0,MATCH("Q"&$A3,Scores[#Headers],0))) -> 0.85185185 | R3: =IFERROR(CORREL(INDEX(Scores[#Data],0,MATCH("Q"&$A3,Scores[#Headers],0)),Scores[MC]),"") -> 0.63750929
A4: 3 | B4: Part I | C4: Passage on Mughal religious intolerance | D4: Based on this passage, which situation was a result of Aurangzeb's actions in India? | E4: 1 | F4: The British seized the opportunity to increase their power in Mughal India | G4: The Puritans of India rebelled against the Muslims | H4: The Mughal rulers limited European trade to a single port | I4: The Mughal dynasty remained strong in India | J4: Text-based | K4: Secondary | L4: 8. Effect | M4: B.2: Cause & Effect | N4: No | O4: 10.01a.1 | P4: =IFERROR(VLOOKUP(Questions[[#This Row],[Content_standard]],Content[#All],2),"") -> Mughal & Ottoman (c. 1750) | Q4: =AVERAGE(INDEX(Scores[#Data],0,MATCH("Q"&$A4,Scores[#Headers],0))) -> 0.82962963 | R4: =IFERROR(CORREL(INDEX(Scores[#Data],0,MATCH("Q"&$A4,Scores[#Headers],0)),Scores[MC]),"") -> 0.5695502
A5: 4 | B5: Part I | C5: Passage on John Locke | D5: This passage would be most useful to a person attempting to prove the | E5: 2 | F5: importance of Enlightenment thought in supporting the divine right of kings | G5: effect of Enlightenment ideas on future political and economic movements | H5: influence of the Enlightenment on the strengthening of absolutism | I5: rejection of Enlightenment ideas such as natural rights | J5: Text-based | K5: Secondary | L5: 1. Best Use | M5: A.2: Evaluating Sources | N5: No | O5: 10.02a.1 | P5: =IFERROR(VLOOKUP(Questions[[#This Row],[Content_standard]],Content[#All],2),"") -> Political Philosophies | Q5: =AVERAGE(INDEX(Scores[#Data],0,MATCH("Q"&$A5,Scores[#Headers],0))) -> 0.68888889 | R5: =IFERROR(CORREL(INDEX(Scores[#Data],0,MATCH("Q"&$A5,Scores[#Headers],0)),Scores[MC]),"") -> 0.50053948
A6: 5 | B6: Part I | C6: Passage on Tokugawa Japan | D6: One major change in Japan that resulted from the events described in this passage was | E6: 2 | F6: the development of equal treaties | G6: an increase in the efforts to modernize | H6: an increase in the power of the samurai class | I6: the strengthening of isolationist policies | J6: Text-based | K6: Secondary | L6: 8. Effect | M6: B.2: Cause & Effect | N6: Yes | O6: 10.04b.2 | P6: =IFERROR(VLOOKUP(Questions[[#This Row],[Content_standard]],Content[#All],2),"") -> Japanese Reaction to Western Imperialism | Q6: =AVERAGE(INDEX(Scores[#Data],0,MATCH("Q"&$A6,Scores[#Headers],0))) -> 0.58518519 | R6: =IFERROR(CORREL(INDEX(Scores[#Data],0,MATCH("Q"&$A6,Scores[#Headers],0)),Scores[MC]),"") -> 0.59583828
A7: 6 | B7: Part I | C7: Passage on Tokugawa Japan | D7: This passage is most useful for studying | E7: 4 | F7: ways to end peasant protests | G7: the reasons why the Shogunate gained power | H7: ways the Qing conducted military campaigns | I7: the impact of Western imperialism | J7: Text-based | K7: Secondary | L7: 1. Best Use | M7: A.2: Evaluating Sources | N7: No | O7: 10.04b.2 | P7: =IFERROR(VLOOKUP(Questions[[#This Row],[Content_standard]],Content[#All],2),"") -> Japanese Reaction to Western Imperialism | Q7: =AVERAGE(INDEX(Scores[#Data],0,MATCH("Q"&$A7,Scores[#Headers],0))) -> 0.71851852 | R7: =IFERROR(CORREL(INDEX(Scores[#Data],0,MATCH("Q"&$A7,Scores[#Headers],0)),Scores[MC]),"") -> 0.63205205
A8: 7 | B8: Part I | C8: Queen Victoria, Speech to Parliament | D8: Who was most harmed by the circumstances described in this speech? | E8: 3 | F8: government leaders | G8: merchant sailors | H8: tenant farmers | I8: business owners | J8: Text-based | K8: Primary | L8: 14. Stakeholder Issue | M8: A.5: Inferences & Conclusions | N8: Yes | O8: 10.03d.2 | P8: =IFERROR(VLOOKUP(Questions[[#This Row],[Content_standard]],Content[#All],2),"") -> Irish Potato Famine | Q8: =AVERAGE(INDEX(Scores[#Data],0,MATCH("Q"&$A8,Scores[#Headers],0))) -> 0.77037037 | R8: =IFERROR(CORREL(INDEX(Scores[#Data],0,MATCH("Q"&$A8,Scores[#Headers],0)),Scores[MC]),"") -> 0.46030037
A9: 8 | B9: Part I | C9: Queen Victoria, Speech to Parliament | D9: The situation described in this speech resulted in | E9: 1 | F9: mass emigration | G9: a unified global response | H9: a shift to communal farming | I9: implementation of major political reforms | J9: Text-based | K9: Primary | L9: 8. Effect | M9: B.2: Cause & Effect | N9: Yes | O9: 10.03d.2 | P9: =IFERROR(VLOOKUP(Questions[[#This Row],[Content_standard]],Content[#All],2),"") -> Irish Potato Famine | Q9: =AVERAGE(INDEX(Scores[#Data],0,MATCH("Q"&$A9,Scores[#Headers],0))) -> 0.42222222 | R9: =IFERROR(CORREL(INDEX(Scores[#Data],0,MATCH("Q"&$A9,Scores[#Headers],0)),Scores[MC]),"") -> 0.34716625
A10: 9 | B10: Part I | C10: "The Real Trouble Will Come With the Wake" cartoon | D10: Which key event influenced the creation of this image? | E10: 1 | F10: the signing of a series of unequal treaties between China and Western powers | G10: the creation of a multinational intervention to protect Chinese interests | H10: the founding of the Republic of China with Sun Yixian [Sun Yat-sen] as president | I10: The establishment of an alliance between China, the United States, and Britain | J10: Visual-based | K10: Primary | L10: 7. Cause | M10: B.2: Cause & Effect | N10: Yes | O10: 10.04a.2 | P10: =IFERROR(VLOOKUP(Questions[[#This Row],[Content_standard]],Content[#All],2),"") -> Control & Spheres of Influence in Africa & China | Q10: =AVERAGE(INDEX(Scores[#Data],0,MATCH("Q"&$A10,Scores[#Headers],0))) -> 0.68888889 | R10: =IFERROR(CORREL(INDEX(Scores[#Data],0,MATCH("Q"&$A10,Scores[#Headers],0)),Scores[MC]),"") -> 0.53218496
A11: 10 | B11: Part I | C11: "The Real Trouble Will Come With the Wake" cartoon | D11: What do the animals surrounding China symbolize in this cartoon? | E11: 1 | F11: nations seeking economic advantages | G11: allies offering aid to the Qing dynasty | H11: rival countries during World War II | I11: opium-importing countries | J11: Visual-based | K11: Primary | L11: 13. Interpret Visual Data | M11: A.3: Sourcing & Point of View | N11: No | O11: 10.04a.2 | P11: =IFERROR(VLOOKUP(Questions[[#This Row],[Content_standard]],Content[#All],2),"") -> Control & Spheres of Influence in Africa & China | Q11: =AVERAGE(INDEX(Scores[#Data],0,MATCH("Q"&$A11,Scores[#Headers],0))) -> 0.62222222 | R11: =IFERROR(CORREL(INDEX(Scores[#Data],0,MATCH("Q"&$A11,Scores[#Headers],0)),Scores[MC]),"") -> 0.47360812
A12: 11 | B12: Part I | C12: The Treaty of Versailles | D12: For which purpose was this document written? | E12: 4 | F12: to grant independence to former German overseas possessions | G12: to support the rebuilding of the German military | H12: to form a permanent alliance with Germany | I12: to punish Germany for its role in World War I | J12: Text-based | K12: Primary | L12: 2. POV | M12: A.3: Sourcing & Point of View | N12: Yes | O12: 10.05c.1 | P12: =IFERROR(VLOOKUP(Questions[[#This Row],[Content_standard]],Content[#All],2),"") -> Fourteen Points, the Treaty of Versailles, League of Nations, & United Nations | Q12: =AVERAGE(INDEX(Scores[#Data],0,MATCH("Q"&$A12,Scores[#Headers],0))) -> 0.81481481 | R12: =IFERROR(CORREL(INDEX(Scores[#Data],0,MATCH("Q"&$A12,Scores[#Headers],0)),Scores[MC]),"") -> 0.61708233
A13: 12 | B13: Part I | C13: The Treaty of Versailles | D13: Which situation was the result of these articles? | E13: 2 | F13: People in France demanded the right to vote in democratic elections. | G13: Resentment led to the rise of the Nazi Party. | H13: Coal mines were given to Germany to pay for damages. | I13: Allied governments were held responsible for World War I. | J13: Text-based | K13: Primary | L13: 8. Effect | M13: B.2: Cause & Effect | N13: Yes | O13: 10.05c.1 | P13: =IFERROR(VLOOKUP(Questions[[#This Row],[Content_standard]],Content[#All],2),"") -> Fourteen Points, the Treaty of Versailles, League of Nations, & United Nations | Q13: =AVERAGE(INDEX(Scores[#Data],0,MATCH("Q"&$A13,Scores[#Headers],0))) -> 0.46666667 | R13: =IFERROR(CORREL(INDEX(Scores[#Data],0,MATCH("Q"&$A13,Scores[#Headers],0)),Scores[MC]),"") -> 0.51292193
... A29: 28 | B29: Part I | C29: Article on Taliban Afghanistan | D29: Based on this passage, which statement described Khaled Hosseini's point of view? | E29: 1 | F29: Years of working to implement democracy in Afghanistan have been reversed quickly. | G29: The Afghan government needed minimal outside support to function effectively. | H29: The majority of Afghans do not want to change their political institutions. | I29: NATO partners did not do enough to root out corruption in the elected government. | J29: Text-based | K29: Primary | L29: 2. POV | M29: A.3: Sourcing & Point of View | N29: No | O29: 10.08b.2 | P29: =IFERROR(VLOOKUP(Questions[[#This Row],[Content_standard]],Content[#All],2),"") -> Advancements in Communications & Transportation Effect on Authority | Q29: =AVERAGE(INDEX(Scores[#Data],0,MATCH("Q"&$A29,Scores[#Headers],0))) -> 0.71111111 | R29: =IFERROR(CORREL(INDEX(Scores[#Data],0,MATCH("Q"&$A29,Scores[#Headers],0)),Scores[MC]),"") -> 0.58324813
A30: 29 | B30: Part II | C30: Passage on British decolonization of India | D30: Explain the historical circumstances that led to the changes described in this passage. | E30: 1 | J30: Text-based | K30: Secondary | M30: C.6: Historical Context | O30: 10.07a.1 | P30: =IFERROR(VLOOKUP(Questions[[#This Row],[Content_standard]],Content[#All],2),"") -> Gandhi’s Nonviolent Nationalist Movement, the Muslim League, & Partition | R30: =IFERROR(CORREL(INDEX(Scores[#Data],0,MATCH("Q"&$A30,Scores[#Headers],0)),Scores[MC]),"")
A31: 30 | B31: Part II | C31: Photograph of the Partition | D31: Explain how audience affects the way that Margaret Bourke-White present the situation of Muslims in New Delhi, based on this photograph. | E31: 1 | J31: Visual-based | K31: Primary | M31: A.3: Sourcing & Point of View | O31: 10.07a.1 | P31: =IFERROR(VLOOKUP(Questions[[#This Row],[Content_standard]],Content[#All],2),"") -> Gandhi’s Nonviolent Nationalist Movement, the Muslim League, & Partition | R31: =IFERROR(CORREL(INDEX(Scores[#Data],0,MATCH("Q"&$A31,Scores[#Headers],0)),Scores[MC]),"")
A32: 31 | B32: Part II | C32: — | D32: Identify and explain a cause-and-effect relationship between the events and/or ideas found in these documents. Be sure to use evidence from both Documents 1 and 2 in your response. | E32: 1 | M32: B.2: Cause & Effect | P32: =IFERROR(VLOOKUP(Questions[[#This Row],[Content_standard]],Content[#All],2),"") | R32: =IFERROR(CORREL(INDEX(Scores[#Data],0,MATCH("Q"&$A32,Scores[#Headers],0)),Scores[MC]),"")
A33: 32 | B33: Part II | C33: Passage on the invention of the power loom | D33: Explain the historical circumstances that led to the changes described in this excerpt. | E33: 1 | J33: Text-based | K33: Secondary | M33: C.6: Historical Context | O33: 10.03b.3 | P33: =IFERROR(VLOOKUP(Questions[[#This Row],[Content_standard]],Content[#All],2),"") -> Energy, Technology, Communication, & Transportation | R33: =IFERROR(CORREL(INDEX(Scores[#Data],0,MATCH("Q"&$A33,Scores[#Headers],0)),Scores[MC]),"")
A34: 33 | B34: Part II | C34: Factories Inquiry Commission report | D34: Explain the purpose of the 1833 Factory Inquiry Commission's report based on this excerpt. | E34: 1 | J34: Text-based | K34: Primary | M34: A.3: Sourcing & Point of View | O34: 10.03d.1 | P34: =IFERROR(VLOOKUP(Questions[[#This Row],[Content_standard]],Content[#All],2),"") -> Suffrage, Education/ Labor Reforms, & Marxism | R34: =IFERROR(CORREL(INDEX(Scores[#Data],0,MATCH("Q"&$A34,Scores[#Headers],0)),Scores[MC]),"")
A35: 34a | B35: Part II | C35: — | D35: Identify a turning point directly associated with the historical developments found in both Documents 1 and 2. | E35: 1 | M35: B.5: Continuity & Change | P35: =IFERROR(VLOOKUP(Questions[[#This Row],[Content_standard]],Content[#All],2),"") | R35: =IFERROR(CORREL(INDEX(Scores[#Data],0,MATCH("Q"&$A35,Scores[#Headers],0)),Scores[MC]),"")
A36: 34b | B36: Part II | C36: — | D36: Explain how the turning point you identified created significant change, using evidence from both Document 1 and 2. | E36: 1 | M36: B.5: Continuity & Change | P36: =IFERROR(VLOOKUP(Questions[[#This Row],[Content_standard]],Content[#All],2),"") | R36: =IFERROR(CORREL(INDEX(Scores[#Data],0,MATCH("Q"&$A36,Scores[#Headers],0)),Scores[MC]),"")
A37: 35 | B37: Part III | C37: Passage on the Napoleonic Wars | D37: — | J37: Text-based | K37: Secondary | M37: A.7: Synthesizing Evidence | O37: 10.02c.1 | P37: =IFERROR(VLOOKUP(Questions[[#This Row],[Content_standard]],Content[#All],2),"") -> French Revolutions | R37: =IFERROR(CORREL(INDEX(Scores[#Data],0,MATCH("Q"&$A37,Scores[#Headers],0)),Scores[MC]),"")
A38: 35 | B38: Part III | C38: Passage on World War I | D38: — | J38: Text-based | K38: Secondary | M38: A.7: Synthesizing Evidence | O38: 10.05b.1 | P38: =IFERROR(VLOOKUP(Questions[[#This Row],[Content_standard]],Content[#All],2),"") -> Technological Development & Devastation | R38: =IFERROR(CORREL(INDEX(Scores[#Data],0,MATCH("Q"&$A38,Scores[#Headers],0)),Scores[MC]),"")
A39: 35 | B39: Part III | C39: Photographs of Hiroshima Before and After the Atomic Bombing | D39: — | J39: Visual-based | K39: Primary | M39: A.7: Synthesizing Evidence | O39: 10.05b.1 | P39: =IFERROR(VLOOKUP(Questions[[#This Row],[Content_standard]],Content[#All],2),"") -> Technological Development & Devastation | R39: =IFERROR(CORREL(INDEX(Scores[#Data],0,MATCH("Q"&$A39,Scores[#Headers],0)),Scores[MC]),"")
A40: 35 | B40: Part III | C40: Passage on Agent Orange | D40: — | J40: Text-based | K40: Secondary | M40: A.7: Synthesizing Evidence | O40: 10.06b.1 | P40: =IFERROR(VLOOKUP(Questions[[#This Row],[Content_standard]],Content[#All],2),"") -> Cuba, Vietnam, Afghanistan | R40: =IFERROR(CORREL(INDEX(Scores[#Data],0,MATCH("Q"&$A40,Scores[#Headers],0)),Scores[MC]),"")
A41: 35 | B41: Part III | C41: Passage on ISIS's environmental damage | D41: — | J41: Text-based | K41: Primary | M41: A.7: Synthesizing Evidence | O41: 10.09c.3 | P41: =IFERROR(VLOOKUP(Questions[[#This Row],[Content_standard]],Content[#All],2),"") -> Environmental Strains | R41: =IFERROR(CORREL(INDEX(Scores[#Data],0,MATCH("Q"&$A41,Scores[#Headers],0)),Scores[MC]),"")

Sheet Task Models
A1: Model | B1: Detail
A2: 1. Best Use | B2: Students are given a stimulus and asked to evaluate and classify (identify) best use.
A3: 2. POV | B3: Students are given a stimulus and asked to identify point of view, purpose, context, bias, format of source, location of source in time and/or place, and/or intended audience of sources using background knowledge.
A4: 3. Claim Validity (With Outside Information) | B4: Students are given a stimulus and asked to identify support for a claim found in the stimulus (bound in the same timeframe/event/space). It must require students to draw on their knowledge rather than on straight comprehension of text.
A5: 4. Claim Validity (Without Outside Information) | B5: Students are given a stimulus and asked to select a plausible claim that logically follows from evidence presented.
A6: 5. Turning Point | B6: Students are given a stimulus and asked to identify the significance of a turning point in history.
A7: 6. Change Over Time | B7: Students are given a stimulus and asked to identify significance of an event, action, idea, or development as part of change or part of continuity in history.
A8: 7. Cause | B8: Students are given a stimulus and asked to identify a central cause of the described phenomenon.
A9: 8. Effect | B9: Students are given a stimulus and asked to identify a central effect of the described phenomenon.
A10: 9. Impact of Setting | B10: Students are given a stimulus and asked to identify the impact of time and place on an issue or event linked to that stimulus.
A11: 10. Compare | B11: Students are given one stimulus or two stimuli and asked to identify a similarity in the described phenomenon (historical development, historical event, geographic setting, economic situation, individual’s action/belief) (implicit comparison).
A12: 11. Contrast | B12: Students are given one/two stimuli and asked to identify a difference in the described phenomenon (historical development, historical event, geographic setting, economic situation, individual’s action/belief) (implicit comparison).
... A19: 18. Response to Problem | B19: Students are given one stimulus or two stimuli and asked to identify a response to a problem (issue).

Sheet Content Standards
A1: Standard | B1: Concept | C1: Specifications
A2: 10.01a.1 | B2: Mughal & Ottoman (c. 1750) | C2: Students will compare and contrast the Mughal Empire and the Ottoman Empire in 1750 in terms of religious and ethnic tolerance, political organization, and commercial activity.
A3: 10.01a.2 | B3: Tokugawa Shogunate | C3: Students will examine efforts to unify, stabilize, and centralize Japan under the rule of the Tokugawa Shogunate.
A4: 10.01a.3 | B4: Comparing Tokugawa Shogunate & Bourbon Dynasty | C4: Students will compare and contrast the Tokugawa Shogunate in Japan with France under the rule of the Bourbon Dynasty, looking at the role of Edo and Paris/Versailles, attempts to control the daimyo and nobles, and the development of bureaucracies.
A5: 10.01b.1 | B5: Tokugawa & Mughal Responses to Outsiders | C5: Students will compare and contrast the Tokugawa and Mughal responses to outsiders, with attention to the impacts of those decisions.
A6: 10.01b.2 | B6: Eurasia World Map | C6: Students will create a world map showing the extent of European maritime empires, the Russian Empire, the Ottoman Empire, Mughal Empire, China under the Qing Dynasty, Japan under the Tokugawa Shogunate, Ashanti, Benin, and Dahomey ca. 1750.
A7: 10.01b.3 | B7: Comparing Empire's Geography & Power | C7: Students will compare the size of these states, empires, and kingdoms relative to the power they wielded in their regions and in the world.
A8: 10.02a.1 | B8: Political Philosophies | C8: Students will examine at least three Enlightenment thinkers, including John Locke, Baron de Montesquieu, and Jean-Jacques Rousseau, and key ideas from their written works.
A9: 10.02b.1 | B9: Gender & Abolition | C9: Students will explore the influence of Enlightenment ideals on issues of gender and abolition by examining the ideas of individuals such as Mary Wollstonecraft and William Wilberforce.
A10: 10.02b.2 | B10: Enlightened Despots | C10: Students will examine enlightened despots including Catherine the Great.
A11: 10.02c.1 | B11: French Revolutions | C11: Students will examine evidence related to the preconditions of the French Revolution and the course of the revolution, noting the roles of Olympe de Gouges, Maximilien Robespierre, and Napoleon Bonaparte.
A12: 10.02c.2 | B12: Latin American Revolutions | C12: Students will examine the evidence related to the impacts of the French Revolution on resistance and revolutionary movements, noting the roles of Toussaint L'Ouverture and Simon Bolivar.
... A178: 11.11c.3 | B178: US vs China Rivalry | C178: Students will examine the economic relationship and the strategic rivalry between the United States and China.

Sheet Skill Standards
A1: Standard | B1: Concept | C1: Specification
A2: A. Gathering, Interpreting, and Using Evidence | B2: A.1: Framing Questions & Hypotheses | C2: Define and frame questions about events and the world in which we live, form hypotheses as potential answers to these questions, use evidence to answer these questions, and consider and analyze counter-hypotheses.
A3: A. Gathering, Interpreting, and Using Evidence | B3: A.2: Evaluating Sources | C3: Identify, describe, and evaluate evidence about events from diverse sources (including written documents, works of art, photographs, charts and graphs, artifacts, oral traditions, and other primary and secondary sources).
A4: A. Gathering, Interpreting, and Using Evidence | B4: A.3: Sourcing & Point of View | C4: Analyze evidence in terms of content, authorship, point of view, bias, purpose, format, and audience.
A5: A. Gathering, Interpreting, and Using Evidence | B5: A.4: Evaluating Arguments | C5: Describe, analyze, and evaluate arguments of others.
A6: A. Gathering, Interpreting, and Using Evidence | B6: A.5: Inferences & Conclusions | C6: Make inferences and draw conclusions from evidence.
A7: A. Gathering, Interpreting, and Using Evidence | B7: A.6: Constructing Arguments | C7: Deconstruct and construct plausible and persuasive arguments, using evidence.
A8: A. Gathering, Interpreting, and Using Evidence | B8: A.7: Synthesizing Evidence | C8: Create meaningful and persuasive understandings of the past by fusing disparate and relevant evidence from primary and secondary sources and drawing connections to the present.
A9: B. Chronological Reasoning and Causation | B9: B.1: Chronological Relationships | C9: Articulate how events are related chronologically to one another in time and explain the ways in which earlier ideas and events may influence subsequent ideas and events.
A10: B. Chronological Reasoning and Causation | B10: B.2: Cause & Effect | C10: Identify causes and effects using examples from different time periods and courses of study across several grade levels.
A11: B. Chronological Reasoning and Causation | B11: B.3: Multiple Causes & Effects | C11: Identify, analyze, and evaluate the relationship between multiple causes and effects
A12: B. Chronological Reasoning and Causation | B12: B.4: Long-Term vs. Immediate Causes | C12: Distinguish between long-term and immediate causes and multiple effects (time, continuity, and change).
... A42: F. Civic Participation | B42: F.8: Civic Responsibility | C42: Fulfill social and political responsibilities associated with citizenship in a democratic society and interdependent global community by developing awareness of and/or engaging in the political process.

Sheet Conversion Chart
C2: 0 | D2: 0.5 | E2: 1 | F2: 1.5 | G2: 2 | H2: 2.5 | I2: 3 | J2: 3.5 | K2: 4 | L2: 4.5 | M2: 5
B3: 0 | C3: 0 | D3: 5 | E3: 10 | F3: 15 | G3: 19 | H3: 23 | I3: 27 | J3: 31 | K3: 35 | L3: 39 | M3: 42
B4: 1 | C4: 3 | D4: 8 | E4: 13 | F4: 17 | G4: 22 | H4: 26 | I4: 30 | J4: 34 | K4: 38 | L4: 41 | M4: 45
B5: 2 | C5: 7 | D5: 11 | E5: 16 | F5: 20 | G5: 25 | H5: 29 | I5: 32 | J5: 36 | K5: 40 | L5: 44 | M5: 47
B6: 3 | C6: 10 | D6: 15 | E6: 19 | F6: 23 | G6: 27 | H6: 31 | I6: 35 | J6: 39 | K6: 42 | L6: 46 | M6: 49
B7: 4 | C7: 13 | D7: 17 | E7: 22 | F7: 26 | G7: 30 | H7: 34 | I7: 38 | J7: 41 | K7: 45 | L7: 48 | M7: 51
B8: 5 | C8: 16 | D8: 20 | E8: 25 | F8: 29 | G8: 32 | H8: 36 | I8: 40 | J8: 44 | K8: 47 | L8: 50 | M8: 53
B9: 6 | C9: 19 | D9: 23 | E9: 27 | F9: 31 | G9: 35 | H9: 39 | I9: 42 | J9: 46 | K9: 49 | L9: 52 | M9: 55
B10: 7 | C10: 22 | D10: 26 | E10: 30 | F10: 34 | G10: 38 | H10: 41 | I10: 45 | J10: 48 | K10: 51 | L10: 54 | M10: 57
B11: 8 | C11: 25 | D11: 29 | E11: 32 | F11: 36 | G11: 40 | H11: 44 | I11: 47 | J11: 50 | K11: 53 | L11: 56 | M11: 59
B12: 9 | C12: 27 | D12: 31 | E12: 35 | F12: 39 | G12: 42 | H12: 46 | I12: 49 | J12: 52 | K12: 55 | L12: 58 | M12: 61
B13: 10 | C13: 30 | D13: 34 | E13: 38 | F13: 41 | G13: 45 | H13: 48 | I13: 51 | J13: 54 | K13: 57 | L13: 60 | M13: 63
B14: 11 | C14: 32 | D14: 36 | E14: 40 | F14: 44 | G14: 47 | H14: 50 | I14: 53 | J14: 56 | K14: 59 | L14: 62 | M14: 64
... B38: 35 | C38: 77 | D38: 79 | E38: 81 | F38: 83 | G38: 85 | H38: 87 | I38: 89 | J38: 91 | K38: 93 | L38: 96 | M38: 100
C40: Scale Scores to Performance Levels
C41: Level 1: 0 - 54 | E41: Level 2: 55 - 64 | G41: Level 3: 65 - 78 | I41: Level 4: 79 - 84 | K41: Level 5: 85 - 100
