Workbook

Sheet Scores
A1: ID | B1: Grade | C1: Class | D1: ELL | E1: IEP | F1: MC | G1: SEQ | H1: IIIA | I1: IIIB | J1: Final | K1: 1 | L1: 2 | M1: 3 | N1: 4 | O1: 5 | P1: 6 | Q1: 7 | R1: 8 | S1: 9 | T1: 10 | U1: 11 | V1: 12 | W1: 13 | X1: 14 | Y1: 15 | Z1: 16 | AA1: 17 | AB1: 18 | AC1: 19 | AD1: 20 | AE1: 21 | AF1: 22 | AG1: 23 | AH1: 24 | AI1: 25 | AJ1: 26 | AK1: 27 | AL1: 28 | AM1: 29 | AN1: 30 | AO1: 31 | AP1: 32 | AQ1: 33 | AR1: 34 | AS1: 35 | AT1: 36 | AU1: 37 | AV1: Q1 | AW1: Q2 | AX1: Q3 | AY1: Q4 | AZ1: Q5 | BA1: Q6 | BB1: Q7 | BC1: Q8 | BD1: Q9 | BE1: Q10 | BF1: Q11 | BG1: Q12 | BH1: Q13 | BI1: Q14 | BJ1: Q15 | BK1: Q16 | BL1: Q17 | BM1: Q18 | BN1: Q19 | BO1: Q20 | BP1: Q21 | BQ1: Q22 | BR1: Q23 | BS1: Q24 | BT1: Q25 | BU1: Q26 | BV1: Q27 | BW1: Q28 | BX1: Passed? | BY1: Passed*
A2: 1 | B2: 11 | C2: Dushin | D2: FALSE | E2: FALSE | F2: =SUM(Scores[[#This Row],[Q1]:[Q28]]) -> 21 | G2: =SUM(Scores[[#This Row],[29]]:Scores[[#This Row],[30]]) -> 6 | H2: =SUM(Scores[[#This Row],[31]:[36]]) -> 4 | I2: =Scores[[#This Row],[37]] -> 1 | J2: =INDEX('Conversion Chart'!$C$3:$M$47,MATCH(SUM(Scores[[#This Row],[MC]:[IIIA]]),'Conversion Chart'!$B$3:$B$47),MATCH(Scores[[#This Row],[IIIB]],'Conversion Chart'!$C$2:$M$2)) -> 71 | K2: 4 | L2: 2 | N2: 3 | O2: 1 | P2: 4 | Q2: 3 | R2: 1 | S2: 1 | T2: 1 | U2: 2 | V2: 4 | W2: 2 | X2: 4 | Y2: 3 | Z2: 1 | AA2: 1 | AB2: 4 | AC2: 3 | AD2: 4 | AE2: 3 | AF2: 4 | AG2: 3 | AH2: 1 | AI2: 1 | AJ2: 4 | AK2: 4 | AL2: 3 | AM2: 3 | AN2: 3 | AO2: 0 | AP2: 1 | AQ2: 1 | AR2: 0 | AS2: 1 | AT2: 1 | AU2: 1 | AV2: =IF(K2=VLOOKUP(VALUE(K$1),Questions!$A:$E,5,FALSE),1,0) -> 1 | AW2: =IF(L2=VLOOKUP(VALUE(L$1),Questions!$A:$E,5,FALSE),1,0) -> 1 | AX2: =IF(M2=VLOOKUP(VALUE(M$1),Questions!$A:$E,5,FALSE),1,0) -> 0 | AY2: =IF(N2=VLOOKUP(VALUE(N$1),Questions!$A:$E,5,FALSE),1,0) -> 1 | AZ2: =IF(O2=VLOOKUP(VALUE(O$1),Questions!$A:$E,5,FALSE),1,0) -> 1 | BA2: =IF(P2=VLOOKUP(VALUE(P$1),Questions!$A:$E,5,FALSE),1,0) -> 1 | BB2: =IF(Q2=VLOOKUP(VALUE(Q$1),Questions!$A:$E,5,FALSE),1,0) -> 1 | BC2: =IF(R2=VLOOKUP(VALUE(R$1),Questions!$A:$E,5,FALSE),1,0) -> 0 | ... BW2: =IF(AL2=VLOOKUP(VALUE(AL$1),Questions!$A:$E,5,FALSE),1,0) -> 1 | BX2: =IF(Scores[[#This Row],[Final]]>=65,1,0) -> 1 | BY2: =IF(Scores[[#This Row],[Final]]>=IF(Scores[[#This Row],[IEP]],55,65),1,0) -> 1
A3: 2 | B3: 11 | C3: Kovelsky | D3: FALSE | E3: TRUE | F3: =SUM(Scores[[#This Row],[Q1]:[Q28]]) -> 13 | G3: =SUM(Scores[[#This Row],[29]]:Scores[[#This Row],[30]]) -> 4 | H3: =SUM(Scores[[#This Row],[31]:[36]]) -> 6 | I3: =Scores[[#This Row],[37]] -> 1 | J3: =INDEX('Conversion Chart'!$C$3:$M$47,MATCH(SUM(Scores[[#This Row],[MC]:[IIIA]]),'Conversion Chart'!$B$3:$B$47),MATCH(Scores[[#This Row],[IIIB]],'Conversion Chart'!$C$2:$M$2)) -> 61 | K3: 1 | L3: 3 | M3: 3 | N3: 1 | O3: 1 | P3: 3 | Q3: 2 | R3: 2 | S3: 2 | T3: 1 | U3: 2 | V3: 3 | W3: 2 | X3: 3 | Y3: 2 | Z3: 3 | AA3: 3 | AB3: 1 | AC3: 3 | AD3: 2 | AE3: 3 | AF3: 2 | AG3: 3 | AH3: 4 | AI3: 1 | AJ3: 1 | AK3: 1 | AL3: 3 | AM3: 2 | AN3: 2 | AO3: 1 | AP3: 1 | AQ3: 1 | AR3: 1 | AS3: 1 | AT3: 1 | AU3: 1 | AV3: =IF(K3=VLOOKUP(VALUE(K$1),Questions!$A:$E,5,FALSE),1,0) -> 0 | AW3: =IF(L3=VLOOKUP(VALUE(L$1),Questions!$A:$E,5,FALSE),1,0) -> 0 | AX3: =IF(M3=VLOOKUP(VALUE(M$1),Questions!$A:$E,5,FALSE),1,0) -> 1 | AY3: =IF(N3=VLOOKUP(VALUE(N$1),Questions!$A:$E,5,FALSE),1,0) -> 0 | AZ3: =IF(O3=VLOOKUP(VALUE(O$1),Questions!$A:$E,5,FALSE),1,0) -> 1 | BA3: =IF(P3=VLOOKUP(VALUE(P$1),Questions!$A:$E,5,FALSE),1,0) -> 0 | BB3: =IF(Q3=VLOOKUP(VALUE(Q$1),Questions!$A:$E,5,FALSE),1,0) -> 0 | BC3: =IF(R3=VLOOKUP(VALUE(R$1),Questions!$A:$E,5,FALSE),1,0) -> 1 | ... BW3: =IF(AL3=VLOOKUP(VALUE(AL$1),Questions!$A:$E,5,FALSE),1,0) -> 1 | BX3: =IF(Scores[[#This Row],[Final]]>=65,1,0) -> 0 | BY3: =IF(Scores[[#This Row],[Final]]>=IF(Scores[[#This Row],[IEP]],55,65),1,0) -> 1
A4: 3 | B4: 9 | C4: Kovelsky | D4: FALSE | E4: FALSE | F4: =SUM(Scores[[#This Row],[Q1]:[Q28]]) -> 0 | G4: =SUM(Scores[[#This Row],[29]]:Scores[[#This Row],[30]]) -> 0 | H4: =SUM(Scores[[#This Row],[31]:[36]]) -> 0 | I4: =Scores[[#This Row],[37]] -> 0 | J4: =INDEX('Conversion Chart'!$C$3:$M$47,MATCH(SUM(Scores[[#This Row],[MC]:[IIIA]]),'Conversion Chart'!$B$3:$B$47),MATCH(Scores[[#This Row],[IIIB]],'Conversion Chart'!$C$2:$M$2)) -> 0 | AV4: =IF(K4=VLOOKUP(VALUE(K$1),Questions!$A:$E,5,FALSE),1,0) -> 0 | AW4: =IF(L4=VLOOKUP(VALUE(L$1),Questions!$A:$E,5,FALSE),1,0) -> 0 | AX4: =IF(M4=VLOOKUP(VALUE(M$1),Questions!$A:$E,5,FALSE),1,0) -> 0 | AY4: =IF(N4=VLOOKUP(VALUE(N$1),Questions!$A:$E,5,FALSE),1,0) -> 0 | AZ4: =IF(O4=VLOOKUP(VALUE(O$1),Questions!$A:$E,5,FALSE),1,0) -> 0 | BA4: =IF(P4=VLOOKUP(VALUE(P$1),Questions!$A:$E,5,FALSE),1,0) -> 0 | BB4: =IF(Q4=VLOOKUP(VALUE(Q$1),Questions!$A:$E,5,FALSE),1,0) -> 0 | BC4: =IF(R4=VLOOKUP(VALUE(R$1),Questions!$A:$E,5,FALSE),1,0) -> 0 | ... BW4: =IF(AL4=VLOOKUP(VALUE(AL$1),Questions!$A:$E,5,FALSE),1,0) -> 0 | BX4: =IF(Scores[[#This Row],[Final]]>=65,1,0) -> 0 | BY4: =IF(Scores[[#This Row],[Final]]>=IF(Scores[[#This Row],[IEP]],55,65),1,0) -> 0
A5: 4 | B5: 9 | C5: Kovelsky | D5: FALSE | E5: FALSE | F5: =SUM(Scores[[#This Row],[Q1]:[Q28]]) -> 8 | G5: =SUM(Scores[[#This Row],[29]]:Scores[[#This Row],[30]]) -> 0 | H5: =SUM(Scores[[#This Row],[31]:[36]]) -> 6 | I5: =Scores[[#This Row],[37]] -> 0 | J5: =INDEX('Conversion Chart'!$C$3:$M$47,MATCH(SUM(Scores[[#This Row],[MC]:[IIIA]]),'Conversion Chart'!$B$3:$B$47),MATCH(Scores[[#This Row],[IIIB]],'Conversion Chart'!$C$2:$M$2)) -> 40 | K5: 2 | L5: 1 | M5: 3 | N5: 1 | O5: 1 | P5: 4 | Q5: 2 | R5: 3 | S5: 2 | T5: 1 | U5: 3 | V5: 1 | W5: 4 | X5: 2 | Y5: 1 | Z5: 2 | AA5: 2 | AB5: 4 | AC5: 3 | AD5: 4 | AE5: 1 | AF5: 3 | AG5: 2 | AH5: 1 | AI5: 4 | AJ5: 2 | AK5: 4 | AL5: 1 | AM5: 0 | AN5: 0 | AO5: 1 | AP5: 1 | AQ5: 1 | AR5: 1 | AS5: 1 | AT5: 1 | AU5: 0 | AV5: =IF(K5=VLOOKUP(VALUE(K$1),Questions!$A:$E,5,FALSE),1,0) -> 0 | AW5: =IF(L5=VLOOKUP(VALUE(L$1),Questions!$A:$E,5,FALSE),1,0) -> 0 | AX5: =IF(M5=VLOOKUP(VALUE(M$1),Questions!$A:$E,5,FALSE),1,0) -> 1 | AY5: =IF(N5=VLOOKUP(VALUE(N$1),Questions!$A:$E,5,FALSE),1,0) -> 0 | AZ5: =IF(O5=VLOOKUP(VALUE(O$1),Questions!$A:$E,5,FALSE),1,0) -> 1 | BA5: =IF(P5=VLOOKUP(VALUE(P$1),Questions!$A:$E,5,FALSE),1,0) -> 1 | BB5: =IF(Q5=VLOOKUP(VALUE(Q$1),Questions!$A:$E,5,FALSE),1,0) -> 0 | BC5: =IF(R5=VLOOKUP(VALUE(R$1),Questions!$A:$E,5,FALSE),1,0) -> 0 | ... BW5: =IF(AL5=VLOOKUP(VALUE(AL$1),Questions!$A:$E,5,FALSE),1,0) -> 0 | BX5: =IF(Scores[[#This Row],[Final]]>=65,1,0) -> 0 | BY5: =IF(Scores[[#This Row],[Final]]>=IF(Scores[[#This Row],[IEP]],55,65),1,0) -> 0
A6: 5 | B6: 11 | C6: Dushin | D6: FALSE | E6: FALSE | F6: =SUM(Scores[[#This Row],[Q1]:[Q28]]) -> 21 | G6: =SUM(Scores[[#This Row],[29]]:Scores[[#This Row],[30]]) -> 6 | H6: =SUM(Scores[[#This Row],[31]:[36]]) -> 6 | I6: =Scores[[#This Row],[37]] -> 3 | J6: =INDEX('Conversion Chart'!$C$3:$M$47,MATCH(SUM(Scores[[#This Row],[MC]:[IIIA]]),'Conversion Chart'!$B$3:$B$47),MATCH(Scores[[#This Row],[IIIB]],'Conversion Chart'!$C$2:$M$2)) -> 79 | K6: 4 | L6: 2 | M6: 3 | N6: 3 | O6: 1 | P6: 2 | Q6: 3 | R6: 2 | S6: 2 | T6: 1 | U6: 2 | V6: 4 | W6: 2 | X6: 4 | Y6: 1 | Z6: 2 | AA6: 1 | AB6: 4 | AC6: 2 | AD6: 4 | AE6: 2 | AF6: 2 | AG6: 3 | AH6: 3 | AI6: 3 | AJ6: 4 | AK6: 4 | AL6: 2 | AM6: 3 | AN6: 3 | AO6: 1 | AP6: 1 | AQ6: 1 | AR6: 1 | AS6: 1 | AT6: 1 | AU6: 3 | AV6: =IF(K6=VLOOKUP(VALUE(K$1),Questions!$A:$E,5,FALSE),1,0) -> 1 | AW6: =IF(L6=VLOOKUP(VALUE(L$1),Questions!$A:$E,5,FALSE),1,0) -> 1 | AX6: =IF(M6=VLOOKUP(VALUE(M$1),Questions!$A:$E,5,FALSE),1,0) -> 1 | AY6: =IF(N6=VLOOKUP(VALUE(N$1),Questions!$A:$E,5,FALSE),1,0) -> 1 | AZ6: =IF(O6=VLOOKUP(VALUE(O$1),Questions!$A:$E,5,FALSE),1,0) -> 1 | BA6: =IF(P6=VLOOKUP(VALUE(P$1),Questions!$A:$E,5,FALSE),1,0) -> 0 | BB6: =IF(Q6=VLOOKUP(VALUE(Q$1),Questions!$A:$E,5,FALSE),1,0) -> 1 | BC6: =IF(R6=VLOOKUP(VALUE(R$1),Questions!$A:$E,5,FALSE),1,0) -> 1 | ... BW6: =IF(AL6=VLOOKUP(VALUE(AL$1),Questions!$A:$E,5,FALSE),1,0) -> 0 | BX6: =IF(Scores[[#This Row],[Final]]>=65,1,0) -> 1 | BY6: =IF(Scores[[#This Row],[Final]]>=IF(Scores[[#This Row],[IEP]],55,65),1,0) -> 1
A7: 6 | B7: 11 | C7: Dushin | D7: FALSE | E7: FALSE | F7: =SUM(Scores[[#This Row],[Q1]:[Q28]]) -> 15 | G7: =SUM(Scores[[#This Row],[29]]:Scores[[#This Row],[30]]) -> 3 | H7: =SUM(Scores[[#This Row],[31]:[36]]) -> 6 | I7: =Scores[[#This Row],[37]] -> 2 | J7: =INDEX('Conversion Chart'!$C$3:$M$47,MATCH(SUM(Scores[[#This Row],[MC]:[IIIA]]),'Conversion Chart'!$B$3:$B$47),MATCH(Scores[[#This Row],[IIIB]],'Conversion Chart'!$C$2:$M$2)) -> 67 | K7: 4 | L7: 3 | M7: 3 | N7: 1 | O7: 1 | P7: 2 | Q7: 1 | R7: 4 | S7: 3 | T7: 1 | U7: 3 | V7: 4 | W7: 1 | X7: 4 | Y7: 3 | Z7: 1 | AA7: 1 | AB7: 4 | AC7: 3 | AD7: 3 | AE7: 1 | AF7: 2 | AG7: 3 | AH7: 2 | AI7: 3 | AJ7: 4 | AK7: 4 | AL7: 3 | AM7: 2 | AN7: 1 | AO7: 1 | AP7: 1 | AQ7: 1 | AR7: 1 | AS7: 1 | AT7: 1 | AU7: 2 | AV7: =IF(K7=VLOOKUP(VALUE(K$1),Questions!$A:$E,5,FALSE),1,0) -> 1 | AW7: =IF(L7=VLOOKUP(VALUE(L$1),Questions!$A:$E,5,FALSE),1,0) -> 0 | AX7: =IF(M7=VLOOKUP(VALUE(M$1),Questions!$A:$E,5,FALSE),1,0) -> 1 | AY7: =IF(N7=VLOOKUP(VALUE(N$1),Questions!$A:$E,5,FALSE),1,0) -> 0 | AZ7: =IF(O7=VLOOKUP(VALUE(O$1),Questions!$A:$E,5,FALSE),1,0) -> 1 | BA7: =IF(P7=VLOOKUP(VALUE(P$1),Questions!$A:$E,5,FALSE),1,0) -> 0 | BB7: =IF(Q7=VLOOKUP(VALUE(Q$1),Questions!$A:$E,5,FALSE),1,0) -> 0 | BC7: =IF(R7=VLOOKUP(VALUE(R$1),Questions!$A:$E,5,FALSE),1,0) -> 0 | ... BW7: =IF(AL7=VLOOKUP(VALUE(AL$1),Questions!$A:$E,5,FALSE),1,0) -> 1 | BX7: =IF(Scores[[#This Row],[Final]]>=65,1,0) -> 1 | BY7: =IF(Scores[[#This Row],[Final]]>=IF(Scores[[#This Row],[IEP]],55,65),1,0) -> 1
A8: 7 | B8: 11 | C8: Antaky | D8: FALSE | E8: FALSE | F8: =SUM(Scores[[#This Row],[Q1]:[Q28]]) -> 25 | G8: =SUM(Scores[[#This Row],[29]]:Scores[[#This Row],[30]]) -> 6 | H8: =SUM(Scores[[#This Row],[31]:[36]]) -> 6 | I8: =Scores[[#This Row],[37]] -> 4 | J8: =INDEX('Conversion Chart'!$C$3:$M$47,MATCH(SUM(Scores[[#This Row],[MC]:[IIIA]]),'Conversion Chart'!$B$3:$B$47),MATCH(Scores[[#This Row],[IIIB]],'Conversion Chart'!$C$2:$M$2)) -> 86 | K8: 4 | L8: 1 | M8: 3 | N8: 3 | O8: 1 | P8: 4 | Q8: 3 | R8: 2 | S8: 2 | T8: 1 | U8: 2 | V8: 4 | W8: 2 | X8: 4 | Y8: 3 | Z8: 1 | AA8: 1 | AB8: 4 | AC8: 3 | AD8: 1 | AE8: 2 | AF8: 2 | AG8: 3 | AH8: 2 | AI8: 1 | AJ8: 4 | AK8: 1 | AL8: 3 | AM8: 3 | AN8: 3 | AO8: 1 | AP8: 1 | AQ8: 1 | AR8: 1 | AS8: 1 | AT8: 1 | AU8: 4 | AV8: =IF(K8=VLOOKUP(VALUE(K$1),Questions!$A:$E,5,FALSE),1,0) -> 1 | AW8: =IF(L8=VLOOKUP(VALUE(L$1),Questions!$A:$E,5,FALSE),1,0) -> 0 | AX8: =IF(M8=VLOOKUP(VALUE(M$1),Questions!$A:$E,5,FALSE),1,0) -> 1 | AY8: =IF(N8=VLOOKUP(VALUE(N$1),Questions!$A:$E,5,FALSE),1,0) -> 1 | AZ8: =IF(O8=VLOOKUP(VALUE(O$1),Questions!$A:$E,5,FALSE),1,0) -> 1 | BA8: =IF(P8=VLOOKUP(VALUE(P$1),Questions!$A:$E,5,FALSE),1,0) -> 1 | BB8: =IF(Q8=VLOOKUP(VALUE(Q$1),Questions!$A:$E,5,FALSE),1,0) -> 1 | BC8: =IF(R8=VLOOKUP(VALUE(R$1),Questions!$A:$E,5,FALSE),1,0) -> 1 | ... BW8: =IF(AL8=VLOOKUP(VALUE(AL$1),Questions!$A:$E,5,FALSE),1,0) -> 1 | BX8: =IF(Scores[[#This Row],[Final]]>=65,1,0) -> 1 | BY8: =IF(Scores[[#This Row],[Final]]>=IF(Scores[[#This Row],[IEP]],55,65),1,0) -> 1
A9: 8 | B9: 9 | C9: Bermejo | D9: FALSE | E9: FALSE | F9: =SUM(Scores[[#This Row],[Q1]:[Q28]]) -> 21 | G9: =SUM(Scores[[#This Row],[29]]:Scores[[#This Row],[30]]) -> 6 | H9: =SUM(Scores[[#This Row],[31]:[36]]) -> 6 | I9: =Scores[[#This Row],[37]] -> 2 | J9: =INDEX('Conversion Chart'!$C$3:$M$47,MATCH(SUM(Scores[[#This Row],[MC]:[IIIA]]),'Conversion Chart'!$B$3:$B$47),MATCH(Scores[[#This Row],[IIIB]],'Conversion Chart'!$C$2:$M$2)) -> 77 | K9: 3 | L9: 1 | M9: 3 | N9: 3 | O9: 1 | P9: 2 | Q9: 3 | R9: 2 | S9: 2 | T9: 1 | U9: 2 | V9: 4 | W9: 2 | X9: 4 | Y9: 3 | Z9: 1 | AA9: 1 | AB9: 4 | AC9: 3 | AD9: 1 | AE9: 2 | AF9: 2 | AG9: 3 | AH9: 2 | AI9: 3 | AJ9: 4 | AK9: 4 | AL9: 3 | AM9: 3 | AN9: 3 | AO9: 1 | AP9: 1 | AQ9: 1 | AR9: 1 | AS9: 1 | AT9: 1 | AU9: 2 | AV9: =IF(K9=VLOOKUP(VALUE(K$1),Questions!$A:$E,5,FALSE),1,0) -> 0 | AW9: =IF(L9=VLOOKUP(VALUE(L$1),Questions!$A:$E,5,FALSE),1,0) -> 0 | AX9: =IF(M9=VLOOKUP(VALUE(M$1),Questions!$A:$E,5,FALSE),1,0) -> 1 | AY9: =IF(N9=VLOOKUP(VALUE(N$1),Questions!$A:$E,5,FALSE),1,0) -> 1 | AZ9: =IF(O9=VLOOKUP(VALUE(O$1),Questions!$A:$E,5,FALSE),1,0) -> 1 | BA9: =IF(P9=VLOOKUP(VALUE(P$1),Questions!$A:$E,5,FALSE),1,0) -> 0 | BB9: =IF(Q9=VLOOKUP(VALUE(Q$1),Questions!$A:$E,5,FALSE),1,0) -> 1 | BC9: =IF(R9=VLOOKUP(VALUE(R$1),Questions!$A:$E,5,FALSE),1,0) -> 1 | ... BW9: =IF(AL9=VLOOKUP(VALUE(AL$1),Questions!$A:$E,5,FALSE),1,0) -> 1 | BX9: =IF(Scores[[#This Row],[Final]]>=65,1,0) -> 1 | BY9: =IF(Scores[[#This Row],[Final]]>=IF(Scores[[#This Row],[IEP]],55,65),1,0) -> 1
A10: 9 | B10: 11 | C10: Antaky | D10: FALSE | E10: FALSE | F10: =SUM(Scores[[#This Row],[Q1]:[Q28]]) -> 22 | G10: =SUM(Scores[[#This Row],[29]]:Scores[[#This Row],[30]]) -> 6 | H10: =SUM(Scores[[#This Row],[31]:[36]]) -> 6 | I10: =Scores[[#This Row],[37]] -> 2 | J10: =INDEX('Conversion Chart'!$C$3:$M$47,MATCH(SUM(Scores[[#This Row],[MC]:[IIIA]]),'Conversion Chart'!$B$3:$B$47),MATCH(Scores[[#This Row],[IIIB]],'Conversion Chart'!$C$2:$M$2)) -> 77 | K10: 4 | L10: 2 | M10: 4 | N10: 3 | O10: 1 | P10: 4 | Q10: 3 | R10: 3 | S10: 2 | T10: 1 | U10: 2 | V10: 4 | W10: 1 | X10: 4 | Y10: 3 | Z10: 1 | AA10: 1 | AB10: 4 | AC10: 3 | AD10: 1 | AE10: 3 | AF10: 2 | AG10: 3 | AH10: 2 | AI10: 1 | AJ10: 4 | AK10: 1 | AL10: 3 | AM10: 3 | AN10: 3 | AO10: 1 | AP10: 1 | AQ10: 1 | AR10: 1 | AS10: 1 | AT10: 1 | AU10: 2 | AV10: =IF(K10=VLOOKUP(VALUE(K$1),Questions!$A:$E,5,FALSE),1,0) -> 1 | AW10: =IF(L10=VLOOKUP(VALUE(L$1),Questions!$A:$E,5,FALSE),1,0) -> 1 | AX10: =IF(M10=VLOOKUP(VALUE(M$1),Questions!$A:$E,5,FALSE),1,0) -> 0 | AY10: =IF(N10=VLOOKUP(VALUE(N$1),Questions!$A:$E,5,FALSE),1,0) -> 1 | AZ10: =IF(O10=VLOOKUP(VALUE(O$1),Questions!$A:$E,5,FALSE),1,0) -> 1 | BA10: =IF(P10=VLOOKUP(VALUE(P$1),Questions!$A:$E,5,FALSE),1,0) -> 1 | BB10: =IF(Q10=VLOOKUP(VALUE(Q$1),Questions!$A:$E,5,FALSE),1,0) -> 1 | BC10: =IF(R10=VLOOKUP(VALUE(R$1),Questions!$A:$E,5,FALSE),1,0) -> 0 | ... BW10: =IF(AL10=VLOOKUP(VALUE(AL$1),Questions!$A:$E,5,FALSE),1,0) -> 1 | BX10: =IF(Scores[[#This Row],[Final]]>=65,1,0) -> 1 | BY10: =IF(Scores[[#This Row],[Final]]>=IF(Scores[[#This Row],[IEP]],55,65),1,0) -> 1
A11: 10 | B11: 9 | C11: Bermejo | D11: FALSE | E11: FALSE | F11: =SUM(Scores[[#This Row],[Q1]:[Q28]]) -> 0 | G11: =SUM(Scores[[#This Row],[29]]:Scores[[#This Row],[30]]) -> 0 | H11: =SUM(Scores[[#This Row],[31]:[36]]) -> 0 | I11: =Scores[[#This Row],[37]] -> 0 | J11: =INDEX('Conversion Chart'!$C$3:$M$47,MATCH(SUM(Scores[[#This Row],[MC]:[IIIA]]),'Conversion Chart'!$B$3:$B$47),MATCH(Scores[[#This Row],[IIIB]],'Conversion Chart'!$C$2:$M$2)) -> 0 | AV11: =IF(K11=VLOOKUP(VALUE(K$1),Questions!$A:$E,5,FALSE),1,0) -> 0 | AW11: =IF(L11=VLOOKUP(VALUE(L$1),Questions!$A:$E,5,FALSE),1,0) -> 0 | AX11: =IF(M11=VLOOKUP(VALUE(M$1),Questions!$A:$E,5,FALSE),1,0) -> 0 | AY11: =IF(N11=VLOOKUP(VALUE(N$1),Questions!$A:$E,5,FALSE),1,0) -> 0 | AZ11: =IF(O11=VLOOKUP(VALUE(O$1),Questions!$A:$E,5,FALSE),1,0) -> 0 | BA11: =IF(P11=VLOOKUP(VALUE(P$1),Questions!$A:$E,5,FALSE),1,0) -> 0 | BB11: =IF(Q11=VLOOKUP(VALUE(Q$1),Questions!$A:$E,5,FALSE),1,0) -> 0 | BC11: =IF(R11=VLOOKUP(VALUE(R$1),Questions!$A:$E,5,FALSE),1,0) -> 0 | ... BW11: =IF(AL11=VLOOKUP(VALUE(AL$1),Questions!$A:$E,5,FALSE),1,0) -> 0 | BX11: =IF(Scores[[#This Row],[Final]]>=65,1,0) -> 0 | BY11: =IF(Scores[[#This Row],[Final]]>=IF(Scores[[#This Row],[IEP]],55,65),1,0) -> 0
A12: 11 | B12: 9 | C12: Kovelsky | D12: FALSE | E12: TRUE | F12: =SUM(Scores[[#This Row],[Q1]:[Q28]]) -> 8 | G12: =SUM(Scores[[#This Row],[29]]:Scores[[#This Row],[30]]) -> 5 | H12: =SUM(Scores[[#This Row],[31]:[36]]) -> 6 | I12: =Scores[[#This Row],[37]] -> 1 | J12: =INDEX('Conversion Chart'!$C$3:$M$47,MATCH(SUM(Scores[[#This Row],[MC]:[IIIA]]),'Conversion Chart'!$B$3:$B$47),MATCH(Scores[[#This Row],[IIIB]],'Conversion Chart'!$C$2:$M$2)) -> 55 | K12: 4 | L12: 1 | M12: 3 | N12: 2 | O12: 4 | P12: 2 | Q12: 3 | R12: 2 | S12: 3 | T12: 1 | U12: 4 | V12: 2 | W12: 2 | X12: 3 | Y12: 1 | Z12: 4 | AA12: 1 | AB12: 4 | AC12: 2 | AD12: 3 | AE12: 1 | AF12: 4 | AG12: 4 | AH12: 2 | AI12: 3 | AJ12: 1 | AK12: 4 | AL12: 4 | AM12: 3 | AN12: 2 | AO12: 1 | AP12: 1 | AQ12: 1 | AR12: 1 | AS12: 1 | AT12: 1 | AU12: 1 | AV12: =IF(K12=VLOOKUP(VALUE(K$1),Questions!$A:$E,5,FALSE),1,0) -> 1 | AW12: =IF(L12=VLOOKUP(VALUE(L$1),Questions!$A:$E,5,FALSE),1,0) -> 0 | AX12: =IF(M12=VLOOKUP(VALUE(M$1),Questions!$A:$E,5,FALSE),1,0) -> 1 | AY12: =IF(N12=VLOOKUP(VALUE(N$1),Questions!$A:$E,5,FALSE),1,0) -> 0 | AZ12: =IF(O12=VLOOKUP(VALUE(O$1),Questions!$A:$E,5,FALSE),1,0) -> 0 | BA12: =IF(P12=VLOOKUP(VALUE(P$1),Questions!$A:$E,5,FALSE),1,0) -> 0 | BB12: =IF(Q12=VLOOKUP(VALUE(Q$1),Questions!$A:$E,5,FALSE),1,0) -> 1 | BC12: =IF(R12=VLOOKUP(VALUE(R$1),Questions!$A:$E,5,FALSE),1,0) -> 1 | ... BW12: =IF(AL12=VLOOKUP(VALUE(AL$1),Questions!$A:$E,5,FALSE),1,0) -> 0 | BX12: =IF(Scores[[#This Row],[Final]]>=65,1,0) -> 0 | BY12: =IF(Scores[[#This Row],[Final]]>=IF(Scores[[#This Row],[IEP]],55,65),1,0) -> 1
A13: 12 | B13: 11 | C13: Antaky | D13: FALSE | E13: FALSE | F13: =SUM(Scores[[#This Row],[Q1]:[Q28]]) -> 15 | G13: =SUM(Scores[[#This Row],[29]]:Scores[[#This Row],[30]]) -> 4 | H13: =SUM(Scores[[#This Row],[31]:[36]]) -> 6 | I13: =Scores[[#This Row],[37]] -> 2 | J13: =INDEX('Conversion Chart'!$C$3:$M$47,MATCH(SUM(Scores[[#This Row],[MC]:[IIIA]]),'Conversion Chart'!$B$3:$B$47),MATCH(Scores[[#This Row],[IIIB]],'Conversion Chart'!$C$2:$M$2)) -> 68 | K13: 4 | L13: 2 | M13: 3 | N13: 3 | O13: 2 | P13: 2 | Q13: 2 | R13: 2 | S13: 3 | T13: 1 | U13: 2 | V13: 3 | W13: 2 | X13: 4 | Y13: 3 | Z13: 1 | AA13: 4 | AB13: 4 | AC13: 1 | AD13: 2 | AE13: 1 | AF13: 2 | AG13: 3 | AH13: 1 | AI13: 4 | AJ13: 4 | AK13: 3 | AL13: 2 | AM13: 2 | AN13: 2 | AO13: 1 | AP13: 1 | AQ13: 1 | AR13: 1 | AS13: 1 | AT13: 1 | AU13: 2 | AV13: =IF(K13=VLOOKUP(VALUE(K$1),Questions!$A:$E,5,FALSE),1,0) -> 1 | AW13: =IF(L13=VLOOKUP(VALUE(L$1),Questions!$A:$E,5,FALSE),1,0) -> 1 | AX13: =IF(M13=VLOOKUP(VALUE(M$1),Questions!$A:$E,5,FALSE),1,0) -> 1 | AY13: =IF(N13=VLOOKUP(VALUE(N$1),Questions!$A:$E,5,FALSE),1,0) -> 1 | AZ13: =IF(O13=VLOOKUP(VALUE(O$1),Questions!$A:$E,5,FALSE),1,0) -> 0 | BA13: =IF(P13=VLOOKUP(VALUE(P$1),Questions!$A:$E,5,FALSE),1,0) -> 0 | BB13: =IF(Q13=VLOOKUP(VALUE(Q$1),Questions!$A:$E,5,FALSE),1,0) -> 0 | BC13: =IF(R13=VLOOKUP(VALUE(R$1),Questions!$A:$E,5,FALSE),1,0) -> 1 | ... BW13: =IF(AL13=VLOOKUP(VALUE(AL$1),Questions!$A:$E,5,FALSE),1,0) -> 0 | BX13: =IF(Scores[[#This Row],[Final]]>=65,1,0) -> 1 | BY13: =IF(Scores[[#This Row],[Final]]>=IF(Scores[[#This Row],[IEP]],55,65),1,0) -> 1
A14: 13 | B14: 11 | C14: Dushin | D14: FALSE | E14: TRUE | F14: =SUM(Scores[[#This Row],[Q1]:[Q28]]) -> 10 | G14: =SUM(Scores[[#This Row],[29]]:Scores[[#This Row],[30]]) -> 4 | H14: =SUM(Scores[[#This Row],[31]:[36]]) -> 5 | I14: =Scores[[#This Row],[37]] -> 2 | J14: =INDEX('Conversion Chart'!$C$3:$M$47,MATCH(SUM(Scores[[#This Row],[MC]:[IIIA]]),'Conversion Chart'!$B$3:$B$47),MATCH(Scores[[#This Row],[IIIB]],'Conversion Chart'!$C$2:$M$2)) -> 60 | K14: 3 | L14: 1 | M14: 1 | N14: 2 | O14: 1 | P14: 1 | Q14: 4 | R14: 2 | S14: 2 | T14: 3 | U14: 1 | V14: 3 | W14: 4 | X14: 3 | Y14: 2 | Z14: 3 | AA14: 1 | AB14: 4 | AC14: 2 | AD14: 3 | AE14: 3 | AF14: 2 | AG14: 3 | AH14: 3 | AI14: 4 | AJ14: 4 | AK14: 1 | AL14: 4 | AM14: 2 | AN14: 2 | AO14: 1 | AP14: 1 | AQ14: 1 | AR14: 0 | AS14: 1 | AT14: 1 | AU14: 2 | AV14: =IF(K14=VLOOKUP(VALUE(K$1),Questions!$A:$E,5,FALSE),1,0) -> 0 | AW14: =IF(L14=VLOOKUP(VALUE(L$1),Questions!$A:$E,5,FALSE),1,0) -> 0 | AX14: =IF(M14=VLOOKUP(VALUE(M$1),Questions!$A:$E,5,FALSE),1,0) -> 0 | AY14: =IF(N14=VLOOKUP(VALUE(N$1),Questions!$A:$E,5,FALSE),1,0) -> 0 | AZ14: =IF(O14=VLOOKUP(VALUE(O$1),Questions!$A:$E,5,FALSE),1,0) -> 1 | BA14: =IF(P14=VLOOKUP(VALUE(P$1),Questions!$A:$E,5,FALSE),1,0) -> 0 | BB14: =IF(Q14=VLOOKUP(VALUE(Q$1),Questions!$A:$E,5,FALSE),1,0) -> 0 | BC14: =IF(R14=VLOOKUP(VALUE(R$1),Questions!$A:$E,5,FALSE),1,0) -> 1 | ... BW14: =IF(AL14=VLOOKUP(VALUE(AL$1),Questions!$A:$E,5,FALSE),1,0) -> 0 | BX14: =IF(Scores[[#This Row],[Final]]>=65,1,0) -> 0 | BY14: =IF(Scores[[#This Row],[Final]]>=IF(Scores[[#This Row],[IEP]],55,65),1,0) -> 1
A15: 14 | B15: 9 | C15: Bermejo | D15: FALSE | E15: FALSE | F15: =SUM(Scores[[#This Row],[Q1]:[Q28]]) -> 11 | G15: =SUM(Scores[[#This Row],[29]]:Scores[[#This Row],[30]]) -> 3 | H15: =SUM(Scores[[#This Row],[31]:[36]]) -> 5 | I15: =Scores[[#This Row],[37]] -> 1 | J15: =INDEX('Conversion Chart'!$C$3:$M$47,MATCH(SUM(Scores[[#This Row],[MC]:[IIIA]]),'Conversion Chart'!$B$3:$B$47),MATCH(Scores[[#This Row],[IIIB]],'Conversion Chart'!$C$2:$M$2)) -> 55 | K15: 4 | L15: 1 | M15: 3 | N15: 1 | O15: 1 | P15: 2 | Q15: 1 | R15: 2 | S15: 3 | T15: 1 | U15: 2 | V15: 3 | W15: 2 | X15: 3 | Y15: 3 | Z15: 4 | AA15: 2 | AB15: 1 | AC15: 2 | AD15: 4 | AE15: 3 | AF15: 1 | AG15: 4 | AH15: 2 | AI15: 3 | AJ15: 4 | AK15: 4 | AL15: 3 | AM15: 2 | AN15: 1 | AO15: 0 | AP15: 1 | AQ15: 1 | AR15: 1 | AS15: 1 | AT15: 1 | AU15: 1 | AV15: =IF(K15=VLOOKUP(VALUE(K$1),Questions!$A:$E,5,FALSE),1,0) -> 1 | AW15: =IF(L15=VLOOKUP(VALUE(L$1),Questions!$A:$E,5,FALSE),1,0) -> 0 | AX15: =IF(M15=VLOOKUP(VALUE(M$1),Questions!$A:$E,5,FALSE),1,0) -> 1 | AY15: =IF(N15=VLOOKUP(VALUE(N$1),Questions!$A:$E,5,FALSE),1,0) -> 0 | AZ15: =IF(O15=VLOOKUP(VALUE(O$1),Questions!$A:$E,5,FALSE),1,0) -> 1 | BA15: =IF(P15=VLOOKUP(VALUE(P$1),Questions!$A:$E,5,FALSE),1,0) -> 0 | BB15: =IF(Q15=VLOOKUP(VALUE(Q$1),Questions!$A:$E,5,FALSE),1,0) -> 0 | BC15: =IF(R15=VLOOKUP(VALUE(R$1),Questions!$A:$E,5,FALSE),1,0) -> 1 | ... BW15: =IF(AL15=VLOOKUP(VALUE(AL$1),Questions!$A:$E,5,FALSE),1,0) -> 1 | BX15: =IF(Scores[[#This Row],[Final]]>=65,1,0) -> 0 | BY15: =IF(Scores[[#This Row],[Final]]>=IF(Scores[[#This Row],[IEP]],55,65),1,0) -> 0
A16: 15 | B16: 11 | C16: Dushin | D16: FALSE | E16: FALSE | F16: =SUM(Scores[[#This Row],[Q1]:[Q28]]) -> 13 | G16: =SUM(Scores[[#This Row],[29]]:Scores[[#This Row],[30]]) -> 5 | H16: =SUM(Scores[[#This Row],[31]:[36]]) -> 5 | I16: =Scores[[#This Row],[37]] -> 1 | J16: =INDEX('Conversion Chart'!$C$3:$M$47,MATCH(SUM(Scores[[#This Row],[MC]:[IIIA]]),'Conversion Chart'!$B$3:$B$47),MATCH(Scores[[#This Row],[IIIB]],'Conversion Chart'!$C$2:$M$2)) -> 61 | K16: 2 | L16: 2 | M16: 2 | N16: 3 | O16: 1 | P16: 1 | Q16: 2 | R16: 2 | S16: 2 | T16: 1 | U16: 4 | V16: 2 | W16: 3 | X16: 3 | Y16: 2 | Z16: 1 | AA16: 1 | AB16: 4 | AC16: 3 | AD16: 2 | AE16: 4 | AF16: 4 | AG16: 4 | AH16: 2 | AI16: 1 | AJ16: 4 | AK16: 1 | AL16: 4 | AM16: 3 | AN16: 2 | AO16: 0 | AP16: 1 | AQ16: 1 | AR16: 1 | AS16: 1 | AT16: 1 | AU16: 1 | AV16: =IF(K16=VLOOKUP(VALUE(K$1),Questions!$A:$E,5,FALSE),1,0) -> 0 | AW16: =IF(L16=VLOOKUP(VALUE(L$1),Questions!$A:$E,5,FALSE),1,0) -> 1 | AX16: =IF(M16=VLOOKUP(VALUE(M$1),Questions!$A:$E,5,FALSE),1,0) -> 0 | AY16: =IF(N16=VLOOKUP(VALUE(N$1),Questions!$A:$E,5,FALSE),1,0) -> 1 | AZ16: =IF(O16=VLOOKUP(VALUE(O$1),Questions!$A:$E,5,FALSE),1,0) -> 1 | BA16: =IF(P16=VLOOKUP(VALUE(P$1),Questions!$A:$E,5,FALSE),1,0) -> 0 | BB16: =IF(Q16=VLOOKUP(VALUE(Q$1),Questions!$A:$E,5,FALSE),1,0) -> 0 | BC16: =IF(R16=VLOOKUP(VALUE(R$1),Questions!$A:$E,5,FALSE),1,0) -> 1 | ... BW16: =IF(AL16=VLOOKUP(VALUE(AL$1),Questions!$A:$E,5,FALSE),1,0) -> 0 | BX16: =IF(Scores[[#This Row],[Final]]>=65,1,0) -> 0 | BY16: =IF(Scores[[#This Row],[Final]]>=IF(Scores[[#This Row],[IEP]],55,65),1,0) -> 0
A17: 16 | B17: 11 | C17: Dushin | D17: FALSE | E17: FALSE | F17: =SUM(Scores[[#This Row],[Q1]:[Q28]]) -> 26 | G17: =SUM(Scores[[#This Row],[29]]:Scores[[#This Row],[30]]) -> 10 | H17: =SUM(Scores[[#This Row],[31]:[36]]) -> 6 | I17: =Scores[[#This Row],[37]] -> 2.5 | J17: =INDEX('Conversion Chart'!$C$3:$M$47,MATCH(SUM(Scores[[#This Row],[MC]:[IIIA]]),'Conversion Chart'!$B$3:$B$47),MATCH(Scores[[#This Row],[IIIB]],'Conversion Chart'!$C$2:$M$2)) -> 86 | K17: 4 | L17: 2 | M17: 3 | N17: 3 | O17: 1 | P17: 4 | Q17: 3 | R17: 2 | S17: 2 | T17: 1 | U17: 2 | V17: 3 | W17: 2 | X17: 4 | Y17: 3 | Z17: 1 | AA17: 1 | AB17: 4 | AC17: 3 | AD17: 4 | AE17: 2 | AF17: 2 | AG17: 3 | AH17: 3 | AI17: 4 | AJ17: 4 | AK17: 1 | AL17: 3 | AM17: 5 | AN17: 5 | AO17: 1 | AP17: 1 | AQ17: 1 | AR17: 1 | AS17: 1 | AT17: 1 | AU17: 2.5 | AV17: =IF(K17=VLOOKUP(VALUE(K$1),Questions!$A:$E,5,FALSE),1,0) -> 1 | AW17: =IF(L17=VLOOKUP(VALUE(L$1),Questions!$A:$E,5,FALSE),1,0) -> 1 | AX17: =IF(M17=VLOOKUP(VALUE(M$1),Questions!$A:$E,5,FALSE),1,0) -> 1 | AY17: =IF(N17=VLOOKUP(VALUE(N$1),Questions!$A:$E,5,FALSE),1,0) -> 1 | AZ17: =IF(O17=VLOOKUP(VALUE(O$1),Questions!$A:$E,5,FALSE),1,0) -> 1 | BA17: =IF(P17=VLOOKUP(VALUE(P$1),Questions!$A:$E,5,FALSE),1,0) -> 1 | BB17: =IF(Q17=VLOOKUP(VALUE(Q$1),Questions!$A:$E,5,FALSE),1,0) -> 1 | BC17: =IF(R17=VLOOKUP(VALUE(R$1),Questions!$A:$E,5,FALSE),1,0) -> 1 | ... BW17: =IF(AL17=VLOOKUP(VALUE(AL$1),Questions!$A:$E,5,FALSE),1,0) -> 1 | BX17: =IF(Scores[[#This Row],[Final]]>=65,1,0) -> 1 | BY17: =IF(Scores[[#This Row],[Final]]>=IF(Scores[[#This Row],[IEP]],55,65),1,0) -> 1
A18: 17 | B18: 9 | C18: Bermejo | D18: FALSE | E18: FALSE | F18: =SUM(Scores[[#This Row],[Q1]:[Q28]]) -> 13 | G18: =SUM(Scores[[#This Row],[29]]:Scores[[#This Row],[30]]) -> 0 | H18: =SUM(Scores[[#This Row],[31]:[36]]) -> 5 | I18: =Scores[[#This Row],[37]] -> 0 | J18: =INDEX('Conversion Chart'!$C$3:$M$47,MATCH(SUM(Scores[[#This Row],[MC]:[IIIA]]),'Conversion Chart'!$B$3:$B$47),MATCH(Scores[[#This Row],[IIIB]],'Conversion Chart'!$C$2:$M$2)) -> 48 | K18: 4 | L18: 2 | M18: 4 | N18: 1 | O18: 4 | P18: 2 | Q18: 3 | R18: 1 | S18: 4 | T18: 2 | U18: 2 | V18: 4 | W18: 2 | X18: 3 | Y18: 3 | Z18: 1 | AA18: 1 | AB18: 3 | AC18: 2 | AD18: 4 | AE18: 2 | AF18: 2 | AG18: 1 | AH18: 4 | AI18: 2 | AJ18: 3 | AK18: 1 | AL18: 4 | AM18: 0 | AN18: 0 | AO18: 0 | AP18: 1 | AQ18: 1 | AR18: 1 | AS18: 1 | AT18: 1 | AU18: 0 | AV18: =IF(K18=VLOOKUP(VALUE(K$1),Questions!$A:$E,5,FALSE),1,0) -> 1 | AW18: =IF(L18=VLOOKUP(VALUE(L$1),Questions!$A:$E,5,FALSE),1,0) -> 1 | AX18: =IF(M18=VLOOKUP(VALUE(M$1),Questions!$A:$E,5,FALSE),1,0) -> 0 | AY18: =IF(N18=VLOOKUP(VALUE(N$1),Questions!$A:$E,5,FALSE),1,0) -> 0 | AZ18: =IF(O18=VLOOKUP(VALUE(O$1),Questions!$A:$E,5,FALSE),1,0) -> 0 | BA18: =IF(P18=VLOOKUP(VALUE(P$1),Questions!$A:$E,5,FALSE),1,0) -> 0 | BB18: =IF(Q18=VLOOKUP(VALUE(Q$1),Questions!$A:$E,5,FALSE),1,0) -> 1 | BC18: =IF(R18=VLOOKUP(VALUE(R$1),Questions!$A:$E,5,FALSE),1,0) -> 0 | ... BW18: =IF(AL18=VLOOKUP(VALUE(AL$1),Questions!$A:$E,5,FALSE),1,0) -> 0 | BX18: =IF(Scores[[#This Row],[Final]]>=65,1,0) -> 0 | BY18: =IF(Scores[[#This Row],[Final]]>=IF(Scores[[#This Row],[IEP]],55,65),1,0) -> 0
A19: 18 | B19: 11 | C19: Dushin | D19: FALSE | E19: FALSE | F19: =SUM(Scores[[#This Row],[Q1]:[Q28]]) -> 11 | G19: =SUM(Scores[[#This Row],[29]]:Scores[[#This Row],[30]]) -> 3 | H19: =SUM(Scores[[#This Row],[31]:[36]]) -> 5 | I19: =Scores[[#This Row],[37]] -> 1 | J19: =INDEX('Conversion Chart'!$C$3:$M$47,MATCH(SUM(Scores[[#This Row],[MC]:[IIIA]]),'Conversion Chart'!$B$3:$B$47),MATCH(Scores[[#This Row],[IIIB]],'Conversion Chart'!$C$2:$M$2)) -> 55 | K19: 4 | L19: 2 | M19: 2 | N19: 4 | O19: 2 | P19: 4 | Q19: 2 | R19: 3 | S19: 2 | T19: 1 | U19: 3 | V19: 4 | W19: 1 | X19: 1 | Y19: 3 | Z19: 2 | AA19: 4 | AB19: 4 | AC19: 2 | AD19: 3 | AE19: 2 | AF19: 1 | AG19: 2 | AH19: 4 | AI19: 1 | AJ19: 4 | AK19: 2 | AL19: 4 | AM19: 2 | AN19: 1 | AO19: 1 | AP19: 1 | AQ19: 1 | AR19: 1 | AS19: 1 | AT19: 0 | AU19: 1 | AV19: =IF(K19=VLOOKUP(VALUE(K$1),Questions!$A:$E,5,FALSE),1,0) -> 1 | AW19: =IF(L19=VLOOKUP(VALUE(L$1),Questions!$A:$E,5,FALSE),1,0) -> 1 | AX19: =IF(M19=VLOOKUP(VALUE(M$1),Questions!$A:$E,5,FALSE),1,0) -> 0 | AY19: =IF(N19=VLOOKUP(VALUE(N$1),Questions!$A:$E,5,FALSE),1,0) -> 0 | AZ19: =IF(O19=VLOOKUP(VALUE(O$1),Questions!$A:$E,5,FALSE),1,0) -> 0 | BA19: =IF(P19=VLOOKUP(VALUE(P$1),Questions!$A:$E,5,FALSE),1,0) -> 1 | BB19: =IF(Q19=VLOOKUP(VALUE(Q$1),Questions!$A:$E,5,FALSE),1,0) -> 0 | BC19: =IF(R19=VLOOKUP(VALUE(R$1),Questions!$A:$E,5,FALSE),1,0) -> 0 | ... BW19: =IF(AL19=VLOOKUP(VALUE(AL$1),Questions!$A:$E,5,FALSE),1,0) -> 0 | BX19: =IF(Scores[[#This Row],[Final]]>=65,1,0) -> 0 | BY19: =IF(Scores[[#This Row],[Final]]>=IF(Scores[[#This Row],[IEP]],55,65),1,0) -> 0
A20: 19 | B20: 9 | C20: Bermejo | D20: FALSE | E20: FALSE | F20: =SUM(Scores[[#This Row],[Q1]:[Q28]]) -> 6 | G20: =SUM(Scores[[#This Row],[29]]:Scores[[#This Row],[30]]) -> 2 | H20: =SUM(Scores[[#This Row],[31]:[36]]) -> 0 | I20: =Scores[[#This Row],[37]] -> 0 | J20: =INDEX('Conversion Chart'!$C$3:$M$47,MATCH(SUM(Scores[[#This Row],[MC]:[IIIA]]),'Conversion Chart'!$B$3:$B$47),MATCH(Scores[[#This Row],[IIIB]],'Conversion Chart'!$C$2:$M$2)) -> 25 | K20: 2 | L20: 4 | M20: 1 | N20: 1 | O20: 2 | P20: 3 | Q20: 2 | R20: 4 | S20: 3 | T20: 1 | U20: 2 | V20: 4 | W20: 1 | X20: 4 | Y20: 2 | Z20: 3 | AA20: 2 | AB20: 1 | AC20: 4 | AD20: 2 | AE20: 2 | AF20: 1 | AG20: 3 | AH20: 1 | AI20: 3 | AJ20: 2 | AK20: 4 | AL20: 1 | AM20: 1 | AN20: 1 | AO20: 0 | AP20: 0 | AQ20: 0 | AR20: 0 | AS20: 0 | AT20: 0 | AU20: 0 | AV20: =IF(K20=VLOOKUP(VALUE(K$1),Questions!$A:$E,5,FALSE),1,0) -> 0 | AW20: =IF(L20=VLOOKUP(VALUE(L$1),Questions!$A:$E,5,FALSE),1,0) -> 0 | AX20: =IF(M20=VLOOKUP(VALUE(M$1),Questions!$A:$E,5,FALSE),1,0) -> 0 | AY20: =IF(N20=VLOOKUP(VALUE(N$1),Questions!$A:$E,5,FALSE),1,0) -> 0 | AZ20: =IF(O20=VLOOKUP(VALUE(O$1),Questions!$A:$E,5,FALSE),1,0) -> 0 | BA20: =IF(P20=VLOOKUP(VALUE(P$1),Questions!$A:$E,5,FALSE),1,0) -> 0 | BB20: =IF(Q20=VLOOKUP(VALUE(Q$1),Questions!$A:$E,5,FALSE),1,0) -> 0 | BC20: =IF(R20=VLOOKUP(VALUE(R$1),Questions!$A:$E,5,FALSE),1,0) -> 0 | ... BW20: =IF(AL20=VLOOKUP(VALUE(AL$1),Questions!$A:$E,5,FALSE),1,0) -> 0 | BX20: =IF(Scores[[#This Row],[Final]]>=65,1,0) -> 0 | BY20: =IF(Scores[[#This Row],[Final]]>=IF(Scores[[#This Row],[IEP]],55,65),1,0) -> 0
A21: 20 | B21: 9 | C21: Bermejo | D21: FALSE | E21: FALSE | F21: =SUM(Scores[[#This Row],[Q1]:[Q28]]) -> 0 | G21: =SUM(Scores[[#This Row],[29]]:Scores[[#This Row],[30]]) -> 0 | H21: =SUM(Scores[[#This Row],[31]:[36]]) -> 0 | I21: =Scores[[#This Row],[37]] -> 0 | J21: =INDEX('Conversion Chart'!$C$3:$M$47,MATCH(SUM(Scores[[#This Row],[MC]:[IIIA]]),'Conversion Chart'!$B$3:$B$47),MATCH(Scores[[#This Row],[IIIB]],'Conversion Chart'!$C$2:$M$2)) -> 0 | AV21: =IF(K21=VLOOKUP(VALUE(K$1),Questions!$A:$E,5,FALSE),1,0) -> 0 | AW21: =IF(L21=VLOOKUP(VALUE(L$1),Questions!$A:$E,5,FALSE),1,0) -> 0 | AX21: =IF(M21=VLOOKUP(VALUE(M$1),Questions!$A:$E,5,FALSE),1,0) -> 0 | AY21: =IF(N21=VLOOKUP(VALUE(N$1),Questions!$A:$E,5,FALSE),1,0) -> 0 | AZ21: =IF(O21=VLOOKUP(VALUE(O$1),Questions!$A:$E,5,FALSE),1,0) -> 0 | BA21: =IF(P21=VLOOKUP(VALUE(P$1),Questions!$A:$E,5,FALSE),1,0) -> 0 | BB21: =IF(Q21=VLOOKUP(VALUE(Q$1),Questions!$A:$E,5,FALSE),1,0) -> 0 | BC21: =IF(R21=VLOOKUP(VALUE(R$1),Questions!$A:$E,5,FALSE),1,0) -> 0 | ... BW21: =IF(AL21=VLOOKUP(VALUE(AL$1),Questions!$A:$E,5,FALSE),1,0) -> 0 | BX21: =IF(Scores[[#This Row],[Final]]>=65,1,0) -> 0 | BY21: =IF(Scores[[#This Row],[Final]]>=IF(Scores[[#This Row],[IEP]],55,65),1,0) -> 0
A22: 21 | B22: 9 | C22: Bermejo | D22: FALSE | E22: FALSE | F22: =SUM(Scores[[#This Row],[Q1]:[Q28]]) -> 22 | G22: =SUM(Scores[[#This Row],[29]]:Scores[[#This Row],[30]]) -> 2 | H22: =SUM(Scores[[#This Row],[31]:[36]]) -> 5 | I22: =Scores[[#This Row],[37]] -> 2 | J22: =INDEX('Conversion Chart'!$C$3:$M$47,MATCH(SUM(Scores[[#This Row],[MC]:[IIIA]]),'Conversion Chart'!$B$3:$B$47),MATCH(Scores[[#This Row],[IIIB]],'Conversion Chart'!$C$2:$M$2)) -> 72 | K22: 4 | L22: 2 | M22: 3 | N22: 3 | O22: 1 | P22: 3 | Q22: 3 | R22: 2 | S22: 2 | T22: 1 | U22: 2 | V22: 4 | W22: 3 | X22: 4 | Y22: 4 | Z22: 1 | AA22: 1 | AB22: 4 | AC22: 3 | AD22: 2 | AE22: 2 | AF22: 2 | AG22: 3 | AH22: 3 | AI22: 4 | AJ22: 4 | AK22: 1 | AL22: 2 | AM22: 1 | AN22: 1 | AO22: 0 | AP22: 1 | AQ22: 1 | AR22: 1 | AS22: 1 | AT22: 1 | AU22: 2 | AV22: =IF(K22=VLOOKUP(VALUE(K$1),Questions!$A:$E,5,FALSE),1,0) -> 1 | AW22: =IF(L22=VLOOKUP(VALUE(L$1),Questions!$A:$E,5,FALSE),1,0) -> 1 | AX22: =IF(M22=VLOOKUP(VALUE(M$1),Questions!$A:$E,5,FALSE),1,0) -> 1 | AY22: =IF(N22=VLOOKUP(VALUE(N$1),Questions!$A:$E,5,FALSE),1,0) -> 1 | AZ22: =IF(O22=VLOOKUP(VALUE(O$1),Questions!$A:$E,5,FALSE),1,0) -> 1 | BA22: =IF(P22=VLOOKUP(VALUE(P$1),Questions!$A:$E,5,FALSE),1,0) -> 0 | BB22: =IF(Q22=VLOOKUP(VALUE(Q$1),Questions!$A:$E,5,FALSE),1,0) -> 1 | BC22: =IF(R22=VLOOKUP(VALUE(R$1),Questions!$A:$E,5,FALSE),1,0) -> 1 | ... BW22: =IF(AL22=VLOOKUP(VALUE(AL$1),Questions!$A:$E,5,FALSE),1,0) -> 0 | BX22: =IF(Scores[[#This Row],[Final]]>=65,1,0) -> 1 | BY22: =IF(Scores[[#This Row],[Final]]>=IF(Scores[[#This Row],[IEP]],55,65),1,0) -> 1
A23: 22 | B23: 11 | C23: Dushin | D23: FALSE | E23: FALSE | F23: =SUM(Scores[[#This Row],[Q1]:[Q28]]) -> 20 | G23: =SUM(Scores[[#This Row],[29]]:Scores[[#This Row],[30]]) -> 6 | H23: =SUM(Scores[[#This Row],[31]:[36]]) -> 4 | I23: =Scores[[#This Row],[37]] -> 2.5 | J23: =INDEX('Conversion Chart'!$C$3:$M$47,MATCH(SUM(Scores[[#This Row],[MC]:[IIIA]]),'Conversion Chart'!$B$3:$B$47),MATCH(Scores[[#This Row],[IIIB]],'Conversion Chart'!$C$2:$M$2)) -> 75 | K23: 4 | L23: 2 | M23: 3 | N23: 3 | O23: 1 | P23: 3 | Q23: 3 | R23: 2 | S23: 2 | T23: 1 | U23: 2 | V23: 4 | W23: 3 | X23: 3 | Y23: 4 | Z23: 4 | AA23: 1 | AB23: 4 | AC23: 3 | AD23: 2 | AE23: 4 | AF23: 2 | AG23: 3 | AH23: 3 | AI23: 1 | AJ23: 4 | AK23: 1 | AL23: 2 | AM23: 4 | AN23: 2 | AO23: 1 | AP23: 0 | AQ23: 1 | AR23: 1 | AS23: 1 | AT23: 0 | AU23: 2.5 | AV23: =IF(K23=VLOOKUP(VALUE(K$1),Questions!$A:$E,5,FALSE),1,0) -> 1 | AW23: =IF(L23=VLOOKUP(VALUE(L$1),Questions!$A:$E,5,FALSE),1,0) -> 1 | AX23: =IF(M23=VLOOKUP(VALUE(M$1),Questions!$A:$E,5,FALSE),1,0) -> 1 | AY23: =IF(N23=VLOOKUP(VALUE(N$1),Questions!$A:$E,5,FALSE),1,0) -> 1 | AZ23: =IF(O23=VLOOKUP(VALUE(O$1),Questions!$A:$E,5,FALSE),1,0) -> 1 | BA23: =IF(P23=VLOOKUP(VALUE(P$1),Questions!$A:$E,5,FALSE),1,0) -> 0 | BB23: =IF(Q23=VLOOKUP(VALUE(Q$1),Questions!$A:$E,5,FALSE),1,0) -> 1 | BC23: =IF(R23=VLOOKUP(VALUE(R$1),Questions!$A:$E,5,FALSE),1,0) -> 1 | ... BW23: =IF(AL23=VLOOKUP(VALUE(AL$1),Questions!$A:$E,5,FALSE),1,0) -> 0 | BX23: =IF(Scores[[#This Row],[Final]]>=65,1,0) -> 1 | BY23: =IF(Scores[[#This Row],[Final]]>=IF(Scores[[#This Row],[IEP]],55,65),1,0) -> 1
A24: 23 | B24: 9 | C24: Bermejo | D24: FALSE | E24: TRUE | F24: =SUM(Scores[[#This Row],[Q1]:[Q28]]) -> 7 | G24: =SUM(Scores[[#This Row],[29]]:Scores[[#This Row],[30]]) -> 1 | H24: =SUM(Scores[[#This Row],[31]:[36]]) -> 3 | I24: =Scores[[#This Row],[37]] -> 0 | J24: =INDEX('Conversion Chart'!$C$3:$M$47,MATCH(SUM(Scores[[#This Row],[MC]:[IIIA]]),'Conversion Chart'!$B$3:$B$47),MATCH(Scores[[#This Row],[IIIB]],'Conversion Chart'!$C$2:$M$2)) -> 33 | K24: 1 | L24: 2 | M24: 1 | N24: 2 | O24: 1 | P24: 2 | Q24: 3 | R24: 3 | S24: 1 | T24: 1 | U24: 3 | V24: 3 | W24: 4 | X24: 2 | Y24: 1 | Z24: 2 | AA24: 1 | AB24: 4 | AC24: 2 | AD24: 3 | AE24: 1 | AF24: 4 | AG24: 2 | AH24: 1 | AI24: 3 | AJ24: 1 | AK24: 4 | AL24: 3 | AM24: 1 | AN24: 0 | AO24: 0 | AP24: 1 | AQ24: 0 | AR24: 1 | AS24: 0 | AT24: 1 | AU24: 0 | AV24: =IF(K24=VLOOKUP(VALUE(K$1),Questions!$A:$E,5,FALSE),1,0) -> 0 | AW24: =IF(L24=VLOOKUP(VALUE(L$1),Questions!$A:$E,5,FALSE),1,0) -> 1 | AX24: =IF(M24=VLOOKUP(VALUE(M$1),Questions!$A:$E,5,FALSE),1,0) -> 0 | AY24: =IF(N24=VLOOKUP(VALUE(N$1),Questions!$A:$E,5,FALSE),1,0) -> 0 | AZ24: =IF(O24=VLOOKUP(VALUE(O$1),Questions!$A:$E,5,FALSE),1,0) -> 1 | BA24: =IF(P24=VLOOKUP(VALUE(P$1),Questions!$A:$E,5,FALSE),1,0) -> 0 | BB24: =IF(Q24=VLOOKUP(VALUE(Q$1),Questions!$A:$E,5,FALSE),1,0) -> 1 | BC24: =IF(R24=VLOOKUP(VALUE(R$1),Questions!$A:$E,5,FALSE),1,0) -> 0 | ... BW24: =IF(AL24=VLOOKUP(VALUE(AL$1),Questions!$A:$E,5,FALSE),1,0) -> 1 | BX24: =IF(Scores[[#This Row],[Final]]>=65,1,0) -> 0 | BY24: =IF(Scores[[#This Row],[Final]]>=IF(Scores[[#This Row],[IEP]],55,65),1,0) -> 0
A25: 24 | B25: 11 | C25: Dushin | D25: FALSE | E25: FALSE | F25: =SUM(Scores[[#This Row],[Q1]:[Q28]]) -> 18 | G25: =SUM(Scores[[#This Row],[29]]:Scores[[#This Row],[30]]) -> 4 | H25: =SUM(Scores[[#This Row],[31]:[36]]) -> 6 | I25: =Scores[[#This Row],[37]] -> 1 | J25: =INDEX('Conversion Chart'!$C$3:$M$47,MATCH(SUM(Scores[[#This Row],[MC]:[IIIA]]),'Conversion Chart'!$B$3:$B$47),MATCH(Scores[[#This Row],[IIIB]],'Conversion Chart'!$C$2:$M$2)) -> 68 | K25: 3 | L25: 4 | M25: 2 | N25: 3 | O25: 1 | P25: 2 | Q25: 3 | R25: 2 | S25: 2 | T25: 1 | U25: 2 | V25: 1 | W25: 2 | X25: 4 | Y25: 3 | Z25: 4 | AA25: 1 | AB25: 4 | AC25: 3 | AD25: 1 | AE25: 2 | AF25: 2 | AG25: 3 | AH25: 2 | AI25: 3 | AJ25: 4 | AK25: 2 | AL25: 3 | AM25: 2 | AN25: 2 | AO25: 1 | AP25: 1 | AQ25: 1 | AR25: 1 | AS25: 1 | AT25: 1 | AU25: 1 | AV25: =IF(K25=VLOOKUP(VALUE(K$1),Questions!$A:$E,5,FALSE),1,0) -> 0 | AW25: =IF(L25=VLOOKUP(VALUE(L$1),Questions!$A:$E,5,FALSE),1,0) -> 0 | AX25: =IF(M25=VLOOKUP(VALUE(M$1),Questions!$A:$E,5,FALSE),1,0) -> 0 | AY25: =IF(N25=VLOOKUP(VALUE(N$1),Questions!$A:$E,5,FALSE),1,0) -> 1 | AZ25: =IF(O25=VLOOKUP(VALUE(O$1),Questions!$A:$E,5,FALSE),1,0) -> 1 | BA25: =IF(P25=VLOOKUP(VALUE(P$1),Questions!$A:$E,5,FALSE),1,0) -> 0 | BB25: =IF(Q25=VLOOKUP(VALUE(Q$1),Questions!$A:$E,5,FALSE),1,0) -> 1 | BC25: =IF(R25=VLOOKUP(VALUE(R$1),Questions!$A:$E,5,FALSE),1,0) -> 1 | ... BW25: =IF(AL25=VLOOKUP(VALUE(AL$1),Questions!$A:$E,5,FALSE),1,0) -> 1 | BX25: =IF(Scores[[#This Row],[Final]]>=65,1,0) -> 1 | BY25: =IF(Scores[[#This Row],[Final]]>=IF(Scores[[#This Row],[IEP]],55,65),1,0) -> 1
A26: 25 | B26: 11 | C26: Dushin | D26: FALSE | E26: FALSE | F26: =SUM(Scores[[#This Row],[Q1]:[Q28]]) -> 11 | G26: =SUM(Scores[[#This Row],[29]]:Scores[[#This Row],[30]]) -> 3 | H26: =SUM(Scores[[#This Row],[31]:[36]]) -> 4 | I26: =Scores[[#This Row],[37]] -> 1 | J26: =INDEX('Conversion Chart'!$C$3:$M$47,MATCH(SUM(Scores[[#This Row],[MC]:[IIIA]]),'Conversion Chart'!$B$3:$B$47),MATCH(Scores[[#This Row],[IIIB]],'Conversion Chart'!$C$2:$M$2)) -> 54 | K26: 2 | L26: 1 | M26: 2 | N26: 3 | O26: 2 | P26: 2 | Q26: 3 | R26: 2 | S26: 3 | T26: 1 | U26: 2 | V26: 1 | W26: 3 | X26: 4 | Y26: 3 | Z26: 4 | AA26: 1 | AB26: 1 | AC26: 2 | AD26: 2 | AE26: 1 | AF26: 4 | AG26: 3 | AH26: 2 | AI26: 3 | AJ26: 4 | AK26: 4 | AL26: 3 | AM26: 2 | AN26: 1 | AO26: 0 | AP26: 0 | AQ26: 1 | AR26: 1 | AS26: 1 | AT26: 1 | AU26: 1 | AV26: =IF(K26=VLOOKUP(VALUE(K$1),Questions!$A:$E,5,FALSE),1,0) -> 0 | AW26: =IF(L26=VLOOKUP(VALUE(L$1),Questions!$A:$E,5,FALSE),1,0) -> 0 | AX26: =IF(M26=VLOOKUP(VALUE(M$1),Questions!$A:$E,5,FALSE),1,0) -> 0 | AY26: =IF(N26=VLOOKUP(VALUE(N$1),Questions!$A:$E,5,FALSE),1,0) -> 1 | AZ26: =IF(O26=VLOOKUP(VALUE(O$1),Questions!$A:$E,5,FALSE),1,0) -> 0 | BA26: =IF(P26=VLOOKUP(VALUE(P$1),Questions!$A:$E,5,FALSE),1,0) -> 0 | BB26: =IF(Q26=VLOOKUP(VALUE(Q$1),Questions!$A:$E,5,FALSE),1,0) -> 1 | BC26: =IF(R26=VLOOKUP(VALUE(R$1),Questions!$A:$E,5,FALSE),1,0) -> 1 | ... BW26: =IF(AL26=VLOOKUP(VALUE(AL$1),Questions!$A:$E,5,FALSE),1,0) -> 1 | BX26: =IF(Scores[[#This Row],[Final]]>=65,1,0) -> 0 | BY26: =IF(Scores[[#This Row],[Final]]>=IF(Scores[[#This Row],[IEP]],55,65),1,0) -> 0
A27: 26 | B27: 11 | C27: Kovelsky | D27: FALSE | E27: FALSE | F27: =SUM(Scores[[#This Row],[Q1]:[Q28]]) -> 11 | G27: =SUM(Scores[[#This Row],[29]]:Scores[[#This Row],[30]]) -> 0 | H27: =SUM(Scores[[#This Row],[31]:[36]]) -> 6 | I27: =Scores[[#This Row],[37]] -> 2 | J27: =INDEX('Conversion Chart'!$C$3:$M$47,MATCH(SUM(Scores[[#This Row],[MC]:[IIIA]]),'Conversion Chart'!$B$3:$B$47),MATCH(Scores[[#This Row],[IIIB]],'Conversion Chart'!$C$2:$M$2)) -> 57 | K27: 4 | L27: 2 | M27: 4 | N27: 3 | O27: 2 | P27: 2 | Q27: 3 | R27: 2 | S27: 3 | T27: 1 | U27: 2 | V27: 2 | W27: 1 | X27: 4 | Y27: 4 | Z27: 4 | AA27: 2 | AB27: 1 | AC27: 2 | AD27: 3 | AE27: 3 | AF27: 2 | AG27: M | AH27: X | AI27: 3 | AJ27: 4 | AK27: 2 | AL27: 3 | AM27: 0 | AN27: 0 | AO27: 1 | AP27: 1 | AQ27: 1 | AR27: 1 | AS27: 1 | AT27: 1 | AU27: 2 | AV27: =IF(K27=VLOOKUP(VALUE(K$1),Questions!$A:$E,5,FALSE),1,0) -> 1 | AW27: =IF(L27=VLOOKUP(VALUE(L$1),Questions!$A:$E,5,FALSE),1,0) -> 1 | AX27: =IF(M27=VLOOKUP(VALUE(M$1),Questions!$A:$E,5,FALSE),1,0) -> 0 | AY27: =IF(N27=VLOOKUP(VALUE(N$1),Questions!$A:$E,5,FALSE),1,0) -> 1 | AZ27: =IF(O27=VLOOKUP(VALUE(O$1),Questions!$A:$E,5,FALSE),1,0) -> 0 | BA27: =IF(P27=VLOOKUP(VALUE(P$1),Questions!$A:$E,5,FALSE),1,0) -> 0 | BB27: =IF(Q27=VLOOKUP(VALUE(Q$1),Questions!$A:$E,5,FALSE),1,0) -> 1 | BC27: =IF(R27=VLOOKUP(VALUE(R$1),Questions!$A:$E,5,FALSE),1,0) -> 1 | ... BW27: =IF(AL27=VLOOKUP(VALUE(AL$1),Questions!$A:$E,5,FALSE),1,0) -> 1 | BX27: =IF(Scores[[#This Row],[Final]]>=65,1,0) -> 0 | BY27: =IF(Scores[[#This Row],[Final]]>=IF(Scores[[#This Row],[IEP]],55,65),1,0) -> 0
A28: 27 | B28: 11 | C28: Dushin | D28: FALSE | E28: FALSE | F28: =SUM(Scores[[#This Row],[Q1]:[Q28]]) -> 20 | G28: =SUM(Scores[[#This Row],[29]]:Scores[[#This Row],[30]]) -> 5 | H28: =SUM(Scores[[#This Row],[31]:[36]]) -> 4 | I28: =Scores[[#This Row],[37]] -> 1 | J28: =INDEX('Conversion Chart'!$C$3:$M$47,MATCH(SUM(Scores[[#This Row],[MC]:[IIIA]]),'Conversion Chart'!$B$3:$B$47),MATCH(Scores[[#This Row],[IIIB]],'Conversion Chart'!$C$2:$M$2)) -> 69 | K28: 4 | L28: 2 | M28: 3 | N28: 3 | O28: 1 | P28: 3 | Q28: 3 | R28: 2 | S28: 3 | T28: 1 | U28: 2 | V28: 4 | W28: 1 | X28: 4 | Y28: 4 | Z28: 1 | AA28: 1 | AB28: 1 | AC28: 3 | AD28: 1 | AE28: 2 | AF28: 2 | AG28: 3 | AH28: 2 | AI28: 3 | AJ28: 4 | AK28: 1 | AL28: 3 | AM28: 2 | AN28: 3 | AO28: 0 | AP28: 1 | AQ28: 1 | AR28: 1 | AS28: 0 | AT28: 1 | AU28: 1 | AV28: =IF(K28=VLOOKUP(VALUE(K$1),Questions!$A:$E,5,FALSE),1,0) -> 1 | AW28: =IF(L28=VLOOKUP(VALUE(L$1),Questions!$A:$E,5,FALSE),1,0) -> 1 | AX28: =IF(M28=VLOOKUP(VALUE(M$1),Questions!$A:$E,5,FALSE),1,0) -> 1 | AY28: =IF(N28=VLOOKUP(VALUE(N$1),Questions!$A:$E,5,FALSE),1,0) -> 1 | AZ28: =IF(O28=VLOOKUP(VALUE(O$1),Questions!$A:$E,5,FALSE),1,0) -> 1 | BA28: =IF(P28=VLOOKUP(VALUE(P$1),Questions!$A:$E,5,FALSE),1,0) -> 0 | BB28: =IF(Q28=VLOOKUP(VALUE(Q$1),Questions!$A:$E,5,FALSE),1,0) -> 1 | BC28: =IF(R28=VLOOKUP(VALUE(R$1),Questions!$A:$E,5,FALSE),1,0) -> 1 | ... BW28: =IF(AL28=VLOOKUP(VALUE(AL$1),Questions!$A:$E,5,FALSE),1,0) -> 1 | BX28: =IF(Scores[[#This Row],[Final]]>=65,1,0) -> 1 | BY28: =IF(Scores[[#This Row],[Final]]>=IF(Scores[[#This Row],[IEP]],55,65),1,0) -> 1
A29: 28 | B29: 9 | C29: Bermejo | D29: FALSE | E29: FALSE | F29: =SUM(Scores[[#This Row],[Q1]:[Q28]]) -> 16 | G29: =SUM(Scores[[#This Row],[29]]:Scores[[#This Row],[30]]) -> 4 | H29: =SUM(Scores[[#This Row],[31]:[36]]) -> 5 | I29: =Scores[[#This Row],[37]] -> 2.5 | J29: =INDEX('Conversion Chart'!$C$3:$M$47,MATCH(SUM(Scores[[#This Row],[MC]:[IIIA]]),'Conversion Chart'!$B$3:$B$47),MATCH(Scores[[#This Row],[IIIB]],'Conversion Chart'!$C$2:$M$2)) -> 70 | K29: 4 | L29: 2 | M29: 3 | N29: 3 | O29: 1 | P29: 4 | Q29: 3 | R29: 3 | S29: 2 | T29: 1 | U29: 1 | V29: 3 | W29: 2 | X29: 4 | Y29: 4 | Z29: 4 | AA29: 1 | AB29: 3 | AC29: 2 | AD29: 3 | AE29: 2 | AF29: 2 | AG29: 4 | AH29: 2 | AI29: 3 | AJ29: 4 | AK29: 4 | AL29: 3 | AM29: 2 | AN29: 2 | AO29: 0 | AP29: 1 | AQ29: 1 | AR29: 1 | AS29: 1 | AT29: 1 | AU29: 2.5 | AV29: =IF(K29=VLOOKUP(VALUE(K$1),Questions!$A:$E,5,FALSE),1,0) -> 1 | AW29: =IF(L29=VLOOKUP(VALUE(L$1),Questions!$A:$E,5,FALSE),1,0) -> 1 | AX29: =IF(M29=VLOOKUP(VALUE(M$1),Questions!$A:$E,5,FALSE),1,0) -> 1 | AY29: =IF(N29=VLOOKUP(VALUE(N$1),Questions!$A:$E,5,FALSE),1,0) -> 1 | AZ29: =IF(O29=VLOOKUP(VALUE(O$1),Questions!$A:$E,5,FALSE),1,0) -> 1 | BA29: =IF(P29=VLOOKUP(VALUE(P$1),Questions!$A:$E,5,FALSE),1,0) -> 1 | BB29: =IF(Q29=VLOOKUP(VALUE(Q$1),Questions!$A:$E,5,FALSE),1,0) -> 1 | BC29: =IF(R29=VLOOKUP(VALUE(R$1),Questions!$A:$E,5,FALSE),1,0) -> 0 | ... BW29: =IF(AL29=VLOOKUP(VALUE(AL$1),Questions!$A:$E,5,FALSE),1,0) -> 1 | BX29: =IF(Scores[[#This Row],[Final]]>=65,1,0) -> 1 | BY29: =IF(Scores[[#This Row],[Final]]>=IF(Scores[[#This Row],[IEP]],55,65),1,0) -> 1
A30: 29 | B30: 11 | C30: Dushin | D30: FALSE | E30: FALSE | F30: =SUM(Scores[[#This Row],[Q1]:[Q28]]) -> 13 | G30: =SUM(Scores[[#This Row],[29]]:Scores[[#This Row],[30]]) -> 3 | H30: =SUM(Scores[[#This Row],[31]:[36]]) -> 6 | I30: =Scores[[#This Row],[37]] -> 1 | J30: =INDEX('Conversion Chart'!$C$3:$M$47,MATCH(SUM(Scores[[#This Row],[MC]:[IIIA]]),'Conversion Chart'!$B$3:$B$47),MATCH(Scores[[#This Row],[IIIB]],'Conversion Chart'!$C$2:$M$2)) -> 60 | K30: 1 | L30: 1 | M30: 4 | N30: 1 | O30: 1 | P30: 4 | Q30: 2 | R30: 1 | S30: 2 | T30: 1 | U30: 2 | V30: 3 | W30: 1 | X30: 4 | Y30: 4 | Z30: 2 | AA30: 1 | AB30: 4 | AC30: 1 | AD30: 3 | AE30: 4 | AF30: 2 | AG30: 3 | AH30: 2 | AI30: 3 | AJ30: 4 | AK30: 1 | AL30: 3 | AM30: 2 | AN30: 1 | AO30: 1 | AP30: 1 | AQ30: 1 | AR30: 1 | AS30: 1 | AT30: 1 | AU30: 1 | AV30: =IF(K30=VLOOKUP(VALUE(K$1),Questions!$A:$E,5,FALSE),1,0) -> 0 | AW30: =IF(L30=VLOOKUP(VALUE(L$1),Questions!$A:$E,5,FALSE),1,0) -> 0 | AX30: =IF(M30=VLOOKUP(VALUE(M$1),Questions!$A:$E,5,FALSE),1,0) -> 0 | AY30: =IF(N30=VLOOKUP(VALUE(N$1),Questions!$A:$E,5,FALSE),1,0) -> 0 | AZ30: =IF(O30=VLOOKUP(VALUE(O$1),Questions!$A:$E,5,FALSE),1,0) -> 1 | BA30: =IF(P30=VLOOKUP(VALUE(P$1),Questions!$A:$E,5,FALSE),1,0) -> 1 | BB30: =IF(Q30=VLOOKUP(VALUE(Q$1),Questions!$A:$E,5,FALSE),1,0) -> 0 | BC30: =IF(R30=VLOOKUP(VALUE(R$1),Questions!$A:$E,5,FALSE),1,0) -> 0 | ... BW30: =IF(AL30=VLOOKUP(VALUE(AL$1),Questions!$A:$E,5,FALSE),1,0) -> 1 | BX30: =IF(Scores[[#This Row],[Final]]>=65,1,0) -> 0 | BY30: =IF(Scores[[#This Row],[Final]]>=IF(Scores[[#This Row],[IEP]],55,65),1,0) -> 0
A31: 30 | B31: 9 | C31: Bermejo | D31: FALSE | E31: TRUE | F31: =SUM(Scores[[#This Row],[Q1]:[Q28]]) -> 11 | G31: =SUM(Scores[[#This Row],[29]]:Scores[[#This Row],[30]]) -> 3 | H31: =SUM(Scores[[#This Row],[31]:[36]]) -> 5 | I31: =Scores[[#This Row],[37]] -> 1 | J31: =INDEX('Conversion Chart'!$C$3:$M$47,MATCH(SUM(Scores[[#This Row],[MC]:[IIIA]]),'Conversion Chart'!$B$3:$B$47),MATCH(Scores[[#This Row],[IIIB]],'Conversion Chart'!$C$2:$M$2)) -> 55 | K31: 4 | L31: 2 | M31: 3 | N31: 3 | O31: 3 | P31: 2 | Q31: 3 | R31: 3 | S31: 2 | T31: 2 | U31: 2 | V31: 3 | W31: 1 | X31: 2 | Y31: 4 | Z31: 4 | AA31: 1 | AB31: 3 | AC31: 3 | AD31: 1 | AE31: 2 | AF31: 1 | AG31: 4 | AH31: 2 | AI31: 3 | AJ31: 1 | AK31: 4 | AL31: 3 | AM31: 2 | AN31: 1 | AO31: 1 | AP31: 0 | AQ31: 1 | AR31: 1 | AS31: 1 | AT31: 1 | AU31: 1 | AV31: =IF(K31=VLOOKUP(VALUE(K$1),Questions!$A:$E,5,FALSE),1,0) -> 1 | AW31: =IF(L31=VLOOKUP(VALUE(L$1),Questions!$A:$E,5,FALSE),1,0) -> 1 | AX31: =IF(M31=VLOOKUP(VALUE(M$1),Questions!$A:$E,5,FALSE),1,0) -> 1 | AY31: =IF(N31=VLOOKUP(VALUE(N$1),Questions!$A:$E,5,FALSE),1,0) -> 1 | AZ31: =IF(O31=VLOOKUP(VALUE(O$1),Questions!$A:$E,5,FALSE),1,0) -> 0 | BA31: =IF(P31=VLOOKUP(VALUE(P$1),Questions!$A:$E,5,FALSE),1,0) -> 0 | BB31: =IF(Q31=VLOOKUP(VALUE(Q$1),Questions!$A:$E,5,FALSE),1,0) -> 1 | BC31: =IF(R31=VLOOKUP(VALUE(R$1),Questions!$A:$E,5,FALSE),1,0) -> 0 | ... BW31: =IF(AL31=VLOOKUP(VALUE(AL$1),Questions!$A:$E,5,FALSE),1,0) -> 1 | BX31: =IF(Scores[[#This Row],[Final]]>=65,1,0) -> 0 | BY31: =IF(Scores[[#This Row],[Final]]>=IF(Scores[[#This Row],[IEP]],55,65),1,0) -> 1
A32: 31 | B32: 9 | C32: Kovelsky | D32: FALSE | E32: FALSE | F32: =SUM(Scores[[#This Row],[Q1]:[Q28]]) -> 20 | G32: =SUM(Scores[[#This Row],[29]]:Scores[[#This Row],[30]]) -> 2 | H32: =SUM(Scores[[#This Row],[31]:[36]]) -> 6 | I32: =Scores[[#This Row],[37]] -> 1.5 | J32: =INDEX('Conversion Chart'!$C$3:$M$47,MATCH(SUM(Scores[[#This Row],[MC]:[IIIA]]),'Conversion Chart'!$B$3:$B$47),MATCH(Scores[[#This Row],[IIIB]],'Conversion Chart'!$C$2:$M$2)) -> 70 | K32: 4 | L32: 2 | M32: 3 | N32: 3 | O32: 1 | P32: 3 | Q32: 3 | R32: 2 | S32: 3 | T32: 1 | U32: 1 | V32: 4 | W32: 1 | X32: 4 | Y32: 3 | Z32: 1 | AA32: 1 | AB32: 4 | AC32: 3 | AD32: 1 | AE32: 3 | AF32: 2 | AG32: 3 | AH32: 3 | AI32: 1 | AJ32: 1 | AK32: 2 | AL32: 3 | AM32: 2 | AN32: 0 | AO32: 1 | AP32: 1 | AQ32: 1 | AR32: 1 | AS32: 1 | AT32: 1 | AU32: 1.5 | AV32: =IF(K32=VLOOKUP(VALUE(K$1),Questions!$A:$E,5,FALSE),1,0) -> 1 | AW32: =IF(L32=VLOOKUP(VALUE(L$1),Questions!$A:$E,5,FALSE),1,0) -> 1 | AX32: =IF(M32=VLOOKUP(VALUE(M$1),Questions!$A:$E,5,FALSE),1,0) -> 1 | AY32: =IF(N32=VLOOKUP(VALUE(N$1),Questions!$A:$E,5,FALSE),1,0) -> 1 | AZ32: =IF(O32=VLOOKUP(VALUE(O$1),Questions!$A:$E,5,FALSE),1,0) -> 1 | BA32: =IF(P32=VLOOKUP(VALUE(P$1),Questions!$A:$E,5,FALSE),1,0) -> 0 | BB32: =IF(Q32=VLOOKUP(VALUE(Q$1),Questions!$A:$E,5,FALSE),1,0) -> 1 | BC32: =IF(R32=VLOOKUP(VALUE(R$1),Questions!$A:$E,5,FALSE),1,0) -> 1 | ... BW32: =IF(AL32=VLOOKUP(VALUE(AL$1),Questions!$A:$E,5,FALSE),1,0) -> 1 | BX32: =IF(Scores[[#This Row],[Final]]>=65,1,0) -> 1 | BY32: =IF(Scores[[#This Row],[Final]]>=IF(Scores[[#This Row],[IEP]],55,65),1,0) -> 1
A33: 32 | B33: 9 | C33: Bermejo | D33: FALSE | E33: FALSE | F33: =SUM(Scores[[#This Row],[Q1]:[Q28]]) -> 12 | G33: =SUM(Scores[[#This Row],[29]]:Scores[[#This Row],[30]]) -> 3 | H33: =SUM(Scores[[#This Row],[31]:[36]]) -> 6 | I33: =Scores[[#This Row],[37]] -> 1 | J33: =INDEX('Conversion Chart'!$C$3:$M$47,MATCH(SUM(Scores[[#This Row],[MC]:[IIIA]]),'Conversion Chart'!$B$3:$B$47),MATCH(Scores[[#This Row],[IIIB]],'Conversion Chart'!$C$2:$M$2)) -> 58 | K33: 4 | L33: 3 | M33: 1 | N33: 1 | O33: 2 | P33: 1 | Q33: 3 | R33: 1 | S33: 4 | T33: 1 | U33: 2 | V33: 3 | W33: 4 | X33: 2 | Y33: 4 | Z33: 4 | AA33: 1 | AB33: 4 | AC33: 3 | AD33: 4 | AE33: 1 | AF33: 2 | AG33: 3 | AH33: 2 | AI33: 4 | AJ33: 4 | AK33: 2 | AL33: 3 | AM33: 2 | AN33: 1 | AO33: 1 | AP33: 1 | AQ33: 1 | AR33: 1 | AS33: 1 | AT33: 1 | AU33: 1 | AV33: =IF(K33=VLOOKUP(VALUE(K$1),Questions!$A:$E,5,FALSE),1,0) -> 1 | AW33: =IF(L33=VLOOKUP(VALUE(L$1),Questions!$A:$E,5,FALSE),1,0) -> 0 | AX33: =IF(M33=VLOOKUP(VALUE(M$1),Questions!$A:$E,5,FALSE),1,0) -> 0 | AY33: =IF(N33=VLOOKUP(VALUE(N$1),Questions!$A:$E,5,FALSE),1,0) -> 0 | AZ33: =IF(O33=VLOOKUP(VALUE(O$1),Questions!$A:$E,5,FALSE),1,0) -> 0 | BA33: =IF(P33=VLOOKUP(VALUE(P$1),Questions!$A:$E,5,FALSE),1,0) -> 0 | BB33: =IF(Q33=VLOOKUP(VALUE(Q$1),Questions!$A:$E,5,FALSE),1,0) -> 1 | BC33: =IF(R33=VLOOKUP(VALUE(R$1),Questions!$A:$E,5,FALSE),1,0) -> 0 | ... BW33: =IF(AL33=VLOOKUP(VALUE(AL$1),Questions!$A:$E,5,FALSE),1,0) -> 1 | BX33: =IF(Scores[[#This Row],[Final]]>=65,1,0) -> 0 | BY33: =IF(Scores[[#This Row],[Final]]>=IF(Scores[[#This Row],[IEP]],55,65),1,0) -> 0
A34: 33 | B34: 11 | C34: Dushin | D34: FALSE | E34: FALSE | F34: =SUM(Scores[[#This Row],[Q1]:[Q28]]) -> 20 | G34: =SUM(Scores[[#This Row],[29]]:Scores[[#This Row],[30]]) -> 5 | H34: =SUM(Scores[[#This Row],[31]:[36]]) -> 5 | I34: =Scores[[#This Row],[37]] -> 1 | J34: =INDEX('Conversion Chart'!$C$3:$M$47,MATCH(SUM(Scores[[#This Row],[MC]:[IIIA]]),'Conversion Chart'!$B$3:$B$47),MATCH(Scores[[#This Row],[IIIB]],'Conversion Chart'!$C$2:$M$2)) -> 70 | K34: 4 | L34: 2 | M34: 1 | N34: 3 | O34: 2 | P34: 4 | Q34: 2 | R34: 1 | S34: 2 | T34: 1 | U34: 2 | V34: 4 | W34: 2 | X34: 1 | Y34: 3 | Z34: 1 | AA34: 1 | AB34: 4 | AC34: 3 | AD34: 1 | AE34: 2 | AF34: 1 | AG34: 2 | AH34: 3 | AI34: 1 | AJ34: 4 | AK34: 1 | AL34: 3 | AM34: 3 | AN34: 2 | AO34: 0 | AP34: 1 | AQ34: 1 | AR34: 1 | AS34: 1 | AT34: 1 | AU34: 1 | AV34: =IF(K34=VLOOKUP(VALUE(K$1),Questions!$A:$E,5,FALSE),1,0) -> 1 | AW34: =IF(L34=VLOOKUP(VALUE(L$1),Questions!$A:$E,5,FALSE),1,0) -> 1 | AX34: =IF(M34=VLOOKUP(VALUE(M$1),Questions!$A:$E,5,FALSE),1,0) -> 0 | AY34: =IF(N34=VLOOKUP(VALUE(N$1),Questions!$A:$E,5,FALSE),1,0) -> 1 | AZ34: =IF(O34=VLOOKUP(VALUE(O$1),Questions!$A:$E,5,FALSE),1,0) -> 0 | BA34: =IF(P34=VLOOKUP(VALUE(P$1),Questions!$A:$E,5,FALSE),1,0) -> 1 | BB34: =IF(Q34=VLOOKUP(VALUE(Q$1),Questions!$A:$E,5,FALSE),1,0) -> 0 | BC34: =IF(R34=VLOOKUP(VALUE(R$1),Questions!$A:$E,5,FALSE),1,0) -> 0 | ... BW34: =IF(AL34=VLOOKUP(VALUE(AL$1),Questions!$A:$E,5,FALSE),1,0) -> 1 | BX34: =IF(Scores[[#This Row],[Final]]>=65,1,0) -> 1 | BY34: =IF(Scores[[#This Row],[Final]]>=IF(Scores[[#This Row],[IEP]],55,65),1,0) -> 1
A35: 34 | B35: 11 | C35: Antaky | D35: FALSE | E35: FALSE | F35: =SUM(Scores[[#This Row],[Q1]:[Q28]]) -> 20 | G35: =SUM(Scores[[#This Row],[29]]:Scores[[#This Row],[30]]) -> 5 | H35: =SUM(Scores[[#This Row],[31]:[36]]) -> 6 | I35: =Scores[[#This Row],[37]] -> 3 | J35: =INDEX('Conversion Chart'!$C$3:$M$47,MATCH(SUM(Scores[[#This Row],[MC]:[IIIA]]),'Conversion Chart'!$B$3:$B$47),MATCH(Scores[[#This Row],[IIIB]],'Conversion Chart'!$C$2:$M$2)) -> 77 | K35: 4 | L35: 2 | M35: 3 | N35: 4 | O35: 1 | P35: 3 | Q35: 3 | R35: 2 | S35: 2 | T35: 1 | U35: 1 | V35: 4 | W35: 2 | X35: 4 | Y35: 3 | Z35: 2 | AA35: 1 | AB35: 4 | AC35: 1 | AD35: 1 | AE35: 2 | AF35: 2 | AG35: 3 | AH35: 3 | AI35: 4 | AJ35: 4 | AK35: 1 | AL35: 2 | AM35: 2 | AN35: 3 | AO35: 1 | AP35: 1 | AQ35: 1 | AR35: 1 | AS35: 1 | AT35: 1 | AU35: 3 | AV35: =IF(K35=VLOOKUP(VALUE(K$1),Questions!$A:$E,5,FALSE),1,0) -> 1 | AW35: =IF(L35=VLOOKUP(VALUE(L$1),Questions!$A:$E,5,FALSE),1,0) -> 1 | AX35: =IF(M35=VLOOKUP(VALUE(M$1),Questions!$A:$E,5,FALSE),1,0) -> 1 | AY35: =IF(N35=VLOOKUP(VALUE(N$1),Questions!$A:$E,5,FALSE),1,0) -> 0 | AZ35: =IF(O35=VLOOKUP(VALUE(O$1),Questions!$A:$E,5,FALSE),1,0) -> 1 | BA35: =IF(P35=VLOOKUP(VALUE(P$1),Questions!$A:$E,5,FALSE),1,0) -> 0 | BB35: =IF(Q35=VLOOKUP(VALUE(Q$1),Questions!$A:$E,5,FALSE),1,0) -> 1 | BC35: =IF(R35=VLOOKUP(VALUE(R$1),Questions!$A:$E,5,FALSE),1,0) -> 1 | ... BW35: =IF(AL35=VLOOKUP(VALUE(AL$1),Questions!$A:$E,5,FALSE),1,0) -> 0 | BX35: =IF(Scores[[#This Row],[Final]]>=65,1,0) -> 1 | BY35: =IF(Scores[[#This Row],[Final]]>=IF(Scores[[#This Row],[IEP]],55,65),1,0) -> 1
A36: 35 | B36: 9 | C36: Bermejo | D36: FALSE | E36: FALSE | F36: =SUM(Scores[[#This Row],[Q1]:[Q28]]) -> 15 | G36: =SUM(Scores[[#This Row],[29]]:Scores[[#This Row],[30]]) -> 6 | H36: =SUM(Scores[[#This Row],[31]:[36]]) -> 6 | I36: =Scores[[#This Row],[37]] -> 2.5 | J36: =INDEX('Conversion Chart'!$C$3:$M$47,MATCH(SUM(Scores[[#This Row],[MC]:[IIIA]]),'Conversion Chart'!$B$3:$B$47),MATCH(Scores[[#This Row],[IIIB]],'Conversion Chart'!$C$2:$M$2)) -> 72 | K36: 4 | L36: 2 | M36: 3 | N36: 1 | O36: 1 | P36: 2 | Q36: 2 | R36: 2 | S36: 2 | T36: 1 | U36: 2 | V36: 4 | W36: 1 | X36: 2 | Y36: 4 | Z36: 4 | AA36: 3 | AB36: 4 | AC36: 1 | AD36: 4 | AE36: 2 | AF36: 1 | AG36: 3 | AH36: 2 | AI36: 3 | AJ36: 4 | AK36: 4 | AL36: 3 | AM36: 3 | AN36: 3 | AO36: 1 | AP36: 1 | AQ36: 1 | AR36: 1 | AS36: 1 | AT36: 1 | AU36: 2.5 | AV36: =IF(K36=VLOOKUP(VALUE(K$1),Questions!$A:$E,5,FALSE),1,0) -> 1 | AW36: =IF(L36=VLOOKUP(VALUE(L$1),Questions!$A:$E,5,FALSE),1,0) -> 1 | AX36: =IF(M36=VLOOKUP(VALUE(M$1),Questions!$A:$E,5,FALSE),1,0) -> 1 | AY36: =IF(N36=VLOOKUP(VALUE(N$1),Questions!$A:$E,5,FALSE),1,0) -> 0 | AZ36: =IF(O36=VLOOKUP(VALUE(O$1),Questions!$A:$E,5,FALSE),1,0) -> 1 | BA36: =IF(P36=VLOOKUP(VALUE(P$1),Questions!$A:$E,5,FALSE),1,0) -> 0 | BB36: =IF(Q36=VLOOKUP(VALUE(Q$1),Questions!$A:$E,5,FALSE),1,0) -> 0 | BC36: =IF(R36=VLOOKUP(VALUE(R$1),Questions!$A:$E,5,FALSE),1,0) -> 1 | ... BW36: =IF(AL36=VLOOKUP(VALUE(AL$1),Questions!$A:$E,5,FALSE),1,0) -> 1 | BX36: =IF(Scores[[#This Row],[Final]]>=65,1,0) -> 1 | BY36: =IF(Scores[[#This Row],[Final]]>=IF(Scores[[#This Row],[IEP]],55,65),1,0) -> 1
A37: 36 | B37: 11 | C37: Other | D37: FALSE | E37: FALSE | F37: =SUM(Scores[[#This Row],[Q1]:[Q28]]) -> 0 | G37: =SUM(Scores[[#This Row],[29]]:Scores[[#This Row],[30]]) -> 0 | H37: =SUM(Scores[[#This Row],[31]:[36]]) -> 0 | I37: =Scores[[#This Row],[37]] -> 0 | J37: =INDEX('Conversion Chart'!$C$3:$M$47,MATCH(SUM(Scores[[#This Row],[MC]:[IIIA]]),'Conversion Chart'!$B$3:$B$47),MATCH(Scores[[#This Row],[IIIB]],'Conversion Chart'!$C$2:$M$2)) -> 0 | AV37: =IF(K37=VLOOKUP(VALUE(K$1),Questions!$A:$E,5,FALSE),1,0) -> 0 | AW37: =IF(L37=VLOOKUP(VALUE(L$1),Questions!$A:$E,5,FALSE),1,0) -> 0 | AX37: =IF(M37=VLOOKUP(VALUE(M$1),Questions!$A:$E,5,FALSE),1,0) -> 0 | AY37: =IF(N37=VLOOKUP(VALUE(N$1),Questions!$A:$E,5,FALSE),1,0) -> 0 | AZ37: =IF(O37=VLOOKUP(VALUE(O$1),Questions!$A:$E,5,FALSE),1,0) -> 0 | BA37: =IF(P37=VLOOKUP(VALUE(P$1),Questions!$A:$E,5,FALSE),1,0) -> 0 | BB37: =IF(Q37=VLOOKUP(VALUE(Q$1),Questions!$A:$E,5,FALSE),1,0) -> 0 | BC37: =IF(R37=VLOOKUP(VALUE(R$1),Questions!$A:$E,5,FALSE),1,0) -> 0 | ... BW37: =IF(AL37=VLOOKUP(VALUE(AL$1),Questions!$A:$E,5,FALSE),1,0) -> 0 | BX37: =IF(Scores[[#This Row],[Final]]>=65,1,0) -> 0 | BY37: =IF(Scores[[#This Row],[Final]]>=IF(Scores[[#This Row],[IEP]],55,65),1,0) -> 0
A38: 37 | B38: 11 | C38: Other | D38: FALSE | E38: FALSE | F38: =SUM(Scores[[#This Row],[Q1]:[Q28]]) -> 10 | G38: =SUM(Scores[[#This Row],[29]]:Scores[[#This Row],[30]]) -> 3 | H38: =SUM(Scores[[#This Row],[31]:[36]]) -> 3 | I38: =Scores[[#This Row],[37]] -> 0.5 | J38: =INDEX('Conversion Chart'!$C$3:$M$47,MATCH(SUM(Scores[[#This Row],[MC]:[IIIA]]),'Conversion Chart'!$B$3:$B$47),MATCH(Scores[[#This Row],[IIIB]],'Conversion Chart'!$C$2:$M$2)) -> 47 | K38: 4 | L38: 2 | M38: 3 | N38: 1 | O38: 1 | P38: 2 | Q38: 2 | R38: 1 | S38: 4 | T38: 1 | U38: 4 | V38: 3 | W38: 3 | X38: 1 | Y38: 4 | Z38: 4 | AA38: 1 | AB38: 4 | AC38: 1 | AD38: 3 | AE38: 3 | AF38: 2 | AG38: 3 | AH38: 4 | AI38: 3 | AJ38: 4 | AK38: 4 | AL38: 4 | AM38: 2 | AN38: 1 | AO38: 0 | AP38: 1 | AQ38: 0 | AR38: 1 | AS38: 0 | AT38: 1 | AU38: 0.5 | AV38: =IF(K38=VLOOKUP(VALUE(K$1),Questions!$A:$E,5,FALSE),1,0) -> 1 | AW38: =IF(L38=VLOOKUP(VALUE(L$1),Questions!$A:$E,5,FALSE),1,0) -> 1 | AX38: =IF(M38=VLOOKUP(VALUE(M$1),Questions!$A:$E,5,FALSE),1,0) -> 1 | AY38: =IF(N38=VLOOKUP(VALUE(N$1),Questions!$A:$E,5,FALSE),1,0) -> 0 | AZ38: =IF(O38=VLOOKUP(VALUE(O$1),Questions!$A:$E,5,FALSE),1,0) -> 1 | BA38: =IF(P38=VLOOKUP(VALUE(P$1),Questions!$A:$E,5,FALSE),1,0) -> 0 | BB38: =IF(Q38=VLOOKUP(VALUE(Q$1),Questions!$A:$E,5,FALSE),1,0) -> 0 | BC38: =IF(R38=VLOOKUP(VALUE(R$1),Questions!$A:$E,5,FALSE),1,0) -> 0 | ... BW38: =IF(AL38=VLOOKUP(VALUE(AL$1),Questions!$A:$E,5,FALSE),1,0) -> 0 | BX38: =IF(Scores[[#This Row],[Final]]>=65,1,0) -> 0 | BY38: =IF(Scores[[#This Row],[Final]]>=IF(Scores[[#This Row],[IEP]],55,65),1,0) -> 0
A39: 38 | B39: 9 | C39: Bermejo | D39: FALSE | E39: FALSE | F39: =SUM(Scores[[#This Row],[Q1]:[Q28]]) -> 23 | G39: =SUM(Scores[[#This Row],[29]]:Scores[[#This Row],[30]]) -> 9 | H39: =SUM(Scores[[#This Row],[31]:[36]]) -> 6 | I39: =Scores[[#This Row],[37]] -> 2 | J39: =INDEX('Conversion Chart'!$C$3:$M$47,MATCH(SUM(Scores[[#This Row],[MC]:[IIIA]]),'Conversion Chart'!$B$3:$B$47),MATCH(Scores[[#This Row],[IIIB]],'Conversion Chart'!$C$2:$M$2)) -> 81 | K39: 4 | L39: 2 | M39: 3 | N39: 3 | O39: 1 | P39: 4 | Q39: 3 | R39: 2 | S39: 2 | T39: 1 | U39: 2 | V39: 4 | W39: 2 | X39: 2 | Y39: 3 | Z39: 1 | AA39: 1 | AB39: 3 | AC39: 3 | AD39: 4 | AE39: 3 | AF39: 2 | AG39: 3 | AH39: 2 | AI39: 1 | AJ39: 4 | AK39: 4 | AL39: 3 | AM39: 5 | AN39: 4 | AO39: 1 | AP39: 1 | AQ39: 1 | AR39: 1 | AS39: 1 | AT39: 1 | AU39: 2 | AV39: =IF(K39=VLOOKUP(VALUE(K$1),Questions!$A:$E,5,FALSE),1,0) -> 1 | AW39: =IF(L39=VLOOKUP(VALUE(L$1),Questions!$A:$E,5,FALSE),1,0) -> 1 | AX39: =IF(M39=VLOOKUP(VALUE(M$1),Questions!$A:$E,5,FALSE),1,0) -> 1 | AY39: =IF(N39=VLOOKUP(VALUE(N$1),Questions!$A:$E,5,FALSE),1,0) -> 1 | AZ39: =IF(O39=VLOOKUP(VALUE(O$1),Questions!$A:$E,5,FALSE),1,0) -> 1 | BA39: =IF(P39=VLOOKUP(VALUE(P$1),Questions!$A:$E,5,FALSE),1,0) -> 1 | BB39: =IF(Q39=VLOOKUP(VALUE(Q$1),Questions!$A:$E,5,FALSE),1,0) -> 1 | BC39: =IF(R39=VLOOKUP(VALUE(R$1),Questions!$A:$E,5,FALSE),1,0) -> 1 | ... BW39: =IF(AL39=VLOOKUP(VALUE(AL$1),Questions!$A:$E,5,FALSE),1,0) -> 1 | BX39: =IF(Scores[[#This Row],[Final]]>=65,1,0) -> 1 | BY39: =IF(Scores[[#This Row],[Final]]>=IF(Scores[[#This Row],[IEP]],55,65),1,0) -> 1
A40: 39 | B40: 9 | C40: Bermejo | D40: FALSE | E40: FALSE | F40: =SUM(Scores[[#This Row],[Q1]:[Q28]]) -> 20 | G40: =SUM(Scores[[#This Row],[29]]:Scores[[#This Row],[30]]) -> 2 | H40: =SUM(Scores[[#This Row],[31]:[36]]) -> 4 | I40: =Scores[[#This Row],[37]] -> 2 | J40: =INDEX('Conversion Chart'!$C$3:$M$47,MATCH(SUM(Scores[[#This Row],[MC]:[IIIA]]),'Conversion Chart'!$B$3:$B$47),MATCH(Scores[[#This Row],[IIIB]],'Conversion Chart'!$C$2:$M$2)) -> 69 | K40: 4 | L40: 2 | M40: 3 | N40: 3 | O40: 1 | P40: 2 | Q40: 4 | R40: 2 | S40: 2 | T40: 2 | U40: 2 | V40: 4 | W40: 2 | X40: 4 | Y40: 2 | Z40: 1 | AA40: 1 | AB40: 3 | AC40: 3 | AD40: 4 | AE40: 3 | AF40: 2 | AG40: 3 | AH40: 3 | AI40: 2 | AJ40: 4 | AK40: 4 | AL40: 3 | AM40: 1 | AN40: 1 | AO40: 1 | AP40: 1 | AQ40: 0 | AR40: 1 | AS40: 1 | AT40: 0 | AU40: 2 | AV40: =IF(K40=VLOOKUP(VALUE(K$1),Questions!$A:$E,5,FALSE),1,0) -> 1 | AW40: =IF(L40=VLOOKUP(VALUE(L$1),Questions!$A:$E,5,FALSE),1,0) -> 1 | AX40: =IF(M40=VLOOKUP(VALUE(M$1),Questions!$A:$E,5,FALSE),1,0) -> 1 | AY40: =IF(N40=VLOOKUP(VALUE(N$1),Questions!$A:$E,5,FALSE),1,0) -> 1 | AZ40: =IF(O40=VLOOKUP(VALUE(O$1),Questions!$A:$E,5,FALSE),1,0) -> 1 | BA40: =IF(P40=VLOOKUP(VALUE(P$1),Questions!$A:$E,5,FALSE),1,0) -> 0 | BB40: =IF(Q40=VLOOKUP(VALUE(Q$1),Questions!$A:$E,5,FALSE),1,0) -> 0 | BC40: =IF(R40=VLOOKUP(VALUE(R$1),Questions!$A:$E,5,FALSE),1,0) -> 1 | ... BW40: =IF(AL40=VLOOKUP(VALUE(AL$1),Questions!$A:$E,5,FALSE),1,0) -> 1 | BX40: =IF(Scores[[#This Row],[Final]]>=65,1,0) -> 1 | BY40: =IF(Scores[[#This Row],[Final]]>=IF(Scores[[#This Row],[IEP]],55,65),1,0) -> 1
A41: 40 | B41: 9 | C41: Kovelsky | D41: FALSE | E41: FALSE | F41: =SUM(Scores[[#This Row],[Q1]:[Q28]]) -> 9 | G41: =SUM(Scores[[#This Row],[29]]:Scores[[#This Row],[30]]) -> 2 | H41: =SUM(Scores[[#This Row],[31]:[36]]) -> 4 | I41: =Scores[[#This Row],[37]] -> 1 | J41: =INDEX('Conversion Chart'!$C$3:$M$47,MATCH(SUM(Scores[[#This Row],[MC]:[IIIA]]),'Conversion Chart'!$B$3:$B$47),MATCH(Scores[[#This Row],[IIIB]],'Conversion Chart'!$C$2:$M$2)) -> 48 | K41: 4 | L41: 4 | M41: 3 | N41: 1 | O41: 1 | P41: 3 | Q41: 3 | R41: 2 | S41: 2 | T41: 4 | U41: 2 | V41: 2 | W41: 1 | X41: 2 | Y41: 1 | Z41: 1 | AA41: 4 | AB41: 1 | AC41: 2 | AD41: 3 | AE41: 2 | AF41: 1 | AG41: 1 | AH41: 2 | AI41: 3 | AJ41: 1 | AK41: 4 | AL41: 1 | AM41: 1 | AN41: 1 | AO41: 1 | AP41: 1 | AQ41: 1 | AR41: 0 | AS41: 0 | AT41: 1 | AU41: 1 | AV41: =IF(K41=VLOOKUP(VALUE(K$1),Questions!$A:$E,5,FALSE),1,0) -> 1 | AW41: =IF(L41=VLOOKUP(VALUE(L$1),Questions!$A:$E,5,FALSE),1,0) -> 0 | AX41: =IF(M41=VLOOKUP(VALUE(M$1),Questions!$A:$E,5,FALSE),1,0) -> 1 | AY41: =IF(N41=VLOOKUP(VALUE(N$1),Questions!$A:$E,5,FALSE),1,0) -> 0 | AZ41: =IF(O41=VLOOKUP(VALUE(O$1),Questions!$A:$E,5,FALSE),1,0) -> 1 | BA41: =IF(P41=VLOOKUP(VALUE(P$1),Questions!$A:$E,5,FALSE),1,0) -> 0 | BB41: =IF(Q41=VLOOKUP(VALUE(Q$1),Questions!$A:$E,5,FALSE),1,0) -> 1 | BC41: =IF(R41=VLOOKUP(VALUE(R$1),Questions!$A:$E,5,FALSE),1,0) -> 1 | ... BW41: =IF(AL41=VLOOKUP(VALUE(AL$1),Questions!$A:$E,5,FALSE),1,0) -> 0 | BX41: =IF(Scores[[#This Row],[Final]]>=65,1,0) -> 0 | BY41: =IF(Scores[[#This Row],[Final]]>=IF(Scores[[#This Row],[IEP]],55,65),1,0) -> 0
A42: 41 | B42: 11 | C42: Dushin | D42: FALSE | E42: FALSE | F42: =SUM(Scores[[#This Row],[Q1]:[Q28]]) -> 24 | G42: =SUM(Scores[[#This Row],[29]]:Scores[[#This Row],[30]]) -> 6 | H42: =SUM(Scores[[#This Row],[31]:[36]]) -> 6 | I42: =Scores[[#This Row],[37]] -> 3.5 | J42: =INDEX('Conversion Chart'!$C$3:$M$47,MATCH(SUM(Scores[[#This Row],[MC]:[IIIA]]),'Conversion Chart'!$B$3:$B$47),MATCH(Scores[[#This Row],[IIIB]],'Conversion Chart'!$C$2:$M$2)) -> 84 | K42: 4 | L42: 2 | M42: 3 | N42: 3 | O42: 1 | P42: 4 | Q42: 3 | R42: 2 | S42: 2 | T42: 1 | U42: 2 | V42: 4 | W42: 2 | X42: 1 | Y42: 3 | Z42: 1 | AA42: 1 | AB42: 4 | AC42: 1 | AD42: 4 | AE42: 2 | AF42: 2 | AG42: 1 | AH42: 3 | AI42: 3 | AJ42: 4 | AK42: 1 | AL42: 3 | AM42: 4 | AN42: 2 | AO42: 1 | AP42: 1 | AQ42: 1 | AR42: 1 | AS42: 1 | AT42: 1 | AU42: 3.5 | AV42: =IF(K42=VLOOKUP(VALUE(K$1),Questions!$A:$E,5,FALSE),1,0) -> 1 | AW42: =IF(L42=VLOOKUP(VALUE(L$1),Questions!$A:$E,5,FALSE),1,0) -> 1 | AX42: =IF(M42=VLOOKUP(VALUE(M$1),Questions!$A:$E,5,FALSE),1,0) -> 1 | AY42: =IF(N42=VLOOKUP(VALUE(N$1),Questions!$A:$E,5,FALSE),1,0) -> 1 | AZ42: =IF(O42=VLOOKUP(VALUE(O$1),Questions!$A:$E,5,FALSE),1,0) -> 1 | BA42: =IF(P42=VLOOKUP(VALUE(P$1),Questions!$A:$E,5,FALSE),1,0) -> 1 | BB42: =IF(Q42=VLOOKUP(VALUE(Q$1),Questions!$A:$E,5,FALSE),1,0) -> 1 | BC42: =IF(R42=VLOOKUP(VALUE(R$1),Questions!$A:$E,5,FALSE),1,0) -> 1 | ... BW42: =IF(AL42=VLOOKUP(VALUE(AL$1),Questions!$A:$E,5,FALSE),1,0) -> 1 | BX42: =IF(Scores[[#This Row],[Final]]>=65,1,0) -> 1 | BY42: =IF(Scores[[#This Row],[Final]]>=IF(Scores[[#This Row],[IEP]],55,65),1,0) -> 1
A43: 42 | B43: 11 | C43: Other | D43: FALSE | E43: FALSE | F43: =SUM(Scores[[#This Row],[Q1]:[Q28]]) -> 19 | G43: =SUM(Scores[[#This Row],[29]]:Scores[[#This Row],[30]]) -> 3 | H43: =SUM(Scores[[#This Row],[31]:[36]]) -> 5 | I43: =Scores[[#This Row],[37]] -> 0 | J43: =INDEX('Conversion Chart'!$C$3:$M$47,MATCH(SUM(Scores[[#This Row],[MC]:[IIIA]]),'Conversion Chart'!$B$3:$B$47),MATCH(Scores[[#This Row],[IIIB]],'Conversion Chart'!$C$2:$M$2)) -> 63 | K43: 4 | L43: 3 | M43: 3 | N43: 3 | O43: 1 | P43: 4 | Q43: 3 | R43: 2 | S43: 2 | T43: 1 | U43: 2 | V43: 3 | W43: 3 | X43: 1 | Y43: 4 | Z43: 1 | AA43: 1 | AB43: 4 | AC43: 3 | AD43: 1 | AE43: 2 | AF43: 2 | AG43: 3 | AH43: 2 | AI43: 4 | AJ43: 4 | AK43: 2 | AL43: 3 | AM43: 1 | AN43: 2 | AO43: 1 | AP43: 0 | AQ43: 1 | AR43: 1 | AS43: 1 | AT43: 1 | AU43: 0 | AV43: =IF(K43=VLOOKUP(VALUE(K$1),Questions!$A:$E,5,FALSE),1,0) -> 1 | AW43: =IF(L43=VLOOKUP(VALUE(L$1),Questions!$A:$E,5,FALSE),1,0) -> 0 | AX43: =IF(M43=VLOOKUP(VALUE(M$1),Questions!$A:$E,5,FALSE),1,0) -> 1 | AY43: =IF(N43=VLOOKUP(VALUE(N$1),Questions!$A:$E,5,FALSE),1,0) -> 1 | AZ43: =IF(O43=VLOOKUP(VALUE(O$1),Questions!$A:$E,5,FALSE),1,0) -> 1 | BA43: =IF(P43=VLOOKUP(VALUE(P$1),Questions!$A:$E,5,FALSE),1,0) -> 1 | BB43: =IF(Q43=VLOOKUP(VALUE(Q$1),Questions!$A:$E,5,FALSE),1,0) -> 1 | BC43: =IF(R43=VLOOKUP(VALUE(R$1),Questions!$A:$E,5,FALSE),1,0) -> 1 | ... BW43: =IF(AL43=VLOOKUP(VALUE(AL$1),Questions!$A:$E,5,FALSE),1,0) -> 1 | BX43: =IF(Scores[[#This Row],[Final]]>=65,1,0) -> 0 | BY43: =IF(Scores[[#This Row],[Final]]>=IF(Scores[[#This Row],[IEP]],55,65),1,0) -> 0
A44: 43 | B44: 11 | C44: Dushin | D44: FALSE | E44: FALSE | F44: =SUM(Scores[[#This Row],[Q1]:[Q28]]) -> 21 | G44: =SUM(Scores[[#This Row],[29]]:Scores[[#This Row],[30]]) -> 4 | H44: =SUM(Scores[[#This Row],[31]:[36]]) -> 3 | I44: =Scores[[#This Row],[37]] -> 0 | J44: =INDEX('Conversion Chart'!$C$3:$M$47,MATCH(SUM(Scores[[#This Row],[MC]:[IIIA]]),'Conversion Chart'!$B$3:$B$47),MATCH(Scores[[#This Row],[IIIB]],'Conversion Chart'!$C$2:$M$2)) -> 64 | K44: 4 | L44: 2 | M44: 3 | N44: 4 | O44: 1 | P44: 2 | Q44: 3 | R44: 2 | S44: 2 | T44: 1 | U44: 2 | V44: 4 | W44: 1 | X44: 3 | Y44: 3 | Z44: 2 | AA44: 1 | AB44: 4 | AC44: 3 | AD44: 2 | AE44: 4 | AF44: 2 | AG44: 3 | AH44: 3 | AI44: 1 | AJ44: 4 | AK44: 1 | AL44: 3 | AM44: 3 | AN44: 1 | AO44: 0 | AP44: 1 | AQ44: 0 | AR44: 1 | AS44: 0 | AT44: 1 | AU44: 0 | AV44: =IF(K44=VLOOKUP(VALUE(K$1),Questions!$A:$E,5,FALSE),1,0) -> 1 | AW44: =IF(L44=VLOOKUP(VALUE(L$1),Questions!$A:$E,5,FALSE),1,0) -> 1 | AX44: =IF(M44=VLOOKUP(VALUE(M$1),Questions!$A:$E,5,FALSE),1,0) -> 1 | AY44: =IF(N44=VLOOKUP(VALUE(N$1),Questions!$A:$E,5,FALSE),1,0) -> 0 | AZ44: =IF(O44=VLOOKUP(VALUE(O$1),Questions!$A:$E,5,FALSE),1,0) -> 1 | BA44: =IF(P44=VLOOKUP(VALUE(P$1),Questions!$A:$E,5,FALSE),1,0) -> 0 | BB44: =IF(Q44=VLOOKUP(VALUE(Q$1),Questions!$A:$E,5,FALSE),1,0) -> 1 | BC44: =IF(R44=VLOOKUP(VALUE(R$1),Questions!$A:$E,5,FALSE),1,0) -> 1 | ... BW44: =IF(AL44=VLOOKUP(VALUE(AL$1),Questions!$A:$E,5,FALSE),1,0) -> 1 | BX44: =IF(Scores[[#This Row],[Final]]>=65,1,0) -> 0 | BY44: =IF(Scores[[#This Row],[Final]]>=IF(Scores[[#This Row],[IEP]],55,65),1,0) -> 0
A45: 44 | B45: 11 | C45: Antaky | D45: FALSE | E45: FALSE | F45: =SUM(Scores[[#This Row],[Q1]:[Q28]]) -> 22 | G45: =SUM(Scores[[#This Row],[29]]:Scores[[#This Row],[30]]) -> 3 | H45: =SUM(Scores[[#This Row],[31]:[36]]) -> 5 | I45: =Scores[[#This Row],[37]] -> 1.5 | J45: =INDEX('Conversion Chart'!$C$3:$M$47,MATCH(SUM(Scores[[#This Row],[MC]:[IIIA]]),'Conversion Chart'!$B$3:$B$47),MATCH(Scores[[#This Row],[IIIB]],'Conversion Chart'!$C$2:$M$2)) -> 72 | K45: 4 | L45: 1 | M45: 3 | N45: 3 | O45: 1 | P45: 4 | Q45: 3 | R45: 2 | S45: 3 | T45: 1 | U45: 2 | V45: 4 | W45: 2 | X45: 4 | Y45: 3 | Z45: 4 | AA45: 1 | AB45: 4 | AC45: 3 | AD45: 1 | AE45: 2 | AF45: 2 | AG45: 3 | AH45: 2 | AI45: 1 | AJ45: 2 | AK45: 1 | AL45: 3 | AM45: 1 | AN45: 2 | AO45: 1 | AP45: 1 | AQ45: 1 | AR45: 1 | AS45: 1 | AT45: 0 | AU45: 1.5 | AV45: =IF(K45=VLOOKUP(VALUE(K$1),Questions!$A:$E,5,FALSE),1,0) -> 1 | AW45: =IF(L45=VLOOKUP(VALUE(L$1),Questions!$A:$E,5,FALSE),1,0) -> 0 | AX45: =IF(M45=VLOOKUP(VALUE(M$1),Questions!$A:$E,5,FALSE),1,0) -> 1 | AY45: =IF(N45=VLOOKUP(VALUE(N$1),Questions!$A:$E,5,FALSE),1,0) -> 1 | AZ45: =IF(O45=VLOOKUP(VALUE(O$1),Questions!$A:$E,5,FALSE),1,0) -> 1 | BA45: =IF(P45=VLOOKUP(VALUE(P$1),Questions!$A:$E,5,FALSE),1,0) -> 1 | BB45: =IF(Q45=VLOOKUP(VALUE(Q$1),Questions!$A:$E,5,FALSE),1,0) -> 1 | BC45: =IF(R45=VLOOKUP(VALUE(R$1),Questions!$A:$E,5,FALSE),1,0) -> 1 | ... BW45: =IF(AL45=VLOOKUP(VALUE(AL$1),Questions!$A:$E,5,FALSE),1,0) -> 1 | BX45: =IF(Scores[[#This Row],[Final]]>=65,1,0) -> 1 | BY45: =IF(Scores[[#This Row],[Final]]>=IF(Scores[[#This Row],[IEP]],55,65),1,0) -> 1
A46: 45 | B46: 11 | C46: Antaky | D46: FALSE | E46: FALSE | F46: =SUM(Scores[[#This Row],[Q1]:[Q28]]) -> 19 | G46: =SUM(Scores[[#This Row],[29]]:Scores[[#This Row],[30]]) -> 5 | H46: =SUM(Scores[[#This Row],[31]:[36]]) -> 6 | I46: =Scores[[#This Row],[37]] -> 2.5 | J46: =INDEX('Conversion Chart'!$C$3:$M$47,MATCH(SUM(Scores[[#This Row],[MC]:[IIIA]]),'Conversion Chart'!$B$3:$B$47),MATCH(Scores[[#This Row],[IIIB]],'Conversion Chart'!$C$2:$M$2)) -> 75 | K46: 4 | L46: 1 | M46: 3 | N46: 3 | O46: 1 | P46: 3 | Q46: 3 | R46: 1 | S46: 2 | T46: 1 | U46: 2 | V46: 4 | W46: 2 | X46: 4 | Y46: 3 | Z46: 1 | AA46: 2 | AB46: 3 | AC46: 1 | AD46: 1 | AE46: 3 | AF46: 2 | AG46: 3 | AH46: 2 | AI46: 1 | AJ46: 4 | AK46: 1 | AL46: 3 | AM46: 3 | AN46: 2 | AO46: 1 | AP46: 1 | AQ46: 1 | AR46: 1 | AS46: 1 | AT46: 1 | AU46: 2.5 | AV46: =IF(K46=VLOOKUP(VALUE(K$1),Questions!$A:$E,5,FALSE),1,0) -> 1 | AW46: =IF(L46=VLOOKUP(VALUE(L$1),Questions!$A:$E,5,FALSE),1,0) -> 0 | AX46: =IF(M46=VLOOKUP(VALUE(M$1),Questions!$A:$E,5,FALSE),1,0) -> 1 | AY46: =IF(N46=VLOOKUP(VALUE(N$1),Questions!$A:$E,5,FALSE),1,0) -> 1 | AZ46: =IF(O46=VLOOKUP(VALUE(O$1),Questions!$A:$E,5,FALSE),1,0) -> 1 | BA46: =IF(P46=VLOOKUP(VALUE(P$1),Questions!$A:$E,5,FALSE),1,0) -> 0 | BB46: =IF(Q46=VLOOKUP(VALUE(Q$1),Questions!$A:$E,5,FALSE),1,0) -> 1 | BC46: =IF(R46=VLOOKUP(VALUE(R$1),Questions!$A:$E,5,FALSE),1,0) -> 0 | ... BW46: =IF(AL46=VLOOKUP(VALUE(AL$1),Questions!$A:$E,5,FALSE),1,0) -> 1 | BX46: =IF(Scores[[#This Row],[Final]]>=65,1,0) -> 1 | BY46: =IF(Scores[[#This Row],[Final]]>=IF(Scores[[#This Row],[IEP]],55,65),1,0) -> 1
A47: 46 | B47: 9 | C47: Kovelsky | D47: FALSE | E47: FALSE | F47: =SUM(Scores[[#This Row],[Q1]:[Q28]]) -> 15 | G47: =SUM(Scores[[#This Row],[29]]:Scores[[#This Row],[30]]) -> 3 | H47: =SUM(Scores[[#This Row],[31]:[36]]) -> 5 | I47: =Scores[[#This Row],[37]] -> 2.5 | J47: =INDEX('Conversion Chart'!$C$3:$M$47,MATCH(SUM(Scores[[#This Row],[MC]:[IIIA]]),'Conversion Chart'!$B$3:$B$47),MATCH(Scores[[#This Row],[IIIB]],'Conversion Chart'!$C$2:$M$2)) -> 67 | K47: 4 | L47: 1 | M47: 1 | N47: 1 | O47: 1 | P47: 3 | Q47: 4 | R47: 2 | S47: 4 | T47: 1 | U47: 2 | V47: 4 | W47: 1 | X47: 4 | Y47: 1 | Z47: 4 | AA47: 1 | AB47: 3 | AC47: 3 | AD47: 4 | AE47: 2 | AF47: 2 | AG47: 4 | AH47: 4 | AI47: 3 | AJ47: 4 | AK47: 1 | AL47: 3 | AM47: 2 | AN47: 1 | AO47: 1 | AP47: 1 | AQ47: 1 | AR47: 1 | AS47: 1 | AT47: 0 | AU47: 2.5 | AV47: =IF(K47=VLOOKUP(VALUE(K$1),Questions!$A:$E,5,FALSE),1,0) -> 1 | AW47: =IF(L47=VLOOKUP(VALUE(L$1),Questions!$A:$E,5,FALSE),1,0) -> 0 | AX47: =IF(M47=VLOOKUP(VALUE(M$1),Questions!$A:$E,5,FALSE),1,0) -> 0 | AY47: =IF(N47=VLOOKUP(VALUE(N$1),Questions!$A:$E,5,FALSE),1,0) -> 0 | AZ47: =IF(O47=VLOOKUP(VALUE(O$1),Questions!$A:$E,5,FALSE),1,0) -> 1 | BA47: =IF(P47=VLOOKUP(VALUE(P$1),Questions!$A:$E,5,FALSE),1,0) -> 0 | BB47: =IF(Q47=VLOOKUP(VALUE(Q$1),Questions!$A:$E,5,FALSE),1,0) -> 0 | BC47: =IF(R47=VLOOKUP(VALUE(R$1),Questions!$A:$E,5,FALSE),1,0) -> 1 | ... BW47: =IF(AL47=VLOOKUP(VALUE(AL$1),Questions!$A:$E,5,FALSE),1,0) -> 1 | BX47: =IF(Scores[[#This Row],[Final]]>=65,1,0) -> 1 | BY47: =IF(Scores[[#This Row],[Final]]>=IF(Scores[[#This Row],[IEP]],55,65),1,0) -> 1
A48: 47 | B48: 9 | C48: Bermejo | D48: FALSE | E48: FALSE | F48: =SUM(Scores[[#This Row],[Q1]:[Q28]]) -> 19 | G48: =SUM(Scores[[#This Row],[29]]:Scores[[#This Row],[30]]) -> 5 | H48: =SUM(Scores[[#This Row],[31]:[36]]) -> 6 | I48: =Scores[[#This Row],[37]] -> 2 | J48: =INDEX('Conversion Chart'!$C$3:$M$47,MATCH(SUM(Scores[[#This Row],[MC]:[IIIA]]),'Conversion Chart'!$B$3:$B$47),MATCH(Scores[[#This Row],[IIIB]],'Conversion Chart'!$C$2:$M$2)) -> 73 | K48: 3 | L48: 2 | M48: 4 | N48: 3 | O48: 1 | P48: 4 | Q48: 3 | R48: 3 | S48: 2 | T48: 1 | U48: 2 | V48: 4 | W48: 2 | X48: 4 | Y48: 3 | Z48: 4 | AA48: 1 | AB48: 4 | AC48: 1 | AD48: 4 | AE48: 2 | AF48: 1 | AG48: 3 | AH48: 1 | AI48: 4 | AJ48: 4 | AK48: 4 | AL48: 3 | AM48: 3 | AN48: 2 | AO48: 1 | AP48: 1 | AQ48: 1 | AR48: 1 | AS48: 1 | AT48: 1 | AU48: 2 | AV48: =IF(K48=VLOOKUP(VALUE(K$1),Questions!$A:$E,5,FALSE),1,0) -> 0 | AW48: =IF(L48=VLOOKUP(VALUE(L$1),Questions!$A:$E,5,FALSE),1,0) -> 1 | AX48: =IF(M48=VLOOKUP(VALUE(M$1),Questions!$A:$E,5,FALSE),1,0) -> 0 | AY48: =IF(N48=VLOOKUP(VALUE(N$1),Questions!$A:$E,5,FALSE),1,0) -> 1 | AZ48: =IF(O48=VLOOKUP(VALUE(O$1),Questions!$A:$E,5,FALSE),1,0) -> 1 | BA48: =IF(P48=VLOOKUP(VALUE(P$1),Questions!$A:$E,5,FALSE),1,0) -> 1 | BB48: =IF(Q48=VLOOKUP(VALUE(Q$1),Questions!$A:$E,5,FALSE),1,0) -> 1 | BC48: =IF(R48=VLOOKUP(VALUE(R$1),Questions!$A:$E,5,FALSE),1,0) -> 0 | ... BW48: =IF(AL48=VLOOKUP(VALUE(AL$1),Questions!$A:$E,5,FALSE),1,0) -> 1 | BX48: =IF(Scores[[#This Row],[Final]]>=65,1,0) -> 1 | BY48: =IF(Scores[[#This Row],[Final]]>=IF(Scores[[#This Row],[IEP]],55,65),1,0) -> 1
A49: 48 | B49: 9 | C49: Bermejo | D49: FALSE | E49: FALSE | F49: =SUM(Scores[[#This Row],[Q1]:[Q28]]) -> 23 | G49: =SUM(Scores[[#This Row],[29]]:Scores[[#This Row],[30]]) -> 3 | H49: =SUM(Scores[[#This Row],[31]:[36]]) -> 6 | I49: =Scores[[#This Row],[37]] -> 1 | J49: =INDEX('Conversion Chart'!$C$3:$M$47,MATCH(SUM(Scores[[#This Row],[MC]:[IIIA]]),'Conversion Chart'!$B$3:$B$47),MATCH(Scores[[#This Row],[IIIB]],'Conversion Chart'!$C$2:$M$2)) -> 72 | K49: 4 | L49: 2 | M49: 3 | N49: 3 | O49: 1 | P49: 2 | Q49: 3 | R49: 2 | S49: 4 | T49: 1 | U49: 2 | V49: 4 | W49: 2 | X49: 4 | Y49: 3 | Z49: 1 | AA49: 1 | AB49: 3 | AC49: 3 | AD49: 4 | AE49: 3 | AF49: 2 | AG49: 3 | AH49: 3 | AI49: 1 | AJ49: 4 | AK49: 2 | AL49: 3 | AM49: 2 | AN49: 1 | AO49: 1 | AP49: 1 | AQ49: 1 | AR49: 1 | AS49: 1 | AT49: 1 | AU49: 1 | AV49: =IF(K49=VLOOKUP(VALUE(K$1),Questions!$A:$E,5,FALSE),1,0) -> 1 | AW49: =IF(L49=VLOOKUP(VALUE(L$1),Questions!$A:$E,5,FALSE),1,0) -> 1 | AX49: =IF(M49=VLOOKUP(VALUE(M$1),Questions!$A:$E,5,FALSE),1,0) -> 1 | AY49: =IF(N49=VLOOKUP(VALUE(N$1),Questions!$A:$E,5,FALSE),1,0) -> 1 | AZ49: =IF(O49=VLOOKUP(VALUE(O$1),Questions!$A:$E,5,FALSE),1,0) -> 1 | BA49: =IF(P49=VLOOKUP(VALUE(P$1),Questions!$A:$E,5,FALSE),1,0) -> 0 | BB49: =IF(Q49=VLOOKUP(VALUE(Q$1),Questions!$A:$E,5,FALSE),1,0) -> 1 | BC49: =IF(R49=VLOOKUP(VALUE(R$1),Questions!$A:$E,5,FALSE),1,0) -> 1 | ... BW49: =IF(AL49=VLOOKUP(VALUE(AL$1),Questions!$A:$E,5,FALSE),1,0) -> 1 | BX49: =IF(Scores[[#This Row],[Final]]>=65,1,0) -> 1 | BY49: =IF(Scores[[#This Row],[Final]]>=IF(Scores[[#This Row],[IEP]],55,65),1,0) -> 1
... A56: 55 | B56: 9 | C56: Bermejo | D56: FALSE | E56: FALSE | F56: =SUM(Scores[[#This Row],[Q1]:[Q28]]) -> 12 | G56: =SUM(Scores[[#This Row],[29]]:Scores[[#This Row],[30]]) -> 2 | H56: =SUM(Scores[[#This Row],[31]:[36]]) -> 6 | I56: =Scores[[#This Row],[37]] -> 1 | J56: =INDEX('Conversion Chart'!$C$3:$M$47,MATCH(SUM(Scores[[#This Row],[MC]:[IIIA]]),'Conversion Chart'!$B$3:$B$47),MATCH(Scores[[#This Row],[IIIB]],'Conversion Chart'!$C$2:$M$2)) -> 57 | K56: 4 | L56: 2 | M56: 2 | N56: 4 | O56: 1 | P56: 3 | Q56: 2 | R56: 4 | S56: 2 | T56: 4 | U56: 2 | V56: 4 | W56: 2 | X56: 4 | Y56: 1 | Z56: 3 | AA56: 4 | AB56: 1 | AC56: 3 | AD56: 4 | AE56: 1 | AF56: 2 | AG56: 3 | AH56: 4 | AI56: 3 | AJ56: 1 | AK56: 2 | AL56: 1 | AM56: 2 | AN56: 0 | AO56: 1 | AP56: 1 | AQ56: 1 | AR56: 1 | AS56: 1 | AT56: 1 | AU56: 1 | AV56: =IF(K56=VLOOKUP(VALUE(K$1),Questions!$A:$E,5,FALSE),1,0) -> 1 | AW56: =IF(L56=VLOOKUP(VALUE(L$1),Questions!$A:$E,5,FALSE),1,0) -> 1 | AX56: =IF(M56=VLOOKUP(VALUE(M$1),Questions!$A:$E,5,FALSE),1,0) -> 0 | AY56: =IF(N56=VLOOKUP(VALUE(N$1),Questions!$A:$E,5,FALSE),1,0) -> 0 | AZ56: =IF(O56=VLOOKUP(VALUE(O$1),Questions!$A:$E,5,FALSE),1,0) -> 1 | BA56: =IF(P56=VLOOKUP(VALUE(P$1),Questions!$A:$E,5,FALSE),1,0) -> 0 | BB56: =IF(Q56=VLOOKUP(VALUE(Q$1),Questions!$A:$E,5,FALSE),1,0) -> 0 | BC56: =IF(R56=VLOOKUP(VALUE(R$1),Questions!$A:$E,5,FALSE),1,0) -> 0 | ... BW56: =IF(AL56=VLOOKUP(VALUE(AL$1),Questions!$A:$E,5,FALSE),1,0) -> 0 | BX56: =IF(Scores[[#This Row],[Final]]>=65,1,0) -> 0 | BY56: =IF(Scores[[#This Row],[Final]]>=IF(Scores[[#This Row],[IEP]],55,65),1,0) -> 0
A57: 56 | B57: 9 | C57: Bermejo | D57: FALSE | E57: FALSE | F57: =SUM(Scores[[#This Row],[Q1]:[Q28]]) -> 0 | G57: =SUM(Scores[[#This Row],[29]]:Scores[[#This Row],[30]]) -> 0 | H57: =SUM(Scores[[#This Row],[31]:[36]]) -> 0 | I57: =Scores[[#This Row],[37]] -> 0 | J57: =INDEX('Conversion Chart'!$C$3:$M$47,MATCH(SUM(Scores[[#This Row],[MC]:[IIIA]]),'Conversion Chart'!$B$3:$B$47),MATCH(Scores[[#This Row],[IIIB]],'Conversion Chart'!$C$2:$M$2)) -> 0 | AV57: =IF(K57=VLOOKUP(VALUE(K$1),Questions!$A:$E,5,FALSE),1,0) -> 0 | AW57: =IF(L57=VLOOKUP(VALUE(L$1),Questions!$A:$E,5,FALSE),1,0) -> 0 | AX57: =IF(M57=VLOOKUP(VALUE(M$1),Questions!$A:$E,5,FALSE),1,0) -> 0 | AY57: =IF(N57=VLOOKUP(VALUE(N$1),Questions!$A:$E,5,FALSE),1,0) -> 0 | AZ57: =IF(O57=VLOOKUP(VALUE(O$1),Questions!$A:$E,5,FALSE),1,0) -> 0 | BA57: =IF(P57=VLOOKUP(VALUE(P$1),Questions!$A:$E,5,FALSE),1,0) -> 0 | BB57: =IF(Q57=VLOOKUP(VALUE(Q$1),Questions!$A:$E,5,FALSE),1,0) -> 0 | BC57: =IF(R57=VLOOKUP(VALUE(R$1),Questions!$A:$E,5,FALSE),1,0) -> 0 | ... BW57: =IF(AL57=VLOOKUP(VALUE(AL$1),Questions!$A:$E,5,FALSE),1,0) -> 0 | BX57: =IF(Scores[[#This Row],[Final]]>=65,1,0) -> 0 | BY57: =IF(Scores[[#This Row],[Final]]>=IF(Scores[[#This Row],[IEP]],55,65),1,0) -> 0
A58: 57 | B58: 9 | C58: Bermejo | D58: FALSE | E58: FALSE | F58: =SUM(Scores[[#This Row],[Q1]:[Q28]]) -> 19 | G58: =SUM(Scores[[#This Row],[29]]:Scores[[#This Row],[30]]) -> 3 | H58: =SUM(Scores[[#This Row],[31]:[36]]) -> 6 | I58: =Scores[[#This Row],[37]] -> 2.5 | J58: =INDEX('Conversion Chart'!$C$3:$M$47,MATCH(SUM(Scores[[#This Row],[MC]:[IIIA]]),'Conversion Chart'!$B$3:$B$47),MATCH(Scores[[#This Row],[IIIB]],'Conversion Chart'!$C$2:$M$2)) -> 73 | K58: 3 | L58: 2 | M58: 1 | N58: 2 | O58: 1 | P58: 4 | Q58: 3 | R58: 2 | S58: 2 | T58: 1 | U58: 2 | V58: 2 | W58: 2 | X58: 4 | Y58: 3 | Z58: 4 | AA58: 1 | AB58: 4 | AC58: 3 | AD58: 1 | AE58: 2 | AF58: 4 | AG58: 3 | AH58: 3 | AI58: 4 | AJ58: 4 | AK58: 4 | AL58: 3 | AM58: 2 | AN58: 1 | AO58: 1 | AP58: 1 | AQ58: 1 | AR58: 1 | AS58: 1 | AT58: 1 | AU58: 2.5 | AV58: =IF(K58=VLOOKUP(VALUE(K$1),Questions!$A:$E,5,FALSE),1,0) -> 0 | AW58: =IF(L58=VLOOKUP(VALUE(L$1),Questions!$A:$E,5,FALSE),1,0) -> 1 | AX58: =IF(M58=VLOOKUP(VALUE(M$1),Questions!$A:$E,5,FALSE),1,0) -> 0 | AY58: =IF(N58=VLOOKUP(VALUE(N$1),Questions!$A:$E,5,FALSE),1,0) -> 0 | AZ58: =IF(O58=VLOOKUP(VALUE(O$1),Questions!$A:$E,5,FALSE),1,0) -> 1 | BA58: =IF(P58=VLOOKUP(VALUE(P$1),Questions!$A:$E,5,FALSE),1,0) -> 1 | BB58: =IF(Q58=VLOOKUP(VALUE(Q$1),Questions!$A:$E,5,FALSE),1,0) -> 1 | BC58: =IF(R58=VLOOKUP(VALUE(R$1),Questions!$A:$E,5,FALSE),1,0) -> 1 | ... BW58: =IF(AL58=VLOOKUP(VALUE(AL$1),Questions!$A:$E,5,FALSE),1,0) -> 1 | BX58: =IF(Scores[[#This Row],[Final]]>=65,1,0) -> 1 | BY58: =IF(Scores[[#This Row],[Final]]>=IF(Scores[[#This Row],[IEP]],55,65),1,0) -> 1
A59: 58 | B59: 9 | C59: Bermejo | D59: FALSE | E59: FALSE | F59: =SUM(Scores[[#This Row],[Q1]:[Q28]]) -> 0 | G59: =SUM(Scores[[#This Row],[29]]:Scores[[#This Row],[30]]) -> 0 | H59: =SUM(Scores[[#This Row],[31]:[36]]) -> 0 | I59: =Scores[[#This Row],[37]] -> 0 | J59: =INDEX('Conversion Chart'!$C$3:$M$47,MATCH(SUM(Scores[[#This Row],[MC]:[IIIA]]),'Conversion Chart'!$B$3:$B$47),MATCH(Scores[[#This Row],[IIIB]],'Conversion Chart'!$C$2:$M$2)) -> 0 | AV59: =IF(K59=VLOOKUP(VALUE(K$1),Questions!$A:$E,5,FALSE),1,0) -> 0 | AW59: =IF(L59=VLOOKUP(VALUE(L$1),Questions!$A:$E,5,FALSE),1,0) -> 0 | AX59: =IF(M59=VLOOKUP(VALUE(M$1),Questions!$A:$E,5,FALSE),1,0) -> 0 | AY59: =IF(N59=VLOOKUP(VALUE(N$1),Questions!$A:$E,5,FALSE),1,0) -> 0 | AZ59: =IF(O59=VLOOKUP(VALUE(O$1),Questions!$A:$E,5,FALSE),1,0) -> 0 | BA59: =IF(P59=VLOOKUP(VALUE(P$1),Questions!$A:$E,5,FALSE),1,0) -> 0 | BB59: =IF(Q59=VLOOKUP(VALUE(Q$1),Questions!$A:$E,5,FALSE),1,0) -> 0 | BC59: =IF(R59=VLOOKUP(VALUE(R$1),Questions!$A:$E,5,FALSE),1,0) -> 0 | ... BW59: =IF(AL59=VLOOKUP(VALUE(AL$1),Questions!$A:$E,5,FALSE),1,0) -> 0 | BX59: =IF(Scores[[#This Row],[Final]]>=65,1,0) -> 0 | BY59: =IF(Scores[[#This Row],[Final]]>=IF(Scores[[#This Row],[IEP]],55,65),1,0) -> 0
A60: 59 | B60: 9 | C60: Bermejo | D60: FALSE | E60: FALSE | F60: =SUM(Scores[[#This Row],[Q1]:[Q28]]) -> 0 | G60: =SUM(Scores[[#This Row],[29]]:Scores[[#This Row],[30]]) -> 0 | H60: =SUM(Scores[[#This Row],[31]:[36]]) -> 0 | I60: =Scores[[#This Row],[37]] -> 0 | J60: =INDEX('Conversion Chart'!$C$3:$M$47,MATCH(SUM(Scores[[#This Row],[MC]:[IIIA]]),'Conversion Chart'!$B$3:$B$47),MATCH(Scores[[#This Row],[IIIB]],'Conversion Chart'!$C$2:$M$2)) -> 0 | AV60: =IF(K60=VLOOKUP(VALUE(K$1),Questions!$A:$E,5,FALSE),1,0) -> 0 | AW60: =IF(L60=VLOOKUP(VALUE(L$1),Questions!$A:$E,5,FALSE),1,0) -> 0 | AX60: =IF(M60=VLOOKUP(VALUE(M$1),Questions!$A:$E,5,FALSE),1,0) -> 0 | AY60: =IF(N60=VLOOKUP(VALUE(N$1),Questions!$A:$E,5,FALSE),1,0) -> 0 | AZ60: =IF(O60=VLOOKUP(VALUE(O$1),Questions!$A:$E,5,FALSE),1,0) -> 0 | BA60: =IF(P60=VLOOKUP(VALUE(P$1),Questions!$A:$E,5,FALSE),1,0) -> 0 | BB60: =IF(Q60=VLOOKUP(VALUE(Q$1),Questions!$A:$E,5,FALSE),1,0) -> 0 | BC60: =IF(R60=VLOOKUP(VALUE(R$1),Questions!$A:$E,5,FALSE),1,0) -> 0 | ... BW60: =IF(AL60=VLOOKUP(VALUE(AL$1),Questions!$A:$E,5,FALSE),1,0) -> 0 | BX60: =IF(Scores[[#This Row],[Final]]>=65,1,0) -> 0 | BY60: =IF(Scores[[#This Row],[Final]]>=IF(Scores[[#This Row],[IEP]],55,65),1,0) -> 0
A61: 60 | B61: 11 | C61: Kovelsky | D61: FALSE | E61: FALSE | F61: =SUM(Scores[[#This Row],[Q1]:[Q28]]) -> 16 | G61: =SUM(Scores[[#This Row],[29]]:Scores[[#This Row],[30]]) -> 2 | H61: =SUM(Scores[[#This Row],[31]:[36]]) -> 5 | I61: =Scores[[#This Row],[37]] -> 2.5 | J61: =INDEX('Conversion Chart'!$C$3:$M$47,MATCH(SUM(Scores[[#This Row],[MC]:[IIIA]]),'Conversion Chart'!$B$3:$B$47),MATCH(Scores[[#This Row],[IIIB]],'Conversion Chart'!$C$2:$M$2)) -> 67 | K61: 3 | L61: 1 | M61: 4 | N61: 3 | O61: 1 | P61: 2 | Q61: 3 | R61: 2 | S61: 2 | T61: 1 | U61: 2 | V61: 3 | W61: 2 | X61: 4 | Y61: 1 | Z61: 1 | AA61: 2 | AB61: 4 | AC61: 3 | AD61: 1 | AE61: 4 | AF61: 4 | AG61: 3 | AH61: 3 | AI61: 3 | AJ61: 4 | AK61: 4 | AL61: 3 | AM61: 2 | AN61: 0 | AO61: 1 | AP61: 1 | AQ61: 0 | AR61: 1 | AS61: 1 | AT61: 1 | AU61: 2.5 | AV61: =IF(K61=VLOOKUP(VALUE(K$1),Questions!$A:$E,5,FALSE),1,0) -> 0 | AW61: =IF(L61=VLOOKUP(VALUE(L$1),Questions!$A:$E,5,FALSE),1,0) -> 0 | AX61: =IF(M61=VLOOKUP(VALUE(M$1),Questions!$A:$E,5,FALSE),1,0) -> 0 | AY61: =IF(N61=VLOOKUP(VALUE(N$1),Questions!$A:$E,5,FALSE),1,0) -> 1 | AZ61: =IF(O61=VLOOKUP(VALUE(O$1),Questions!$A:$E,5,FALSE),1,0) -> 1 | BA61: =IF(P61=VLOOKUP(VALUE(P$1),Questions!$A:$E,5,FALSE),1,0) -> 0 | BB61: =IF(Q61=VLOOKUP(VALUE(Q$1),Questions!$A:$E,5,FALSE),1,0) -> 1 | BC61: =IF(R61=VLOOKUP(VALUE(R$1),Questions!$A:$E,5,FALSE),1,0) -> 1 | ... BW61: =IF(AL61=VLOOKUP(VALUE(AL$1),Questions!$A:$E,5,FALSE),1,0) -> 1 | BX61: =IF(Scores[[#This Row],[Final]]>=65,1,0) -> 1 | BY61: =IF(Scores[[#This Row],[Final]]>=IF(Scores[[#This Row],[IEP]],55,65),1,0) -> 1
A62: 61 | B62: 11 | C62: Kovelsky | D62: FALSE | E62: FALSE | F62: =SUM(Scores[[#This Row],[Q1]:[Q28]]) -> 20 | G62: =SUM(Scores[[#This Row],[29]]:Scores[[#This Row],[30]]) -> 3 | H62: =SUM(Scores[[#This Row],[31]:[36]]) -> 2 | I62: =Scores[[#This Row],[37]] -> 0 | J62: =INDEX('Conversion Chart'!$C$3:$M$47,MATCH(SUM(Scores[[#This Row],[MC]:[IIIA]]),'Conversion Chart'!$B$3:$B$47),MATCH(Scores[[#This Row],[IIIB]],'Conversion Chart'!$C$2:$M$2)) -> 60 | K62: 4 | L62: 2 | M62: 3 | N62: 4 | O62: 1 | P62: 2 | Q62: 3 | R62: 3 | S62: 2 | T62: 1 | U62: 2 | V62: 4 | W62: 2 | X62: 4 | Y62: 3 | Z62: 1 | AA62: 1 | AB62: 2 | AC62: 2 | AD62: 4 | AE62: 2 | AF62: 2 | AG62: 3 | AH62: 2 | AI62: 1 | AJ62: 4 | AK62: 4 | AL62: 1 | AM62: 2 | AN62: 1 | AO62: 0 | AP62: 0 | AQ62: 1 | AR62: 1 | AS62: 0 | AT62: 0 | AU62: 0 | AV62: =IF(K62=VLOOKUP(VALUE(K$1),Questions!$A:$E,5,FALSE),1,0) -> 1 | AW62: =IF(L62=VLOOKUP(VALUE(L$1),Questions!$A:$E,5,FALSE),1,0) -> 1 | AX62: =IF(M62=VLOOKUP(VALUE(M$1),Questions!$A:$E,5,FALSE),1,0) -> 1 | AY62: =IF(N62=VLOOKUP(VALUE(N$1),Questions!$A:$E,5,FALSE),1,0) -> 0 | AZ62: =IF(O62=VLOOKUP(VALUE(O$1),Questions!$A:$E,5,FALSE),1,0) -> 1 | BA62: =IF(P62=VLOOKUP(VALUE(P$1),Questions!$A:$E,5,FALSE),1,0) -> 0 | BB62: =IF(Q62=VLOOKUP(VALUE(Q$1),Questions!$A:$E,5,FALSE),1,0) -> 1 | BC62: =IF(R62=VLOOKUP(VALUE(R$1),Questions!$A:$E,5,FALSE),1,0) -> 0 | ... BW62: =IF(AL62=VLOOKUP(VALUE(AL$1),Questions!$A:$E,5,FALSE),1,0) -> 0 | BX62: =IF(Scores[[#This Row],[Final]]>=65,1,0) -> 0 | BY62: =IF(Scores[[#This Row],[Final]]>=IF(Scores[[#This Row],[IEP]],55,65),1,0) -> 0
A63: 62 | B63: 11 | C63: Dushin | D63: FALSE | E63: TRUE | F63: =SUM(Scores[[#This Row],[Q1]:[Q28]]) -> 16 | G63: =SUM(Scores[[#This Row],[29]]:Scores[[#This Row],[30]]) -> 6 | H63: =SUM(Scores[[#This Row],[31]:[36]]) -> 6 | I63: =Scores[[#This Row],[37]] -> 4 | J63: =INDEX('Conversion Chart'!$C$3:$M$47,MATCH(SUM(Scores[[#This Row],[MC]:[IIIA]]),'Conversion Chart'!$B$3:$B$47),MATCH(Scores[[#This Row],[IIIB]],'Conversion Chart'!$C$2:$M$2)) -> 77 | K63: 4 | L63: 1 | M63: 3 | N63: 3 | O63: 1 | P63: 2 | Q63: 3 | R63: 3 | S63: 2 | T63: 1 | U63: 2 | V63: 3 | W63: 2 | X63: 2 | Y63: 4 | Z63: 1 | AA63: 3 | AB63: 1 | AC63: 3 | AD63: 3 | AE63: 2 | AF63: 4 | AG63: 3 | AH63: 3 | AI63: 1 | AJ63: 4 | AK63: 4 | AL63: 2 | AM63: 3 | AN63: 3 | AO63: 1 | AP63: 1 | AQ63: 1 | AR63: 1 | AS63: 1 | AT63: 1 | AU63: 4 | AV63: =IF(K63=VLOOKUP(VALUE(K$1),Questions!$A:$E,5,FALSE),1,0) -> 1 | AW63: =IF(L63=VLOOKUP(VALUE(L$1),Questions!$A:$E,5,FALSE),1,0) -> 0 | AX63: =IF(M63=VLOOKUP(VALUE(M$1),Questions!$A:$E,5,FALSE),1,0) -> 1 | AY63: =IF(N63=VLOOKUP(VALUE(N$1),Questions!$A:$E,5,FALSE),1,0) -> 1 | AZ63: =IF(O63=VLOOKUP(VALUE(O$1),Questions!$A:$E,5,FALSE),1,0) -> 1 | BA63: =IF(P63=VLOOKUP(VALUE(P$1),Questions!$A:$E,5,FALSE),1,0) -> 0 | BB63: =IF(Q63=VLOOKUP(VALUE(Q$1),Questions!$A:$E,5,FALSE),1,0) -> 1 | BC63: =IF(R63=VLOOKUP(VALUE(R$1),Questions!$A:$E,5,FALSE),1,0) -> 0 | ... BW63: =IF(AL63=VLOOKUP(VALUE(AL$1),Questions!$A:$E,5,FALSE),1,0) -> 0 | BX63: =IF(Scores[[#This Row],[Final]]>=65,1,0) -> 1 | BY63: =IF(Scores[[#This Row],[Final]]>=IF(Scores[[#This Row],[IEP]],55,65),1,0) -> 1
A64: 63 | B64: 9 | C64: Bermejo | D64: FALSE | E64: FALSE | F64: =SUM(Scores[[#This Row],[Q1]:[Q28]]) -> 16 | G64: =SUM(Scores[[#This Row],[29]]:Scores[[#This Row],[30]]) -> 2 | H64: =SUM(Scores[[#This Row],[31]:[36]]) -> 3 | I64: =Scores[[#This Row],[37]] -> 1 | J64: =INDEX('Conversion Chart'!$C$3:$M$47,MATCH(SUM(Scores[[#This Row],[MC]:[IIIA]]),'Conversion Chart'!$B$3:$B$47),MATCH(Scores[[#This Row],[IIIB]],'Conversion Chart'!$C$2:$M$2)) -> 58 | K64: 4 | L64: 2 | M64: 3 | N64: 3 | O64: 1 | P64: 2 | Q64: 3 | R64: 2 | S64: 2 | T64: 1 | U64: 2 | V64: 4 | W64: 2 | X64: 3 | Y64: 4 | Z64: 1 | AA64: 3 | AB64: 2 | AC64: 2 | AD64: 3 | AE64: 2 | AF64: 2 | AG64: 3 | AH64: 1 | AI64: 2 | AJ64: 3 | AK64: 2 | AL64: 4 | AM64: 1 | AN64: 1 | AO64: 0 | AP64: 0 | AQ64: 1 | AR64: 0 | AS64: 1 | AT64: 1 | AU64: 1 | AV64: =IF(K64=VLOOKUP(VALUE(K$1),Questions!$A:$E,5,FALSE),1,0) -> 1 | AW64: =IF(L64=VLOOKUP(VALUE(L$1),Questions!$A:$E,5,FALSE),1,0) -> 1 | AX64: =IF(M64=VLOOKUP(VALUE(M$1),Questions!$A:$E,5,FALSE),1,0) -> 1 | AY64: =IF(N64=VLOOKUP(VALUE(N$1),Questions!$A:$E,5,FALSE),1,0) -> 1 | AZ64: =IF(O64=VLOOKUP(VALUE(O$1),Questions!$A:$E,5,FALSE),1,0) -> 1 | BA64: =IF(P64=VLOOKUP(VALUE(P$1),Questions!$A:$E,5,FALSE),1,0) -> 0 | BB64: =IF(Q64=VLOOKUP(VALUE(Q$1),Questions!$A:$E,5,FALSE),1,0) -> 1 | BC64: =IF(R64=VLOOKUP(VALUE(R$1),Questions!$A:$E,5,FALSE),1,0) -> 1 | ... BW64: =IF(AL64=VLOOKUP(VALUE(AL$1),Questions!$A:$E,5,FALSE),1,0) -> 0 | BX64: =IF(Scores[[#This Row],[Final]]>=65,1,0) -> 0 | BY64: =IF(Scores[[#This Row],[Final]]>=IF(Scores[[#This Row],[IEP]],55,65),1,0) -> 0
A65: 64 | B65: 11 | C65: Dushin | D65: FALSE | E65: TRUE | F65: =SUM(Scores[[#This Row],[Q1]:[Q28]]) -> 11 | G65: =SUM(Scores[[#This Row],[29]]:Scores[[#This Row],[30]]) -> 4 | H65: =SUM(Scores[[#This Row],[31]:[36]]) -> 4 | I65: =Scores[[#This Row],[37]] -> 1.5 | J65: =INDEX('Conversion Chart'!$C$3:$M$47,MATCH(SUM(Scores[[#This Row],[MC]:[IIIA]]),'Conversion Chart'!$B$3:$B$47),MATCH(Scores[[#This Row],[IIIB]],'Conversion Chart'!$C$2:$M$2)) -> 58 | K65: 3 | L65: 2 | M65: 4 | N65: 2 | O65: 3 | P65: 4 | Q65: 3 | R65: 2 | S65: 1 | T65: 1 | U65: 2 | V65: 3 | W65: 4 | X65: 4 | Y65: 1 | Z65: 4 | AA65: 3 | AB65: 1 | AC65: 3 | AD65: 2 | AE65: 4 | AF65: 1 | AG65: 3 | AH65: 4 | AI65: 3 | AJ65: 4 | AK65: 4 | AL65: 3 | AM65: 3 | AN65: 1 | AO65: 0 | AP65: 1 | AQ65: 0 | AR65: 1 | AS65: 1 | AT65: 1 | AU65: 1.5 | AV65: =IF(K65=VLOOKUP(VALUE(K$1),Questions!$A:$E,5,FALSE),1,0) -> 0 | AW65: =IF(L65=VLOOKUP(VALUE(L$1),Questions!$A:$E,5,FALSE),1,0) -> 1 | AX65: =IF(M65=VLOOKUP(VALUE(M$1),Questions!$A:$E,5,FALSE),1,0) -> 0 | AY65: =IF(N65=VLOOKUP(VALUE(N$1),Questions!$A:$E,5,FALSE),1,0) -> 0 | AZ65: =IF(O65=VLOOKUP(VALUE(O$1),Questions!$A:$E,5,FALSE),1,0) -> 0 | BA65: =IF(P65=VLOOKUP(VALUE(P$1),Questions!$A:$E,5,FALSE),1,0) -> 1 | BB65: =IF(Q65=VLOOKUP(VALUE(Q$1),Questions!$A:$E,5,FALSE),1,0) -> 1 | BC65: =IF(R65=VLOOKUP(VALUE(R$1),Questions!$A:$E,5,FALSE),1,0) -> 1 | ... BW65: =IF(AL65=VLOOKUP(VALUE(AL$1),Questions!$A:$E,5,FALSE),1,0) -> 1 | BX65: =IF(Scores[[#This Row],[Final]]>=65,1,0) -> 0 | BY65: =IF(Scores[[#This Row],[Final]]>=IF(Scores[[#This Row],[IEP]],55,65),1,0) -> 1
A66: 65 | B66: 9 | C66: Bermejo | D66: FALSE | E66: TRUE | F66: =SUM(Scores[[#This Row],[Q1]:[Q28]]) -> 6 | G66: =SUM(Scores[[#This Row],[29]]:Scores[[#This Row],[30]]) -> 4 | H66: =SUM(Scores[[#This Row],[31]:[36]]) -> 5 | I66: =Scores[[#This Row],[37]] -> 1 | J66: =INDEX('Conversion Chart'!$C$3:$M$47,MATCH(SUM(Scores[[#This Row],[MC]:[IIIA]]),'Conversion Chart'!$B$3:$B$47),MATCH(Scores[[#This Row],[IIIB]],'Conversion Chart'!$C$2:$M$2)) -> 48 | K66: 2 | L66: 1 | M66: 3 | N66: 4 | O66: 4 | P66: 2 | Q66: 3 | R66: 2 | S66: 2 | T66: 3 | U66: 4 | V66: 3 | W66: 1 | X66: 4 | Y66: 4 | Z66: 4 | AA66: 3 | AB66: 2 | AC66: 3 | AD66: 1 | AE66: 3 | AF66: 1 | AG66: 2 | AH66: 2 | AI66: 3 | AJ66: 3 | AK66: 4 | AL66: 1 | AM66: 2 | AN66: 2 | AO66: 0 | AP66: 1 | AQ66: 1 | AR66: 1 | AS66: 1 | AT66: 1 | AU66: 1 | AV66: =IF(K66=VLOOKUP(VALUE(K$1),Questions!$A:$E,5,FALSE),1,0) -> 0 | AW66: =IF(L66=VLOOKUP(VALUE(L$1),Questions!$A:$E,5,FALSE),1,0) -> 0 | AX66: =IF(M66=VLOOKUP(VALUE(M$1),Questions!$A:$E,5,FALSE),1,0) -> 1 | AY66: =IF(N66=VLOOKUP(VALUE(N$1),Questions!$A:$E,5,FALSE),1,0) -> 0 | AZ66: =IF(O66=VLOOKUP(VALUE(O$1),Questions!$A:$E,5,FALSE),1,0) -> 0 | BA66: =IF(P66=VLOOKUP(VALUE(P$1),Questions!$A:$E,5,FALSE),1,0) -> 0 | BB66: =IF(Q66=VLOOKUP(VALUE(Q$1),Questions!$A:$E,5,FALSE),1,0) -> 1 | BC66: =IF(R66=VLOOKUP(VALUE(R$1),Questions!$A:$E,5,FALSE),1,0) -> 1 | ... BW66: =IF(AL66=VLOOKUP(VALUE(AL$1),Questions!$A:$E,5,FALSE),1,0) -> 0 | BX66: =IF(Scores[[#This Row],[Final]]>=65,1,0) -> 0 | BY66: =IF(Scores[[#This Row],[Final]]>=IF(Scores[[#This Row],[IEP]],55,65),1,0) -> 0
A67: 66 | B67: 11 | C67: Dushin | D67: FALSE | E67: TRUE | F67: =SUM(Scores[[#This Row],[Q1]:[Q28]]) -> 0 | G67: =SUM(Scores[[#This Row],[29]]:Scores[[#This Row],[30]]) -> 0 | H67: =SUM(Scores[[#This Row],[31]:[36]]) -> 0 | I67: =Scores[[#This Row],[37]] -> 0 | J67: =INDEX('Conversion Chart'!$C$3:$M$47,MATCH(SUM(Scores[[#This Row],[MC]:[IIIA]]),'Conversion Chart'!$B$3:$B$47),MATCH(Scores[[#This Row],[IIIB]],'Conversion Chart'!$C$2:$M$2)) -> 0 | AV67: =IF(K67=VLOOKUP(VALUE(K$1),Questions!$A:$E,5,FALSE),1,0) -> 0 | AW67: =IF(L67=VLOOKUP(VALUE(L$1),Questions!$A:$E,5,FALSE),1,0) -> 0 | AX67: =IF(M67=VLOOKUP(VALUE(M$1),Questions!$A:$E,5,FALSE),1,0) -> 0 | AY67: =IF(N67=VLOOKUP(VALUE(N$1),Questions!$A:$E,5,FALSE),1,0) -> 0 | AZ67: =IF(O67=VLOOKUP(VALUE(O$1),Questions!$A:$E,5,FALSE),1,0) -> 0 | BA67: =IF(P67=VLOOKUP(VALUE(P$1),Questions!$A:$E,5,FALSE),1,0) -> 0 | BB67: =IF(Q67=VLOOKUP(VALUE(Q$1),Questions!$A:$E,5,FALSE),1,0) -> 0 | BC67: =IF(R67=VLOOKUP(VALUE(R$1),Questions!$A:$E,5,FALSE),1,0) -> 0 | ... BW67: =IF(AL67=VLOOKUP(VALUE(AL$1),Questions!$A:$E,5,FALSE),1,0) -> 0 | BX67: =IF(Scores[[#This Row],[Final]]>=65,1,0) -> 0 | BY67: =IF(Scores[[#This Row],[Final]]>=IF(Scores[[#This Row],[IEP]],55,65),1,0) -> 0
A68: 67 | B68: 11 | C68: Dushin | D68: FALSE | E68: TRUE | F68: =SUM(Scores[[#This Row],[Q1]:[Q28]]) -> 0 | G68: =SUM(Scores[[#This Row],[29]]:Scores[[#This Row],[30]]) -> 0 | H68: =SUM(Scores[[#This Row],[31]:[36]]) -> 0 | I68: =Scores[[#This Row],[37]] -> 0 | J68: =INDEX('Conversion Chart'!$C$3:$M$47,MATCH(SUM(Scores[[#This Row],[MC]:[IIIA]]),'Conversion Chart'!$B$3:$B$47),MATCH(Scores[[#This Row],[IIIB]],'Conversion Chart'!$C$2:$M$2)) -> 0 | AV68: =IF(K68=VLOOKUP(VALUE(K$1),Questions!$A:$E,5,FALSE),1,0) -> 0 | AW68: =IF(L68=VLOOKUP(VALUE(L$1),Questions!$A:$E,5,FALSE),1,0) -> 0 | AX68: =IF(M68=VLOOKUP(VALUE(M$1),Questions!$A:$E,5,FALSE),1,0) -> 0 | AY68: =IF(N68=VLOOKUP(VALUE(N$1),Questions!$A:$E,5,FALSE),1,0) -> 0 | AZ68: =IF(O68=VLOOKUP(VALUE(O$1),Questions!$A:$E,5,FALSE),1,0) -> 0 | BA68: =IF(P68=VLOOKUP(VALUE(P$1),Questions!$A:$E,5,FALSE),1,0) -> 0 | BB68: =IF(Q68=VLOOKUP(VALUE(Q$1),Questions!$A:$E,5,FALSE),1,0) -> 0 | BC68: =IF(R68=VLOOKUP(VALUE(R$1),Questions!$A:$E,5,FALSE),1,0) -> 0 | ... BW68: =IF(AL68=VLOOKUP(VALUE(AL$1),Questions!$A:$E,5,FALSE),1,0) -> 0 | BX68: =IF(Scores[[#This Row],[Final]]>=65,1,0) -> 0 | BY68: =IF(Scores[[#This Row],[Final]]>=IF(Scores[[#This Row],[IEP]],55,65),1,0) -> 0
A69: 68 | B69: 11 | C69: Dushin | D69: FALSE | E69: FALSE | F69: =SUM(Scores[[#This Row],[Q1]:[Q28]]) -> 20 | G69: =SUM(Scores[[#This Row],[29]]:Scores[[#This Row],[30]]) -> 5 | H69: =SUM(Scores[[#This Row],[31]:[36]]) -> 4 | I69: =Scores[[#This Row],[37]] -> 2 | J69: =INDEX('Conversion Chart'!$C$3:$M$47,MATCH(SUM(Scores[[#This Row],[MC]:[IIIA]]),'Conversion Chart'!$B$3:$B$47),MATCH(Scores[[#This Row],[IIIB]],'Conversion Chart'!$C$2:$M$2)) -> 72 | K69: 4 | L69: 2 | M69: 3 | N69: 3 | O69: 1 | P69: 3 | Q69: 3 | R69: 1 | S69: 2 | T69: 1 | U69: 2 | V69: 4 | W69: 2 | X69: 4 | Y69: 1 | Z69: 1 | AA69: 1 | AB69: 4 | AC69: 3 | AD69: 3 | AE69: 4 | AF69: 3 | AG69: 3 | AH69: 2 | AI69: 4 | AJ69: 4 | AK69: 1 | AL69: 3 | AM69: 3 | AN69: 2 | AO69: 0 | AP69: 1 | AQ69: 1 | AR69: 0 | AS69: 1 | AT69: 1 | AU69: 2 | AV69: =IF(K69=VLOOKUP(VALUE(K$1),Questions!$A:$E,5,FALSE),1,0) -> 1 | AW69: =IF(L69=VLOOKUP(VALUE(L$1),Questions!$A:$E,5,FALSE),1,0) -> 1 | AX69: =IF(M69=VLOOKUP(VALUE(M$1),Questions!$A:$E,5,FALSE),1,0) -> 1 | AY69: =IF(N69=VLOOKUP(VALUE(N$1),Questions!$A:$E,5,FALSE),1,0) -> 1 | AZ69: =IF(O69=VLOOKUP(VALUE(O$1),Questions!$A:$E,5,FALSE),1,0) -> 1 | BA69: =IF(P69=VLOOKUP(VALUE(P$1),Questions!$A:$E,5,FALSE),1,0) -> 0 | BB69: =IF(Q69=VLOOKUP(VALUE(Q$1),Questions!$A:$E,5,FALSE),1,0) -> 1 | BC69: =IF(R69=VLOOKUP(VALUE(R$1),Questions!$A:$E,5,FALSE),1,0) -> 0 | ... BW69: =IF(AL69=VLOOKUP(VALUE(AL$1),Questions!$A:$E,5,FALSE),1,0) -> 1 | BX69: =IF(Scores[[#This Row],[Final]]>=65,1,0) -> 1 | BY69: =IF(Scores[[#This Row],[Final]]>=IF(Scores[[#This Row],[IEP]],55,65),1,0) -> 1
A70: 69 | B70: 9 | C70: Bermejo | D70: TRUE | E70: FALSE | F70: =SUM(Scores[[#This Row],[Q1]:[Q28]]) -> 12 | G70: =SUM(Scores[[#This Row],[29]]:Scores[[#This Row],[30]]) -> 6 | H70: =SUM(Scores[[#This Row],[31]:[36]]) -> 6 | I70: =Scores[[#This Row],[37]] -> 1.5 | J70: =INDEX('Conversion Chart'!$C$3:$M$47,MATCH(SUM(Scores[[#This Row],[MC]:[IIIA]]),'Conversion Chart'!$B$3:$B$47),MATCH(Scores[[#This Row],[IIIB]],'Conversion Chart'!$C$2:$M$2)) -> 65 | K70: 4 | L70: 1 | M70: 3 | N70: 1 | O70: 3 | P70: 4 | Q70: 4 | R70: 2 | S70: 3 | T70: 1 | U70: 1 | V70: 3 | W70: 2 | X70: 4 | Y70: 3 | Z70: 1 | AA70: 4 | AB70: 3 | AC70: 3 | AD70: 4 | AE70: 4 | AF70: 1 | AG70: 4 | AH70: 2 | AI70: 3 | AJ70: 2 | AK70: 4 | AL70: 3 | AM70: 3 | AN70: 3 | AO70: 1 | AP70: 1 | AQ70: 1 | AR70: 1 | AS70: 1 | AT70: 1 | AU70: 1.5 | AV70: =IF(K70=VLOOKUP(VALUE(K$1),Questions!$A:$E,5,FALSE),1,0) -> 1 | AW70: =IF(L70=VLOOKUP(VALUE(L$1),Questions!$A:$E,5,FALSE),1,0) -> 0 | AX70: =IF(M70=VLOOKUP(VALUE(M$1),Questions!$A:$E,5,FALSE),1,0) -> 1 | AY70: =IF(N70=VLOOKUP(VALUE(N$1),Questions!$A:$E,5,FALSE),1,0) -> 0 | AZ70: =IF(O70=VLOOKUP(VALUE(O$1),Questions!$A:$E,5,FALSE),1,0) -> 0 | BA70: =IF(P70=VLOOKUP(VALUE(P$1),Questions!$A:$E,5,FALSE),1,0) -> 1 | BB70: =IF(Q70=VLOOKUP(VALUE(Q$1),Questions!$A:$E,5,FALSE),1,0) -> 0 | BC70: =IF(R70=VLOOKUP(VALUE(R$1),Questions!$A:$E,5,FALSE),1,0) -> 1 | ... BW70: =IF(AL70=VLOOKUP(VALUE(AL$1),Questions!$A:$E,5,FALSE),1,0) -> 1 | BX70: =IF(Scores[[#This Row],[Final]]>=65,1,0) -> 1 | BY70: =IF(Scores[[#This Row],[Final]]>=IF(Scores[[#This Row],[IEP]],55,65),1,0) -> 1
A71: 70 | B71: 11 | C71: Kovelsky | D71: FALSE | E71: FALSE | F71: =SUM(Scores[[#This Row],[Q1]:[Q28]]) -> 25 | G71: =SUM(Scores[[#This Row],[29]]:Scores[[#This Row],[30]]) -> 3 | H71: =SUM(Scores[[#This Row],[31]:[36]]) -> 6 | I71: =Scores[[#This Row],[37]] -> 3 | J71: =INDEX('Conversion Chart'!$C$3:$M$47,MATCH(SUM(Scores[[#This Row],[MC]:[IIIA]]),'Conversion Chart'!$B$3:$B$47),MATCH(Scores[[#This Row],[IIIB]],'Conversion Chart'!$C$2:$M$2)) -> 80 | K71: 4 | L71: 2 | M71: 3 | N71: 2 | O71: 1 | P71: 4 | Q71: 3 | R71: 2 | S71: 2 | T71: 1 | U71: 2 | V71: 4 | W71: 2 | X71: 3 | Y71: 3 | Z71: 1 | AA71: 1 | AB71: 4 | AC71: 3 | AD71: 3 | AE71: 2 | AF71: 2 | AG71: 3 | AH71: 3 | AI71: 1 | AJ71: 4 | AK71: 1 | AL71: 3 | AM71: 2 | AN71: 1 | AO71: 1 | AP71: 1 | AQ71: 1 | AR71: 1 | AS71: 1 | AT71: 1 | AU71: 3 | AV71: =IF(K71=VLOOKUP(VALUE(K$1),Questions!$A:$E,5,FALSE),1,0) -> 1 | AW71: =IF(L71=VLOOKUP(VALUE(L$1),Questions!$A:$E,5,FALSE),1,0) -> 1 | AX71: =IF(M71=VLOOKUP(VALUE(M$1),Questions!$A:$E,5,FALSE),1,0) -> 1 | AY71: =IF(N71=VLOOKUP(VALUE(N$1),Questions!$A:$E,5,FALSE),1,0) -> 0 | AZ71: =IF(O71=VLOOKUP(VALUE(O$1),Questions!$A:$E,5,FALSE),1,0) -> 1 | BA71: =IF(P71=VLOOKUP(VALUE(P$1),Questions!$A:$E,5,FALSE),1,0) -> 1 | BB71: =IF(Q71=VLOOKUP(VALUE(Q$1),Questions!$A:$E,5,FALSE),1,0) -> 1 | BC71: =IF(R71=VLOOKUP(VALUE(R$1),Questions!$A:$E,5,FALSE),1,0) -> 1 | ... BW71: =IF(AL71=VLOOKUP(VALUE(AL$1),Questions!$A:$E,5,FALSE),1,0) -> 1 | BX71: =IF(Scores[[#This Row],[Final]]>=65,1,0) -> 1 | BY71: =IF(Scores[[#This Row],[Final]]>=IF(Scores[[#This Row],[IEP]],55,65),1,0) -> 1
A72: 71 | B72: 11 | C72: Dushin | D72: FALSE | E72: FALSE | F72: =SUM(Scores[[#This Row],[Q1]:[Q28]]) -> 0 | G72: =SUM(Scores[[#This Row],[29]]:Scores[[#This Row],[30]]) -> 0 | H72: =SUM(Scores[[#This Row],[31]:[36]]) -> 0 | I72: =Scores[[#This Row],[37]] -> 0 | J72: =INDEX('Conversion Chart'!$C$3:$M$47,MATCH(SUM(Scores[[#This Row],[MC]:[IIIA]]),'Conversion Chart'!$B$3:$B$47),MATCH(Scores[[#This Row],[IIIB]],'Conversion Chart'!$C$2:$M$2)) -> 0 | AV72: =IF(K72=VLOOKUP(VALUE(K$1),Questions!$A:$E,5,FALSE),1,0) -> 0 | AW72: =IF(L72=VLOOKUP(VALUE(L$1),Questions!$A:$E,5,FALSE),1,0) -> 0 | AX72: =IF(M72=VLOOKUP(VALUE(M$1),Questions!$A:$E,5,FALSE),1,0) -> 0 | AY72: =IF(N72=VLOOKUP(VALUE(N$1),Questions!$A:$E,5,FALSE),1,0) -> 0 | AZ72: =IF(O72=VLOOKUP(VALUE(O$1),Questions!$A:$E,5,FALSE),1,0) -> 0 | BA72: =IF(P72=VLOOKUP(VALUE(P$1),Questions!$A:$E,5,FALSE),1,0) -> 0 | BB72: =IF(Q72=VLOOKUP(VALUE(Q$1),Questions!$A:$E,5,FALSE),1,0) -> 0 | BC72: =IF(R72=VLOOKUP(VALUE(R$1),Questions!$A:$E,5,FALSE),1,0) -> 0 | ... BW72: =IF(AL72=VLOOKUP(VALUE(AL$1),Questions!$A:$E,5,FALSE),1,0) -> 0 | BX72: =IF(Scores[[#This Row],[Final]]>=65,1,0) -> 0 | BY72: =IF(Scores[[#This Row],[Final]]>=IF(Scores[[#This Row],[IEP]],55,65),1,0) -> 0
A73: 72 | B73: 11 | C73: Dushin | D73: FALSE | E73: FALSE | F73: =SUM(Scores[[#This Row],[Q1]:[Q28]]) -> 16 | G73: =SUM(Scores[[#This Row],[29]]:Scores[[#This Row],[30]]) -> 4 | H73: =SUM(Scores[[#This Row],[31]:[36]]) -> 4 | I73: =Scores[[#This Row],[37]] -> 1.5 | J73: =INDEX('Conversion Chart'!$C$3:$M$47,MATCH(SUM(Scores[[#This Row],[MC]:[IIIA]]),'Conversion Chart'!$B$3:$B$47),MATCH(Scores[[#This Row],[IIIB]],'Conversion Chart'!$C$2:$M$2)) -> 65 | K73: 4 | L73: 1 | M73: 3 | N73: 1 | O73: 1 | P73: 2 | Q73: 3 | R73: 2 | S73: 2 | T73: 1 | U73: 2 | V73: 4 | W73: 3 | X73: 4 | Y73: 4 | Z73: 1 | AA73: 3 | AB73: 2 | AC73: 3 | AD73: 1 | AE73: 3 | AF73: 2 | AG73: 3 | AH73: 2 | AI73: 4 | AJ73: 2 | AK73: 1 | AL73: 3 | AM73: 3 | AN73: 1 | AO73: 0 | AP73: 1 | AQ73: 1 | AR73: 0 | AS73: 1 | AT73: 1 | AU73: 1.5 | AV73: =IF(K73=VLOOKUP(VALUE(K$1),Questions!$A:$E,5,FALSE),1,0) -> 1 | AW73: =IF(L73=VLOOKUP(VALUE(L$1),Questions!$A:$E,5,FALSE),1,0) -> 0 | AX73: =IF(M73=VLOOKUP(VALUE(M$1),Questions!$A:$E,5,FALSE),1,0) -> 1 | AY73: =IF(N73=VLOOKUP(VALUE(N$1),Questions!$A:$E,5,FALSE),1,0) -> 0 | AZ73: =IF(O73=VLOOKUP(VALUE(O$1),Questions!$A:$E,5,FALSE),1,0) -> 1 | BA73: =IF(P73=VLOOKUP(VALUE(P$1),Questions!$A:$E,5,FALSE),1,0) -> 0 | BB73: =IF(Q73=VLOOKUP(VALUE(Q$1),Questions!$A:$E,5,FALSE),1,0) -> 1 | BC73: =IF(R73=VLOOKUP(VALUE(R$1),Questions!$A:$E,5,FALSE),1,0) -> 1 | ... BW73: =IF(AL73=VLOOKUP(VALUE(AL$1),Questions!$A:$E,5,FALSE),1,0) -> 1 | BX73: =IF(Scores[[#This Row],[Final]]>=65,1,0) -> 1 | BY73: =IF(Scores[[#This Row],[Final]]>=IF(Scores[[#This Row],[IEP]],55,65),1,0) -> 1
A74: 73 | B74: 9 | C74: Bermejo | D74: FALSE | E74: TRUE | F74: =SUM(Scores[[#This Row],[Q1]:[Q28]]) -> 20 | G74: =SUM(Scores[[#This Row],[29]]:Scores[[#This Row],[30]]) -> 2 | H74: =SUM(Scores[[#This Row],[31]:[36]]) -> 4 | I74: =Scores[[#This Row],[37]] -> 1.5 | J74: =INDEX('Conversion Chart'!$C$3:$M$47,MATCH(SUM(Scores[[#This Row],[MC]:[IIIA]]),'Conversion Chart'!$B$3:$B$47),MATCH(Scores[[#This Row],[IIIB]],'Conversion Chart'!$C$2:$M$2)) -> 67 | K74: 4 | L74: 2 | M74: 2 | N74: 4 | O74: 1 | P74: 3 | Q74: 3 | R74: 2 | S74: 3 | T74: 1 | U74: 2 | V74: 3 | W74: 2 | X74: 4 | Y74: 3 | Z74: 1 | AA74: 1 | AB74: 4 | AC74: 3 | AD74: 4 | AE74: 2 | AF74: 2 | AG74: 3 | AH74: 2 | AI74: 4 | AJ74: 4 | AK74: 2 | AL74: 3 | AM74: 1 | AN74: 1 | AO74: 1 | AP74: 1 | AQ74: 1 | AR74: 0 | AS74: 1 | AT74: 0 | AU74: 1.5 | AV74: =IF(K74=VLOOKUP(VALUE(K$1),Questions!$A:$E,5,FALSE),1,0) -> 1 | AW74: =IF(L74=VLOOKUP(VALUE(L$1),Questions!$A:$E,5,FALSE),1,0) -> 1 | AX74: =IF(M74=VLOOKUP(VALUE(M$1),Questions!$A:$E,5,FALSE),1,0) -> 0 | AY74: =IF(N74=VLOOKUP(VALUE(N$1),Questions!$A:$E,5,FALSE),1,0) -> 0 | AZ74: =IF(O74=VLOOKUP(VALUE(O$1),Questions!$A:$E,5,FALSE),1,0) -> 1 | BA74: =IF(P74=VLOOKUP(VALUE(P$1),Questions!$A:$E,5,FALSE),1,0) -> 0 | BB74: =IF(Q74=VLOOKUP(VALUE(Q$1),Questions!$A:$E,5,FALSE),1,0) -> 1 | BC74: =IF(R74=VLOOKUP(VALUE(R$1),Questions!$A:$E,5,FALSE),1,0) -> 1 | ... BW74: =IF(AL74=VLOOKUP(VALUE(AL$1),Questions!$A:$E,5,FALSE),1,0) -> 1 | BX74: =IF(Scores[[#This Row],[Final]]>=65,1,0) -> 1 | BY74: =IF(Scores[[#This Row],[Final]]>=IF(Scores[[#This Row],[IEP]],55,65),1,0) -> 1
A75: 74 | B75: 11 | C75: Dushin | D75: FALSE | E75: TRUE | F75: =SUM(Scores[[#This Row],[Q1]:[Q28]]) -> 26 | G75: =SUM(Scores[[#This Row],[29]]:Scores[[#This Row],[30]]) -> 4 | H75: =SUM(Scores[[#This Row],[31]:[36]]) -> 6 | I75: =Scores[[#This Row],[37]] -> 3 | J75: =INDEX('Conversion Chart'!$C$3:$M$47,MATCH(SUM(Scores[[#This Row],[MC]:[IIIA]]),'Conversion Chart'!$B$3:$B$47),MATCH(Scores[[#This Row],[IIIB]],'Conversion Chart'!$C$2:$M$2)) -> 82 | K75: 4 | L75: 2 | M75: 3 | N75: 3 | O75: 1 | P75: 4 | Q75: 3 | R75: 2 | S75: 2 | T75: 1 | U75: 2 | V75: 3 | W75: 2 | X75: 4 | Y75: 3 | Z75: 1 | AA75: 1 | AB75: 4 | AC75: 3 | AD75: 4 | AE75: 2 | AF75: 2 | AG75: 3 | AH75: 2 | AI75: 1 | AJ75: 4 | AK75: 1 | AL75: 3 | AM75: 2 | AN75: 2 | AO75: 1 | AP75: 1 | AQ75: 1 | AR75: 1 | AS75: 1 | AT75: 1 | AU75: 3 | AV75: =IF(K75=VLOOKUP(VALUE(K$1),Questions!$A:$E,5,FALSE),1,0) -> 1 | AW75: =IF(L75=VLOOKUP(VALUE(L$1),Questions!$A:$E,5,FALSE),1,0) -> 1 | AX75: =IF(M75=VLOOKUP(VALUE(M$1),Questions!$A:$E,5,FALSE),1,0) -> 1 | AY75: =IF(N75=VLOOKUP(VALUE(N$1),Questions!$A:$E,5,FALSE),1,0) -> 1 | AZ75: =IF(O75=VLOOKUP(VALUE(O$1),Questions!$A:$E,5,FALSE),1,0) -> 1 | BA75: =IF(P75=VLOOKUP(VALUE(P$1),Questions!$A:$E,5,FALSE),1,0) -> 1 | BB75: =IF(Q75=VLOOKUP(VALUE(Q$1),Questions!$A:$E,5,FALSE),1,0) -> 1 | BC75: =IF(R75=VLOOKUP(VALUE(R$1),Questions!$A:$E,5,FALSE),1,0) -> 1 | ... BW75: =IF(AL75=VLOOKUP(VALUE(AL$1),Questions!$A:$E,5,FALSE),1,0) -> 1 | BX75: =IF(Scores[[#This Row],[Final]]>=65,1,0) -> 1 | BY75: =IF(Scores[[#This Row],[Final]]>=IF(Scores[[#This Row],[IEP]],55,65),1,0) -> 1
A76: 75 | B76: 9 | C76: Bermejo | D76: FALSE | E76: FALSE | F76: =SUM(Scores[[#This Row],[Q1]:[Q28]]) -> 17 | G76: =SUM(Scores[[#This Row],[29]]:Scores[[#This Row],[30]]) -> 3 | H76: =SUM(Scores[[#This Row],[31]:[36]]) -> 5 | I76: =Scores[[#This Row],[37]] -> 0 | J76: =INDEX('Conversion Chart'!$C$3:$M$47,MATCH(SUM(Scores[[#This Row],[MC]:[IIIA]]),'Conversion Chart'!$B$3:$B$47),MATCH(Scores[[#This Row],[IIIB]],'Conversion Chart'!$C$2:$M$2)) -> 60 | K76: 4 | L76: 2 | M76: 3 | N76: 1 | O76: 1 | P76: 4 | Q76: 3 | R76: 2 | S76: 2 | T76: 1 | U76: 2 | V76: 3 | W76: 1 | X76: 2 | Y76: 2 | Z76: 1 | AA76: 1 | AB76: 2 | AC76: 3 | AD76: 2 | AE76: 3 | AF76: 2 | AG76: 1 | AH76: 2 | AI76: 2 | AJ76: 4 | AK76: 1 | AL76: 3 | AM76: 2 | AN76: 1 | AO76: 1 | AP76: 1 | AQ76: 0 | AR76: 1 | AS76: 1 | AT76: 1 | AU76: 0 | AV76: =IF(K76=VLOOKUP(VALUE(K$1),Questions!$A:$E,5,FALSE),1,0) -> 1 | AW76: =IF(L76=VLOOKUP(VALUE(L$1),Questions!$A:$E,5,FALSE),1,0) -> 1 | AX76: =IF(M76=VLOOKUP(VALUE(M$1),Questions!$A:$E,5,FALSE),1,0) -> 1 | AY76: =IF(N76=VLOOKUP(VALUE(N$1),Questions!$A:$E,5,FALSE),1,0) -> 0 | AZ76: =IF(O76=VLOOKUP(VALUE(O$1),Questions!$A:$E,5,FALSE),1,0) -> 1 | BA76: =IF(P76=VLOOKUP(VALUE(P$1),Questions!$A:$E,5,FALSE),1,0) -> 1 | BB76: =IF(Q76=VLOOKUP(VALUE(Q$1),Questions!$A:$E,5,FALSE),1,0) -> 1 | BC76: =IF(R76=VLOOKUP(VALUE(R$1),Questions!$A:$E,5,FALSE),1,0) -> 1 | ... BW76: =IF(AL76=VLOOKUP(VALUE(AL$1),Questions!$A:$E,5,FALSE),1,0) -> 1 | BX76: =IF(Scores[[#This Row],[Final]]>=65,1,0) -> 0 | BY76: =IF(Scores[[#This Row],[Final]]>=IF(Scores[[#This Row],[IEP]],55,65),1,0) -> 0
A77: 76 | B77: 11 | C77: Kovelsky | D77: FALSE | E77: TRUE | F77: =SUM(Scores[[#This Row],[Q1]:[Q28]]) -> 17 | G77: =SUM(Scores[[#This Row],[29]]:Scores[[#This Row],[30]]) -> 3 | H77: =SUM(Scores[[#This Row],[31]:[36]]) -> 5 | I77: =Scores[[#This Row],[37]] -> 3 | J77: =INDEX('Conversion Chart'!$C$3:$M$47,MATCH(SUM(Scores[[#This Row],[MC]:[IIIA]]),'Conversion Chart'!$B$3:$B$47),MATCH(Scores[[#This Row],[IIIB]],'Conversion Chart'!$C$2:$M$2)) -> 71 | K77: 4 | L77: 1 | M77: 3 | N77: 2 | O77: 1 | P77: 2 | Q77: 3 | R77: 2 | S77: 2 | T77: 1 | U77: 2 | V77: 4 | W77: 2 | X77: 1 | Y77: 3 | Z77: 4 | AA77: 1 | AB77: 3 | AC77: 3 | AD77: 1 | AE77: 3 | AF77: 2 | AG77: 3 | AH77: 3 | AI77: 3 | AJ77: 4 | AK77: 4 | AL77: 4 | AM77: 2 | AN77: 1 | AO77: 1 | AP77: 1 | AQ77: 1 | AR77: 1 | AS77: 1 | AT77: 0 | AU77: 3 | AV77: =IF(K77=VLOOKUP(VALUE(K$1),Questions!$A:$E,5,FALSE),1,0) -> 1 | AW77: =IF(L77=VLOOKUP(VALUE(L$1),Questions!$A:$E,5,FALSE),1,0) -> 0 | AX77: =IF(M77=VLOOKUP(VALUE(M$1),Questions!$A:$E,5,FALSE),1,0) -> 1 | AY77: =IF(N77=VLOOKUP(VALUE(N$1),Questions!$A:$E,5,FALSE),1,0) -> 0 | AZ77: =IF(O77=VLOOKUP(VALUE(O$1),Questions!$A:$E,5,FALSE),1,0) -> 1 | BA77: =IF(P77=VLOOKUP(VALUE(P$1),Questions!$A:$E,5,FALSE),1,0) -> 0 | BB77: =IF(Q77=VLOOKUP(VALUE(Q$1),Questions!$A:$E,5,FALSE),1,0) -> 1 | BC77: =IF(R77=VLOOKUP(VALUE(R$1),Questions!$A:$E,5,FALSE),1,0) -> 1 | ... BW77: =IF(AL77=VLOOKUP(VALUE(AL$1),Questions!$A:$E,5,FALSE),1,0) -> 0 | BX77: =IF(Scores[[#This Row],[Final]]>=65,1,0) -> 1 | BY77: =IF(Scores[[#This Row],[Final]]>=IF(Scores[[#This Row],[IEP]],55,65),1,0) -> 1
A78: 77 | B78: 9 | C78: Bermejo | D78: FALSE | E78: FALSE | F78: =SUM(Scores[[#This Row],[Q1]:[Q28]]) -> 8 | G78: =SUM(Scores[[#This Row],[29]]:Scores[[#This Row],[30]]) -> 2 | H78: =SUM(Scores[[#This Row],[31]:[36]]) -> 6 | I78: =Scores[[#This Row],[37]] -> 1 | J78: =INDEX('Conversion Chart'!$C$3:$M$47,MATCH(SUM(Scores[[#This Row],[MC]:[IIIA]]),'Conversion Chart'!$B$3:$B$47),MATCH(Scores[[#This Row],[IIIB]],'Conversion Chart'!$C$2:$M$2)) -> 50 | K78: 4 | L78: 3 | M78: 4 | N78: 1 | O78: 3 | P78: 3 | Q78: 1 | R78: 2 | S78: 3 | T78: 1 | U78: 1 | V78: 3 | W78: 2 | X78: 4 | Y78: 2 | Z78: 4 | AA78: 2 | AB78: 2 | AC78: 3 | AD78: 1 | AE78: 2 | AF78: 3 | AG78: 4 | AH78: 2 | AI78: 3 | AJ78: 2 | AK78: 1 | AL78: 2 | AM78: 1 | AN78: 1 | AO78: 1 | AP78: 1 | AQ78: 1 | AR78: 1 | AS78: 1 | AT78: 1 | AU78: 1 | AV78: =IF(K78=VLOOKUP(VALUE(K$1),Questions!$A:$E,5,FALSE),1,0) -> 1 | AW78: =IF(L78=VLOOKUP(VALUE(L$1),Questions!$A:$E,5,FALSE),1,0) -> 0 | AX78: =IF(M78=VLOOKUP(VALUE(M$1),Questions!$A:$E,5,FALSE),1,0) -> 0 | AY78: =IF(N78=VLOOKUP(VALUE(N$1),Questions!$A:$E,5,FALSE),1,0) -> 0 | AZ78: =IF(O78=VLOOKUP(VALUE(O$1),Questions!$A:$E,5,FALSE),1,0) -> 0 | BA78: =IF(P78=VLOOKUP(VALUE(P$1),Questions!$A:$E,5,FALSE),1,0) -> 0 | BB78: =IF(Q78=VLOOKUP(VALUE(Q$1),Questions!$A:$E,5,FALSE),1,0) -> 0 | BC78: =IF(R78=VLOOKUP(VALUE(R$1),Questions!$A:$E,5,FALSE),1,0) -> 1 | ... BW78: =IF(AL78=VLOOKUP(VALUE(AL$1),Questions!$A:$E,5,FALSE),1,0) -> 0 | BX78: =IF(Scores[[#This Row],[Final]]>=65,1,0) -> 0 | BY78: =IF(Scores[[#This Row],[Final]]>=IF(Scores[[#This Row],[IEP]],55,65),1,0) -> 0
A79: 78 | B79: 9 | C79: Bermejo | D79: FALSE | E79: FALSE | F79: =SUM(Scores[[#This Row],[Q1]:[Q28]]) -> 19 | G79: =SUM(Scores[[#This Row],[29]]:Scores[[#This Row],[30]]) -> 2 | H79: =SUM(Scores[[#This Row],[31]:[36]]) -> 3 | I79: =Scores[[#This Row],[37]] -> 2 | J79: =INDEX('Conversion Chart'!$C$3:$M$47,MATCH(SUM(Scores[[#This Row],[MC]:[IIIA]]),'Conversion Chart'!$B$3:$B$47),MATCH(Scores[[#This Row],[IIIB]],'Conversion Chart'!$C$2:$M$2)) -> 67 | K79: 4 | L79: 1 | M79: 3 | N79: 1 | O79: 1 | P79: 3 | Q79: 2 | R79: 2 | S79: 2 | T79: 1 | U79: 2 | V79: 4 | W79: 2 | X79: 3 | Y79: 3 | Z79: 1 | AA79: 1 | AB79: 4 | AC79: 3 | AD79: 4 | AE79: 4 | AF79: 1 | AG79: 3 | AH79: 3 | AI79: 2 | AJ79: 4 | AK79: 2 | AL79: 3 | AM79: 1 | AN79: 1 | AO79: 0 | AP79: 1 | AQ79: 1 | AR79: 0 | AS79: 1 | AT79: 0 | AU79: 2 | AV79: =IF(K79=VLOOKUP(VALUE(K$1),Questions!$A:$E,5,FALSE),1,0) -> 1 | AW79: =IF(L79=VLOOKUP(VALUE(L$1),Questions!$A:$E,5,FALSE),1,0) -> 0 | AX79: =IF(M79=VLOOKUP(VALUE(M$1),Questions!$A:$E,5,FALSE),1,0) -> 1 | AY79: =IF(N79=VLOOKUP(VALUE(N$1),Questions!$A:$E,5,FALSE),1,0) -> 0 | AZ79: =IF(O79=VLOOKUP(VALUE(O$1),Questions!$A:$E,5,FALSE),1,0) -> 1 | BA79: =IF(P79=VLOOKUP(VALUE(P$1),Questions!$A:$E,5,FALSE),1,0) -> 0 | BB79: =IF(Q79=VLOOKUP(VALUE(Q$1),Questions!$A:$E,5,FALSE),1,0) -> 0 | BC79: =IF(R79=VLOOKUP(VALUE(R$1),Questions!$A:$E,5,FALSE),1,0) -> 1 | ... BW79: =IF(AL79=VLOOKUP(VALUE(AL$1),Questions!$A:$E,5,FALSE),1,0) -> 1 | BX79: =IF(Scores[[#This Row],[Final]]>=65,1,0) -> 1 | BY79: =IF(Scores[[#This Row],[Final]]>=IF(Scores[[#This Row],[IEP]],55,65),1,0) -> 1
A80: 79 | B80: 9 | C80: Bermejo | D80: FALSE | E80: FALSE | F80: =SUM(Scores[[#This Row],[Q1]:[Q28]]) -> 24 | G80: =SUM(Scores[[#This Row],[29]]:Scores[[#This Row],[30]]) -> 3 | H80: =SUM(Scores[[#This Row],[31]:[36]]) -> 5 | I80: =Scores[[#This Row],[37]] -> 3 | J80: =INDEX('Conversion Chart'!$C$3:$M$47,MATCH(SUM(Scores[[#This Row],[MC]:[IIIA]]),'Conversion Chart'!$B$3:$B$47),MATCH(Scores[[#This Row],[IIIB]],'Conversion Chart'!$C$2:$M$2)) -> 78 | K80: 4 | L80: 2 | M80: 3 | N80: 3 | O80: 1 | P80: 2 | Q80: 3 | R80: 2 | S80: 2 | T80: 1 | U80: 2 | V80: 4 | W80: 2 | X80: 4 | Y80: 3 | Z80: 1 | AA80: 1 | AB80: 3 | AC80: 3 | AD80: 4 | AE80: 2 | AF80: 2 | AG80: 3 | AH80: 2 | AI80: 1 | AJ80: 4 | AK80: 4 | AL80: 3 | AM80: 2 | AN80: 1 | AO80: 1 | AP80: 1 | AQ80: 1 | AR80: 1 | AS80: 1 | AT80: 0 | AU80: 3 | AV80: =IF(K80=VLOOKUP(VALUE(K$1),Questions!$A:$E,5,FALSE),1,0) -> 1 | AW80: =IF(L80=VLOOKUP(VALUE(L$1),Questions!$A:$E,5,FALSE),1,0) -> 1 | AX80: =IF(M80=VLOOKUP(VALUE(M$1),Questions!$A:$E,5,FALSE),1,0) -> 1 | AY80: =IF(N80=VLOOKUP(VALUE(N$1),Questions!$A:$E,5,FALSE),1,0) -> 1 | AZ80: =IF(O80=VLOOKUP(VALUE(O$1),Questions!$A:$E,5,FALSE),1,0) -> 1 | BA80: =IF(P80=VLOOKUP(VALUE(P$1),Questions!$A:$E,5,FALSE),1,0) -> 0 | BB80: =IF(Q80=VLOOKUP(VALUE(Q$1),Questions!$A:$E,5,FALSE),1,0) -> 1 | BC80: =IF(R80=VLOOKUP(VALUE(R$1),Questions!$A:$E,5,FALSE),1,0) -> 1 | ... BW80: =IF(AL80=VLOOKUP(VALUE(AL$1),Questions!$A:$E,5,FALSE),1,0) -> 1 | BX80: =IF(Scores[[#This Row],[Final]]>=65,1,0) -> 1 | BY80: =IF(Scores[[#This Row],[Final]]>=IF(Scores[[#This Row],[IEP]],55,65),1,0) -> 1
A81: 80 | B81: 11 | C81: Antaky | D81: FALSE | E81: FALSE | F81: =SUM(Scores[[#This Row],[Q1]:[Q28]]) -> 19 | G81: =SUM(Scores[[#This Row],[29]]:Scores[[#This Row],[30]]) -> 4 | H81: =SUM(Scores[[#This Row],[31]:[36]]) -> 6 | I81: =Scores[[#This Row],[37]] -> 2 | J81: =INDEX('Conversion Chart'!$C$3:$M$47,MATCH(SUM(Scores[[#This Row],[MC]:[IIIA]]),'Conversion Chart'!$B$3:$B$47),MATCH(Scores[[#This Row],[IIIB]],'Conversion Chart'!$C$2:$M$2)) -> 72 | K81: 4 | L81: 2 | M81: 2 | N81: 1 | O81: 1 | P81: 4 | Q81: 3 | R81: 2 | S81: 2 | T81: 2 | U81: 2 | V81: 3 | W81: 2 | X81: 4 | Y81: 4 | Z81: 4 | AA81: 1 | AB81: 4 | AC81: 3 | AD81: 2 | AE81: 2 | AF81: 2 | AG81: 3 | AH81: 2 | AI81: 3 | AJ81: 4 | AK81: 1 | AL81: 3 | AM81: 2 | AN81: 2 | AO81: 1 | AP81: 1 | AQ81: 1 | AR81: 1 | AS81: 1 | AT81: 1 | AU81: 2 | AV81: =IF(K81=VLOOKUP(VALUE(K$1),Questions!$A:$E,5,FALSE),1,0) -> 1 | AW81: =IF(L81=VLOOKUP(VALUE(L$1),Questions!$A:$E,5,FALSE),1,0) -> 1 | AX81: =IF(M81=VLOOKUP(VALUE(M$1),Questions!$A:$E,5,FALSE),1,0) -> 0 | AY81: =IF(N81=VLOOKUP(VALUE(N$1),Questions!$A:$E,5,FALSE),1,0) -> 0 | AZ81: =IF(O81=VLOOKUP(VALUE(O$1),Questions!$A:$E,5,FALSE),1,0) -> 1 | BA81: =IF(P81=VLOOKUP(VALUE(P$1),Questions!$A:$E,5,FALSE),1,0) -> 1 | BB81: =IF(Q81=VLOOKUP(VALUE(Q$1),Questions!$A:$E,5,FALSE),1,0) -> 1 | BC81: =IF(R81=VLOOKUP(VALUE(R$1),Questions!$A:$E,5,FALSE),1,0) -> 1 | ... BW81: =IF(AL81=VLOOKUP(VALUE(AL$1),Questions!$A:$E,5,FALSE),1,0) -> 1 | BX81: =IF(Scores[[#This Row],[Final]]>=65,1,0) -> 1 | BY81: =IF(Scores[[#This Row],[Final]]>=IF(Scores[[#This Row],[IEP]],55,65),1,0) -> 1
A82: 81 | B82: 9 | C82: Kovelsky | D82: FALSE | E82: FALSE | F82: =SUM(Scores[[#This Row],[Q1]:[Q28]]) -> 8 | G82: =SUM(Scores[[#This Row],[29]]:Scores[[#This Row],[30]]) -> 2 | H82: =SUM(Scores[[#This Row],[31]:[36]]) -> 6 | I82: =Scores[[#This Row],[37]] -> 2 | J82: =INDEX('Conversion Chart'!$C$3:$M$47,MATCH(SUM(Scores[[#This Row],[MC]:[IIIA]]),'Conversion Chart'!$B$3:$B$47),MATCH(Scores[[#This Row],[IIIB]],'Conversion Chart'!$C$2:$M$2)) -> 55 | K82: 4 | L82: 3 | M82: 3 | N82: 1 | O82: 1 | P82: 1 | Q82: 1 | R82: 3 | S82: 2 | T82: 1 | U82: 3 | V82: 3 | W82: 3 | X82: 1 | Y82: 2 | Z82: 4 | AA82: 3 | AB82: 3 | AC82: 1 | AD82: 2 | AE82: 1 | AF82: 2 | AG82: 1 | AH82: 2 | AI82: 1 | AJ82: 4 | AK82: 2 | AL82: 4 | AM82: 1 | AN82: 1 | AO82: 1 | AP82: 1 | AQ82: 1 | AR82: 1 | AS82: 1 | AT82: 1 | AU82: 2 | AV82: =IF(K82=VLOOKUP(VALUE(K$1),Questions!$A:$E,5,FALSE),1,0) -> 1 | AW82: =IF(L82=VLOOKUP(VALUE(L$1),Questions!$A:$E,5,FALSE),1,0) -> 0 | AX82: =IF(M82=VLOOKUP(VALUE(M$1),Questions!$A:$E,5,FALSE),1,0) -> 1 | AY82: =IF(N82=VLOOKUP(VALUE(N$1),Questions!$A:$E,5,FALSE),1,0) -> 0 | AZ82: =IF(O82=VLOOKUP(VALUE(O$1),Questions!$A:$E,5,FALSE),1,0) -> 1 | BA82: =IF(P82=VLOOKUP(VALUE(P$1),Questions!$A:$E,5,FALSE),1,0) -> 0 | BB82: =IF(Q82=VLOOKUP(VALUE(Q$1),Questions!$A:$E,5,FALSE),1,0) -> 0 | BC82: =IF(R82=VLOOKUP(VALUE(R$1),Questions!$A:$E,5,FALSE),1,0) -> 0 | ... BW82: =IF(AL82=VLOOKUP(VALUE(AL$1),Questions!$A:$E,5,FALSE),1,0) -> 0 | BX82: =IF(Scores[[#This Row],[Final]]>=65,1,0) -> 0 | BY82: =IF(Scores[[#This Row],[Final]]>=IF(Scores[[#This Row],[IEP]],55,65),1,0) -> 0
A83: 82 | B83: 11 | C83: Kovelsky | D83: FALSE | E83: FALSE | F83: =SUM(Scores[[#This Row],[Q1]:[Q28]]) -> 17 | G83: =SUM(Scores[[#This Row],[29]]:Scores[[#This Row],[30]]) -> 2 | H83: =SUM(Scores[[#This Row],[31]:[36]]) -> 5 | I83: =Scores[[#This Row],[37]] -> 2 | J83: =INDEX('Conversion Chart'!$C$3:$M$47,MATCH(SUM(Scores[[#This Row],[MC]:[IIIA]]),'Conversion Chart'!$B$3:$B$47),MATCH(Scores[[#This Row],[IIIB]],'Conversion Chart'!$C$2:$M$2)) -> 67 | K83: 4 | L83: 1 | M83: 3 | N83: 1 | O83: 1 | P83: 2 | Q83: 3 | R83: 2 | S83: 3 | T83: 1 | U83: 2 | V83: 4 | W83: 1 | X83: 4 | Y83: 3 | Z83: 2 | AA83: 1 | AB83: 4 | AC83: 3 | AD83: 3 | AE83: 3 | AF83: 2 | AG83: 3 | AH83: 2 | AI83: 1 | AJ83: 1 | AK83: 2 | AL83: 3 | AM83: 1 | AN83: 1 | AO83: 1 | AP83: 1 | AQ83: 1 | AR83: 1 | AS83: 1 | AT83: 0 | AU83: 2 | AV83: =IF(K83=VLOOKUP(VALUE(K$1),Questions!$A:$E,5,FALSE),1,0) -> 1 | AW83: =IF(L83=VLOOKUP(VALUE(L$1),Questions!$A:$E,5,FALSE),1,0) -> 0 | AX83: =IF(M83=VLOOKUP(VALUE(M$1),Questions!$A:$E,5,FALSE),1,0) -> 1 | AY83: =IF(N83=VLOOKUP(VALUE(N$1),Questions!$A:$E,5,FALSE),1,0) -> 0 | AZ83: =IF(O83=VLOOKUP(VALUE(O$1),Questions!$A:$E,5,FALSE),1,0) -> 1 | BA83: =IF(P83=VLOOKUP(VALUE(P$1),Questions!$A:$E,5,FALSE),1,0) -> 0 | BB83: =IF(Q83=VLOOKUP(VALUE(Q$1),Questions!$A:$E,5,FALSE),1,0) -> 1 | BC83: =IF(R83=VLOOKUP(VALUE(R$1),Questions!$A:$E,5,FALSE),1,0) -> 1 | ... BW83: =IF(AL83=VLOOKUP(VALUE(AL$1),Questions!$A:$E,5,FALSE),1,0) -> 1 | BX83: =IF(Scores[[#This Row],[Final]]>=65,1,0) -> 1 | BY83: =IF(Scores[[#This Row],[Final]]>=IF(Scores[[#This Row],[IEP]],55,65),1,0) -> 1
A84: 83 | B84: 9 | C84: Kovelsky | D84: FALSE | E84: FALSE | F84: =SUM(Scores[[#This Row],[Q1]:[Q28]]) -> 13 | G84: =SUM(Scores[[#This Row],[29]]:Scores[[#This Row],[30]]) -> 6 | H84: =SUM(Scores[[#This Row],[31]:[36]]) -> 5 | I84: =Scores[[#This Row],[37]] -> 1.5 | J84: =INDEX('Conversion Chart'!$C$3:$M$47,MATCH(SUM(Scores[[#This Row],[MC]:[IIIA]]),'Conversion Chart'!$B$3:$B$47),MATCH(Scores[[#This Row],[IIIB]],'Conversion Chart'!$C$2:$M$2)) -> 65 | K84: 4 | L84: 2 | M84: 1 | N84: 1 | O84: 1 | P84: 3 | Q84: 2 | R84: 4 | S84: 2 | T84: 1 | U84: 2 | V84: 4 | W84: 2 | X84: 3 | Y84: 3 | Z84: 4 | AA84: 2 | AB84: 2 | AC84: 2 | AD84: 1 | AE84: 1 | AF84: 2 | AG84: 3 | AH84: 4 | AI84: 4 | AJ84: 4 | AK84: 2 | AL84: 3 | AM84: 3 | AN84: 3 | AO84: 1 | AP84: 1 | AQ84: 0 | AR84: 1 | AS84: 1 | AT84: 1 | AU84: 1.5 | AV84: =IF(K84=VLOOKUP(VALUE(K$1),Questions!$A:$E,5,FALSE),1,0) -> 1 | AW84: =IF(L84=VLOOKUP(VALUE(L$1),Questions!$A:$E,5,FALSE),1,0) -> 1 | AX84: =IF(M84=VLOOKUP(VALUE(M$1),Questions!$A:$E,5,FALSE),1,0) -> 0 | AY84: =IF(N84=VLOOKUP(VALUE(N$1),Questions!$A:$E,5,FALSE),1,0) -> 0 | AZ84: =IF(O84=VLOOKUP(VALUE(O$1),Questions!$A:$E,5,FALSE),1,0) -> 1 | BA84: =IF(P84=VLOOKUP(VALUE(P$1),Questions!$A:$E,5,FALSE),1,0) -> 0 | BB84: =IF(Q84=VLOOKUP(VALUE(Q$1),Questions!$A:$E,5,FALSE),1,0) -> 0 | BC84: =IF(R84=VLOOKUP(VALUE(R$1),Questions!$A:$E,5,FALSE),1,0) -> 0 | ... BW84: =IF(AL84=VLOOKUP(VALUE(AL$1),Questions!$A:$E,5,FALSE),1,0) -> 1 | BX84: =IF(Scores[[#This Row],[Final]]>=65,1,0) -> 1 | BY84: =IF(Scores[[#This Row],[Final]]>=IF(Scores[[#This Row],[IEP]],55,65),1,0) -> 1
... A92: 91 | B92: 11 | C92: Antaky | D92: FALSE | E92: FALSE | F92: =SUM(Scores[[#This Row],[Q1]:[Q28]]) -> 15 | G92: =SUM(Scores[[#This Row],[29]]:Scores[[#This Row],[30]]) -> 5 | H92: =SUM(Scores[[#This Row],[31]:[36]]) -> 6 | I92: =Scores[[#This Row],[37]] -> 3 | J92: =INDEX('Conversion Chart'!$C$3:$M$47,MATCH(SUM(Scores[[#This Row],[MC]:[IIIA]]),'Conversion Chart'!$B$3:$B$47),MATCH(Scores[[#This Row],[IIIB]],'Conversion Chart'!$C$2:$M$2)) -> 72 | K92: 4 | L92: 2 | M92: 3 | N92: 3 | O92: 1 | P92: 1 | Q92: 3 | R92: 2 | S92: 3 | T92: 2 | U92: 2 | V92: 3 | W92: 1 | X92: 4 | Y92: 1 | Z92: 2 | AA92: 1 | AB92: 3 | AC92: 3 | AD92: 1 | AE92: 1 | AF92: 2 | AG92: 3 | AH92: 2 | AI92: 3 | AJ92: 4 | AK92: 4 | AL92: 3 | AM92: 3 | AN92: 2 | AO92: 1 | AP92: 1 | AQ92: 1 | AR92: 1 | AS92: 1 | AT92: 1 | AU92: 3 | AV92: =IF(K92=VLOOKUP(VALUE(K$1),Questions!$A:$E,5,FALSE),1,0) -> 1 | AW92: =IF(L92=VLOOKUP(VALUE(L$1),Questions!$A:$E,5,FALSE),1,0) -> 1 | AX92: =IF(M92=VLOOKUP(VALUE(M$1),Questions!$A:$E,5,FALSE),1,0) -> 1 | AY92: =IF(N92=VLOOKUP(VALUE(N$1),Questions!$A:$E,5,FALSE),1,0) -> 1 | AZ92: =IF(O92=VLOOKUP(VALUE(O$1),Questions!$A:$E,5,FALSE),1,0) -> 1 | BA92: =IF(P92=VLOOKUP(VALUE(P$1),Questions!$A:$E,5,FALSE),1,0) -> 0 | BB92: =IF(Q92=VLOOKUP(VALUE(Q$1),Questions!$A:$E,5,FALSE),1,0) -> 1 | BC92: =IF(R92=VLOOKUP(VALUE(R$1),Questions!$A:$E,5,FALSE),1,0) -> 1 | ... BW92: =IF(AL92=VLOOKUP(VALUE(AL$1),Questions!$A:$E,5,FALSE),1,0) -> 1 | BX92: =IF(Scores[[#This Row],[Final]]>=65,1,0) -> 1 | BY92: =IF(Scores[[#This Row],[Final]]>=IF(Scores[[#This Row],[IEP]],55,65),1,0) -> 1
A93: 92 | B93: 11 | C93: Dushin | D93: FALSE | E93: FALSE | F93: =SUM(Scores[[#This Row],[Q1]:[Q28]]) -> 0 | G93: =SUM(Scores[[#This Row],[29]]:Scores[[#This Row],[30]]) -> 0 | H93: =SUM(Scores[[#This Row],[31]:[36]]) -> 0 | I93: =Scores[[#This Row],[37]] -> 0 | J93: =INDEX('Conversion Chart'!$C$3:$M$47,MATCH(SUM(Scores[[#This Row],[MC]:[IIIA]]),'Conversion Chart'!$B$3:$B$47),MATCH(Scores[[#This Row],[IIIB]],'Conversion Chart'!$C$2:$M$2)) -> 0 | AV93: =IF(K93=VLOOKUP(VALUE(K$1),Questions!$A:$E,5,FALSE),1,0) -> 0 | AW93: =IF(L93=VLOOKUP(VALUE(L$1),Questions!$A:$E,5,FALSE),1,0) -> 0 | AX93: =IF(M93=VLOOKUP(VALUE(M$1),Questions!$A:$E,5,FALSE),1,0) -> 0 | AY93: =IF(N93=VLOOKUP(VALUE(N$1),Questions!$A:$E,5,FALSE),1,0) -> 0 | AZ93: =IF(O93=VLOOKUP(VALUE(O$1),Questions!$A:$E,5,FALSE),1,0) -> 0 | BA93: =IF(P93=VLOOKUP(VALUE(P$1),Questions!$A:$E,5,FALSE),1,0) -> 0 | BB93: =IF(Q93=VLOOKUP(VALUE(Q$1),Questions!$A:$E,5,FALSE),1,0) -> 0 | BC93: =IF(R93=VLOOKUP(VALUE(R$1),Questions!$A:$E,5,FALSE),1,0) -> 0 | ... BW93: =IF(AL93=VLOOKUP(VALUE(AL$1),Questions!$A:$E,5,FALSE),1,0) -> 0 | BX93: =IF(Scores[[#This Row],[Final]]>=65,1,0) -> 0 | BY93: =IF(Scores[[#This Row],[Final]]>=IF(Scores[[#This Row],[IEP]],55,65),1,0) -> 0
A94: 93 | B94: 11 | C94: Kovelsky | D94: FALSE | E94: FALSE | F94: =SUM(Scores[[#This Row],[Q1]:[Q28]]) -> 15 | G94: =SUM(Scores[[#This Row],[29]]:Scores[[#This Row],[30]]) -> 8 | H94: =SUM(Scores[[#This Row],[31]:[36]]) -> 6 | I94: =Scores[[#This Row],[37]] -> 4 | J94: =INDEX('Conversion Chart'!$C$3:$M$47,MATCH(SUM(Scores[[#This Row],[MC]:[IIIA]]),'Conversion Chart'!$B$3:$B$47),MATCH(Scores[[#This Row],[IIIB]],'Conversion Chart'!$C$2:$M$2)) -> 78 | K94: 4 | L94: 2 | M94: 1 | N94: 3 | O94: 1 | P94: 2 | Q94: 3 | R94: 4 | S94: 3 | T94: 1 | U94: 1 | V94: 4 | W94: 2 | X94: 3 | Y94: 3 | Z94: 4 | AA94: 1 | AB94: 3 | AC94: 1 | AD94: 1 | AE94: 2 | AF94: 2 | AG94: 3 | AH94: 2 | AI94: 3 | AJ94: 4 | AK94: 2 | AL94: 3 | AM94: 4 | AN94: 4 | AO94: 1 | AP94: 1 | AQ94: 1 | AR94: 1 | AS94: 1 | AT94: 1 | AU94: 4 | AV94: =IF(K94=VLOOKUP(VALUE(K$1),Questions!$A:$E,5,FALSE),1,0) -> 1 | AW94: =IF(L94=VLOOKUP(VALUE(L$1),Questions!$A:$E,5,FALSE),1,0) -> 1 | AX94: =IF(M94=VLOOKUP(VALUE(M$1),Questions!$A:$E,5,FALSE),1,0) -> 0 | AY94: =IF(N94=VLOOKUP(VALUE(N$1),Questions!$A:$E,5,FALSE),1,0) -> 1 | AZ94: =IF(O94=VLOOKUP(VALUE(O$1),Questions!$A:$E,5,FALSE),1,0) -> 1 | BA94: =IF(P94=VLOOKUP(VALUE(P$1),Questions!$A:$E,5,FALSE),1,0) -> 0 | BB94: =IF(Q94=VLOOKUP(VALUE(Q$1),Questions!$A:$E,5,FALSE),1,0) -> 1 | BC94: =IF(R94=VLOOKUP(VALUE(R$1),Questions!$A:$E,5,FALSE),1,0) -> 0 | ... BW94: =IF(AL94=VLOOKUP(VALUE(AL$1),Questions!$A:$E,5,FALSE),1,0) -> 1 | BX94: =IF(Scores[[#This Row],[Final]]>=65,1,0) -> 1 | BY94: =IF(Scores[[#This Row],[Final]]>=IF(Scores[[#This Row],[IEP]],55,65),1,0) -> 1
A95: 94 | B95: 11 | C95: Dushin | D95: FALSE | E95: FALSE | F95: =SUM(Scores[[#This Row],[Q1]:[Q28]]) -> 14 | G95: =SUM(Scores[[#This Row],[29]]:Scores[[#This Row],[30]]) -> 7 | H95: =SUM(Scores[[#This Row],[31]:[36]]) -> 6 | I95: =Scores[[#This Row],[37]] -> 3.5 | J95: =INDEX('Conversion Chart'!$C$3:$M$47,MATCH(SUM(Scores[[#This Row],[MC]:[IIIA]]),'Conversion Chart'!$B$3:$B$47),MATCH(Scores[[#This Row],[IIIB]],'Conversion Chart'!$C$2:$M$2)) -> 75 | K95: 1 | L95: 4 | M95: 2 | N95: 3 | O95: 1 | P95: 2 | Q95: 3 | R95: 3 | S95: 4 | T95: 1 | U95: 2 | V95: 3 | W95: 2 | X95: 3 | Y95: 4 | Z95: 1 | AA95: 3 | AB95: 4 | AC95: 3 | AD95: 4 | AE95: 1 | AF95: 2 | AG95: 4 | AH95: 3 | AI95: 4 | AJ95: 4 | AK95: 4 | AL95: 3 | AM95: 4 | AN95: 3 | AO95: 1 | AP95: 1 | AQ95: 1 | AR95: 1 | AS95: 1 | AT95: 1 | AU95: 3.5 | AV95: =IF(K95=VLOOKUP(VALUE(K$1),Questions!$A:$E,5,FALSE),1,0) -> 0 | AW95: =IF(L95=VLOOKUP(VALUE(L$1),Questions!$A:$E,5,FALSE),1,0) -> 0 | AX95: =IF(M95=VLOOKUP(VALUE(M$1),Questions!$A:$E,5,FALSE),1,0) -> 0 | AY95: =IF(N95=VLOOKUP(VALUE(N$1),Questions!$A:$E,5,FALSE),1,0) -> 1 | AZ95: =IF(O95=VLOOKUP(VALUE(O$1),Questions!$A:$E,5,FALSE),1,0) -> 1 | BA95: =IF(P95=VLOOKUP(VALUE(P$1),Questions!$A:$E,5,FALSE),1,0) -> 0 | BB95: =IF(Q95=VLOOKUP(VALUE(Q$1),Questions!$A:$E,5,FALSE),1,0) -> 1 | BC95: =IF(R95=VLOOKUP(VALUE(R$1),Questions!$A:$E,5,FALSE),1,0) -> 0 | ... BW95: =IF(AL95=VLOOKUP(VALUE(AL$1),Questions!$A:$E,5,FALSE),1,0) -> 1 | BX95: =IF(Scores[[#This Row],[Final]]>=65,1,0) -> 1 | BY95: =IF(Scores[[#This Row],[Final]]>=IF(Scores[[#This Row],[IEP]],55,65),1,0) -> 1
A96: 95 | B96: 9 | C96: Bermejo | D96: FALSE | E96: FALSE | F96: =SUM(Scores[[#This Row],[Q1]:[Q28]]) -> 0 | G96: =SUM(Scores[[#This Row],[29]]:Scores[[#This Row],[30]]) -> 0 | H96: =SUM(Scores[[#This Row],[31]:[36]]) -> 0 | I96: =Scores[[#This Row],[37]] -> 0 | J96: =INDEX('Conversion Chart'!$C$3:$M$47,MATCH(SUM(Scores[[#This Row],[MC]:[IIIA]]),'Conversion Chart'!$B$3:$B$47),MATCH(Scores[[#This Row],[IIIB]],'Conversion Chart'!$C$2:$M$2)) -> 0 | AV96: =IF(K96=VLOOKUP(VALUE(K$1),Questions!$A:$E,5,FALSE),1,0) -> 0 | AW96: =IF(L96=VLOOKUP(VALUE(L$1),Questions!$A:$E,5,FALSE),1,0) -> 0 | AX96: =IF(M96=VLOOKUP(VALUE(M$1),Questions!$A:$E,5,FALSE),1,0) -> 0 | AY96: =IF(N96=VLOOKUP(VALUE(N$1),Questions!$A:$E,5,FALSE),1,0) -> 0 | AZ96: =IF(O96=VLOOKUP(VALUE(O$1),Questions!$A:$E,5,FALSE),1,0) -> 0 | BA96: =IF(P96=VLOOKUP(VALUE(P$1),Questions!$A:$E,5,FALSE),1,0) -> 0 | BB96: =IF(Q96=VLOOKUP(VALUE(Q$1),Questions!$A:$E,5,FALSE),1,0) -> 0 | BC96: =IF(R96=VLOOKUP(VALUE(R$1),Questions!$A:$E,5,FALSE),1,0) -> 0 | ... BW96: =IF(AL96=VLOOKUP(VALUE(AL$1),Questions!$A:$E,5,FALSE),1,0) -> 0 | BX96: =IF(Scores[[#This Row],[Final]]>=65,1,0) -> 0 | BY96: =IF(Scores[[#This Row],[Final]]>=IF(Scores[[#This Row],[IEP]],55,65),1,0) -> 0
A97: 96 | B97: 11 | C97: Dushin | D97: FALSE | E97: TRUE | F97: =SUM(Scores[[#This Row],[Q1]:[Q28]]) -> 24 | G97: =SUM(Scores[[#This Row],[29]]:Scores[[#This Row],[30]]) -> 8 | H97: =SUM(Scores[[#This Row],[31]:[36]]) -> 5 | I97: =Scores[[#This Row],[37]] -> 3.5 | J97: =INDEX('Conversion Chart'!$C$3:$M$47,MATCH(SUM(Scores[[#This Row],[MC]:[IIIA]]),'Conversion Chart'!$B$3:$B$47),MATCH(Scores[[#This Row],[IIIB]],'Conversion Chart'!$C$2:$M$2)) -> 85 | K97: 4 | L97: 1 | M97: 3 | N97: 3 | O97: 1 | P97: 3 | Q97: 3 | R97: 2 | S97: 2 | T97: 1 | U97: 2 | V97: 4 | W97: 2 | X97: 3 | Y97: 3 | Z97: 1 | AA97: 1 | AB97: 4 | AC97: 3 | AD97: 4 | AE97: 2 | AF97: 2 | AG97: 3 | AH97: 3 | AI97: 1 | AJ97: 4 | AK97: 2 | AL97: 3 | AM97: 4 | AN97: 4 | AO97: 1 | AP97: 0 | AQ97: 1 | AR97: 1 | AS97: 1 | AT97: 1 | AU97: 3.5 | AV97: =IF(K97=VLOOKUP(VALUE(K$1),Questions!$A:$E,5,FALSE),1,0) -> 1 | AW97: =IF(L97=VLOOKUP(VALUE(L$1),Questions!$A:$E,5,FALSE),1,0) -> 0 | AX97: =IF(M97=VLOOKUP(VALUE(M$1),Questions!$A:$E,5,FALSE),1,0) -> 1 | AY97: =IF(N97=VLOOKUP(VALUE(N$1),Questions!$A:$E,5,FALSE),1,0) -> 1 | AZ97: =IF(O97=VLOOKUP(VALUE(O$1),Questions!$A:$E,5,FALSE),1,0) -> 1 | BA97: =IF(P97=VLOOKUP(VALUE(P$1),Questions!$A:$E,5,FALSE),1,0) -> 0 | BB97: =IF(Q97=VLOOKUP(VALUE(Q$1),Questions!$A:$E,5,FALSE),1,0) -> 1 | BC97: =IF(R97=VLOOKUP(VALUE(R$1),Questions!$A:$E,5,FALSE),1,0) -> 1 | ... BW97: =IF(AL97=VLOOKUP(VALUE(AL$1),Questions!$A:$E,5,FALSE),1,0) -> 1 | BX97: =IF(Scores[[#This Row],[Final]]>=65,1,0) -> 1 | BY97: =IF(Scores[[#This Row],[Final]]>=IF(Scores[[#This Row],[IEP]],55,65),1,0) -> 1
A98: 97 | B98: 9 | C98: Bermejo | D98: FALSE | E98: FALSE | F98: =SUM(Scores[[#This Row],[Q1]:[Q28]]) -> 20 | G98: =SUM(Scores[[#This Row],[29]]:Scores[[#This Row],[30]]) -> 8 | H98: =SUM(Scores[[#This Row],[31]:[36]]) -> 6 | I98: =Scores[[#This Row],[37]] -> 2 | J98: =INDEX('Conversion Chart'!$C$3:$M$47,MATCH(SUM(Scores[[#This Row],[MC]:[IIIA]]),'Conversion Chart'!$B$3:$B$47),MATCH(Scores[[#This Row],[IIIB]],'Conversion Chart'!$C$2:$M$2)) -> 77 | K98: 4 | L98: 1 | M98: 3 | N98: 3 | O98: 1 | P98: 2 | Q98: 3 | R98: 2 | S98: 2 | T98: 1 | U98: 2 | V98: 3 | W98: 2 | X98: 4 | Y98: 3 | Z98: 1 | AA98: 2 | AB98: 4 | AC98: 1 | AD98: 4 | AE98: 2 | AF98: 2 | AG98: 3 | AH98: 2 | AI98: 1 | AJ98: 2 | AK98: 4 | AL98: 3 | AM98: 4 | AN98: 4 | AO98: 1 | AP98: 1 | AQ98: 1 | AR98: 1 | AS98: 1 | AT98: 1 | AU98: 2 | AV98: =IF(K98=VLOOKUP(VALUE(K$1),Questions!$A:$E,5,FALSE),1,0) -> 1 | AW98: =IF(L98=VLOOKUP(VALUE(L$1),Questions!$A:$E,5,FALSE),1,0) -> 0 | AX98: =IF(M98=VLOOKUP(VALUE(M$1),Questions!$A:$E,5,FALSE),1,0) -> 1 | AY98: =IF(N98=VLOOKUP(VALUE(N$1),Questions!$A:$E,5,FALSE),1,0) -> 1 | AZ98: =IF(O98=VLOOKUP(VALUE(O$1),Questions!$A:$E,5,FALSE),1,0) -> 1 | BA98: =IF(P98=VLOOKUP(VALUE(P$1),Questions!$A:$E,5,FALSE),1,0) -> 0 | BB98: =IF(Q98=VLOOKUP(VALUE(Q$1),Questions!$A:$E,5,FALSE),1,0) -> 1 | BC98: =IF(R98=VLOOKUP(VALUE(R$1),Questions!$A:$E,5,FALSE),1,0) -> 1 | ... BW98: =IF(AL98=VLOOKUP(VALUE(AL$1),Questions!$A:$E,5,FALSE),1,0) -> 1 | BX98: =IF(Scores[[#This Row],[Final]]>=65,1,0) -> 1 | BY98: =IF(Scores[[#This Row],[Final]]>=IF(Scores[[#This Row],[IEP]],55,65),1,0) -> 1
A99: 98 | B99: 9 | C99: Kovelsky | D99: FALSE | E99: FALSE | F99: =SUM(Scores[[#This Row],[Q1]:[Q28]]) -> 20 | G99: =SUM(Scores[[#This Row],[29]]:Scores[[#This Row],[30]]) -> 2 | H99: =SUM(Scores[[#This Row],[31]:[36]]) -> 6 | I99: =Scores[[#This Row],[37]] -> 1 | J99: =INDEX('Conversion Chart'!$C$3:$M$47,MATCH(SUM(Scores[[#This Row],[MC]:[IIIA]]),'Conversion Chart'!$B$3:$B$47),MATCH(Scores[[#This Row],[IIIB]],'Conversion Chart'!$C$2:$M$2)) -> 68 | K99: 3 | L99: 2 | M99: 3 | N99: 4 | O99: 1 | P99: 4 | Q99: 3 | R99: 2 | S99: 2 | T99: 1 | U99: 2 | V99: 3 | W99: 2 | X99: 4 | Y99: 3 | Z99: 4 | AA99: 1 | AB99: 4 | AC99: 3 | AD99: 1 | AE99: 3 | AF99: 2 | AG99: 3 | AH99: 3 | AI99: 4 | AJ99: 4 | AK99: 1 | AL99: 2 | AM99: 1 | AN99: 1 | AO99: 1 | AP99: 1 | AQ99: 1 | AR99: 1 | AS99: 1 | AT99: 1 | AU99: 1 | AV99: =IF(K99=VLOOKUP(VALUE(K$1),Questions!$A:$E,5,FALSE),1,0) -> 0 | AW99: =IF(L99=VLOOKUP(VALUE(L$1),Questions!$A:$E,5,FALSE),1,0) -> 1 | AX99: =IF(M99=VLOOKUP(VALUE(M$1),Questions!$A:$E,5,FALSE),1,0) -> 1 | AY99: =IF(N99=VLOOKUP(VALUE(N$1),Questions!$A:$E,5,FALSE),1,0) -> 0 | AZ99: =IF(O99=VLOOKUP(VALUE(O$1),Questions!$A:$E,5,FALSE),1,0) -> 1 | BA99: =IF(P99=VLOOKUP(VALUE(P$1),Questions!$A:$E,5,FALSE),1,0) -> 1 | BB99: =IF(Q99=VLOOKUP(VALUE(Q$1),Questions!$A:$E,5,FALSE),1,0) -> 1 | BC99: =IF(R99=VLOOKUP(VALUE(R$1),Questions!$A:$E,5,FALSE),1,0) -> 1 | ... BW99: =IF(AL99=VLOOKUP(VALUE(AL$1),Questions!$A:$E,5,FALSE),1,0) -> 0 | BX99: =IF(Scores[[#This Row],[Final]]>=65,1,0) -> 1 | BY99: =IF(Scores[[#This Row],[Final]]>=IF(Scores[[#This Row],[IEP]],55,65),1,0) -> 1
A100: 99 | B100: 11 | C100: Kovelsky | D100: FALSE | E100: FALSE | F100: =SUM(Scores[[#This Row],[Q1]:[Q28]]) -> 18 | G100: =SUM(Scores[[#This Row],[29]]:Scores[[#This Row],[30]]) -> 4 | H100: =SUM(Scores[[#This Row],[31]:[36]]) -> 6 | I100: =Scores[[#This Row],[37]] -> 1 | J100: =INDEX('Conversion Chart'!$C$3:$M$47,MATCH(SUM(Scores[[#This Row],[MC]:[IIIA]]),'Conversion Chart'!$B$3:$B$47),MATCH(Scores[[#This Row],[IIIB]],'Conversion Chart'!$C$2:$M$2)) -> 68 | K100: 4 | L100: 3 | M100: 3 | N100: 2 | O100: 1 | P100: 3 | Q100: 3 | R100: 2 | S100: 2 | T100: 1 | U100: 2 | V100: 4 | W100: 1 | X100: 4 | Y100: 4 | Z100: 1 | AA100: 1 | AB100: 4 | AC100: 3 | AD100: 4 | AE100: 2 | AF100: 3 | AG100: 4 | AH100: 2 | AI100: 3 | AJ100: 4 | AK100: 2 | AL100: 3 | AM100: 2 | AN100: 2 | AO100: 1 | AP100: 1 | AQ100: 1 | AR100: 1 | AS100: 1 | AT100: 1 | AU100: 1 | AV100: =IF(K100=VLOOKUP(VALUE(K$1),Questions!$A:$E,5,FALSE),1,0) -> 1 | AW100: =IF(L100=VLOOKUP(VALUE(L$1),Questions!$A:$E,5,FALSE),1,0) -> 0 | AX100: =IF(M100=VLOOKUP(VALUE(M$1),Questions!$A:$E,5,FALSE),1,0) -> 1 | AY100: =IF(N100=VLOOKUP(VALUE(N$1),Questions!$A:$E,5,FALSE),1,0) -> 0 | AZ100: =IF(O100=VLOOKUP(VALUE(O$1),Questions!$A:$E,5,FALSE),1,0) -> 1 | BA100: =IF(P100=VLOOKUP(VALUE(P$1),Questions!$A:$E,5,FALSE),1,0) -> 0 | BB100: =IF(Q100=VLOOKUP(VALUE(Q$1),Questions!$A:$E,5,FALSE),1,0) -> 1 | BC100: =IF(R100=VLOOKUP(VALUE(R$1),Questions!$A:$E,5,FALSE),1,0) -> 1 | ... BW100: =IF(AL100=VLOOKUP(VALUE(AL$1),Questions!$A:$E,5,FALSE),1,0) -> 1 | BX100: =IF(Scores[[#This Row],[Final]]>=65,1,0) -> 1 | BY100: =IF(Scores[[#This Row],[Final]]>=IF(Scores[[#This Row],[IEP]],55,65),1,0) -> 1
A101: 100 | B101: 11 | C101: Other | D101: FALSE | E101: FALSE | F101: =SUM(Scores[[#This Row],[Q1]:[Q28]]) -> 0 | G101: =SUM(Scores[[#This Row],[29]]:Scores[[#This Row],[30]]) -> 0 | H101: =SUM(Scores[[#This Row],[31]:[36]]) -> 0 | I101: =Scores[[#This Row],[37]] -> 0 | J101: =INDEX('Conversion Chart'!$C$3:$M$47,MATCH(SUM(Scores[[#This Row],[MC]:[IIIA]]),'Conversion Chart'!$B$3:$B$47),MATCH(Scores[[#This Row],[IIIB]],'Conversion Chart'!$C$2:$M$2)) -> 0 | AV101: =IF(K101=VLOOKUP(VALUE(K$1),Questions!$A:$E,5,FALSE),1,0) -> 0 | AW101: =IF(L101=VLOOKUP(VALUE(L$1),Questions!$A:$E,5,FALSE),1,0) -> 0 | AX101: =IF(M101=VLOOKUP(VALUE(M$1),Questions!$A:$E,5,FALSE),1,0) -> 0 | AY101: =IF(N101=VLOOKUP(VALUE(N$1),Questions!$A:$E,5,FALSE),1,0) -> 0 | AZ101: =IF(O101=VLOOKUP(VALUE(O$1),Questions!$A:$E,5,FALSE),1,0) -> 0 | BA101: =IF(P101=VLOOKUP(VALUE(P$1),Questions!$A:$E,5,FALSE),1,0) -> 0 | BB101: =IF(Q101=VLOOKUP(VALUE(Q$1),Questions!$A:$E,5,FALSE),1,0) -> 0 | BC101: =IF(R101=VLOOKUP(VALUE(R$1),Questions!$A:$E,5,FALSE),1,0) -> 0 | ... BW101: =IF(AL101=VLOOKUP(VALUE(AL$1),Questions!$A:$E,5,FALSE),1,0) -> 0 | BX101: =IF(Scores[[#This Row],[Final]]>=65,1,0) -> 0 | BY101: =IF(Scores[[#This Row],[Final]]>=IF(Scores[[#This Row],[IEP]],55,65),1,0) -> 0
A102: 101 | B102: 9 | C102: Bermejo | D102: FALSE | E102: FALSE | F102: =SUM(Scores[[#This Row],[Q1]:[Q28]]) -> 21 | G102: =SUM(Scores[[#This Row],[29]]:Scores[[#This Row],[30]]) -> 2 | H102: =SUM(Scores[[#This Row],[31]:[36]]) -> 4 | I102: =Scores[[#This Row],[37]] -> 3 | J102: =INDEX('Conversion Chart'!$C$3:$M$47,MATCH(SUM(Scores[[#This Row],[MC]:[IIIA]]),'Conversion Chart'!$B$3:$B$47),MATCH(Scores[[#This Row],[IIIB]],'Conversion Chart'!$C$2:$M$2)) -> 73 | K102: 4 | L102: 2 | M102: 3 | N102: 3 | O102: 1 | P102: 2 | Q102: 3 | R102: 2 | S102: 3 | T102: 1 | U102: 2 | V102: 4 | W102: 1 | X102: 4 | Y102: 3 | Z102: 4 | AA102: 1 | AB102: 4 | AC102: 3 | AD102: 4 | AE102: 2 | AF102: 2 | AG102: 3 | AH102: 2 | AI102: 2 | AJ102: 4 | AK102: 2 | AL102: 3 | AM102: 1 | AN102: 1 | AO102: 1 | AP102: 1 | AQ102: 0 | AR102: 1 | AS102: 1 | AT102: 0 | AU102: 3 | AV102: =IF(K102=VLOOKUP(VALUE(K$1),Questions!$A:$E,5,FALSE),1,0) -> 1 | AW102: =IF(L102=VLOOKUP(VALUE(L$1),Questions!$A:$E,5,FALSE),1,0) -> 1 | AX102: =IF(M102=VLOOKUP(VALUE(M$1),Questions!$A:$E,5,FALSE),1,0) -> 1 | AY102: =IF(N102=VLOOKUP(VALUE(N$1),Questions!$A:$E,5,FALSE),1,0) -> 1 | AZ102: =IF(O102=VLOOKUP(VALUE(O$1),Questions!$A:$E,5,FALSE),1,0) -> 1 | BA102: =IF(P102=VLOOKUP(VALUE(P$1),Questions!$A:$E,5,FALSE),1,0) -> 0 | BB102: =IF(Q102=VLOOKUP(VALUE(Q$1),Questions!$A:$E,5,FALSE),1,0) -> 1 | BC102: =IF(R102=VLOOKUP(VALUE(R$1),Questions!$A:$E,5,FALSE),1,0) -> 1 | ... BW102: =IF(AL102=VLOOKUP(VALUE(AL$1),Questions!$A:$E,5,FALSE),1,0) -> 1 | BX102: =IF(Scores[[#This Row],[Final]]>=65,1,0) -> 1 | BY102: =IF(Scores[[#This Row],[Final]]>=IF(Scores[[#This Row],[IEP]],55,65),1,0) -> 1
A103: 102 | B103: 11 | C103: Kovelsky | D103: FALSE | E103: FALSE | F103: =SUM(Scores[[#This Row],[Q1]:[Q28]]) -> 15 | G103: =SUM(Scores[[#This Row],[29]]:Scores[[#This Row],[30]]) -> 3 | H103: =SUM(Scores[[#This Row],[31]:[36]]) -> 6 | I103: =Scores[[#This Row],[37]] -> 1.5 | J103: =INDEX('Conversion Chart'!$C$3:$M$47,MATCH(SUM(Scores[[#This Row],[MC]:[IIIA]]),'Conversion Chart'!$B$3:$B$47),MATCH(Scores[[#This Row],[IIIB]],'Conversion Chart'!$C$2:$M$2)) -> 65 | K103: 4 | L103: 3 | M103: 3 | N103: 2 | O103: 1 | P103: 1 | Q103: 3 | R103: 2 | S103: 2 | T103: 1 | U103: 2 | V103: 3 | W103: 3 | X103: 4 | Y103: 1 | Z103: 1 | AA103: 1 | AB103: 4 | AC103: 4 | AD103: 3 | AE103: 2 | AF103: 3 | AG103: 4 | AH103: 2 | AI103: 3 | AJ103: 4 | AK103: 2 | AL103: 3 | AM103: 1 | AN103: 2 | AO103: 1 | AP103: 1 | AQ103: 1 | AR103: 1 | AS103: 1 | AT103: 1 | AU103: 1.5 | AV103: =IF(K103=VLOOKUP(VALUE(K$1),Questions!$A:$E,5,FALSE),1,0) -> 1 | AW103: =IF(L103=VLOOKUP(VALUE(L$1),Questions!$A:$E,5,FALSE),1,0) -> 0 | AX103: =IF(M103=VLOOKUP(VALUE(M$1),Questions!$A:$E,5,FALSE),1,0) -> 1 | AY103: =IF(N103=VLOOKUP(VALUE(N$1),Questions!$A:$E,5,FALSE),1,0) -> 0 | AZ103: =IF(O103=VLOOKUP(VALUE(O$1),Questions!$A:$E,5,FALSE),1,0) -> 1 | BA103: =IF(P103=VLOOKUP(VALUE(P$1),Questions!$A:$E,5,FALSE),1,0) -> 0 | BB103: =IF(Q103=VLOOKUP(VALUE(Q$1),Questions!$A:$E,5,FALSE),1,0) -> 1 | BC103: =IF(R103=VLOOKUP(VALUE(R$1),Questions!$A:$E,5,FALSE),1,0) -> 1 | ... BW103: =IF(AL103=VLOOKUP(VALUE(AL$1),Questions!$A:$E,5,FALSE),1,0) -> 1 | BX103: =IF(Scores[[#This Row],[Final]]>=65,1,0) -> 1 | BY103: =IF(Scores[[#This Row],[Final]]>=IF(Scores[[#This Row],[IEP]],55,65),1,0) -> 1
A104: 103 | B104: 9 | C104: Other | D104: FALSE | E104: FALSE | F104: =SUM(Scores[[#This Row],[Q1]:[Q28]]) -> 0 | G104: =SUM(Scores[[#This Row],[29]]:Scores[[#This Row],[30]]) -> 0 | H104: =SUM(Scores[[#This Row],[31]:[36]]) -> 0 | I104: =Scores[[#This Row],[37]] -> 0 | J104: =INDEX('Conversion Chart'!$C$3:$M$47,MATCH(SUM(Scores[[#This Row],[MC]:[IIIA]]),'Conversion Chart'!$B$3:$B$47),MATCH(Scores[[#This Row],[IIIB]],'Conversion Chart'!$C$2:$M$2)) -> 0 | AV104: =IF(K104=VLOOKUP(VALUE(K$1),Questions!$A:$E,5,FALSE),1,0) -> 0 | AW104: =IF(L104=VLOOKUP(VALUE(L$1),Questions!$A:$E,5,FALSE),1,0) -> 0 | AX104: =IF(M104=VLOOKUP(VALUE(M$1),Questions!$A:$E,5,FALSE),1,0) -> 0 | AY104: =IF(N104=VLOOKUP(VALUE(N$1),Questions!$A:$E,5,FALSE),1,0) -> 0 | AZ104: =IF(O104=VLOOKUP(VALUE(O$1),Questions!$A:$E,5,FALSE),1,0) -> 0 | BA104: =IF(P104=VLOOKUP(VALUE(P$1),Questions!$A:$E,5,FALSE),1,0) -> 0 | BB104: =IF(Q104=VLOOKUP(VALUE(Q$1),Questions!$A:$E,5,FALSE),1,0) -> 0 | BC104: =IF(R104=VLOOKUP(VALUE(R$1),Questions!$A:$E,5,FALSE),1,0) -> 0 | ... BW104: =IF(AL104=VLOOKUP(VALUE(AL$1),Questions!$A:$E,5,FALSE),1,0) -> 0 | BX104: =IF(Scores[[#This Row],[Final]]>=65,1,0) -> 0 | BY104: =IF(Scores[[#This Row],[Final]]>=IF(Scores[[#This Row],[IEP]],55,65),1,0) -> 0
A105: 104 | B105: 11 | C105: Dushin | D105: FALSE | E105: FALSE | F105: =SUM(Scores[[#This Row],[Q1]:[Q28]]) -> 20 | G105: =SUM(Scores[[#This Row],[29]]:Scores[[#This Row],[30]]) -> 4 | H105: =SUM(Scores[[#This Row],[31]:[36]]) -> 6 | I105: =Scores[[#This Row],[37]] -> 2.5 | J105: =INDEX('Conversion Chart'!$C$3:$M$47,MATCH(SUM(Scores[[#This Row],[MC]:[IIIA]]),'Conversion Chart'!$B$3:$B$47),MATCH(Scores[[#This Row],[IIIB]],'Conversion Chart'!$C$2:$M$2)) -> 75 | K105: 4 | L105: 3 | M105: 3 | N105: 3 | O105: 1 | P105: 4 | Q105: 1 | R105: 2 | S105: 2 | T105: 1 | U105: 2 | V105: 4 | W105: 2 | X105: 4 | Y105: 3 | Z105: 1 | AA105: 3 | AB105: 4 | AC105: 3 | AD105: 1 | AE105: 1 | AF105: 2 | AG105: 3 | AH105: 2 | AI105: 3 | AJ105: 4 | AK105: 1 | AL105: 2 | AM105: 4 | AN105: 0 | AO105: 1 | AP105: 1 | AQ105: 1 | AR105: 1 | AS105: 1 | AT105: 1 | AU105: 2.5 | AV105: =IF(K105=VLOOKUP(VALUE(K$1),Questions!$A:$E,5,FALSE),1,0) -> 1 | AW105: =IF(L105=VLOOKUP(VALUE(L$1),Questions!$A:$E,5,FALSE),1,0) -> 0 | AX105: =IF(M105=VLOOKUP(VALUE(M$1),Questions!$A:$E,5,FALSE),1,0) -> 1 | AY105: =IF(N105=VLOOKUP(VALUE(N$1),Questions!$A:$E,5,FALSE),1,0) -> 1 | AZ105: =IF(O105=VLOOKUP(VALUE(O$1),Questions!$A:$E,5,FALSE),1,0) -> 1 | BA105: =IF(P105=VLOOKUP(VALUE(P$1),Questions!$A:$E,5,FALSE),1,0) -> 1 | BB105: =IF(Q105=VLOOKUP(VALUE(Q$1),Questions!$A:$E,5,FALSE),1,0) -> 0 | BC105: =IF(R105=VLOOKUP(VALUE(R$1),Questions!$A:$E,5,FALSE),1,0) -> 1 | ... BW105: =IF(AL105=VLOOKUP(VALUE(AL$1),Questions!$A:$E,5,FALSE),1,0) -> 0 | BX105: =IF(Scores[[#This Row],[Final]]>=65,1,0) -> 1 | BY105: =IF(Scores[[#This Row],[Final]]>=IF(Scores[[#This Row],[IEP]],55,65),1,0) -> 1
A106: 105 | B106: 11 | C106: Dushin | D106: FALSE | E106: TRUE | F106: =SUM(Scores[[#This Row],[Q1]:[Q28]]) -> 16 | G106: =SUM(Scores[[#This Row],[29]]:Scores[[#This Row],[30]]) -> 1 | H106: =SUM(Scores[[#This Row],[31]:[36]]) -> 5 | I106: =Scores[[#This Row],[37]] -> 0 | J106: =INDEX('Conversion Chart'!$C$3:$M$47,MATCH(SUM(Scores[[#This Row],[MC]:[IIIA]]),'Conversion Chart'!$B$3:$B$47),MATCH(Scores[[#This Row],[IIIB]],'Conversion Chart'!$C$2:$M$2)) -> 55 | K106: 4 | L106: 1 | M106: 1 | N106: 2 | O106: 1 | P106: 2 | Q106: 2 | R106: 2 | S106: 2 | T106: 1 | U106: 2 | V106: 4 | W106: 2 | X106: 3 | Y106: 4 | Z106: 4 | AA106: 1 | AB106: 3 | AC106: 3 | AD106: 4 | AE106: 2 | AF106: 2 | AG106: 1 | AH106: 2 | AI106: 1 | AJ106: 4 | AK106: 4 | AL106: 3 | AM106: 1 | AN106: 0 | AO106: 1 | AP106: 0 | AQ106: 1 | AR106: 1 | AS106: 1 | AT106: 1 | AU106: 0 | AV106: =IF(K106=VLOOKUP(VALUE(K$1),Questions!$A:$E,5,FALSE),1,0) -> 1 | AW106: =IF(L106=VLOOKUP(VALUE(L$1),Questions!$A:$E,5,FALSE),1,0) -> 0 | AX106: =IF(M106=VLOOKUP(VALUE(M$1),Questions!$A:$E,5,FALSE),1,0) -> 0 | AY106: =IF(N106=VLOOKUP(VALUE(N$1),Questions!$A:$E,5,FALSE),1,0) -> 0 | AZ106: =IF(O106=VLOOKUP(VALUE(O$1),Questions!$A:$E,5,FALSE),1,0) -> 1 | BA106: =IF(P106=VLOOKUP(VALUE(P$1),Questions!$A:$E,5,FALSE),1,0) -> 0 | BB106: =IF(Q106=VLOOKUP(VALUE(Q$1),Questions!$A:$E,5,FALSE),1,0) -> 0 | BC106: =IF(R106=VLOOKUP(VALUE(R$1),Questions!$A:$E,5,FALSE),1,0) -> 1 | ... BW106: =IF(AL106=VLOOKUP(VALUE(AL$1),Questions!$A:$E,5,FALSE),1,0) -> 1 | BX106: =IF(Scores[[#This Row],[Final]]>=65,1,0) -> 0 | BY106: =IF(Scores[[#This Row],[Final]]>=IF(Scores[[#This Row],[IEP]],55,65),1,0) -> 1
A107: 106 | B107: 9 | C107: Bermejo | D107: TRUE | E107: FALSE | F107: =SUM(Scores[[#This Row],[Q1]:[Q28]]) -> 12 | G107: =SUM(Scores[[#This Row],[29]]:Scores[[#This Row],[30]]) -> 5 | H107: =SUM(Scores[[#This Row],[31]:[36]]) -> 0 | I107: =Scores[[#This Row],[37]] -> 0 | J107: =INDEX('Conversion Chart'!$C$3:$M$47,MATCH(SUM(Scores[[#This Row],[MC]:[IIIA]]),'Conversion Chart'!$B$3:$B$47),MATCH(Scores[[#This Row],[IIIB]],'Conversion Chart'!$C$2:$M$2)) -> 46 | K107: 4 | L107: 2 | M107: 3 | N107: 1 | O107: 2 | P107: 2 | Q107: 4 | R107: 2 | S107: 2 | T107: 1 | U107: 3 | V107: 2 | W107: 2 | X107: 4 | Y107: 2 | Z107: 1 | AA107: 2 | AB107: 4 | AC107: 4 | AD107: 2 | AE107: 1 | AF107: 2 | AG107: 1 | AH107: 4 | AI107: 2 | AJ107: 1 | AK107: 2 | AL107: 3 | AM107: 3 | AN107: 2 | AO107: 0 | AP107: 0 | AQ107: 0 | AR107: 0 | AS107: 0 | AT107: 0 | AU107: 0 | AV107: =IF(K107=VLOOKUP(VALUE(K$1),Questions!$A:$E,5,FALSE),1,0) -> 1 | AW107: =IF(L107=VLOOKUP(VALUE(L$1),Questions!$A:$E,5,FALSE),1,0) -> 1 | AX107: =IF(M107=VLOOKUP(VALUE(M$1),Questions!$A:$E,5,FALSE),1,0) -> 1 | AY107: =IF(N107=VLOOKUP(VALUE(N$1),Questions!$A:$E,5,FALSE),1,0) -> 0 | AZ107: =IF(O107=VLOOKUP(VALUE(O$1),Questions!$A:$E,5,FALSE),1,0) -> 0 | BA107: =IF(P107=VLOOKUP(VALUE(P$1),Questions!$A:$E,5,FALSE),1,0) -> 0 | BB107: =IF(Q107=VLOOKUP(VALUE(Q$1),Questions!$A:$E,5,FALSE),1,0) -> 0 | BC107: =IF(R107=VLOOKUP(VALUE(R$1),Questions!$A:$E,5,FALSE),1,0) -> 1 | ... BW107: =IF(AL107=VLOOKUP(VALUE(AL$1),Questions!$A:$E,5,FALSE),1,0) -> 1 | BX107: =IF(Scores[[#This Row],[Final]]>=65,1,0) -> 0 | BY107: =IF(Scores[[#This Row],[Final]]>=IF(Scores[[#This Row],[IEP]],55,65),1,0) -> 0
A108: 107 | B108: 11 | C108: Antaky | D108: FALSE | E108: FALSE | F108: =SUM(Scores[[#This Row],[Q1]:[Q28]]) -> 22 | G108: =SUM(Scores[[#This Row],[29]]:Scores[[#This Row],[30]]) -> 8 | H108: =SUM(Scores[[#This Row],[31]:[36]]) -> 6 | I108: =Scores[[#This Row],[37]] -> 2 | J108: =INDEX('Conversion Chart'!$C$3:$M$47,MATCH(SUM(Scores[[#This Row],[MC]:[IIIA]]),'Conversion Chart'!$B$3:$B$47),MATCH(Scores[[#This Row],[IIIB]],'Conversion Chart'!$C$2:$M$2)) -> 79 | K108: 4 | L108: 2 | M108: 4 | N108: 1 | O108: 1 | P108: 4 | Q108: 3 | R108: 2 | S108: 2 | T108: 1 | U108: 2 | V108: 4 | W108: 2 | X108: 4 | Y108: 3 | Z108: 1 | AA108: 1 | AB108: 4 | AC108: 1 | AD108: 1 | AE108: 2 | AF108: 2 | AG108: 1 | AH108: 3 | AI108: 1 | AJ108: 2 | AK108: 1 | AL108: 3 | AM108: 4 | AN108: 4 | AO108: 1 | AP108: 1 | AQ108: 1 | AR108: 1 | AS108: 1 | AT108: 1 | AU108: 2 | AV108: =IF(K108=VLOOKUP(VALUE(K$1),Questions!$A:$E,5,FALSE),1,0) -> 1 | AW108: =IF(L108=VLOOKUP(VALUE(L$1),Questions!$A:$E,5,FALSE),1,0) -> 1 | AX108: =IF(M108=VLOOKUP(VALUE(M$1),Questions!$A:$E,5,FALSE),1,0) -> 0 | AY108: =IF(N108=VLOOKUP(VALUE(N$1),Questions!$A:$E,5,FALSE),1,0) -> 0 | AZ108: =IF(O108=VLOOKUP(VALUE(O$1),Questions!$A:$E,5,FALSE),1,0) -> 1 | BA108: =IF(P108=VLOOKUP(VALUE(P$1),Questions!$A:$E,5,FALSE),1,0) -> 1 | BB108: =IF(Q108=VLOOKUP(VALUE(Q$1),Questions!$A:$E,5,FALSE),1,0) -> 1 | BC108: =IF(R108=VLOOKUP(VALUE(R$1),Questions!$A:$E,5,FALSE),1,0) -> 1 | ... BW108: =IF(AL108=VLOOKUP(VALUE(AL$1),Questions!$A:$E,5,FALSE),1,0) -> 1 | BX108: =IF(Scores[[#This Row],[Final]]>=65,1,0) -> 1 | BY108: =IF(Scores[[#This Row],[Final]]>=IF(Scores[[#This Row],[IEP]],55,65),1,0) -> 1
A109: 108 | B109: 11 | C109: Dushin | D109: FALSE | E109: FALSE | F109: =SUM(Scores[[#This Row],[Q1]:[Q28]]) -> 18 | G109: =SUM(Scores[[#This Row],[29]]:Scores[[#This Row],[30]]) -> 5 | H109: =SUM(Scores[[#This Row],[31]:[36]]) -> 6 | I109: =Scores[[#This Row],[37]] -> 2.5 | J109: =INDEX('Conversion Chart'!$C$3:$M$47,MATCH(SUM(Scores[[#This Row],[MC]:[IIIA]]),'Conversion Chart'!$B$3:$B$47),MATCH(Scores[[#This Row],[IIIB]],'Conversion Chart'!$C$2:$M$2)) -> 74 | K109: 4 | L109: 4 | M109: 3 | N109: 1 | O109: 1 | P109: 4 | Q109: 3 | R109: 2 | S109: 2 | T109: 1 | U109: 2 | V109: 4 | W109: 1 | X109: 2 | Y109: 3 | Z109: 4 | AA109: 2 | AB109: 2 | AC109: 3 | AD109: 1 | AE109: 2 | AF109: 3 | AG109: 3 | AH109: 3 | AI109: 4 | AJ109: 4 | AK109: 1 | AL109: 3 | AM109: 3 | AN109: 2 | AO109: 1 | AP109: 1 | AQ109: 1 | AR109: 1 | AS109: 1 | AT109: 1 | AU109: 2.5 | AV109: =IF(K109=VLOOKUP(VALUE(K$1),Questions!$A:$E,5,FALSE),1,0) -> 1 | AW109: =IF(L109=VLOOKUP(VALUE(L$1),Questions!$A:$E,5,FALSE),1,0) -> 0 | AX109: =IF(M109=VLOOKUP(VALUE(M$1),Questions!$A:$E,5,FALSE),1,0) -> 1 | AY109: =IF(N109=VLOOKUP(VALUE(N$1),Questions!$A:$E,5,FALSE),1,0) -> 0 | AZ109: =IF(O109=VLOOKUP(VALUE(O$1),Questions!$A:$E,5,FALSE),1,0) -> 1 | BA109: =IF(P109=VLOOKUP(VALUE(P$1),Questions!$A:$E,5,FALSE),1,0) -> 1 | BB109: =IF(Q109=VLOOKUP(VALUE(Q$1),Questions!$A:$E,5,FALSE),1,0) -> 1 | BC109: =IF(R109=VLOOKUP(VALUE(R$1),Questions!$A:$E,5,FALSE),1,0) -> 1 | ... BW109: =IF(AL109=VLOOKUP(VALUE(AL$1),Questions!$A:$E,5,FALSE),1,0) -> 1 | BX109: =IF(Scores[[#This Row],[Final]]>=65,1,0) -> 1 | BY109: =IF(Scores[[#This Row],[Final]]>=IF(Scores[[#This Row],[IEP]],55,65),1,0) -> 1
A110: 109 | B110: 9 | C110: Bermejo | D110: FALSE | E110: TRUE | F110: =SUM(Scores[[#This Row],[Q1]:[Q28]]) -> 9 | G110: =SUM(Scores[[#This Row],[29]]:Scores[[#This Row],[30]]) -> 5 | H110: =SUM(Scores[[#This Row],[31]:[36]]) -> 5 | I110: =Scores[[#This Row],[37]] -> 2 | J110: =INDEX('Conversion Chart'!$C$3:$M$47,MATCH(SUM(Scores[[#This Row],[MC]:[IIIA]]),'Conversion Chart'!$B$3:$B$47),MATCH(Scores[[#This Row],[IIIB]],'Conversion Chart'!$C$2:$M$2)) -> 60 | K110: 3 | L110: 4 | M110: 2 | N110: 4 | O110: 1 | P110: 3 | Q110: 2 | R110: 3 | S110: 2 | T110: 1 | U110: 4 | V110: 1 | W110: 3 | X110: 1 | Y110: 2 | Z110: 1 | AA110: 1 | AB110: 3 | AC110: 1 | AD110: 3 | AE110: 2 | AF110: 2 | AG110: 3 | AH110: 1 | AI110: 4 | AJ110: 3 | AK110: 2 | AL110: 3 | AM110: 3 | AN110: 2 | AO110: 1 | AP110: 1 | AQ110: 1 | AR110: 1 | AS110: 1 | AT110: 0 | AU110: 2 | AV110: =IF(K110=VLOOKUP(VALUE(K$1),Questions!$A:$E,5,FALSE),1,0) -> 0 | AW110: =IF(L110=VLOOKUP(VALUE(L$1),Questions!$A:$E,5,FALSE),1,0) -> 0 | AX110: =IF(M110=VLOOKUP(VALUE(M$1),Questions!$A:$E,5,FALSE),1,0) -> 0 | AY110: =IF(N110=VLOOKUP(VALUE(N$1),Questions!$A:$E,5,FALSE),1,0) -> 0 | AZ110: =IF(O110=VLOOKUP(VALUE(O$1),Questions!$A:$E,5,FALSE),1,0) -> 1 | BA110: =IF(P110=VLOOKUP(VALUE(P$1),Questions!$A:$E,5,FALSE),1,0) -> 0 | BB110: =IF(Q110=VLOOKUP(VALUE(Q$1),Questions!$A:$E,5,FALSE),1,0) -> 0 | BC110: =IF(R110=VLOOKUP(VALUE(R$1),Questions!$A:$E,5,FALSE),1,0) -> 0 | ... BW110: =IF(AL110=VLOOKUP(VALUE(AL$1),Questions!$A:$E,5,FALSE),1,0) -> 1 | BX110: =IF(Scores[[#This Row],[Final]]>=65,1,0) -> 0 | BY110: =IF(Scores[[#This Row],[Final]]>=IF(Scores[[#This Row],[IEP]],55,65),1,0) -> 1
A111: 110 | B111: 11 | C111: Dushin | D111: FALSE | E111: FALSE | F111: =SUM(Scores[[#This Row],[Q1]:[Q28]]) -> 14 | G111: =SUM(Scores[[#This Row],[29]]:Scores[[#This Row],[30]]) -> 4 | H111: =SUM(Scores[[#This Row],[31]:[36]]) -> 5 | I111: =Scores[[#This Row],[37]] -> 2.5 | J111: =INDEX('Conversion Chart'!$C$3:$M$47,MATCH(SUM(Scores[[#This Row],[MC]:[IIIA]]),'Conversion Chart'!$B$3:$B$47),MATCH(Scores[[#This Row],[IIIB]],'Conversion Chart'!$C$2:$M$2)) -> 67 | K111: 1 | L111: 1 | M111: 3 | N111: 3 | O111: 1 | P111: 1 | Q111: 3 | R111: 3 | S111: 2 | T111: 1 | U111: 2 | V111: 4 | W111: 4 | X111: 1 | Y111: 3 | Z111: 4 | AA111: 4 | AB111: 3 | AC111: 3 | AD111: 1 | AE111: 1 | AF111: 4 | AG111: 3 | AH111: 4 | AI111: 3 | AJ111: 4 | AK111: 1 | AL111: 3 | AM111: 2 | AN111: 2 | AO111: 1 | AP111: 1 | AQ111: 1 | AR111: 0 | AS111: 1 | AT111: 1 | AU111: 2.5 | AV111: =IF(K111=VLOOKUP(VALUE(K$1),Questions!$A:$E,5,FALSE),1,0) -> 0 | AW111: =IF(L111=VLOOKUP(VALUE(L$1),Questions!$A:$E,5,FALSE),1,0) -> 0 | AX111: =IF(M111=VLOOKUP(VALUE(M$1),Questions!$A:$E,5,FALSE),1,0) -> 1 | AY111: =IF(N111=VLOOKUP(VALUE(N$1),Questions!$A:$E,5,FALSE),1,0) -> 1 | AZ111: =IF(O111=VLOOKUP(VALUE(O$1),Questions!$A:$E,5,FALSE),1,0) -> 1 | BA111: =IF(P111=VLOOKUP(VALUE(P$1),Questions!$A:$E,5,FALSE),1,0) -> 0 | BB111: =IF(Q111=VLOOKUP(VALUE(Q$1),Questions!$A:$E,5,FALSE),1,0) -> 1 | BC111: =IF(R111=VLOOKUP(VALUE(R$1),Questions!$A:$E,5,FALSE),1,0) -> 0 | ... BW111: =IF(AL111=VLOOKUP(VALUE(AL$1),Questions!$A:$E,5,FALSE),1,0) -> 1 | BX111: =IF(Scores[[#This Row],[Final]]>=65,1,0) -> 1 | BY111: =IF(Scores[[#This Row],[Final]]>=IF(Scores[[#This Row],[IEP]],55,65),1,0) -> 1
A112: 111 | B112: 11 | C112: Dushin | D112: FALSE | E112: FALSE | F112: =SUM(Scores[[#This Row],[Q1]:[Q28]]) -> 21 | G112: =SUM(Scores[[#This Row],[29]]:Scores[[#This Row],[30]]) -> 4 | H112: =SUM(Scores[[#This Row],[31]:[36]]) -> 6 | I112: =Scores[[#This Row],[37]] -> 2.5 | J112: =INDEX('Conversion Chart'!$C$3:$M$47,MATCH(SUM(Scores[[#This Row],[MC]:[IIIA]]),'Conversion Chart'!$B$3:$B$47),MATCH(Scores[[#This Row],[IIIB]],'Conversion Chart'!$C$2:$M$2)) -> 76 | K112: 4 | L112: 2 | M112: 3 | N112: 3 | O112: 1 | P112: 4 | Q112: 3 | R112: 2 | S112: 2 | T112: 1 | U112: 2 | V112: 3 | W112: 2 | X112: 2 | Y112: 1 | Z112: 4 | AA112: 1 | AB112: 4 | AC112: 3 | AD112: 4 | AE112: 2 | AF112: 2 | AG112: 1 | AH112: 1 | AI112: 1 | AJ112: 4 | AK112: 4 | AL112: 3 | AM112: 2 | AN112: 2 | AO112: 1 | AP112: 1 | AQ112: 1 | AR112: 1 | AS112: 1 | AT112: 1 | AU112: 2.5 | AV112: =IF(K112=VLOOKUP(VALUE(K$1),Questions!$A:$E,5,FALSE),1,0) -> 1 | AW112: =IF(L112=VLOOKUP(VALUE(L$1),Questions!$A:$E,5,FALSE),1,0) -> 1 | AX112: =IF(M112=VLOOKUP(VALUE(M$1),Questions!$A:$E,5,FALSE),1,0) -> 1 | AY112: =IF(N112=VLOOKUP(VALUE(N$1),Questions!$A:$E,5,FALSE),1,0) -> 1 | AZ112: =IF(O112=VLOOKUP(VALUE(O$1),Questions!$A:$E,5,FALSE),1,0) -> 1 | BA112: =IF(P112=VLOOKUP(VALUE(P$1),Questions!$A:$E,5,FALSE),1,0) -> 1 | BB112: =IF(Q112=VLOOKUP(VALUE(Q$1),Questions!$A:$E,5,FALSE),1,0) -> 1 | BC112: =IF(R112=VLOOKUP(VALUE(R$1),Questions!$A:$E,5,FALSE),1,0) -> 1 | ... BW112: =IF(AL112=VLOOKUP(VALUE(AL$1),Questions!$A:$E,5,FALSE),1,0) -> 1 | BX112: =IF(Scores[[#This Row],[Final]]>=65,1,0) -> 1 | BY112: =IF(Scores[[#This Row],[Final]]>=IF(Scores[[#This Row],[IEP]],55,65),1,0) -> 1
A113: 112 | B113: 11 | C113: Antaky | D113: FALSE | E113: FALSE | F113: =SUM(Scores[[#This Row],[Q1]:[Q28]]) -> 24 | G113: =SUM(Scores[[#This Row],[29]]:Scores[[#This Row],[30]]) -> 9 | H113: =SUM(Scores[[#This Row],[31]:[36]]) -> 6 | I113: =Scores[[#This Row],[37]] -> 3.5 | J113: =INDEX('Conversion Chart'!$C$3:$M$47,MATCH(SUM(Scores[[#This Row],[MC]:[IIIA]]),'Conversion Chart'!$B$3:$B$47),MATCH(Scores[[#This Row],[IIIB]],'Conversion Chart'!$C$2:$M$2)) -> 86 | K113: 4 | L113: 2 | M113: 4 | N113: 3 | O113: 3 | P113: 2 | Q113: 3 | R113: 2 | S113: 2 | T113: 1 | U113: 2 | V113: 4 | W113: 2 | X113: 4 | Y113: 3 | Z113: 4 | AA113: 1 | AB113: 4 | AC113: 3 | AD113: 4 | AE113: 2 | AF113: 2 | AG113: 3 | AH113: 3 | AI113: 1 | AJ113: 4 | AK113: 1 | AL113: 3 | AM113: 4 | AN113: 5 | AO113: 1 | AP113: 1 | AQ113: 1 | AR113: 1 | AS113: 1 | AT113: 1 | AU113: 3.5 | AV113: =IF(K113=VLOOKUP(VALUE(K$1),Questions!$A:$E,5,FALSE),1,0) -> 1 | AW113: =IF(L113=VLOOKUP(VALUE(L$1),Questions!$A:$E,5,FALSE),1,0) -> 1 | AX113: =IF(M113=VLOOKUP(VALUE(M$1),Questions!$A:$E,5,FALSE),1,0) -> 0 | AY113: =IF(N113=VLOOKUP(VALUE(N$1),Questions!$A:$E,5,FALSE),1,0) -> 1 | AZ113: =IF(O113=VLOOKUP(VALUE(O$1),Questions!$A:$E,5,FALSE),1,0) -> 0 | BA113: =IF(P113=VLOOKUP(VALUE(P$1),Questions!$A:$E,5,FALSE),1,0) -> 0 | BB113: =IF(Q113=VLOOKUP(VALUE(Q$1),Questions!$A:$E,5,FALSE),1,0) -> 1 | BC113: =IF(R113=VLOOKUP(VALUE(R$1),Questions!$A:$E,5,FALSE),1,0) -> 1 | ... BW113: =IF(AL113=VLOOKUP(VALUE(AL$1),Questions!$A:$E,5,FALSE),1,0) -> 1 | BX113: =IF(Scores[[#This Row],[Final]]>=65,1,0) -> 1 | BY113: =IF(Scores[[#This Row],[Final]]>=IF(Scores[[#This Row],[IEP]],55,65),1,0) -> 1
...

Sheet Questions
A1: # | B1: Part | C1: Stimulus | D1: Question | E1: Key | F1: Option_1 | G1: Option_2 | H1: Option_3 | I1: Option_4 | J1: Stimulus_type | K1: Source_type | L1: Task_model | M1: Skill_standard | N1: Need_OI? | O1: Content_standard | P1: Unit | Q1: Specification | R1: Pct_Correct | S1: Point_Biserial
A2: # | B2: Part | C2: Stimulus | D2: Question | E2: Key | F2: Option_1 | G2: Option_2 | H2: Option_3 | I2: Option_4 | J2: Stimulus_type | K2: Source_type | L2: Task_model | M2: Skill_standard | N2: Need_OI? | O2: Content_standard | P2: Unit | Q2: Specification | R2: Pct_Correct | S2: Point_Biserial
A3: 1 | B3: Part I | C3: The Lancaster Treaty of 1744 | D3: Which conclusion can best be drawn from this excerpt? | E3: 4 | F3: Europeans understood and respected Native American cultural traditions. | G3: Religious freedom was guaranteed in Pennsylvania. | H3: Native Americans had great respect for the king of England. | I3: Treaty making was a way to discuss differences between Native Americans and colonists. | J3: Text-based | K3: Primary | L3: 1. Best Use | M3: A.5: Inferences & Conclusions | N3: No | O3: 11.01a.1 | P3: =IFERROR(VALUE(RIGHT(LEFT([1]!Questions[[#This Row],[Content_standard]],5),2)),"") -> 1 | Q3: =IFERROR(VLOOKUP([1]!Questions[[#This Row],[Content_standard]],[1]!Content_Standards[#Data],2,FALSE),"") -> Colonization Impact on Native Americans | R3: =AVERAGE(INDEX([1]!Scores[#Data],0,MATCH("Q"&$A3,[1]!Scores[#Headers],0))) -> 0.71370968 | S3: {=IFERROR(CORREL(INDEX([1]!Scores[#Data],0,MATCH("Q"&$A3,[1]!Scores[#Headers],0)),[1]!Scores[MC]-INDEX([1]!Scores[#Data],0,MATCH("Q"&$A3,[1]!Scores[#Headers],0))),"")} -> 0.56496718
A4: 2 | B4: Part I | C4: The Lancaster Treaty of 1744 | D4: What was a result of the concerns expressed in this excerpt? | E4: 2 | F4: Native Americans were allowed to maintain control of their ancestral lands. | G4: American expansion continued to push Native Americans west. | H4: Native Americans remained neutral during the American Revolution. | I4: Cooperation with colonists led to significant Native American population growth. | J4: Text-based | K4: Primary | L4: 8. Effect | M4: B.2: Cause & Effect | N4: Yes | O4: 11.01a.2 | P4: =IFERROR(VALUE(RIGHT(LEFT([1]!Questions[[#This Row],[Content_standard]],5),2)),"") -> 2 | Q4: =IFERROR(VLOOKUP([1]!Questions[[#This Row],[Content_standard]],[1]!Content_Standards[#Data],2,FALSE),"") -> Declaration of Independence | R4: =AVERAGE(INDEX([1]!Scores[#Data],0,MATCH("Q"&$A4,[1]!Scores[#Headers],0))) -> 0.49193548 | S4: {=IFERROR(CORREL(INDEX([1]!Scores[#Data],0,MATCH("Q"&$A4,[1]!Scores[#Headers],0)),[1]!Scores[MC]-INDEX([1]!Scores[#Data],0,MATCH("Q"&$A4,[1]!Scores[#Headers],0))),"")} -> 0.44336767
A5: 3 | B5: Part I | C5: Virginia Declaration of Rights | D5: This excerpt is an example of which historical development in United States history? | E5: 3 | F5: the growth of colonial support for the British Parliament | G5: support for the inclusion of women in colonial public life | H5: the evolution of colonial self-government | I5: emphasis on the election of educated men to colonial offices | J5: Text-based | K5: Primary | L5: 5. Turning Point | M5: C.6: Historical Context | N5: Yes | O5: 11.02b.1 | P5: =IFERROR(VALUE(RIGHT(LEFT([1]!Questions[[#This Row],[Content_standard]],5),2)),"") -> 2 | Q5: =IFERROR(VLOOKUP([1]!Questions[[#This Row],[Content_standard]],[1]!Content_Standards[#Data],2,FALSE),"") -> Declaration of Independence | R5: =AVERAGE(INDEX([1]!Scores[#Data],0,MATCH("Q"&$A5,[1]!Scores[#Headers],0))) -> 0.5766129 | S5: {=IFERROR(CORREL(INDEX([1]!Scores[#Data],0,MATCH("Q"&$A5,[1]!Scores[#Headers],0)),[1]!Scores[MC]-INDEX([1]!Scores[#Data],0,MATCH("Q"&$A5,[1]!Scores[#Headers],0))),"")} -> 0.47825164
A6: 4 | B6: Part I | C6: Virginia Declaration of Rights | D6: Which principle of the Declaration of Independence is reflected in this excerpt? | E6: 3 | F6: separation of powers | G6: federalism | H6: consent of the governed | I6: universal suffrage | J6: Text-based | K6: Primary | L6: 12. Informed Civic Action | M6: C.3: Comparing Developments | N6: Yes | O6: 11.02b.1 | P6: =IFERROR(VALUE(RIGHT(LEFT([1]!Questions[[#This Row],[Content_standard]],5),2)),"") -> 3 | Q6: =IFERROR(VLOOKUP([1]!Questions[[#This Row],[Content_standard]],[1]!Content_Standards[#Data],2,FALSE),"") -> Expansion of Slavery | R6: =AVERAGE(INDEX([1]!Scores[#Data],0,MATCH("Q"&$A6,[1]!Scores[#Headers],0))) -> 0.39112903 | S6: {=IFERROR(CORREL(INDEX([1]!Scores[#Data],0,MATCH("Q"&$A6,[1]!Scores[#Headers],0)),[1]!Scores[MC]-INDEX([1]!Scores[#Data],0,MATCH("Q"&$A6,[1]!Scores[#Headers],0))),"")} -> 0.43853754
A7: 5 | B7: Part I | C7: Passage on the Missouri Compromise | D7: Based on this passage, what was former President Thomas Jefferson's point of view concerning the congressional debate over Missouri's admission to the Union? | E7: 1 | F7: He feared that disagreement over slavery would threaten the Union. | G7: He believed that Missouri should be admitted as a free state. | H7: He thought an amendment should be passed to protect slavery. | I7: He supported the right of states to secede from the Union. | J7: Text-based | K7: Secondary | L7: 2. POV | M7: A.3: Sourcing & Point of View | N7: No | O7: 11.03b.4 | P7: =IFERROR(VALUE(RIGHT(LEFT([1]!Questions[[#This Row],[Content_standard]],5),2)),"") -> 3 | Q7: =IFERROR(VLOOKUP([1]!Questions[[#This Row],[Content_standard]],[1]!Content_Standards[#Data],2,FALSE),"") -> Expansion of Slavery | R7: =AVERAGE(INDEX([1]!Scores[#Data],0,MATCH("Q"&$A7,[1]!Scores[#Headers],0))) -> 0.67741935 | S7: {=IFERROR(CORREL(INDEX([1]!Scores[#Data],0,MATCH("Q"&$A7,[1]!Scores[#Headers],0)),[1]!Scores[MC]-INDEX([1]!Scores[#Data],0,MATCH("Q"&$A7,[1]!Scores[#Headers],0))),"")} -> 0.60255209
A8: 6 | B8: Part I | C8: Passage on the Missouri Compromise | D8: What was an important effect of the compromise reached by Congress in 1820? | E8: 4 | F8: Foreign debts became the greatest challenge to national unity. | G8: Sectional tensions were no longer a threat to the nation. | H8: Slavery ended west of the Mississippi River. | I8: It preserved the Union for more than 30 years. | J8: Text-based | K8: Secondary | L8: 8. Effect | M8: B.2: Cause & Effect | N8: Yes | O8: 11.03b.4 | P8: =IFERROR(VALUE(RIGHT(LEFT([1]!Questions[[#This Row],[Content_standard]],5),2)),"") -> 3 | Q8: =IFERROR(VLOOKUP([1]!Questions[[#This Row],[Content_standard]],[1]!Content_Standards[#Data],2,FALSE),"") -> Union vs. Confederacy | R8: =AVERAGE(INDEX([1]!Scores[#Data],0,MATCH("Q"&$A8,[1]!Scores[#Headers],0))) -> 0.26209677 | S8: {=IFERROR(CORREL(INDEX([1]!Scores[#Data],0,MATCH("Q"&$A8,[1]!Scores[#Headers],0)),[1]!Scores[MC]-INDEX([1]!Scores[#Data],0,MATCH("Q"&$A8,[1]!Scores[#Headers],0))),"")} -> 0.29412507
A9: 7 | B9: Part I | C9: President Abraham Lincoln, First Inaugural Address | D9: What was the primary purpose of President Abraham Lincoln adding this paragraph to his first inaugural address? | E9: 3 | F9: to introduce industry to the rural South | G9: to gain passage of the 13th, 14th, and 15th Amendments | H9: to reassure the South and avoid civil war | I9: to overturn the Dred Scott decision | J9: Text-based | K9: Primary | L9: 2. POV | M9: A.3: Sourcing & Point of View | N9: No | O9: 11.03c.1 | P9: =IFERROR(VALUE(RIGHT(LEFT([1]!Questions[[#This Row],[Content_standard]],5),2)),"") -> 3 | Q9: =IFERROR(VLOOKUP([1]!Questions[[#This Row],[Content_standard]],[1]!Content_Standards[#Data],2,FALSE),"") -> Federal Power: Habeas Corpus & Emancipation | R9: =AVERAGE(INDEX([1]!Scores[#Data],0,MATCH("Q"&$A9,[1]!Scores[#Headers],0))) -> 0.59677419 | S9: {=IFERROR(CORREL(INDEX([1]!Scores[#Data],0,MATCH("Q"&$A9,[1]!Scores[#Headers],0)),[1]!Scores[MC]-INDEX([1]!Scores[#Data],0,MATCH("Q"&$A9,[1]!Scores[#Headers],0))),"")} -> 0.54176134
A10: 8 | B10: Part I | C10: President Abraham Lincoln, First Inaugural Address | D10: Several years after this address, President Lincoln expressed a different view of slavery when he | E10: 2 | F10: stated support for John Brown's raid at Harper's Ferry | G10: issued the Emancipation Proclamation | H10: enforced the Kansas-Nebraska Act | I10: suspended habeas corpus in the states in rebellion | J10: Text-based | K10: Primary | L10: 16. Sequence of Events | M10: C.3: Comparing Developments | N10: Yes | O10: 11.03c.2 | P10: =IFERROR(VALUE(RIGHT(LEFT([1]!Questions[[#This Row],[Content_standard]],5),2)),"") -> 5 | Q10: =IFERROR(VLOOKUP([1]!Questions[[#This Row],[Content_standard]],[1]!Content_Standards[#Data],2,FALSE),"") -> Urbanization & Immigration | R10: =AVERAGE(INDEX([1]!Scores[#Data],0,MATCH("Q"&$A10,[1]!Scores[#Headers],0))) -> 0.63306452 | S10: {=IFERROR(CORREL(INDEX([1]!Scores[#Data],0,MATCH("Q"&$A10,[1]!Scores[#Headers],0)),[1]!Scores[MC]-INDEX([1]!Scores[#Data],0,MATCH("Q"&$A10,[1]!Scores[#Headers],0))),"")} -> 0.52328
A11: 9 | B11: Part I | C11: Frederick Law Olmsted, Address to the American Social Science Association | D11: What change in the late-19th-century United States is described in this passage? | E11: 2 | F11: the growth in private home ownership | G11: an increase in urbanization | H11: a decrease in employment for factory workers | I11: a reduction in agricultural technology | J11: Text-based | K11: Primary | L11: 5. Turning Point | M11: B.5: Continuity & Change | N11: Yes | O11: 11.05b.1 | P11: =IFERROR(VALUE(RIGHT(LEFT([1]!Questions[[#This Row],[Content_standard]],5),2)),"") -> 5 | Q11: =IFERROR(VLOOKUP([1]!Questions[[#This Row],[Content_standard]],[1]!Content_Standards[#Data],2,FALSE),"") -> Urbanization & Immigration | R11: =AVERAGE(INDEX([1]!Scores[#Data],0,MATCH("Q"&$A11,[1]!Scores[#Headers],0))) -> 0.55645161 | S11: {=IFERROR(CORREL(INDEX([1]!Scores[#Data],0,MATCH("Q"&$A11,[1]!Scores[#Headers],0)),[1]!Scores[MC]-INDEX([1]!Scores[#Data],0,MATCH("Q"&$A11,[1]!Scores[#Headers],0))),"")} -> 0.45137199
A12: 10 | B12: Part I | C12: Frederick Law Olmsted, Address to the American Social Science Association | D12: The situation described in this passage resulted in | E12: 1 | F12: increased demands on local governments to provide services | G12: women's groups seeking the right to vote | H12: pressure to limit freedom of the press | I12: attempts by temperance groups to ban the sale of alcohol | J12: Text-based | K12: Primary | L12: 8. Effect | M12: B.2: Cause & Effect | N12: Yes | O12: 11.05b.1 | P12: =IFERROR(VALUE(RIGHT(LEFT([1]!Questions[[#This Row],[Content_standard]],5),2)),"") -> 4 | Q12: =IFERROR(VLOOKUP([1]!Questions[[#This Row],[Content_standard]],[1]!Content_Standards[#Data],2,FALSE),"") -> Limiting of Black Rights | R12: =AVERAGE(INDEX([1]!Scores[#Data],0,MATCH("Q"&$A12,[1]!Scores[#Headers],0))) -> 0.72177419 | S12: {=IFERROR(CORREL(INDEX([1]!Scores[#Data],0,MATCH("Q"&$A12,[1]!Scores[#Headers],0)),[1]!Scores[MC]-INDEX([1]!Scores[#Data],0,MATCH("Q"&$A12,[1]!Scores[#Headers],0))),"")} -> 0.57852319
A13: 11 | B13: Part I | C13: Photograph of segregated facilities | D13: Conditions such as the one shown in this photograph were a result of | E13: 2 | F13: actions of the Freedmen's Bureau | G13: the passage of Jim Crow laws | H13: citizenship guarantees in the Dawes Act | I13: the enactment of affirmative action programs | J13: Visual-based | K13: Primary | L13: 7. Cause | M13: B.2: Cause & Effect | N13: Yes | O13: 11.04a.2 | P13: =IFERROR(VALUE(RIGHT(LEFT([1]!Questions[[#This Row],[Content_standard]],5),2)),"") -> 4 | Q13: =IFERROR(VLOOKUP([1]!Questions[[#This Row],[Content_standard]],[1]!Content_Standards[#Data],2,FALSE),"") -> Limiting of Black Rights | R13: =AVERAGE(INDEX([1]!Scores[#Data],0,MATCH("Q"&$A13,[1]!Scores[#Headers],0))) -> 0.67741935 | S13: {=IFERROR(CORREL(INDEX([1]!Scores[#Data],0,MATCH("Q"&$A13,[1]!Scores[#Headers],0)),[1]!Scores[MC]-INDEX([1]!Scores[#Data],0,MATCH("Q"&$A13,[1]!Scores[#Headers],0))),"")} -> 0.61051092
A14: 12 | B14: Part I | C14: Photograph of segregated facilities | D14: Which United States Supreme Court decision provided legal support for the situation shown in this photograph? | E14: 4 | F14: Gibbons v. Ogden | G14: Worcester v. Georgia | H14: Dred Scott v. Sanford | I14: Plessy v. Ferguson | J14: Visual-based | K14: Primary | L14: 7. Cause | M14: B.2: Cause & Effect | N14: Yes | O14: 11.04a.2 | P14: =IFERROR(VALUE(RIGHT(LEFT([1]!Questions[[#This Row],[Content_standard]],5),2)),"") -> 6 | Q14: =IFERROR(VLOOKUP([1]!Questions[[#This Row],[Content_standard]],[1]!Content_Standards[#Data],2,FALSE),"") -> Imperialism in the Caribbean & Latin America | R14: =AVERAGE(INDEX([1]!Scores[#Data],0,MATCH("Q"&$A14,[1]!Scores[#Headers],0))) -> 0.46370968 | S14: {=IFERROR(CORREL(INDEX([1]!Scores[#Data],0,MATCH("Q"&$A14,[1]!Scores[#Headers],0)),[1]!Scores[MC]-INDEX([1]!Scores[#Data],0,MATCH("Q"&$A14,[1]!Scores[#Headers],0))),"")} -> 0.46992008
... A30: 28 | B30: Part I | C30: Photograph of WPA Worker, Photograph from American Recovery and Reinvestment Act | D30: These photographs suggest a federal government supportive of | E30: 3 | F30: assuming ownership of failed corporations | G30: returning to laissez-faire capitalistic principles | H30: investing in public works and infrastructure projects | I30: helping the owners of big businesses and not labor | J30: Visual-based | K30: Primary | L30: 18. Response to Problem | M30: A.7: Synthesizing Evidence | N30: No | O30: 11.10c.2 | P30: =IFERROR(VALUE(RIGHT(LEFT([1]!Questions[[#This Row],[Content_standard]],5),2)),"") -> 10 | Q30: =IFERROR(VLOOKUP([1]!Questions[[#This Row],[Content_standard]],[1]!Content_Standards[#Data],2,FALSE),"") -> Individuals & Groups Fight for Equality | R30: =AVERAGE(INDEX([1]!Scores[#Data],0,MATCH("Q"&$A30,[1]!Scores[#Headers],0))) -> 0.69354839 | S30: {=IFERROR(CORREL(INDEX([1]!Scores[#Data],0,MATCH("Q"&$A30,[1]!Scores[#Headers],0)),[1]!Scores[MC]-INDEX([1]!Scores[#Data],0,MATCH("Q"&$A30,[1]!Scores[#Headers],0))),"")} -> 0.56050216
A31: 29 | B31: Part II | C31: Judith Heumann, Joint House-Senate Hearing on Discrimination on the Basis of Disability; President George H. W. Bush, Remarks at the Signing of the Americans with Disabilities Act | J31: Text-based | K31: Primary | M31: A.7: Synthesizing Evidence | O31: 11.10b.1 | P31: =IFERROR(VALUE(RIGHT(LEFT([1]!Questions[[#This Row],[Content_standard]],5),2)),"") -> 9 | Q31: =IFERROR(VLOOKUP([1]!Questions[[#This Row],[Content_standard]],[1]!Content_Standards[#Data],2,FALSE),"") -> Vietnam War
A32: 30 | B32: Part II | C32: Clark M. Clifford, Chairman of the President's Intelligence Advisory Board, Letter to President Lyndon Johnson; President Lyndon B. Johnson, Press Conference | J32: Text-based | K32: Primary | M32: A.3: Sourcing & Point of View | O32: 11.09a.5 | P32: =IFERROR(VALUE(RIGHT(LEFT([1]!Questions[[#This Row],[Content_standard]],5),2)),"") -> 2 | Q32: =IFERROR(VLOOKUP([1]!Questions[[#This Row],[Content_standard]],[1]!Content_Standards[#Data],2,FALSE),"") -> Articles of Confederation
A33: 31 | B33: Part IIIA | C33: Passage on the Articles of Confederation | D33: According to Gordon Wood, what was one historical circumstance that led to the creation of a stronger national government? | J33: Text-based | K33: Secondary | M33: C.6: Historical Context | O33: 11.02c.1 | P33: =IFERROR(VALUE(RIGHT(LEFT([1]!Questions[[#This Row],[Content_standard]],5),2)),"") -> 2 | Q33: =IFERROR(VLOOKUP([1]!Questions[[#This Row],[Content_standard]],[1]!Content_Standards[#Data],2,FALSE),"") -> Articles of Confederation
A34: 32 | B34: Part IIIA | C34: Passage on Shays' Rebellion; Engraved illustration of Shays' Rebellion | D34: Based on these documents, what was one historical circumstance that led to the creation of a stronger national government? | J34: Multiple | K34: Both | M34: C.6: Historical Context | O34: 11.02c.1 | P34: =IFERROR(VALUE(RIGHT(LEFT([1]!Questions[[#This Row],[Content_standard]],5),2)),"") -> 2 | Q34: =IFERROR(VLOOKUP([1]!Questions[[#This Row],[Content_standard]],[1]!Content_Standards[#Data],2,FALSE),"") -> Constitution Development & Debates
A35: 33 | B35: Part IIIA | C35: Passage on Shays' Rebellion and the Constitutional Convention | D35: Based on this document, what was one effort to address the creation of a stronger national government? | J35: Text-based | K35: Secondary | M35: F.2: Civic Engagement | O35: 11.02c.2 | P35: =IFERROR(VALUE(RIGHT(LEFT([1]!Questions[[#This Row],[Content_standard]],5),2)),"") -> 2 | Q35: =IFERROR(VLOOKUP([1]!Questions[[#This Row],[Content_standard]],[1]!Content_Standards[#Data],2,FALSE),"") -> Federalist vs. Antifederalist
A36: 34 | B36: Part IIIA | C36: Passage on ratification debates | D36: According to Pauline Maier, what was one effort to address the creation of a stronger national government? | J36: Text-based | K36: Secondary | M36: F.2: Civic Engagement | O36: 11.02c.4 | P36: =IFERROR(VALUE(RIGHT(LEFT([1]!Questions[[#This Row],[Content_standard]],5),2)),"") -> 2 | Q36: =IFERROR(VLOOKUP([1]!Questions[[#This Row],[Content_standard]],[1]!Content_Standards[#Data],2,FALSE),"") -> Bill of Rights
A37: 35 | B37: Part IIIA | C37: Passage on the Bill of Rights | D37: According to Linda Monk, what was one impact of the efforts to create a stronger national government? | J37: Text-based | K37: Secondary | M37: B.2: Cause & Effect | O37: 11.02c.5 | P37: =IFERROR(VALUE(RIGHT(LEFT([1]!Questions[[#This Row],[Content_standard]],5),2)),"") -> 2 | Q37: =IFERROR(VLOOKUP([1]!Questions[[#This Row],[Content_standard]],[1]!Content_Standards[#Data],2,FALSE),"") -> Federal Government Structure & Principles
A38: 36 | B38: Part IIIA | C38: Barack Obama, Speech on the Constitution | D38: According to President Barack Obama, what was one impact of the efforts to create a stronger national government? | J38: Text-based | K38: Primary | M38: C.6: Historical Context | O38: 11.02c.3 | P38: =IFERROR(VALUE(RIGHT(LEFT([1]!Questions[[#This Row],[Content_standard]],5),2)),"") | Q38: =IFERROR(VLOOKUP([1]!Questions[[#This Row],[Content_standard]],[1]!Content_Standards[#Data],2,FALSE),"")
A39: 37 | B39: Part IIIB | C39: — | D39: — | M39: A.6: Constructing Arguments | P39: =IFERROR(VALUE(RIGHT(LEFT([1]!Questions[[#This Row],[Content_standard]],5),2)),"") | Q39: =IFERROR(VLOOKUP([1]!Questions[[#This Row],[Content_standard]],[1]!Content_Standards[#Data],2,FALSE),"")

Sheet Scores Breakdown
E2: MC | F2: (Multiple Items)
B3: Score | C3: Number of Students | E3: Class | F3: (Multiple Items)
B4: 23 | C4: 1
B5: 25 | C5: 2 | E5: Grade | F5: MC Score | G5: SEQ Score | H5: IIIA Score | I5: IIIB Score | J5: Final Score | K5: Passing Rate | L5: Passing* Rate
B6: 33 | C6: 1 | E6: 9 | F6: 16.211538 | G6: 3.2596154 | H6: 4.6634615 | I6: 1.4375 | J6: 62.846154 | K6: 0.57692308 | L6: 0.67307692
B7: 36 | C7: 1 | E7: 11 | F7: 16.655172 | G7: 4 | H7: 4.9655172 | I7: 1.954023 | J7: 66.942529 | K7: 0.65517241 | L7: 0.75862069
B8: 38 | C8: 3 | E8: 10 | F8: 13 | G8: 4 | H8: 4 | I8: 1 | J8: 58 | K8: 0 | L8: 0
B9: 40 | C9: 3 | E9: Grand Total | F9: 16.395833 | G9: 3.5989583 | H9: 4.796875 | I9: 1.6692708 | J9: 64.677083 | K9: 0.609375 | L9: 0.70833333
B10: 42 | C10: 1
B11: 46 | C11: 5 | E11: MC | F11: (Multiple Items)
B12: 47 | C12: 1 | E12: Final | F12: (All)
B13: 48 | C13: 4
B14: 50 | C14: 2 | E14: Class | F14: MC Score | G14: SEQ Score | H14: IIIA Score | I14: IIIB Score | J14: Final Score | K14: Passing Rate | L14: Passing* Rate
B15: 51 | C15: 1 | E15: Bermejo | F15: 16.731343 | G15: 3.5820896 | H15: 4.8059701 | I15: 1.5 | J15: 64.567164 | K15: 0.62686567 | L15: 0.74626866
B16: 52 | C16: 5 | E16: Dushin | F16: 16.723077 | G16: 4.2769231 | H16: 4.8153846 | I16: 1.9153846 | J16: 66.738462 | K16: 0.61538462 | L16: 0.73846154
B17: 53 | C17: 1 | E17: Kovelsky | F17: 15.666667 | G17: 2.8833333 | H17: 4.7666667 | I17: 1.5916667 | J17: 62.566667 | K17: 0.58333333 | L17: 0.63333333
B18: 54 | C18: 4 | E18: 9 | F18: 15.243243 | G18: 2.7027027 | H18: 4.3783784 | I18: 1.2837838 | J18: 59.513514 | K18: 0.45945946 | L18: 0.51351351
B19: 55 | C19: 12 | E19: 11 | F19: 16.347826 | G19: 3.173913 | H19: 5.3913043 | I19: 2.0869565 | J19: 67.478261 | K19: 0.7826087 | L19: 0.82608696
B20: 57 | C20: 3 | E20: Antaky | F20: 19.9 | G20: 5.3 | H20: 5.75 | I20: 2.075 | J20: 74.2 | K20: 0.9 | L20: 0.9
B21: 58 | C21: 9 | E21: Other | F21: 17.142857 | G21: 2.4285714 | H21: 4.7142857 | I21: 1.1428571 | J21: 63 | K21: 0.42857143 | L21: 0.57142857
B22: 60 | C22: 10 | E22: Grand Total | F22: 16.739726 | G22: 3.716895 | H22: 4.8812785 | I22: 1.6894977 | J22: 65.493151 | K22: 0.63013699 | L22: 0.72146119
B23: 61 | C23: 8
B24: 63 | C24: 1 | E24: MC | F24: (Multiple Items)
B25: 64 | C25: 3
B26: 65 | C26: 7 | E26: IEP? | F26: MC Score | G26: SEQ Score | H26: IIIA Score | I26: IIIB Score | J26: Final Score | K26: Passing Rate | L26: Passing* Rate
B27: 66 | C27: 15 | E27: Yes | F27: 14.275 | G27: 3.375 | H27: 4.425 | I27: 1.4125 | J27: 59.75 | K27: 0.3 | L27: 0.8
B28: 67 | C28: 11 | E28: No | F28: 17.290503 | G28: 3.7932961 | H28: 4.9832402 | I28: 1.7513966 | J28: 66.776536 | K28: 0.70391061 | L28: 0.70391061
B29: 68 | C29: 11 | E29: Grand Total | F29: 16.739726 | G29: 3.716895 | H29: 4.8812785 | I29: 1.6894977 | J29: 65.493151 | K29: 0.63013699 | L29: 0.72146119
B30: 69 | C30: 5
B31: 70 | C31: 6
B32: 71 | C32: 9 | E32: MC | F32: (Multiple Items)
B33: 72 | C33: 15
B34: 73 | C34: 8 | E34: ELL? | F34: MC Score | G34: SEQ Score | H34: IIIA Score | I34: IIIB Score | J34: Final Score | K34: Passing Rate | L34: Passing* Rate
B35: 74 | C35: 2 | E35: Yes | F35: 11.3 | G35: 3.4 | H35: 4.1 | I35: 0.85 | J35: 53 | K35: 0.2 | L35: 0.4
B36: 75 | C36: 7 | E36: No | F36: 17 | G36: 3.7320574 | H36: 4.9186603 | I36: 1.7296651 | J36: 66.090909 | K36: 0.6507177 | L36: 0.73684211
B37: 76 | C37: 3 | E37: Grand Total | F37: 16.739726 | G37: 3.716895 | H37: 4.8812785 | I37: 1.6894977 | J37: 65.493151 | K37: 0.63013699 | L37: 0.72146119
B38: 77 | C38: 9
B39: 78 | C39: 4 | I39: MC | J39: (Multiple Items)
B40: 79 | C40: 3 | E40: MC | F40: (Multiple Items) | I40: Class | J40: (Multiple Items)
B41: 80 | C41: 2
B42: 81 | C42: 2 | E42: Class | F42: SEQ Set 1 | G42: SEQ Set 2 | I42: Class | J42: SEQ Set 1 | K42: SEQ Set 2 | L42: Difference
B43: 82 | C43: 3 | E43: Bermejo | F43: 2.0447761 | G43: 1.5373134 | I43: 9 | J43: 1.9038462 | K43: 1.3557692 | L43: =J43-K43 -> 0.54807692
B44: 83 | C44: 2 | E44: Dushin | F44: 2.5384615 | G44: 1.7384615 | I44: 11 | J44: 2.3333333 | K44: 1.6666667 | L44: =J44-K44 -> 0.66666667
B45: 84 | C45: 3 | E45: Kovelsky | F45: 1.6833333 | G45: 1.2 | I45: 10 | J45: 2 | K45: 2 | L45: =J45-K45 -> 0
B46: 85 | C46: 3 | E46: Antaky | F46: 2.7 | G46: 2.6 | I46: Grand Total | J46: 2.0989583 | K46: 1.5 | L46: =AVERAGE(Table6[Difference]) -> 0.40491453
B47: 86 | C47: 5 | E47: Other | F47: 1.5714286 | G47: 0.85714286
B48: 89 | C48: 2 | E48: Grand Total | F48: 2.1369863 | G48: 1.5799087
B49: 90 | C49: 1
B50: Grand Total | C50: 219

Sheet Question Breakdown
B3: Stimulus Type | C3: Average of Pct_Correct | D3: Count
B4: Data-based | C4: 0.43333333 | D4: 2
B5: Multiple | D5: 1
B6: Text-based | C6: 0.68095238 | D6: 21
B7: Visual-based | C7: 0.57222222 | D7: 12
B9: Source Type | C9: Average of Pct_Correct | D9: Count
B10: Both | D10: 1
B11: Primary | C11: 0.62222222 | D11: 27
B12: Secondary | C12: 0.58333333 | D12: 8
B14: Outside Info | C14: Average of Pct_Correct | D14: Count
B15: No | C15: 0.78888889 | D15: 6
B16: Yes | C16: 0.56969697 | D16: 22

Sheet Task Models
A1: Model | B1: Detail
A2: 1. Best Use | B2: Students are given a stimulus and asked to evaluate and classify (identify) best use.
A3: 2. POV | B3: Students are given a stimulus and asked to identify point of view, purpose, context, bias, format of source, location of source in time and/or place, and/or intended audience of sources using background knowledge.
A4: 3. Claim Validity (With Outside Information) | B4: Students are given a stimulus and asked to identify support for a claim found in the stimulus (bound in the same timeframe/event/space). It must require students to draw on their knowledge rather than on straight comprehension of text.
A5: 4. Claim Validity (Without Outside Information) | B5: Students are given a stimulus and asked to select a plausible claim that logically follows from evidence presented.
A6: 5. Turning Point | B6: Students are given a stimulus and asked to identify the significance of a turning point in history.
A7: 6. Change Over Time | B7: Students are given a stimulus and asked to identify significance of an event, action, idea, or development as part of change or part of continuity in history.
A8: 7. Cause | B8: Students are given a stimulus and asked to identify a central cause of the described phenomenon.
A9: 8. Effect | B9: Students are given a stimulus and asked to identify a central effect of the described phenomenon.
A10: 9. Impact of Setting | B10: Students are given a stimulus and asked to identify the impact of time and place on an issue or event linked to that stimulus.
A11: 10. Compare | B11: Students are given one stimulus or two stimuli and asked to identify a similarity in the described phenomenon (historical development, historical event, geographic setting, economic situation, individual’s action/belief) (implicit comparison).
A12: 11. Contrast | B12: Students are given one/two stimuli and asked to identify a difference in the described phenomenon (historical development, historical event, geographic setting, economic situation, individual’s action/belief) (implicit comparison).
... A19: 18. Response to Problem | B19: Students are given one stimulus or two stimuli and asked to identify a response to a problem (issue).

Sheet Skill Standards
A1: Standard | B1: Concept | C1: Specification
A2: A. Gathering, Interpreting, and Using Evidence | B2: A.1: Framing Questions & Hypotheses | C2: Define and frame questions about events and the world in which we live, form hypotheses as potential answers to these questions, use evidence to answer these questions, and consider and analyze counter-hypotheses.
A3: A. Gathering, Interpreting, and Using Evidence | B3: A.2: Evaluating Sources | C3: Identify, describe, and evaluate evidence about events from diverse sources (including written documents, works of art, photographs, charts and graphs, artifacts, oral traditions, and other primary and secondary sources).
A4: A. Gathering, Interpreting, and Using Evidence | B4: A.3: Sourcing & Point of View | C4: Analyze evidence in terms of content, authorship, point of view, bias, purpose, format, and audience.
A5: A. Gathering, Interpreting, and Using Evidence | B5: A.4: Evaluating Arguments | C5: Describe, analyze, and evaluate arguments of others.
A6: A. Gathering, Interpreting, and Using Evidence | B6: A.5: Inferences & Conclusions | C6: Make inferences and draw conclusions from evidence.
A7: A. Gathering, Interpreting, and Using Evidence | B7: A.6: Constructing Arguments | C7: Deconstruct and construct plausible and persuasive arguments, using evidence.
A8: A. Gathering, Interpreting, and Using Evidence | B8: A.7: Synthesizing Evidence | C8: Create meaningful and persuasive understandings of the past by fusing disparate and relevant evidence from primary and secondary sources and drawing connections to the present.
A9: B. Chronological Reasoning and Causation | B9: B.1: Chronological Relationships | C9: Articulate how events are related chronologically to one another in time and explain the ways in which earlier ideas and events may influence subsequent ideas and events.
A10: B. Chronological Reasoning and Causation | B10: B.2: Cause & Effect | C10: Identify causes and effects using examples from different time periods and courses of study across several grade levels.
A11: B. Chronological Reasoning and Causation | B11: B.3: Multiple Causes & Effects | C11: Identify, analyze, and evaluate the relationship between multiple causes and effects
A12: B. Chronological Reasoning and Causation | B12: B.4: Long-Term vs. Immediate Causes | C12: Distinguish between long-term and immediate causes and multiple effects (time, continuity, and change).
... A42: F. Civic Participation | B42: F.8: Civic Responsibility | C42: Fulfill social and political responsibilities associated with citizenship in a democratic society and interdependent global community by developing awareness of and/or engaging in the political process.

Sheet Content Standards
A1: # | B1: Framework | C1: Specifications
A2: 10.01a.1 | B2: Mughal & Ottoman (c. 1750) | C2: Students will compare and contrast the Mughal Empire and the Ottoman Empire in 1750 in terms of religious and ethnic tolerance, political organization, and commercial activity.
A3: 10.01a.2 | B3: Tokugawa Shogunate | C3: Students will examine efforts to unify, stabilize, and centralize Japan under the rule of the Tokugawa Shogunate.
A4: 10.01a.3 | B4: Comparing Tokugawa Shogunate & Bourbon Dynasty | C4: Students will compare and contrast the Tokugawa Shogunate in Japan with France under the rule of the Bourbon Dynasty, looking at the role of Edo and Paris/Versailles, attempts to control the daimyo and nobles, and the development of bureaucracies.
A5: 10.01b.1 | B5: Tokugawa & Mughal Responses to Outsiders | C5: Students will compare and contrast the Tokugawa and Mughal responses to outsiders, with attention to the impacts of those decisions.
A6: 10.01b.2 | B6: Eurasia World Map | C6: Students will create a world map showing the extent of European maritime empires, the Russian Empire, the Ottoman Empire, Mughal Empire, China under the Qing Dynasty, Japan under the Tokugawa Shogunate, Ashanti, Benin, and Dahomey ca. 1750.
A7: 10.01b.3 | B7: Comparing Empire's Geography & Power | C7: Students will compare the size of these states, empires, and kingdoms relative to the power they wielded in their regions and in the world.
A8: 10.02a.1 | B8: Political Philosophies | C8: Students will examine at least three Enlightenment thinkers, including John Locke, Baron de Montesquieu, and Jean-Jacques Rousseau, and key ideas from their written works.
A9: 10.02b.1 | B9: Gender & Abolition | C9: Students will explore the influence of Enlightenment ideals on issues of gender and abolition by examining the ideas of individuals such as Mary Wollstonecraft and William Wilberforce.
A10: 10.02b.2 | B10: Enlightened Despots | C10: Students will examine enlightened despots including Catherine the Great.
A11: 10.02c.1 | B11: French Revolutions | C11: Students will examine evidence related to the preconditions of the French Revolution and the course of the revolution, noting the roles of Olympe de Gouges, Maximilien Robespierre, and Napoleon Bonaparte.
A12: 10.02c.2 | B12: Latin American Revolutions | C12: Students will examine the evidence related to the impacts of the French Revolution on resistance and revolutionary movements, noting the roles of Toussaint L'Ouverture and Simon Bolivar.
... A178: 11.11c.3 | B178: US vs China Rivalry | C178: Students will examine the economic relationship and the strategic rivalry between the United States and China.

Sheet Conversion Chart
C2: 0 | D2: 0.5 | E2: 1 | F2: 1.5 | G2: 2 | H2: 2.5 | I2: 3 | J2: 3.5 | K2: 4 | L2: 4.5 | M2: 5
B3: 0 | C3: 0 | D3: 6 | E3: 11 | F3: 15 | G3: 20 | H3: 24 | I3: 28 | J3: 32 | K3: 36 | L3: 39 | M3: 42
B4: 1 | C4: 4 | D4: 9 | E4: 14 | F4: 18 | G4: 23 | H4: 27 | I4: 31 | J4: 34 | K4: 38 | L4: 41 | M4: 44
B5: 2 | C5: 7 | D5: 12 | E5: 17 | F5: 21 | G5: 25 | H5: 29 | I5: 33 | J5: 37 | K5: 40 | L5: 43 | M5: 46
B6: 3 | C6: 11 | D6: 15 | E6: 20 | F6: 24 | G6: 28 | H6: 32 | I6: 36 | J6: 39 | K6: 42 | L6: 45 | M6: 48
B7: 4 | C7: 14 | D7: 18 | E7: 23 | F7: 27 | G7: 31 | H7: 34 | I7: 38 | J7: 41 | K7: 44 | L7: 47 | M7: 50
B8: 5 | C8: 17 | D8: 21 | E8: 25 | F8: 29 | G8: 33 | H8: 37 | I8: 40 | J8: 43 | K8: 46 | L8: 49 | M8: 52
B9: 6 | C9: 20 | D9: 24 | E9: 28 | F9: 32 | G9: 36 | H9: 39 | I9: 42 | J9: 45 | K9: 48 | L9: 51 | M9: 54
B10: 7 | C10: 23 | D10: 27 | E10: 31 | F10: 34 | G10: 38 | H10: 41 | I10: 44 | J10: 47 | K10: 50 | L10: 53 | M10: 55
B11: 8 | C11: 25 | D11: 29 | E11: 33 | F11: 37 | G11: 40 | H11: 43 | I11: 46 | J11: 49 | K11: 52 | L11: 54 | M11: 57
B12: 9 | C12: 28 | D12: 32 | E12: 36 | F12: 39 | G12: 42 | H12: 45 | I12: 48 | J12: 51 | K12: 54 | L12: 56 | M12: 58
B13: 10 | C13: 31 | D13: 34 | E13: 38 | F13: 41 | G13: 44 | H13: 47 | I13: 50 | J13: 53 | K13: 55 | L13: 58 | M13: 60
B14: 11 | C14: 33 | D14: 37 | E14: 40 | F14: 43 | G14: 46 | H14: 49 | I14: 52 | J14: 54 | K14: 57 | L14: 59 | M14: 61
... B38: 35 | C38: 72 | D38: 74 | E38: 76 | F38: 77 | G38: 78 | H38: 80 | I38: 81 | J38: 83 | K38: 84 | L38: 86 | M38: 87
B39: =B38+1 -> 36 | C39: 73 | D39: 75 | E39: 77 | F39: 78 | G39: 79 | H39: 81 | I39: 82 | J39: 84 | K39: 86 | L39: 86 | M39: 88
B40: =B39+1 -> 37 | C40: 75 | D40: 76 | E40: 77 | F40: 79 | G40: 80 | H40: 82 | I40: 83 | J40: 85 | K40: 86 | L40: 87 | M40: 89
B41: =B40+1 -> 38 | C41: 76 | D41: 77 | E41: 78 | F41: 80 | G41: 81 | H41: 83 | I41: 84 | J41: 86 | K41: 87 | L41: 89 | M41: 90
B42: =B41+1 -> 39 | C42: 77 | D42: 78 | E42: 79 | F42: 81 | G42: 82 | H42: 84 | I42: 86 | J42: 86 | K42: 88 | L42: 90 | M42: 92
B43: =B42+1 -> 40 | C43: 77 | D43: 79 | E43: 80 | F43: 82 | G43: 83 | H43: 85 | I43: 86 | J43: 87 | K43: 89 | L43: 91 | M43: 93
B44: =B43+1 -> 41 | C44: 78 | D44: 80 | E44: 81 | F44: 83 | G44: 84 | H44: 86 | I44: 87 | J44: 89 | K44: 90 | L44: 92 | M44: 94
B45: =B44+1 -> 42 | C45: 79 | D45: 81 | E45: 82 | F45: 84 | G45: 86 | H45: 86 | I45: 88 | J45: 90 | K45: 92 | L45: 94 | M45: 96
B46: =B45+1 -> 43 | C46: 80 | D46: 82 | E46: 83 | F46: 85 | G46: 86 | H46: 87 | I46: 89 | J46: 91 | K46: 93 | L46: 95 | M46: 98
B47: =B46+1 -> 44 | C47: 81 | D47: 83 | E47: 84 | F47: 86 | G47: 87 | H47: 89 | I47: 90 | J47: 92 | K47: 94 | L47: 97 | M47: 100
C49: Scale Scores to Performance Levels
C50: Level 1: | E50: Level 2: | G50: Level 3: | I50: Level 4: | K50: Level 5:
C51: 0-54 | E51: 55-64 | G51: 65-75 | I51: 76-84 | K51: 85-100
